Workbook

Sheet TRIP MANAGER
A1: TRIP MANAGER — OVERFLIGHT & LANDING PERMIT ENGINE
A2: Enter DEP ICAO, ARR ICAO, ETD and REGISTRATION for each leg. Overflown countries and permit lines below recalculate automatically.
A4: 1 · TRIP & AIRCRAFT
A5: TRIP REFERENCE | B5: JTL-2608-001 | C5: Register status → | D5: =IF($B$5="","",IFERROR(INDEX(mayfly!$C:$C,MATCH($B$5,mayfly!$A:$A,0))&" | owner: "&INDEX(mayfly!$D:$D,MATCH($B$5,mayfly!$A:$A,0))&" | legs in register: "&COUNTIF(mayfly!$A:$A,$B$5),"NOT IN THE MAYFLY REGISTER - add it there first")) -> ACTIVE | owner: OPS DESK | legs in register: 4 | E5: BILL TO — DEFAULT (CLIENT ID) | F5: CLI-001
A6: OPERATOR | B6: JTL AVIATION, INC | C6: Operator on file for this tail → | E6: CLIENT / BILL-TO NAME | F6: =IF($F$5="","",IFERROR(INDEX(Clients!$D:$D,MATCH($F$5,Clients!$A:$A,0))&"","UNKNOWN CLIENT ID")) -> JTL AVIATION INC
A7: REGISTRATION | B7: N450GA | C7: =IF($B$7="","",IFERROR(IF(INDEX(Aircraft!$T:$T,MATCH($B$7,Aircraft!$B:$B,0))="","OPERATOR NAME NOT SET ON Operators SHEET",INDEX(Aircraft!$T:$T,MATCH($B$7,Aircraft!$B:$B,0))),"TAIL NOT IN FLEET — OPERATOR CANNOT BE VERIFIED")) -> OPERATOR NAME NOT SET ON Operators SHEET | E7: BILLING ADDRESS | F7: =IF($F$5="","",IFERROR(INDEX(Clients!$E:$E,MATCH($F$5,Clients!$A:$A,0))&IF(INDEX(Clients!$F:$F,MATCH($F$5,Clients!$A:$A,0))="","",", "&INDEX(Clients!$F:$F,MATCH($F$5,Clients!$A:$A,0)))&", "&INDEX(Clients!$G:$G,MATCH($F$5,Clients!$A:$A,0))&", "&INDEX(Clients!$H:$H,MATCH($F$5,Clients!$A:$A,0)),"UNKNOWN CLIENT ID")) -> 12065 PARK VIEW LANE, HOUSTON TX, USA
A8: AIRCRAFT TYPE (ICAO) | B8: =IF($B$7="","",IFERROR(INDEX(Aircraft!$C:$C,MATCH($B$7,Aircraft!$B:$B,0)),"NOT IN FLEET")) -> GLF6 | E8: BILLING EMAIL | F8: =IF($F$5="","",IFERROR(INDEX(Clients!$K:$K,MATCH($F$5,Clients!$A:$A,0))&"","UNKNOWN CLIENT ID")) -> ops@jetelio.com
A9: MTOW (KG) | B9: =IF($B$7="","",IFERROR(INDEX(Aircraft!$H:$H,MATCH($B$7,Aircraft!$B:$B,0)),"NOT IN FLEET")) -> 45178 | E9: CURRENCY | F9: =IF($F$5="","",IFERROR(INDEX(Clients!$M:$M,MATCH($F$5,Clients!$A:$A,0))&"","UNKNOWN CLIENT ID")) -> USD
A10: BLOCK SPEED (KTS) | B10: 470 | C10: =IF($B$8="","",IFERROR("Published cruise for "&$B$8&" is "&TEXT(INDEX('AIRCRAFT PERFORMANCE'!$E:$E,MATCH($B$8,'AIRCRAFT PERFORMANCE'!$A:$A,0)),"#,##0")&" kts - indicative only","Type not in the performance table")) -> Published cruise for GLF6 is 488 kts - indicative only | E10: PAYMENT TERMS | F10: =IF($F$5="","",IFERROR(INDEX(Clients!$N:$N,MATCH($F$5,Clients!$A:$A,0))&"","UNKNOWN CLIENT ID")) -> NET 30
A11: TAXI / CLIMB ALLOWANCE (HRS) | B11: 0.4 | C11: Added to each leg's airborne time | E11: ACCOUNT OWNED BY OPERATOR | F11: =IF($F$5="","",IFERROR(INDEX(Clients!$B:$B,MATCH($F$5,Clients!$A:$A,0))&"","UNKNOWN CLIENT ID")) -> OPV-20
A12: DEFAULT PERMIT LEAD TIME (HRS) | B12: 72 | C12: Used when a country has no lead time in the countries sheet | E12: ACCOUNT CHECK | F12: =IF($F$5="","",IFERROR(IF(INDEX(Clients!$B:$B,MATCH($F$5,Clients!$A:$A,0))=INDEX(Aircraft!$N:$N,MATCH($B$7,Aircraft!$B:$B,0)),"OK","BILL-TO BELONGS TO A DIFFERENT OPERATOR"),"CANNOT VERIFY - TAIL NOT IN FLEET")) -> BILL-TO BELONGS TO A DIFFERENT OPERATOR
A13: TRIP DISTANCE (NM) | B13: =SUM($J$18:$J$25) -> 9947
A14: TRIP EET (HRS) | B14: =ROUND(SUM($K$18:$K$25),2) -> 22.76
A16: 2 · LEGS (up to 8 · leg 2+ departure defaults to the previous leg's arrival, overwrite if needed)
A17: LEG | B17: DEP ICAO | C17: DEP AIRPORT | D17: DEP COUNTRY | E17: ETD DATE | F17: ETD (Z) | G17: ARR ICAO | H17: ARR AIRPORT | I17: ARR COUNTRY | J17: DIST (NM) | K17: EET (HRS) | L17: ETA DATE | M17: ETA (Z) | N17: BILL TO (LEG) | O17: DEP LAT | P17: DEP LON | Q17: ARR LAT | R17: ARR LON | S17: GC ANGLE (RAD) | T17: DEP ISO3 | U17: ARR ISO3 | V17: AVOID STATES / FIR (country name) | W17: INCLUDE STATES / FIR (country name) | X17: ROUTE CHECK | Y17: RANGE CHECK | AH17: NATIONALITY | AI17: FIRST? | AJ17: NAT RANK | AK17: GROUND ISO3 | AL17: GROUND AIRPORT | AM17: GROUND LEG | AN17: GROUND DATETIME | AO17: FIRST? | AP17: GH RANK
A18: L1 | B18: FALA | C18: =IF($B18="","",IFERROR(INDEX(airports!$E:$E,MATCH($B18,airports!$A:$A,0)),"ICAO NOT IN AIRPORTS")) -> Lanseria International Airport | D18: =IF($B18="","",IFERROR(INDEX(airports!$H:$H,MATCH($B18,airports!$A:$A,0)),"")) -> South Africa | E18: 46248 | F18: 0.375 | G18: FTTJ | H18: =IF($G18="","",IFERROR(INDEX(airports!$E:$E,MATCH($G18,airports!$A:$A,0)),"ICAO NOT IN AIRPORTS")) -> N'Djamena International Airport | I18: =IF($G18="","",IFERROR(INDEX(airports!$H:$H,MATCH($G18,airports!$A:$A,0)),"")) -> Chad | J18: =IF($S18="","",ROUND($S18*3440.065,0)) -> 2407 | K18: =IF(OR($J18="",$B$10=""),"",ROUND($J18/$B$10+$B$11,2)) -> 5.52 | L18: =IF(OR($E18="",$K18=""),"",INT($E18+$F18+$K18/24)) -> 46248 | M18: =IF($L18="","",MOD($E18+$F18+$K18/24,1)) -> 0.605 | N18: =IF($B18="","",$F$5) -> CLI-001 | O18: =IF($B18="","",IFERROR(INDEX(airports!$O:$O,MATCH($B18,airports!$A:$A,0)),"")) -> -25.93896 | P18: =IF($B18="","",IFERROR(INDEX(airports!$P:$P,MATCH($B18,airports!$A:$A,0)),"")) -> 27.92664 | Q18: =IF($G18="","",IFERROR(INDEX(airports!$O:$O,MATCH($G18,airports!$A:$A,0)),"")) -> 12.1337 | R18: =IF($G18="","",IFERROR(INDEX(airports!$P:$P,MATCH($G18,airports!$A:$A,0)),"")) -> 15.034 | S18: =IF(OR($O18="",$Q18=""),"",ACOS(MIN(1,SIN(RADIANS($O18))*SIN(RADIANS($Q18))+COS(RADIANS($O18))*COS(RADIANS($Q18))*COS(RADIANS($R18-$P18))))) -> 0.69965352 | T18: {=IF($O18="","",IFERROR(IF(INDEX(geo_grid!$B$2:$JU$231,INT(($O18+40)/0.5)+1,INT(($P18+30)/0.5)+1)="","",INDEX(geo_grid!$B$2:$JU$231,INT(($O18+40)/0.5)+1,INT(($P18+30)/0.5)+1)),"OUTSIDE GRID"))} -> ZAF | U18: {=IF($Q18="","",IFERROR(IF(INDEX(geo_grid!$B$2:$JU$231,INT(($Q18+40)/0.5)+1,INT(($R18+30)/0.5)+1)="","",INDEX(geo_grid!$B$2:$JU$231,INT(($Q18+40)/0.5)+1,INT(($R18+30)/0.5)+1)),"OUTSIDE GRID"))} -> TCD | X18: {=IF($B18="","",IF(AND($V18="",$W18=""),"NO CONSTRAINT",TRIM(IF($V18="","",IF(SUMPRODUCT(--((ISNUMBER(SEARCH(","&permit_calc!$A$3:$A$144&",",","&SUBSTITUTE(UPPER($V18)," ","")&","))+ISNUMBER(SEARCH(","&SUBSTITUTE(UPPER(permit_calc!$B$3:$B$144)," ","")&",",","&SUBSTITUTE(UPPER($V18)," ","")&",")))>0),--(INDEX(permit_calc!$C$3:$J$144,0,ROW()-17)>0))>0,"AVOID CONFLICT - track crosses an excluded state. ",""))&IF($W18="","",IF(SUMPRODUCT(--((ISNUMBER(SEARCH(","&permit_calc!$A$3:$A$144&",",","&SUBSTITUTE(UPPER($W18)," ","")&","))+ISNUMBER(SEARCH(","&SUBSTITUTE(UPPER(permit_calc!$B$3:$B$144)," ","")&",",","&SUBSTITUTE(UPPER($W18)," ","")&",")))>0),--(INDEX(permit_calc!$C$3:$J$144,0,ROW()-17)>0))<LEN($W18)-LEN(SUBSTITUTE($W18,",",""))+1,"INCLUDE NOT ON TRACK - required state not overflown. ","")))))} -> NO CONSTRAINT | Y18: =IF($B18="","",IFERROR(IF($J18>INDEX('AIRCRAFT PERFORMANCE'!$I:$I,MATCH($B$8,'AIRCRAFT PERFORMANCE'!$A:$A,0)),"EXCEEDS PRACTICAL RANGE OF "&TEXT(INDEX('AIRCRAFT PERFORMANCE'!$I:$I,MATCH($B$8,'AIRCRAFT PERFORMANCE'!$A:$A,0)),"#,##0")&" NM - TECHNICAL STOP REQUIRED","WITHIN RANGE"),"TYPE NOT IN PERFORMANCE TABLE")) -> WITHIN RANGE | AH18: =IFERROR(INDEX('PAX & CREW'!$L$3:$L$62,MATCH(ROW()-17,'PAX & CREW'!$AJ$3:$AJ$62,0)),"") -> United States | AI18: =IF($AH18="","",IF(COUNTIF($AH$18:$AH18,$AH18)=1,1,0)) -> 1 | AJ18: =IF($AI18=1,SUM($AI$18:$AI18),"") -> 1 | AK18: =IF($B$18="","",$T$18) -> ZAF | AL18: =IF($B$18="","",$B$18) -> FALA | AM18: =IF($B$18="","","L1") -> L1 | AN18: =IF($B$18="","",$E$18+$F$18) -> 46248.375 | AO18: =IF($AK18="","",IF(COUNTIF($AK$18:$AK18,$AK18)=1,1,0)) -> 1 | AP18: =IF($AO18=1,SUM($AO$18:$AO18),"") -> 1
A19: L2 | B19: FTTJ | C19: =IF($B19="","",IFERROR(INDEX(airports!$E:$E,MATCH($B19,airports!$A:$A,0)),"ICAO NOT IN AIRPORTS")) -> N'Djamena International Airport | D19: =IF($B19="","",IFERROR(INDEX(airports!$H:$H,MATCH($B19,airports!$A:$A,0)),"")) -> Chad | E19: 46250 | F19: 0.25 | G19: HECA | H19: =IF($G19="","",IFERROR(INDEX(airports!$E:$E,MATCH($G19,airports!$A:$A,0)),"ICAO NOT IN AIRPORTS")) -> Cairo International Airport | I19: =IF($G19="","",IFERROR(INDEX(airports!$H:$H,MATCH($G19,airports!$A:$A,0)),"")) -> Egypt | J19: =IF($S19="","",ROUND($S19*3440.065,0)) -> 1412 | K19: =IF(OR($J19="",$B$10=""),"",ROUND($J19/$B$10+$B$11,2)) -> 3.4 | L19: =IF(OR($E19="",$K19=""),"",INT($E19+$F19+$K19/24)) -> 46250 | M19: =IF($L19="","",MOD($E19+$F19+$K19/24,1)) -> 0.39166667 | N19: =IF($B19="","",$F$5) -> CLI-001 | O19: =IF($B19="","",IFERROR(INDEX(airports!$O:$O,MATCH($B19,airports!$A:$A,0)),"")) -> 12.1337 | P19: =IF($B19="","",IFERROR(INDEX(airports!$P:$P,MATCH($B19,airports!$A:$A,0)),"")) -> 15.034 | Q19: =IF($G19="","",IFERROR(INDEX(airports!$O:$O,MATCH($G19,airports!$A:$A,0)),"")) -> 30.11153 | R19: =IF($G19="","",IFERROR(INDEX(airports!$P:$P,MATCH($G19,airports!$A:$A,0)),"")) -> 31.39669 | S19: =IF(OR($O19="",$Q19=""),"",ACOS(MIN(1,SIN(RADIANS($O19))*SIN(RADIANS($Q19))+COS(RADIANS($O19))*COS(RADIANS($Q19))*COS(RADIANS($R19-$P19))))) -> 0.41049814 | T19: {=IF($O19="","",IFERROR(IF(INDEX(geo_grid!$B$2:$JU$231,INT(($O19+40)/0.5)+1,INT(($P19+30)/0.5)+1)="","",INDEX(geo_grid!$B$2:$JU$231,INT(($O19+40)/0.5)+1,INT(($P19+30)/0.5)+1)),"OUTSIDE GRID"))} -> TCD | U19: {=IF($Q19="","",IFERROR(IF(INDEX(geo_grid!$B$2:$JU$231,INT(($Q19+40)/0.5)+1,INT(($R19+30)/0.5)+1)="","",INDEX(geo_grid!$B$2:$JU$231,INT(($Q19+40)/0.5)+1,INT(($R19+30)/0.5)+1)),"OUTSIDE GRID"))} -> EGY | X19: {=IF($B19="","",IF(AND($V19="",$W19=""),"NO CONSTRAINT",TRIM(IF($V19="","",IF(SUMPRODUCT(--((ISNUMBER(SEARCH(","&permit_calc!$A$3:$A$144&",",","&SUBSTITUTE(UPPER($V19)," ","")&","))+ISNUMBER(SEARCH(","&SUBSTITUTE(UPPER(permit_calc!$B$3:$B$144)," ","")&",",","&SUBSTITUTE(UPPER($V19)," ","")&",")))>0),--(INDEX(permit_calc!$C$3:$J$144,0,ROW()-17)>0))>0,"AVOID CONFLICT - track crosses an excluded state. ",""))&IF($W19="","",IF(SUMPRODUCT(--((ISNUMBER(SEARCH(","&permit_calc!$A$3:$A$144&",",","&SUBSTITUTE(UPPER($W19)," ","")&","))+ISNUMBER(SEARCH(","&SUBSTITUTE(UPPER(permit_calc!$B$3:$B$144)," ","")&",",","&SUBSTITUTE(UPPER($W19)," ","")&",")))>0),--(INDEX(permit_calc!$C$3:$J$144,0,ROW()-17)>0))<LEN($W19)-LEN(SUBSTITUTE($W19,",",""))+1,"INCLUDE NOT ON TRACK - required state not overflown. ","")))))} -> NO CONSTRAINT | Y19: =IF($B19="","",IFERROR(IF($J19>INDEX('AIRCRAFT PERFORMANCE'!$I:$I,MATCH($B$8,'AIRCRAFT PERFORMANCE'!$A:$A,0)),"EXCEEDS PRACTICAL RANGE OF "&TEXT(INDEX('AIRCRAFT PERFORMANCE'!$I:$I,MATCH($B$8,'AIRCRAFT PERFORMANCE'!$A:$A,0)),"#,##0")&" NM - TECHNICAL STOP REQUIRED","WITHIN RANGE"),"TYPE NOT IN PERFORMANCE TABLE")) -> WITHIN RANGE | AH19: =IFERROR(INDEX('PAX & CREW'!$L$3:$L$62,MATCH(ROW()-17,'PAX & CREW'!$AJ$3:$AJ$62,0)),"") -> South Africa | AI19: =IF($AH19="","",IF(COUNTIF($AH$18:$AH19,$AH19)=1,1,0)) -> 1 | AJ19: =IF($AI19=1,SUM($AI$18:$AI19),"") -> 2 | AK19: =IF($U18="","",$U18) -> TCD | AL19: =IF($U18="","",$G18) -> FTTJ | AM19: =IF($U18="","",$A18) -> L1 | AN19: =IF($U18="","",$L18+$M18) -> 46248.605 | AO19: =IF($AK19="","",IF(COUNTIF($AK$18:$AK19,$AK19)=1,1,0)) -> 1 | AP19: =IF($AO19=1,SUM($AO$18:$AO19),"") -> 2
A20: L3 | B20: HECA | C20: =IF($B20="","",IFERROR(INDEX(airports!$E:$E,MATCH($B20,airports!$A:$A,0)),"ICAO NOT IN AIRPORTS")) -> Cairo International Airport | D20: =IF($B20="","",IFERROR(INDEX(airports!$H:$H,MATCH($B20,airports!$A:$A,0)),"")) -> Egypt | E20: 46251 | F20: 0.16666667 | G20: GMAD | H20: =IF($G20="","",IFERROR(INDEX(airports!$E:$E,MATCH($G20,airports!$A:$A,0)),"ICAO NOT IN AIRPORTS")) -> Al Massira Airport | I20: =IF($G20="","",IFERROR(INDEX(airports!$H:$H,MATCH($G20,airports!$A:$A,0)),"")) -> Morocco | J20: =IF($S20="","",ROUND($S20*3440.065,0)) -> 2106 | K20: =IF(OR($J20="",$B$10=""),"",ROUND($J20/$B$10+$B$11,2)) -> 4.88 | L20: =IF(OR($E20="",$K20=""),"",INT($E20+$F20+$K20/24)) -> 46251 | M20: =IF($L20="","",MOD($E20+$F20+$K20/24,1)) -> 0.37 | N20: =IF($B20="","",$F$5) -> CLI-001 | O20: =IF($B20="","",IFERROR(INDEX(airports!$O:$O,MATCH($B20,airports!$A:$A,0)),"")) -> 30.11153 | P20: =IF($B20="","",IFERROR(INDEX(airports!$P:$P,MATCH($B20,airports!$A:$A,0)),"")) -> 31.39669 | Q20: =IF($G20="","",IFERROR(INDEX(airports!$O:$O,MATCH($G20,airports!$A:$A,0)),"")) -> 30.32248 | R20: =IF($G20="","",IFERROR(INDEX(airports!$P:$P,MATCH($G20,airports!$A:$A,0)),"")) -> -9.412 | S20: =IF(OR($O20="",$Q20=""),"",ACOS(MIN(1,SIN(RADIANS($O20))*SIN(RADIANS($Q20))+COS(RADIANS($O20))*COS(RADIANS($Q20))*COS(RADIANS($R20-$P20))))) -> 0.61206182 | T20: {=IF($O20="","",IFERROR(IF(INDEX(geo_grid!$B$2:$JU$231,INT(($O20+40)/0.5)+1,INT(($P20+30)/0.5)+1)="","",INDEX(geo_grid!$B$2:$JU$231,INT(($O20+40)/0.5)+1,INT(($P20+30)/0.5)+1)),"OUTSIDE GRID"))} -> EGY | U20: {=IF($Q20="","",IFERROR(IF(INDEX(geo_grid!$B$2:$JU$231,INT(($Q20+40)/0.5)+1,INT(($R20+30)/0.5)+1)="","",INDEX(geo_grid!$B$2:$JU$231,INT(($Q20+40)/0.5)+1,INT(($R20+30)/0.5)+1)),"OUTSIDE GRID"))} -> MAR | X20: {=IF($B20="","",IF(AND($V20="",$W20=""),"NO CONSTRAINT",TRIM(IF($V20="","",IF(SUMPRODUCT(--((ISNUMBER(SEARCH(","&permit_calc!$A$3:$A$144&",",","&SUBSTITUTE(UPPER($V20)," ","")&","))+ISNUMBER(SEARCH(","&SUBSTITUTE(UPPER(permit_calc!$B$3:$B$144)," ","")&",",","&SUBSTITUTE(UPPER($V20)," ","")&",")))>0),--(INDEX(permit_calc!$C$3:$J$144,0,ROW()-17)>0))>0,"AVOID CONFLICT - track crosses an excluded state. ",""))&IF($W20="","",IF(SUMPRODUCT(--((ISNUMBER(SEARCH(","&permit_calc!$A$3:$A$144&",",","&SUBSTITUTE(UPPER($W20)," ","")&","))+ISNUMBER(SEARCH(","&SUBSTITUTE(UPPER(permit_calc!$B$3:$B$144)," ","")&",",","&SUBSTITUTE(UPPER($W20)," ","")&",")))>0),--(INDEX(permit_calc!$C$3:$J$144,0,ROW()-17)>0))<LEN($W20)-LEN(SUBSTITUTE($W20,",",""))+1,"INCLUDE NOT ON TRACK - required state not overflown. ","")))))} -> NO CONSTRAINT | Y20: =IF($B20="","",IFERROR(IF($J20>INDEX('AIRCRAFT PERFORMANCE'!$I:$I,MATCH($B$8,'AIRCRAFT PERFORMANCE'!$A:$A,0)),"EXCEEDS PRACTICAL RANGE OF "&TEXT(INDEX('AIRCRAFT PERFORMANCE'!$I:$I,MATCH($B$8,'AIRCRAFT PERFORMANCE'!$A:$A,0)),"#,##0")&" NM - TECHNICAL STOP REQUIRED","WITHIN RANGE"),"TYPE NOT IN PERFORMANCE TABLE")) -> WITHIN RANGE | AH20: =IFERROR(INDEX('PAX & CREW'!$L$3:$L$62,MATCH(ROW()-17,'PAX & CREW'!$AJ$3:$AJ$62,0)),"") -> Oman | AI20: =IF($AH20="","",IF(COUNTIF($AH$18:$AH20,$AH20)=1,1,0)) -> 1 | AJ20: =IF($AI20=1,SUM($AI$18:$AI20),"") -> 3 | AK20: =IF($U19="","",$U19) -> EGY | AL20: =IF($U19="","",$G19) -> HECA | AM20: =IF($U19="","",$A19) -> L2 | AN20: =IF($U19="","",$L19+$M19) -> 46250.392 | AO20: =IF($AK20="","",IF(COUNTIF($AK$18:$AK20,$AK20)=1,1,0)) -> 1 | AP20: =IF($AO20=1,SUM($AO$18:$AO20),"") -> 3
A21: L4 | B21: GMAD | C21: =IF($B21="","",IFERROR(INDEX(airports!$E:$E,MATCH($B21,airports!$A:$A,0)),"ICAO NOT IN AIRPORTS")) -> Al Massira Airport | D21: =IF($B21="","",IFERROR(INDEX(airports!$H:$H,MATCH($B21,airports!$A:$A,0)),"")) -> Morocco | E21: 46253 | F21: 0.041666667 | G21: FAOR | H21: =IF($G21="","",IFERROR(INDEX(airports!$E:$E,MATCH($G21,airports!$A:$A,0)),"ICAO NOT IN AIRPORTS")) -> O.R. Tambo International Airport | I21: =IF($G21="","",IFERROR(INDEX(airports!$H:$H,MATCH($G21,airports!$A:$A,0)),"")) -> South Africa | J21: =IF($S21="","",ROUND($S21*3440.065,0)) -> 4022 | K21: =IF(OR($J21="",$B$10=""),"",ROUND($J21/$B$10+$B$11,2)) -> 8.96 | L21: =IF(OR($E21="",$K21=""),"",INT($E21+$F21+$K21/24)) -> 46253 | M21: =IF($L21="","",MOD($E21+$F21+$K21/24,1)) -> 0.415 | N21: CLI-002 | O21: =IF($B21="","",IFERROR(INDEX(airports!$O:$O,MATCH($B21,airports!$A:$A,0)),"")) -> 30.32248 | P21: =IF($B21="","",IFERROR(INDEX(airports!$P:$P,MATCH($B21,airports!$A:$A,0)),"")) -> -9.412 | Q21: =IF($G21="","",IFERROR(INDEX(airports!$O:$O,MATCH($G21,airports!$A:$A,0)),"")) -> -26.14008 | R21: =IF($G21="","",IFERROR(INDEX(airports!$P:$P,MATCH($G21,airports!$A:$A,0)),"")) -> 28.2468 | S21: =IF(OR($O21="",$Q21=""),"",ACOS(MIN(1,SIN(RADIANS($O21))*SIN(RADIANS($Q21))+COS(RADIANS($O21))*COS(RADIANS($Q21))*COS(RADIANS($R21-$P21))))) -> 1.1690355 | T21: {=IF($O21="","",IFERROR(IF(INDEX(geo_grid!$B$2:$JU$231,INT(($O21+40)/0.5)+1,INT(($P21+30)/0.5)+1)="","",INDEX(geo_grid!$B$2:$JU$231,INT(($O21+40)/0.5)+1,INT(($P21+30)/0.5)+1)),"OUTSIDE GRID"))} -> MAR | U21: {=IF($Q21="","",IFERROR(IF(INDEX(geo_grid!$B$2:$JU$231,INT(($Q21+40)/0.5)+1,INT(($R21+30)/0.5)+1)="","",INDEX(geo_grid!$B$2:$JU$231,INT(($Q21+40)/0.5)+1,INT(($R21+30)/0.5)+1)),"OUTSIDE GRID"))} -> ZAF | X21: {=IF($B21="","",IF(AND($V21="",$W21=""),"NO CONSTRAINT",TRIM(IF($V21="","",IF(SUMPRODUCT(--((ISNUMBER(SEARCH(","&permit_calc!$A$3:$A$144&",",","&SUBSTITUTE(UPPER($V21)," ","")&","))+ISNUMBER(SEARCH(","&SUBSTITUTE(UPPER(permit_calc!$B$3:$B$144)," ","")&",",","&SUBSTITUTE(UPPER($V21)," ","")&",")))>0),--(INDEX(permit_calc!$C$3:$J$144,0,ROW()-17)>0))>0,"AVOID CONFLICT - track crosses an excluded state. ",""))&IF($W21="","",IF(SUMPRODUCT(--((ISNUMBER(SEARCH(","&permit_calc!$A$3:$A$144&",",","&SUBSTITUTE(UPPER($W21)," ","")&","))+ISNUMBER(SEARCH(","&SUBSTITUTE(UPPER(permit_calc!$B$3:$B$144)," ","")&",",","&SUBSTITUTE(UPPER($W21)," ","")&",")))>0),--(INDEX(permit_calc!$C$3:$J$144,0,ROW()-17)>0))<LEN($W21)-LEN(SUBSTITUTE($W21,",",""))+1,"INCLUDE NOT ON TRACK - required state not overflown. ","")))))} -> NO CONSTRAINT | Y21: =IF($B21="","",IFERROR(IF($J21>INDEX('AIRCRAFT PERFORMANCE'!$I:$I,MATCH($B$8,'AIRCRAFT PERFORMANCE'!$A:$A,0)),"EXCEEDS PRACTICAL RANGE OF "&TEXT(INDEX('AIRCRAFT PERFORMANCE'!$I:$I,MATCH($B$8,'AIRCRAFT PERFORMANCE'!$A:$A,0)),"#,##0")&" NM - TECHNICAL STOP REQUIRED","WITHIN RANGE"),"TYPE NOT IN PERFORMANCE TABLE")) -> WITHIN RANGE | AH21: =IFERROR(INDEX('PAX & CREW'!$L$3:$L$62,MATCH(ROW()-17,'PAX & CREW'!$AJ$3:$AJ$62,0)),"") -> South Africa | AI21: =IF($AH21="","",IF(COUNTIF($AH$18:$AH21,$AH21)=1,1,0)) -> 0 | AJ21: =IF($AI21=1,SUM($AI$18:$AI21),"") | AK21: =IF($U20="","",$U20) -> MAR | AL21: =IF($U20="","",$G20) -> GMAD | AM21: =IF($U20="","",$A20) -> L3 | AN21: =IF($U20="","",$L20+$M20) -> 46251.37 | AO21: =IF($AK21="","",IF(COUNTIF($AK$18:$AK21,$AK21)=1,1,0)) -> 1 | AP21: =IF($AO21=1,SUM($AO$18:$AO21),"") -> 4
A22: L5 | C22: =IF($B22="","",IFERROR(INDEX(airports!$E:$E,MATCH($B22,airports!$A:$A,0)),"ICAO NOT IN AIRPORTS")) | D22: =IF($B22="","",IFERROR(INDEX(airports!$H:$H,MATCH($B22,airports!$A:$A,0)),"")) | H22: =IF($G22="","",IFERROR(INDEX(airports!$E:$E,MATCH($G22,airports!$A:$A,0)),"ICAO NOT IN AIRPORTS")) | I22: =IF($G22="","",IFERROR(INDEX(airports!$H:$H,MATCH($G22,airports!$A:$A,0)),"")) | J22: =IF($S22="","",ROUND($S22*3440.065,0)) | K22: =IF(OR($J22="",$B$10=""),"",ROUND($J22/$B$10+$B$11,2)) | L22: =IF(OR($E22="",$K22=""),"",INT($E22+$F22+$K22/24)) | M22: =IF($L22="","",MOD($E22+$F22+$K22/24,1)) | N22: =IF($B22="","",$F$5) | O22: =IF($B22="","",IFERROR(INDEX(airports!$O:$O,MATCH($B22,airports!$A:$A,0)),"")) | P22: =IF($B22="","",IFERROR(INDEX(airports!$P:$P,MATCH($B22,airports!$A:$A,0)),"")) | Q22: =IF($G22="","",IFERROR(INDEX(airports!$O:$O,MATCH($G22,airports!$A:$A,0)),"")) | R22: =IF($G22="","",IFERROR(INDEX(airports!$P:$P,MATCH($G22,airports!$A:$A,0)),"")) | S22: =IF(OR($O22="",$Q22=""),"",ACOS(MIN(1,SIN(RADIANS($O22))*SIN(RADIANS($Q22))+COS(RADIANS($O22))*COS(RADIANS($Q22))*COS(RADIANS($R22-$P22))))) | T22: {=IF($O22="","",IFERROR(IF(INDEX(geo_grid!$B$2:$JU$231,INT(($O22+40)/0.5)+1,INT(($P22+30)/0.5)+1)="","",INDEX(geo_grid!$B$2:$JU$231,INT(($O22+40)/0.5)+1,INT(($P22+30)/0.5)+1)),"OUTSIDE GRID"))} | U22: {=IF($Q22="","",IFERROR(IF(INDEX(geo_grid!$B$2:$JU$231,INT(($Q22+40)/0.5)+1,INT(($R22+30)/0.5)+1)="","",INDEX(geo_grid!$B$2:$JU$231,INT(($Q22+40)/0.5)+1,INT(($R22+30)/0.5)+1)),"OUTSIDE GRID"))} | X22: {=IF($B22="","",IF(AND($V22="",$W22=""),"NO CONSTRAINT",TRIM(IF($V22="","",IF(SUMPRODUCT(--((ISNUMBER(SEARCH(","&permit_calc!$A$3:$A$144&",",","&SUBSTITUTE(UPPER($V22)," ","")&","))+ISNUMBER(SEARCH(","&SUBSTITUTE(UPPER(permit_calc!$B$3:$B$144)," ","")&",",","&SUBSTITUTE(UPPER($V22)," ","")&",")))>0),--(INDEX(permit_calc!$C$3:$J$144,0,ROW()-17)>0))>0,"AVOID CONFLICT - track crosses an excluded state. ",""))&IF($W22="","",IF(SUMPRODUCT(--((ISNUMBER(SEARCH(","&permit_calc!$A$3:$A$144&",",","&SUBSTITUTE(UPPER($W22)," ","")&","))+ISNUMBER(SEARCH(","&SUBSTITUTE(UPPER(permit_calc!$B$3:$B$144)," ","")&",",","&SUBSTITUTE(UPPER($W22)," ","")&",")))>0),--(INDEX(permit_calc!$C$3:$J$144,0,ROW()-17)>0))<LEN($W22)-LEN(SUBSTITUTE($W22,",",""))+1,"INCLUDE NOT ON TRACK - required state not overflown. ","")))))} | Y22: =IF($B22="","",IFERROR(IF($J22>INDEX('AIRCRAFT PERFORMANCE'!$I:$I,MATCH($B$8,'AIRCRAFT PERFORMANCE'!$A:$A,0)),"EXCEEDS PRACTICAL RANGE OF "&TEXT(INDEX('AIRCRAFT PERFORMANCE'!$I:$I,MATCH($B$8,'AIRCRAFT PERFORMANCE'!$A:$A,0)),"#,##0")&" NM - TECHNICAL STOP REQUIRED","WITHIN RANGE"),"TYPE NOT IN PERFORMANCE TABLE")) | AH22: =IFERROR(INDEX('PAX & CREW'!$L$3:$L$62,MATCH(ROW()-17,'PAX & CREW'!$AJ$3:$AJ$62,0)),"") | AI22: =IF($AH22="","",IF(COUNTIF($AH$18:$AH22,$AH22)=1,1,0)) | AJ22: =IF($AI22=1,SUM($AI$18:$AI22),"") | AK22: =IF($U21="","",$U21) -> ZAF | AL22: =IF($U21="","",$G21) -> FAOR | AM22: =IF($U21="","",$A21) -> L4 | AN22: =IF($U21="","",$L21+$M21) -> 46253.415 | AO22: =IF($AK22="","",IF(COUNTIF($AK$18:$AK22,$AK22)=1,1,0)) -> 0 | AP22: =IF($AO22=1,SUM($AO$18:$AO22),"")
A23: L6 | B23: =IF($G22="","",$G22) | C23: =IF($B23="","",IFERROR(INDEX(airports!$E:$E,MATCH($B23,airports!$A:$A,0)),"ICAO NOT IN AIRPORTS")) | D23: =IF($B23="","",IFERROR(INDEX(airports!$H:$H,MATCH($B23,airports!$A:$A,0)),"")) | H23: =IF($G23="","",IFERROR(INDEX(airports!$E:$E,MATCH($G23,airports!$A:$A,0)),"ICAO NOT IN AIRPORTS")) | I23: =IF($G23="","",IFERROR(INDEX(airports!$H:$H,MATCH($G23,airports!$A:$A,0)),"")) | J23: =IF($S23="","",ROUND($S23*3440.065,0)) | K23: =IF(OR($J23="",$B$10=""),"",ROUND($J23/$B$10+$B$11,2)) | L23: =IF(OR($E23="",$K23=""),"",INT($E23+$F23+$K23/24)) | M23: =IF($L23="","",MOD($E23+$F23+$K23/24,1)) | N23: =IF($B23="","",$F$5) | O23: =IF($B23="","",IFERROR(INDEX(airports!$O:$O,MATCH($B23,airports!$A:$A,0)),"")) | P23: =IF($B23="","",IFERROR(INDEX(airports!$P:$P,MATCH($B23,airports!$A:$A,0)),"")) | Q23: =IF($G23="","",IFERROR(INDEX(airports!$O:$O,MATCH($G23,airports!$A:$A,0)),"")) | R23: =IF($G23="","",IFERROR(INDEX(airports!$P:$P,MATCH($G23,airports!$A:$A,0)),"")) | S23: =IF(OR($O23="",$Q23=""),"",ACOS(MIN(1,SIN(RADIANS($O23))*SIN(RADIANS($Q23))+COS(RADIANS($O23))*COS(RADIANS($Q23))*COS(RADIANS($R23-$P23))))) | T23: {=IF($O23="","",IFERROR(IF(INDEX(geo_grid!$B$2:$JU$231,INT(($O23+40)/0.5)+1,INT(($P23+30)/0.5)+1)="","",INDEX(geo_grid!$B$2:$JU$231,INT(($O23+40)/0.5)+1,INT(($P23+30)/0.5)+1)),"OUTSIDE GRID"))} | U23: {=IF($Q23="","",IFERROR(IF(INDEX(geo_grid!$B$2:$JU$231,INT(($Q23+40)/0.5)+1,INT(($R23+30)/0.5)+1)="","",INDEX(geo_grid!$B$2:$JU$231,INT(($Q23+40)/0.5)+1,INT(($R23+30)/0.5)+1)),"OUTSIDE GRID"))} | X23: {=IF($B23="","",IF(AND($V23="",$W23=""),"NO CONSTRAINT",TRIM(IF($V23="","",IF(SUMPRODUCT(--((ISNUMBER(SEARCH(","&permit_calc!$A$3:$A$144&",",","&SUBSTITUTE(UPPER($V23)," ","")&","))+ISNUMBER(SEARCH(","&SUBSTITUTE(UPPER(permit_calc!$B$3:$B$144)," ","")&",",","&SUBSTITUTE(UPPER($V23)," ","")&",")))>0),--(INDEX(permit_calc!$C$3:$J$144,0,ROW()-17)>0))>0,"AVOID CONFLICT - track crosses an excluded state. ",""))&IF($W23="","",IF(SUMPRODUCT(--((ISNUMBER(SEARCH(","&permit_calc!$A$3:$A$144&",",","&SUBSTITUTE(UPPER($W23)," ","")&","))+ISNUMBER(SEARCH(","&SUBSTITUTE(UPPER(permit_calc!$B$3:$B$144)," ","")&",",","&SUBSTITUTE(UPPER($W23)," ","")&",")))>0),--(INDEX(permit_calc!$C$3:$J$144,0,ROW()-17)>0))<LEN($W23)-LEN(SUBSTITUTE($W23,",",""))+1,"INCLUDE NOT ON TRACK - required state not overflown. ","")))))} | Y23: =IF($B23="","",IFERROR(IF($J23>INDEX('AIRCRAFT PERFORMANCE'!$I:$I,MATCH($B$8,'AIRCRAFT PERFORMANCE'!$A:$A,0)),"EXCEEDS PRACTICAL RANGE OF "&TEXT(INDEX('AIRCRAFT PERFORMANCE'!$I:$I,MATCH($B$8,'AIRCRAFT PERFORMANCE'!$A:$A,0)),"#,##0")&" NM - TECHNICAL STOP REQUIRED","WITHIN RANGE"),"TYPE NOT IN PERFORMANCE TABLE")) | AH23: =IFERROR(INDEX('PAX & CREW'!$L$3:$L$62,MATCH(ROW()-17,'PAX & CREW'!$AJ$3:$AJ$62,0)),"") | AI23: =IF($AH23="","",IF(COUNTIF($AH$18:$AH23,$AH23)=1,1,0)) | AJ23: =IF($AI23=1,SUM($AI$18:$AI23),"") | AK23: =IF($U22="","",$U22) | AL23: =IF($U22="","",$G22) | AM23: =IF($U22="","",$A22) | AN23: =IF($U22="","",$L22+$M22) | AO23: =IF($AK23="","",IF(COUNTIF($AK$18:$AK23,$AK23)=1,1,0)) | AP23: =IF($AO23=1,SUM($AO$18:$AO23),"")
A24: L7 | B24: =IF($G23="","",$G23) | C24: =IF($B24="","",IFERROR(INDEX(airports!$E:$E,MATCH($B24,airports!$A:$A,0)),"ICAO NOT IN AIRPORTS")) | D24: =IF($B24="","",IFERROR(INDEX(airports!$H:$H,MATCH($B24,airports!$A:$A,0)),"")) | H24: =IF($G24="","",IFERROR(INDEX(airports!$E:$E,MATCH($G24,airports!$A:$A,0)),"ICAO NOT IN AIRPORTS")) | I24: =IF($G24="","",IFERROR(INDEX(airports!$H:$H,MATCH($G24,airports!$A:$A,0)),"")) | J24: =IF($S24="","",ROUND($S24*3440.065,0)) | K24: =IF(OR($J24="",$B$10=""),"",ROUND($J24/$B$10+$B$11,2)) | L24: =IF(OR($E24="",$K24=""),"",INT($E24+$F24+$K24/24)) | M24: =IF($L24="","",MOD($E24+$F24+$K24/24,1)) | N24: =IF($B24="","",$F$5) | O24: =IF($B24="","",IFERROR(INDEX(airports!$O:$O,MATCH($B24,airports!$A:$A,0)),"")) | P24: =IF($B24="","",IFERROR(INDEX(airports!$P:$P,MATCH($B24,airports!$A:$A,0)),"")) | Q24: =IF($G24="","",IFERROR(INDEX(airports!$O:$O,MATCH($G24,airports!$A:$A,0)),"")) | R24: =IF($G24="","",IFERROR(INDEX(airports!$P:$P,MATCH($G24,airports!$A:$A,0)),"")) | S24: =IF(OR($O24="",$Q24=""),"",ACOS(MIN(1,SIN(RADIANS($O24))*SIN(RADIANS($Q24))+COS(RADIANS($O24))*COS(RADIANS($Q24))*COS(RADIANS($R24-$P24))))) | T24: {=IF($O24="","",IFERROR(IF(INDEX(geo_grid!$B$2:$JU$231,INT(($O24+40)/0.5)+1,INT(($P24+30)/0.5)+1)="","",INDEX(geo_grid!$B$2:$JU$231,INT(($O24+40)/0.5)+1,INT(($P24+30)/0.5)+1)),"OUTSIDE GRID"))} | U24: {=IF($Q24="","",IFERROR(IF(INDEX(geo_grid!$B$2:$JU$231,INT(($Q24+40)/0.5)+1,INT(($R24+30)/0.5)+1)="","",INDEX(geo_grid!$B$2:$JU$231,INT(($Q24+40)/0.5)+1,INT(($R24+30)/0.5)+1)),"OUTSIDE GRID"))} | X24: {=IF($B24="","",IF(AND($V24="",$W24=""),"NO CONSTRAINT",TRIM(IF($V24="","",IF(SUMPRODUCT(--((ISNUMBER(SEARCH(","&permit_calc!$A$3:$A$144&",",","&SUBSTITUTE(UPPER($V24)," ","")&","))+ISNUMBER(SEARCH(","&SUBSTITUTE(UPPER(permit_calc!$B$3:$B$144)," ","")&",",","&SUBSTITUTE(UPPER($V24)," ","")&",")))>0),--(INDEX(permit_calc!$C$3:$J$144,0,ROW()-17)>0))>0,"AVOID CONFLICT - track crosses an excluded state. ",""))&IF($W24="","",IF(SUMPRODUCT(--((ISNUMBER(SEARCH(","&permit_calc!$A$3:$A$144&",",","&SUBSTITUTE(UPPER($W24)," ","")&","))+ISNUMBER(SEARCH(","&SUBSTITUTE(UPPER(permit_calc!$B$3:$B$144)," ","")&",",","&SUBSTITUTE(UPPER($W24)," ","")&",")))>0),--(INDEX(permit_calc!$C$3:$J$144,0,ROW()-17)>0))<LEN($W24)-LEN(SUBSTITUTE($W24,",",""))+1,"INCLUDE NOT ON TRACK - required state not overflown. ","")))))} | Y24: =IF($B24="","",IFERROR(IF($J24>INDEX('AIRCRAFT PERFORMANCE'!$I:$I,MATCH($B$8,'AIRCRAFT PERFORMANCE'!$A:$A,0)),"EXCEEDS PRACTICAL RANGE OF "&TEXT(INDEX('AIRCRAFT PERFORMANCE'!$I:$I,MATCH($B$8,'AIRCRAFT PERFORMANCE'!$A:$A,0)),"#,##0")&" NM - TECHNICAL STOP REQUIRED","WITHIN RANGE"),"TYPE NOT IN PERFORMANCE TABLE")) | AH24: =IFERROR(INDEX('PAX & CREW'!$L$3:$L$62,MATCH(ROW()-17,'PAX & CREW'!$AJ$3:$AJ$62,0)),"") | AI24: =IF($AH24="","",IF(COUNTIF($AH$18:$AH24,$AH24)=1,1,0)) | AJ24: =IF($AI24=1,SUM($AI$18:$AI24),"") | AK24: =IF($U23="","",$U23) | AL24: =IF($U23="","",$G23) | AM24: =IF($U23="","",$A23) | AN24: =IF($U23="","",$L23+$M23) | AO24: =IF($AK24="","",IF(COUNTIF($AK$18:$AK24,$AK24)=1,1,0)) | AP24: =IF($AO24=1,SUM($AO$18:$AO24),"")
A25: L8 | B25: =IF($G24="","",$G24) | C25: =IF($B25="","",IFERROR(INDEX(airports!$E:$E,MATCH($B25,airports!$A:$A,0)),"ICAO NOT IN AIRPORTS")) | D25: =IF($B25="","",IFERROR(INDEX(airports!$H:$H,MATCH($B25,airports!$A:$A,0)),"")) | H25: =IF($G25="","",IFERROR(INDEX(airports!$E:$E,MATCH($G25,airports!$A:$A,0)),"ICAO NOT IN AIRPORTS")) | I25: =IF($G25="","",IFERROR(INDEX(airports!$H:$H,MATCH($G25,airports!$A:$A,0)),"")) | J25: =IF($S25="","",ROUND($S25*3440.065,0)) | K25: =IF(OR($J25="",$B$10=""),"",ROUND($J25/$B$10+$B$11,2)) | L25: =IF(OR($E25="",$K25=""),"",INT($E25+$F25+$K25/24)) | M25: =IF($L25="","",MOD($E25+$F25+$K25/24,1)) | N25: =IF($B25="","",$F$5) | O25: =IF($B25="","",IFERROR(INDEX(airports!$O:$O,MATCH($B25,airports!$A:$A,0)),"")) | P25: =IF($B25="","",IFERROR(INDEX(airports!$P:$P,MATCH($B25,airports!$A:$A,0)),"")) | Q25: =IF($G25="","",IFERROR(INDEX(airports!$O:$O,MATCH($G25,airports!$A:$A,0)),"")) | R25: =IF($G25="","",IFERROR(INDEX(airports!$P:$P,MATCH($G25,airports!$A:$A,0)),"")) | S25: =IF(OR($O25="",$Q25=""),"",ACOS(MIN(1,SIN(RADIANS($O25))*SIN(RADIANS($Q25))+COS(RADIANS($O25))*COS(RADIANS($Q25))*COS(RADIANS($R25-$P25))))) | T25: {=IF($O25="","",IFERROR(IF(INDEX(geo_grid!$B$2:$JU$231,INT(($O25+40)/0.5)+1,INT(($P25+30)/0.5)+1)="","",INDEX(geo_grid!$B$2:$JU$231,INT(($O25+40)/0.5)+1,INT(($P25+30)/0.5)+1)),"OUTSIDE GRID"))} | U25: {=IF($Q25="","",IFERROR(IF(INDEX(geo_grid!$B$2:$JU$231,INT(($Q25+40)/0.5)+1,INT(($R25+30)/0.5)+1)="","",INDEX(geo_grid!$B$2:$JU$231,INT(($Q25+40)/0.5)+1,INT(($R25+30)/0.5)+1)),"OUTSIDE GRID"))} | X25: {=IF($B25="","",IF(AND($V25="",$W25=""),"NO CONSTRAINT",TRIM(IF($V25="","",IF(SUMPRODUCT(--((ISNUMBER(SEARCH(","&permit_calc!$A$3:$A$144&",",","&SUBSTITUTE(UPPER($V25)," ","")&","))+ISNUMBER(SEARCH(","&SUBSTITUTE(UPPER(permit_calc!$B$3:$B$144)," ","")&",",","&SUBSTITUTE(UPPER($V25)," ","")&",")))>0),--(INDEX(permit_calc!$C$3:$J$144,0,ROW()-17)>0))>0,"AVOID CONFLICT - track crosses an excluded state. ",""))&IF($W25="","",IF(SUMPRODUCT(--((ISNUMBER(SEARCH(","&permit_calc!$A$3:$A$144&",",","&SUBSTITUTE(UPPER($W25)," ","")&","))+ISNUMBER(SEARCH(","&SUBSTITUTE(UPPER(permit_calc!$B$3:$B$144)," ","")&",",","&SUBSTITUTE(UPPER($W25)," ","")&",")))>0),--(INDEX(permit_calc!$C$3:$J$144,0,ROW()-17)>0))<LEN($W25)-LEN(SUBSTITUTE($W25,",",""))+1,"INCLUDE NOT ON TRACK - required state not overflown. ","")))))} | Y25: =IF($B25="","",IFERROR(IF($J25>INDEX('AIRCRAFT PERFORMANCE'!$I:$I,MATCH($B$8,'AIRCRAFT PERFORMANCE'!$A:$A,0)),"EXCEEDS PRACTICAL RANGE OF "&TEXT(INDEX('AIRCRAFT PERFORMANCE'!$I:$I,MATCH($B$8,'AIRCRAFT PERFORMANCE'!$A:$A,0)),"#,##0")&" NM - TECHNICAL STOP REQUIRED","WITHIN RANGE"),"TYPE NOT IN PERFORMANCE TABLE")) | AH25: =IFERROR(INDEX('PAX & CREW'!$L$3:$L$62,MATCH(ROW()-17,'PAX & CREW'!$AJ$3:$AJ$62,0)),"") | AI25: =IF($AH25="","",IF(COUNTIF($AH$18:$AH25,$AH25)=1,1,0)) | AJ25: =IF($AI25=1,SUM($AI$18:$AI25),"") | AK25: =IF($U24="","",$U24) | AL25: =IF($U24="","",$G24) | AM25: =IF($U24="","",$A24) | AN25: =IF($U24="","",$L24+$M24) | AO25: =IF($AK25="","",IF(COUNTIF($AK$18:$AK25,$AK25)=1,1,0)) | AP25: =IF($AO25=1,SUM($AO$18:$AO25),"")
A26: TOTALS | J26: =SUM($J$18:$J$25) -> 9947 | K26: =ROUND(SUM($K$18:$K$25),2) -> 22.76 | L26: =IF(OR($E26="",$K26=""),"",INT($E26+$F26+$K26/24)) | M26: =IF($L26="","",MOD($E26+$F26+$K26/24,1)) | AH26: =IFERROR(INDEX('PAX & CREW'!$L$3:$L$62,MATCH(ROW()-17,'PAX & CREW'!$AJ$3:$AJ$62,0)),"") | AI26: =IF($AH26="","",IF(COUNTIF($AH$18:$AH26,$AH26)=1,1,0)) | AJ26: =IF($AI26=1,SUM($AI$18:$AI26),"") | AK26: =IF($U25="","",$U25) | AL26: =IF($U25="","",$G25) | AM26: =IF($U25="","",$A25) | AN26: =IF($U25="","",$L25+$M25) | AO26: =IF($AK26="","",IF(COUNTIF($AK$18:$AK26,$AK26)=1,1,0)) | AP26: =IF($AO26=1,SUM($AO$18:$AO26),"")
V27: Enter ISO3 codes separated by commas, e.g. LBY, SDN. FIR boundaries are approximated by state airspace — verify against the AIP. AVOID flags a conflict when the great-circle track crosses an excluded state; INCLUDE flags when a required state is not on track. Re-route by inserting a technical stop or adjusting the leg. | AH27: =IFERROR(INDEX('PAX & CREW'!$L$3:$L$62,MATCH(ROW()-17,'PAX & CREW'!$AJ$3:$AJ$62,0)),"") | AI27: =IF($AH27="","",IF(COUNTIF($AH$18:$AH27,$AH27)=1,1,0)) | AJ27: =IF($AI27=1,SUM($AI$18:$AI27),"")
A28: 3 · PERMITS (overflight for every en-route country except the leg's departure state and its destination; the destination raises a landing permit — ground services are in section 4) | AH28: =IFERROR(INDEX('PAX & CREW'!$L$3:$L$62,MATCH(ROW()-17,'PAX & CREW'!$AJ$3:$AJ$62,0)),"") | AI28: =IF($AH28="","",IF(COUNTIF($AH$18:$AH28,$AH28)=1,1,0)) | AJ28: =IF($AI28=1,SUM($AI$18:$AI28),"")
A29: # | B29: COUNTRY | C29: ISO3 | D29: PERMIT TYPE | E29: AIRPORT | F29: LEGS | G29: PROVIDER | H29: REF DATE (UTC) | I29: LEAD TIME (HRS) | J29: FILE BY (UTC) | K29: DAYS TO DEADLINE | L29: REQUIRED | M29: STATUS | AE29: ROW KIND | AF29: LEG INDEX | AH29: =IFERROR(INDEX('PAX & CREW'!$L$3:$L$62,MATCH(ROW()-17,'PAX & CREW'!$AJ$3:$AJ$62,0)),"") | AI29: =IF($AH29="","",IF(COUNTIF($AH$18:$AH29,$AH29)=1,1,0)) | AJ29: =IF($AI29=1,SUM($AI$18:$AI29),"")
A30: =IF(ROW()-29>COUNTIF(permit_calc!$L$3:$L$144,1)+COUNTA($G$18:$G$25),"",ROW()-29) -> 1 | B30: =IF($A30="","",IF($AE30="OVF",INDEX(permit_calc!$B$3:$B$144,MATCH($A30,permit_calc!$N$3:$N$144,0)),IFERROR(INDEX(countries!$B:$B,MATCH($C30,countries!$D:$D,0)),$C30))) -> Botswana | C30: {=IF($A30="","",IF($AE30="OVF",INDEX(permit_calc!$A$3:$A$144,MATCH($A30,permit_calc!$N$3:$N$144,0)),INDEX($U$18:$U$25,$AF30)))} -> BWA | D30: =IF($A30="","",$AE30) -> OVF | E30: {=IF($A30="","",IF($AE30="OVF","",INDEX($G$18:$G$25,$AF30)))} | F30: {=IF($A30="","",IF($AE30="OVF",INDEX(permit_calc!$M$3:$M$144,MATCH($A30,permit_calc!$N$3:$N$144,0)),INDEX($A$18:$A$25,$AF30)))} -> L1, L4 | G30: JTL | H30: {=IF($A30="","",IF($AE30="OVF",INDEX($E$18:$E$25,INDEX(permit_calc!$O$3:$O$144,MATCH($A30,permit_calc!$N$3:$N$144,0)))+INDEX($F$18:$F$25,INDEX(permit_calc!$O$3:$O$144,MATCH($A30,permit_calc!$N$3:$N$144,0))),INDEX($L$18:$L$25,$AF30)+INDEX($M$18:$M$25,$AF30)))} -> 46248.375 | I30: =IF($A30="","",IFERROR(IF(INDEX(countries!$I:$I,MATCH($C30,countries!$D:$D,0))=0,$B$12,INDEX(countries!$I:$I,MATCH($C30,countries!$D:$D,0))),$B$12)) -> 72 | J30: =IF($A30="","",$H30-$I30/24) -> 46245.375 | K30: =IF($A30="","",ROUND($J30-NOW(),1)) -> 1.8 | L30: =IF($A30="","",IF($AE30="OVF",IFERROR(INDEX(countries!$G:$G,MATCH($C30,countries!$D:$D,0)),"VERIFY"),IFERROR(INDEX(countries!$H:$H,MATCH($C30,countries!$D:$D,0)),"VERIFY"))) -> REQUIRED | M30: =IF($A30="","",IF(OR(UPPER($G30)="OWN",UPPER($G30)="EXCLUDED"),"CLIENT ARRANGING",IF($K30<0,"OVERDUE",IF($K30<1,"URGENT - FILE NOW",IF($K30<3,"DUE SOON","PENDING"))))) -> DUE SOON | AE30: =IF($A30="","",IF($A30<=COUNTIF(permit_calc!$L$3:$L$144,1),"OVF","LDG")) -> OVF | AF30: =IF($AE30="","",IF($AE30="OVF","",$A30-COUNTIF(permit_calc!$L$3:$L$144,1))) | AH30: =IFERROR(INDEX('PAX & CREW'!$L$3:$L$62,MATCH(ROW()-17,'PAX & CREW'!$AJ$3:$AJ$62,0)),"") | AI30: =IF($AH30="","",IF(COUNTIF($AH$18:$AH30,$AH30)=1,1,0)) | AJ30: =IF($AI30=1,SUM($AI$18:$AI30),"")
A31: =IF(ROW()-29>COUNTIF(permit_calc!$L$3:$L$144,1)+COUNTA($G$18:$G$25),"",ROW()-29) -> 2 | B31: =IF($A31="","",IF($AE31="OVF",INDEX(permit_calc!$B$3:$B$144,MATCH($A31,permit_calc!$N$3:$N$144,0)),IFERROR(INDEX(countries!$B:$B,MATCH($C31,countries!$D:$D,0)),$C31))) -> Namibia | C31: {=IF($A31="","",IF($AE31="OVF",INDEX(permit_calc!$A$3:$A$144,MATCH($A31,permit_calc!$N$3:$N$144,0)),INDEX($U$18:$U$25,$AF31)))} -> NAM | D31: =IF($A31="","",$AE31) -> OVF | E31: {=IF($A31="","",IF($AE31="OVF","",INDEX($G$18:$G$25,$AF31)))} | F31: {=IF($A31="","",IF($AE31="OVF",INDEX(permit_calc!$M$3:$M$144,MATCH($A31,permit_calc!$N$3:$N$144,0)),INDEX($A$18:$A$25,$AF31)))} -> L1, L4 | G31: JTL | H31: {=IF($A31="","",IF($AE31="OVF",INDEX($E$18:$E$25,INDEX(permit_calc!$O$3:$O$144,MATCH($A31,permit_calc!$N$3:$N$144,0)))+INDEX($F$18:$F$25,INDEX(permit_calc!$O$3:$O$144,MATCH($A31,permit_calc!$N$3:$N$144,0))),INDEX($L$18:$L$25,$AF31)+INDEX($M$18:$M$25,$AF31)))} -> 46248.375 | I31: =IF($A31="","",IFERROR(IF(INDEX(countries!$I:$I,MATCH($C31,countries!$D:$D,0))=0,$B$12,INDEX(countries!$I:$I,MATCH($C31,countries!$D:$D,0))),$B$12)) -> 72 | J31: =IF($A31="","",$H31-$I31/24) -> 46245.375 | K31: =IF($A31="","",ROUND($J31-NOW(),1)) -> 1.8 | L31: =IF($A31="","",IF($AE31="OVF",IFERROR(INDEX(countries!$G:$G,MATCH($C31,countries!$D:$D,0)),"VERIFY"),IFERROR(INDEX(countries!$H:$H,MATCH($C31,countries!$D:$D,0)),"VERIFY"))) -> REQUIRED | M31: =IF($A31="","",IF(OR(UPPER($G31)="OWN",UPPER($G31)="EXCLUDED"),"CLIENT ARRANGING",IF($K31<0,"OVERDUE",IF($K31<1,"URGENT - FILE NOW",IF($K31<3,"DUE SOON","PENDING"))))) -> DUE SOON | AE31: =IF($A31="","",IF($A31<=COUNTIF(permit_calc!$L$3:$L$144,1),"OVF","LDG")) -> OVF | AF31: =IF($AE31="","",IF($AE31="OVF","",$A31-COUNTIF(permit_calc!$L$3:$L$144,1))) | AH31: =IFERROR(INDEX('PAX & CREW'!$L$3:$L$62,MATCH(ROW()-17,'PAX & CREW'!$AJ$3:$AJ$62,0)),"") | AI31: =IF($AH31="","",IF(COUNTIF($AH$18:$AH31,$AH31)=1,1,0)) | AJ31: =IF($AI31=1,SUM($AI$18:$AI31),"")
A32: =IF(ROW()-29>COUNTIF(permit_calc!$L$3:$L$144,1)+COUNTA($G$18:$G$25),"",ROW()-29) -> 3 | B32: =IF($A32="","",IF($AE32="OVF",INDEX(permit_calc!$B$3:$B$144,MATCH($A32,permit_calc!$N$3:$N$144,0)),IFERROR(INDEX(countries!$B:$B,MATCH($C32,countries!$D:$D,0)),$C32))) -> Zambia | C32: {=IF($A32="","",IF($AE32="OVF",INDEX(permit_calc!$A$3:$A$144,MATCH($A32,permit_calc!$N$3:$N$144,0)),INDEX($U$18:$U$25,$AF32)))} -> ZMB | D32: =IF($A32="","",$AE32) -> OVF | E32: {=IF($A32="","",IF($AE32="OVF","",INDEX($G$18:$G$25,$AF32)))} | F32: {=IF($A32="","",IF($AE32="OVF",INDEX(permit_calc!$M$3:$M$144,MATCH($A32,permit_calc!$N$3:$N$144,0)),INDEX($A$18:$A$25,$AF32)))} -> L1 | G32: JTL | H32: {=IF($A32="","",IF($AE32="OVF",INDEX($E$18:$E$25,INDEX(permit_calc!$O$3:$O$144,MATCH($A32,permit_calc!$N$3:$N$144,0)))+INDEX($F$18:$F$25,INDEX(permit_calc!$O$3:$O$144,MATCH($A32,permit_calc!$N$3:$N$144,0))),INDEX($L$18:$L$25,$AF32)+INDEX($M$18:$M$25,$AF32)))} -> 46248.375 | I32: =IF($A32="","",IFERROR(IF(INDEX(countries!$I:$I,MATCH($C32,countries!$D:$D,0))=0,$B$12,INDEX(countries!$I:$I,MATCH($C32,countries!$D:$D,0))),$B$12)) -> 72 | J32: =IF($A32="","",$H32-$I32/24) -> 46245.375 | K32: =IF($A32="","",ROUND($J32-NOW(),1)) -> 1.8 | L32: =IF($A32="","",IF($AE32="OVF",IFERROR(INDEX(countries!$G:$G,MATCH($C32,countries!$D:$D,0)),"VERIFY"),IFERROR(INDEX(countries!$H:$H,MATCH($C32,countries!$D:$D,0)),"VERIFY"))) -> REQUIRED | M32: =IF($A32="","",IF(OR(UPPER($G32)="OWN",UPPER($G32)="EXCLUDED"),"CLIENT ARRANGING",IF($K32<0,"OVERDUE",IF($K32<1,"URGENT - FILE NOW",IF($K32<3,"DUE SOON","PENDING"))))) -> DUE SOON | AE32: =IF($A32="","",IF($A32<=COUNTIF(permit_calc!$L$3:$L$144,1),"OVF","LDG")) -> OVF | AF32: =IF($AE32="","",IF($AE32="OVF","",$A32-COUNTIF(permit_calc!$L$3:$L$144,1))) | AH32: =IFERROR(INDEX('PAX & CREW'!$L$3:$L$62,MATCH(ROW()-17,'PAX & CREW'!$AJ$3:$AJ$62,0)),"") | AI32: =IF($AH32="","",IF(COUNTIF($AH$18:$AH32,$AH32)=1,1,0)) | AJ32: =IF($AI32=1,SUM($AI$18:$AI32),"")
A33: =IF(ROW()-29>COUNTIF(permit_calc!$L$3:$L$144,1)+COUNTA($G$18:$G$25),"",ROW()-29) -> 4 | B33: =IF($A33="","",IF($AE33="OVF",INDEX(permit_calc!$B$3:$B$144,MATCH($A33,permit_calc!$N$3:$N$144,0)),IFERROR(INDEX(countries!$B:$B,MATCH($C33,countries!$D:$D,0)),$C33))) -> Angola | C33: {=IF($A33="","",IF($AE33="OVF",INDEX(permit_calc!$A$3:$A$144,MATCH($A33,permit_calc!$N$3:$N$144,0)),INDEX($U$18:$U$25,$AF33)))} -> AGO | D33: =IF($A33="","",$AE33) -> OVF | E33: {=IF($A33="","",IF($AE33="OVF","",INDEX($G$18:$G$25,$AF33)))} | F33: {=IF($A33="","",IF($AE33="OVF",INDEX(permit_calc!$M$3:$M$144,MATCH($A33,permit_calc!$N$3:$N$144,0)),INDEX($A$18:$A$25,$AF33)))} -> L1, L4 | G33: JTL | H33: {=IF($A33="","",IF($AE33="OVF",INDEX($E$18:$E$25,INDEX(permit_calc!$O$3:$O$144,MATCH($A33,permit_calc!$N$3:$N$144,0)))+INDEX($F$18:$F$25,INDEX(permit_calc!$O$3:$O$144,MATCH($A33,permit_calc!$N$3:$N$144,0))),INDEX($L$18:$L$25,$AF33)+INDEX($M$18:$M$25,$AF33)))} -> 46248.375 | I33: =IF($A33="","",IFERROR(IF(INDEX(countries!$I:$I,MATCH($C33,countries!$D:$D,0))=0,$B$12,INDEX(countries!$I:$I,MATCH($C33,countries!$D:$D,0))),$B$12)) -> 72 | J33: =IF($A33="","",$H33-$I33/24) -> 46245.375 | K33: =IF($A33="","",ROUND($J33-NOW(),1)) -> 1.8 | L33: =IF($A33="","",IF($AE33="OVF",IFERROR(INDEX(countries!$G:$G,MATCH($C33,countries!$D:$D,0)),"VERIFY"),IFERROR(INDEX(countries!$H:$H,MATCH($C33,countries!$D:$D,0)),"VERIFY"))) -> REQUIRED | M33: =IF($A33="","",IF(OR(UPPER($G33)="OWN",UPPER($G33)="EXCLUDED"),"CLIENT ARRANGING",IF($K33<0,"OVERDUE",IF($K33<1,"URGENT - FILE NOW",IF($K33<3,"DUE SOON","PENDING"))))) -> DUE SOON | AE33: =IF($A33="","",IF($A33<=COUNTIF(permit_calc!$L$3:$L$144,1),"OVF","LDG")) -> OVF | AF33: =IF($AE33="","",IF($AE33="OVF","",$A33-COUNTIF(permit_calc!$L$3:$L$144,1))) | AH33: =IFERROR(INDEX('PAX & CREW'!$L$3:$L$62,MATCH(ROW()-17,'PAX & CREW'!$AJ$3:$AJ$62,0)),"") | AI33: =IF($AH33="","",IF(COUNTIF($AH$18:$AH33,$AH33)=1,1,0)) | AJ33: =IF($AI33=1,SUM($AI$18:$AI33),"")
A34: =IF(ROW()-29>COUNTIF(permit_calc!$L$3:$L$144,1)+COUNTA($G$18:$G$25),"",ROW()-29) -> 5 | B34: =IF($A34="","",IF($AE34="OVF",INDEX(permit_calc!$B$3:$B$144,MATCH($A34,permit_calc!$N$3:$N$144,0)),IFERROR(INDEX(countries!$B:$B,MATCH($C34,countries!$D:$D,0)),$C34))) -> Democratic Republic of the Congo | C34: {=IF($A34="","",IF($AE34="OVF",INDEX(permit_calc!$A$3:$A$144,MATCH($A34,permit_calc!$N$3:$N$144,0)),INDEX($U$18:$U$25,$AF34)))} -> COD | D34: =IF($A34="","",$AE34) -> OVF | E34: {=IF($A34="","",IF($AE34="OVF","",INDEX($G$18:$G$25,$AF34)))} | F34: {=IF($A34="","",IF($AE34="OVF",INDEX(permit_calc!$M$3:$M$144,MATCH($A34,permit_calc!$N$3:$N$144,0)),INDEX($A$18:$A$25,$AF34)))} -> L1, L4 | G34: JTL | H34: {=IF($A34="","",IF($AE34="OVF",INDEX($E$18:$E$25,INDEX(permit_calc!$O$3:$O$144,MATCH($A34,permit_calc!$N$3:$N$144,0)))+INDEX($F$18:$F$25,INDEX(permit_calc!$O$3:$O$144,MATCH($A34,permit_calc!$N$3:$N$144,0))),INDEX($L$18:$L$25,$AF34)+INDEX($M$18:$M$25,$AF34)))} -> 46248.375 | I34: =IF($A34="","",IFERROR(IF(INDEX(countries!$I:$I,MATCH($C34,countries!$D:$D,0))=0,$B$12,INDEX(countries!$I:$I,MATCH($C34,countries!$D:$D,0))),$B$12)) -> 72 | J34: =IF($A34="","",$H34-$I34/24) -> 46245.375 | K34: =IF($A34="","",ROUND($J34-NOW(),1)) -> 1.8 | L34: =IF($A34="","",IF($AE34="OVF",IFERROR(INDEX(countries!$G:$G,MATCH($C34,countries!$D:$D,0)),"VERIFY"),IFERROR(INDEX(countries!$H:$H,MATCH($C34,countries!$D:$D,0)),"VERIFY"))) -> REQUIRED | M34: =IF($A34="","",IF(OR(UPPER($G34)="OWN",UPPER($G34)="EXCLUDED"),"CLIENT ARRANGING",IF($K34<0,"OVERDUE",IF($K34<1,"URGENT - FILE NOW",IF($K34<3,"DUE SOON","PENDING"))))) -> DUE SOON | AE34: =IF($A34="","",IF($A34<=COUNTIF(permit_calc!$L$3:$L$144,1),"OVF","LDG")) -> OVF | AF34: =IF($AE34="","",IF($AE34="OVF","",$A34-COUNTIF(permit_calc!$L$3:$L$144,1))) | AH34: =IFERROR(INDEX('PAX & CREW'!$L$3:$L$62,MATCH(ROW()-17,'PAX & CREW'!$AJ$3:$AJ$62,0)),"") | AI34: =IF($AH34="","",IF(COUNTIF($AH$18:$AH34,$AH34)=1,1,0)) | AJ34: =IF($AI34=1,SUM($AI$18:$AI34),"")
A35: =IF(ROW()-29>COUNTIF(permit_calc!$L$3:$L$144,1)+COUNTA($G$18:$G$25),"",ROW()-29) -> 6 | B35: =IF($A35="","",IF($AE35="OVF",INDEX(permit_calc!$B$3:$B$144,MATCH($A35,permit_calc!$N$3:$N$144,0)),IFERROR(INDEX(countries!$B:$B,MATCH($C35,countries!$D:$D,0)),$C35))) -> Republic of the Congo | C35: {=IF($A35="","",IF($AE35="OVF",INDEX(permit_calc!$A$3:$A$144,MATCH($A35,permit_calc!$N$3:$N$144,0)),INDEX($U$18:$U$25,$AF35)))} -> COG | D35: =IF($A35="","",$AE35) -> OVF | E35: {=IF($A35="","",IF($AE35="OVF","",INDEX($G$18:$G$25,$AF35)))} | F35: {=IF($A35="","",IF($AE35="OVF",INDEX(permit_calc!$M$3:$M$144,MATCH($A35,permit_calc!$N$3:$N$144,0)),INDEX($A$18:$A$25,$AF35)))} -> L1, L4 | G35: JTL | H35: {=IF($A35="","",IF($AE35="OVF",INDEX($E$18:$E$25,INDEX(permit_calc!$O$3:$O$144,MATCH($A35,permit_calc!$N$3:$N$144,0)))+INDEX($F$18:$F$25,INDEX(permit_calc!$O$3:$O$144,MATCH($A35,permit_calc!$N$3:$N$144,0))),INDEX($L$18:$L$25,$AF35)+INDEX($M$18:$M$25,$AF35)))} -> 46248.375 | I35: =IF($A35="","",IFERROR(IF(INDEX(countries!$I:$I,MATCH($C35,countries!$D:$D,0))=0,$B$12,INDEX(countries!$I:$I,MATCH($C35,countries!$D:$D,0))),$B$12)) -> 72 | J35: =IF($A35="","",$H35-$I35/24) -> 46245.375 | K35: =IF($A35="","",ROUND($J35-NOW(),1)) -> 1.8 | L35: =IF($A35="","",IF($AE35="OVF",IFERROR(INDEX(countries!$G:$G,MATCH($C35,countries!$D:$D,0)),"VERIFY"),IFERROR(INDEX(countries!$H:$H,MATCH($C35,countries!$D:$D,0)),"VERIFY"))) -> REQUIRED | M35: =IF($A35="","",IF(OR(UPPER($G35)="OWN",UPPER($G35)="EXCLUDED"),"CLIENT ARRANGING",IF($K35<0,"OVERDUE",IF($K35<1,"URGENT - FILE NOW",IF($K35<3,"DUE SOON","PENDING"))))) -> DUE SOON | AE35: =IF($A35="","",IF($A35<=COUNTIF(permit_calc!$L$3:$L$144,1),"OVF","LDG")) -> OVF | AF35: =IF($AE35="","",IF($AE35="OVF","",$A35-COUNTIF(permit_calc!$L$3:$L$144,1))) | AH35: =IFERROR(INDEX('PAX & CREW'!$L$3:$L$62,MATCH(ROW()-17,'PAX & CREW'!$AJ$3:$AJ$62,0)),"") | AI35: =IF($AH35="","",IF(COUNTIF($AH$18:$AH35,$AH35)=1,1,0)) | AJ35: =IF($AI35=1,SUM($AI$18:$AI35),"")
A36: =IF(ROW()-29>COUNTIF(permit_calc!$L$3:$L$144,1)+COUNTA($G$18:$G$25),"",ROW()-29) -> 7 | B36: =IF($A36="","",IF($AE36="OVF",INDEX(permit_calc!$B$3:$B$144,MATCH($A36,permit_calc!$N$3:$N$144,0)),IFERROR(INDEX(countries!$B:$B,MATCH($C36,countries!$D:$D,0)),$C36))) -> Central African Republic | C36: {=IF($A36="","",IF($AE36="OVF",INDEX(permit_calc!$A$3:$A$144,MATCH($A36,permit_calc!$N$3:$N$144,0)),INDEX($U$18:$U$25,$AF36)))} -> CAF | D36: =IF($A36="","",$AE36) -> OVF | E36: {=IF($A36="","",IF($AE36="OVF","",INDEX($G$18:$G$25,$AF36)))} | F36: {=IF($A36="","",IF($AE36="OVF",INDEX(permit_calc!$M$3:$M$144,MATCH($A36,permit_calc!$N$3:$N$144,0)),INDEX($A$18:$A$25,$AF36)))} -> L1 | G36: JTL | H36: {=IF($A36="","",IF($AE36="OVF",INDEX($E$18:$E$25,INDEX(permit_calc!$O$3:$O$144,MATCH($A36,permit_calc!$N$3:$N$144,0)))+INDEX($F$18:$F$25,INDEX(permit_calc!$O$3:$O$144,MATCH($A36,permit_calc!$N$3:$N$144,0))),INDEX($L$18:$L$25,$AF36)+INDEX($M$18:$M$25,$AF36)))} -> 46248.375 | I36: =IF($A36="","",IFERROR(IF(INDEX(countries!$I:$I,MATCH($C36,countries!$D:$D,0))=0,$B$12,INDEX(countries!$I:$I,MATCH($C36,countries!$D:$D,0))),$B$12)) -> 72 | J36: =IF($A36="","",$H36-$I36/24) -> 46245.375 | K36: =IF($A36="","",ROUND($J36-NOW(),1)) -> 1.8 | L36: =IF($A36="","",IF($AE36="OVF",IFERROR(INDEX(countries!$G:$G,MATCH($C36,countries!$D:$D,0)),"VERIFY"),IFERROR(INDEX(countries!$H:$H,MATCH($C36,countries!$D:$D,0)),"VERIFY"))) -> REQUIRED | M36: =IF($A36="","",IF(OR(UPPER($G36)="OWN",UPPER($G36)="EXCLUDED"),"CLIENT ARRANGING",IF($K36<0,"OVERDUE",IF($K36<1,"URGENT - FILE NOW",IF($K36<3,"DUE SOON","PENDING"))))) -> DUE SOON | AE36: =IF($A36="","",IF($A36<=COUNTIF(permit_calc!$L$3:$L$144,1),"OVF","LDG")) -> OVF | AF36: =IF($AE36="","",IF($AE36="OVF","",$A36-COUNTIF(permit_calc!$L$3:$L$144,1))) | AH36: =IFERROR(INDEX('PAX & CREW'!$L$3:$L$62,MATCH(ROW()-17,'PAX & CREW'!$AJ$3:$AJ$62,0)),"") | AI36: =IF($AH36="","",IF(COUNTIF($AH$18:$AH36,$AH36)=1,1,0)) | AJ36: =IF($AI36=1,SUM($AI$18:$AI36),"")
A37: =IF(ROW()-29>COUNTIF(permit_calc!$L$3:$L$144,1)+COUNTA($G$18:$G$25),"",ROW()-29) -> 8 | B37: =IF($A37="","",IF($AE37="OVF",INDEX(permit_calc!$B$3:$B$144,MATCH($A37,permit_calc!$N$3:$N$144,0)),IFERROR(INDEX(countries!$B:$B,MATCH($C37,countries!$D:$D,0)),$C37))) -> Libya | C37: {=IF($A37="","",IF($AE37="OVF",INDEX(permit_calc!$A$3:$A$144,MATCH($A37,permit_calc!$N$3:$N$144,0)),INDEX($U$18:$U$25,$AF37)))} -> LBY | D37: =IF($A37="","",$AE37) -> OVF | E37: {=IF($A37="","",IF($AE37="OVF","",INDEX($G$18:$G$25,$AF37)))} | F37: {=IF($A37="","",IF($AE37="OVF",INDEX(permit_calc!$M$3:$M$144,MATCH($A37,permit_calc!$N$3:$N$144,0)),INDEX($A$18:$A$25,$AF37)))} -> L2, L3 | G37: JTL | H37: {=IF($A37="","",IF($AE37="OVF",INDEX($E$18:$E$25,INDEX(permit_calc!$O$3:$O$144,MATCH($A37,permit_calc!$N$3:$N$144,0)))+INDEX($F$18:$F$25,INDEX(permit_calc!$O$3:$O$144,MATCH($A37,permit_calc!$N$3:$N$144,0))),INDEX($L$18:$L$25,$AF37)+INDEX($M$18:$M$25,$AF37)))} -> 46250.25 | I37: =IF($A37="","",IFERROR(IF(INDEX(countries!$I:$I,MATCH($C37,countries!$D:$D,0))=0,$B$12,INDEX(countries!$I:$I,MATCH($C37,countries!$D:$D,0))),$B$12)) -> 72 | J37: =IF($A37="","",$H37-$I37/24) -> 46247.25 | K37: =IF($A37="","",ROUND($J37-NOW(),1)) -> 3.6 | L37: =IF($A37="","",IF($AE37="OVF",IFERROR(INDEX(countries!$G:$G,MATCH($C37,countries!$D:$D,0)),"VERIFY"),IFERROR(INDEX(countries!$H:$H,MATCH($C37,countries!$D:$D,0)),"VERIFY"))) -> REQUIRED | M37: =IF($A37="","",IF(OR(UPPER($G37)="OWN",UPPER($G37)="EXCLUDED"),"CLIENT ARRANGING",IF($K37<0,"OVERDUE",IF($K37<1,"URGENT - FILE NOW",IF($K37<3,"DUE SOON","PENDING"))))) -> PENDING | AE37: =IF($A37="","",IF($A37<=COUNTIF(permit_calc!$L$3:$L$144,1),"OVF","LDG")) -> OVF | AF37: =IF($AE37="","",IF($AE37="OVF","",$A37-COUNTIF(permit_calc!$L$3:$L$144,1))) | AH37: =IFERROR(INDEX('PAX & CREW'!$L$3:$L$62,MATCH(ROW()-17,'PAX & CREW'!$AJ$3:$AJ$62,0)),"") | AI37: =IF($AH37="","",IF(COUNTIF($AH$18:$AH37,$AH37)=1,1,0)) | AJ37: =IF($AI37=1,SUM($AI$18:$AI37),"")
A38: =IF(ROW()-29>COUNTIF(permit_calc!$L$3:$L$144,1)+COUNTA($G$18:$G$25),"",ROW()-29) -> 9 | B38: =IF($A38="","",IF($AE38="OVF",INDEX(permit_calc!$B$3:$B$144,MATCH($A38,permit_calc!$N$3:$N$144,0)),IFERROR(INDEX(countries!$B:$B,MATCH($C38,countries!$D:$D,0)),$C38))) -> Tunisia | C38: {=IF($A38="","",IF($AE38="OVF",INDEX(permit_calc!$A$3:$A$144,MATCH($A38,permit_calc!$N$3:$N$144,0)),INDEX($U$18:$U$25,$AF38)))} -> TUN | D38: =IF($A38="","",$AE38) -> OVF | E38: {=IF($A38="","",IF($AE38="OVF","",INDEX($G$18:$G$25,$AF38)))} | F38: {=IF($A38="","",IF($AE38="OVF",INDEX(permit_calc!$M$3:$M$144,MATCH($A38,permit_calc!$N$3:$N$144,0)),INDEX($A$18:$A$25,$AF38)))} -> L3 | G38: JTL | H38: {=IF($A38="","",IF($AE38="OVF",INDEX($E$18:$E$25,INDEX(permit_calc!$O$3:$O$144,MATCH($A38,permit_calc!$N$3:$N$144,0)))+INDEX($F$18:$F$25,INDEX(permit_calc!$O$3:$O$144,MATCH($A38,permit_calc!$N$3:$N$144,0))),INDEX($L$18:$L$25,$AF38)+INDEX($M$18:$M$25,$AF38)))} -> 46251.167 | I38: =IF($A38="","",IFERROR(IF(INDEX(countries!$I:$I,MATCH($C38,countries!$D:$D,0))=0,$B$12,INDEX(countries!$I:$I,MATCH($C38,countries!$D:$D,0))),$B$12)) -> 72 | J38: =IF($A38="","",$H38-$I38/24) -> 46248.167 | K38: =IF($A38="","",ROUND($J38-NOW(),1)) -> 4.6 | L38: =IF($A38="","",IF($AE38="OVF",IFERROR(INDEX(countries!$G:$G,MATCH($C38,countries!$D:$D,0)),"VERIFY"),IFERROR(INDEX(countries!$H:$H,MATCH($C38,countries!$D:$D,0)),"VERIFY"))) -> REQUIRED | M38: =IF($A38="","",IF(OR(UPPER($G38)="OWN",UPPER($G38)="EXCLUDED"),"CLIENT ARRANGING",IF($K38<0,"OVERDUE",IF($K38<1,"URGENT - FILE NOW",IF($K38<3,"DUE SOON","PENDING"))))) -> PENDING | AE38: =IF($A38="","",IF($A38<=COUNTIF(permit_calc!$L$3:$L$144,1),"OVF","LDG")) -> OVF | AF38: =IF($AE38="","",IF($AE38="OVF","",$A38-COUNTIF(permit_calc!$L$3:$L$144,1)))
A39: =IF(ROW()-29>COUNTIF(permit_calc!$L$3:$L$144,1)+COUNTA($G$18:$G$25),"",ROW()-29) -> 10 | B39: =IF($A39="","",IF($AE39="OVF",INDEX(permit_calc!$B$3:$B$144,MATCH($A39,permit_calc!$N$3:$N$144,0)),IFERROR(INDEX(countries!$B:$B,MATCH($C39,countries!$D:$D,0)),$C39))) -> Algeria | C39: {=IF($A39="","",IF($AE39="OVF",INDEX(permit_calc!$A$3:$A$144,MATCH($A39,permit_calc!$N$3:$N$144,0)),INDEX($U$18:$U$25,$AF39)))} -> DZA | D39: =IF($A39="","",$AE39) -> OVF | E39: {=IF($A39="","",IF($AE39="OVF","",INDEX($G$18:$G$25,$AF39)))} | F39: {=IF($A39="","",IF($AE39="OVF",INDEX(permit_calc!$M$3:$M$144,MATCH($A39,permit_calc!$N$3:$N$144,0)),INDEX($A$18:$A$25,$AF39)))} -> L3, L4 | G39: JTL | H39: {=IF($A39="","",IF($AE39="OVF",INDEX($E$18:$E$25,INDEX(permit_calc!$O$3:$O$144,MATCH($A39,permit_calc!$N$3:$N$144,0)))+INDEX($F$18:$F$25,INDEX(permit_calc!$O$3:$O$144,MATCH($A39,permit_calc!$N$3:$N$144,0))),INDEX($L$18:$L$25,$AF39)+INDEX($M$18:$M$25,$AF39)))} -> 46251.167 | I39: =IF($A39="","",IFERROR(IF(INDEX(countries!$I:$I,MATCH($C39,countries!$D:$D,0))=0,$B$12,INDEX(countries!$I:$I,MATCH($C39,countries!$D:$D,0))),$B$12)) -> 72 | J39: =IF($A39="","",$H39-$I39/24) -> 46248.167 | K39: =IF($A39="","",ROUND($J39-NOW(),1)) -> 4.6 | L39: =IF($A39="","",IF($AE39="OVF",IFERROR(INDEX(countries!$G:$G,MATCH($C39,countries!$D:$D,0)),"VERIFY"),IFERROR(INDEX(countries!$H:$H,MATCH($C39,countries!$D:$D,0)),"VERIFY"))) -> REQUIRED | M39: =IF($A39="","",IF(OR(UPPER($G39)="OWN",UPPER($G39)="EXCLUDED"),"CLIENT ARRANGING",IF($K39<0,"OVERDUE",IF($K39<1,"URGENT - FILE NOW",IF($K39<3,"DUE SOON","PENDING"))))) -> PENDING | AE39: =IF($A39="","",IF($A39<=COUNTIF(permit_calc!$L$3:$L$144,1),"OVF","LDG")) -> OVF | AF39: =IF($AE39="","",IF($AE39="OVF","",$A39-COUNTIF(permit_calc!$L$3:$L$144,1)))
A40: =IF(ROW()-29>COUNTIF(permit_calc!$L$3:$L$144,1)+COUNTA($G$18:$G$25),"",ROW()-29) -> 11 | B40: =IF($A40="","",IF($AE40="OVF",INDEX(permit_calc!$B$3:$B$144,MATCH($A40,permit_calc!$N$3:$N$144,0)),IFERROR(INDEX(countries!$B:$B,MATCH($C40,countries!$D:$D,0)),$C40))) -> Mali | C40: {=IF($A40="","",IF($AE40="OVF",INDEX(permit_calc!$A$3:$A$144,MATCH($A40,permit_calc!$N$3:$N$144,0)),INDEX($U$18:$U$25,$AF40)))} -> MLI | D40: =IF($A40="","",$AE40) -> OVF | E40: {=IF($A40="","",IF($AE40="OVF","",INDEX($G$18:$G$25,$AF40)))} | F40: {=IF($A40="","",IF($AE40="OVF",INDEX(permit_calc!$M$3:$M$144,MATCH($A40,permit_calc!$N$3:$N$144,0)),INDEX($A$18:$A$25,$AF40)))} -> L4 | G40: JTL | H40: {=IF($A40="","",IF($AE40="OVF",INDEX($E$18:$E$25,INDEX(permit_calc!$O$3:$O$144,MATCH($A40,permit_calc!$N$3:$N$144,0)))+INDEX($F$18:$F$25,INDEX(permit_calc!$O$3:$O$144,MATCH($A40,permit_calc!$N$3:$N$144,0))),INDEX($L$18:$L$25,$AF40)+INDEX($M$18:$M$25,$AF40)))} -> 46253.042 | I40: =IF($A40="","",IFERROR(IF(INDEX(countries!$I:$I,MATCH($C40,countries!$D:$D,0))=0,$B$12,INDEX(countries!$I:$I,MATCH($C40,countries!$D:$D,0))),$B$12)) -> 72 | J40: =IF($A40="","",$H40-$I40/24) -> 46250.042 | K40: =IF($A40="","",ROUND($J40-NOW(),1)) -> 6.4 | L40: =IF($A40="","",IF($AE40="OVF",IFERROR(INDEX(countries!$G:$G,MATCH($C40,countries!$D:$D,0)),"VERIFY"),IFERROR(INDEX(countries!$H:$H,MATCH($C40,countries!$D:$D,0)),"VERIFY"))) -> REQUIRED | M40: =IF($A40="","",IF(OR(UPPER($G40)="OWN",UPPER($G40)="EXCLUDED"),"CLIENT ARRANGING",IF($K40<0,"OVERDUE",IF($K40<1,"URGENT - FILE NOW",IF($K40<3,"DUE SOON","PENDING"))))) -> PENDING | AE40: =IF($A40="","",IF($A40<=COUNTIF(permit_calc!$L$3:$L$144,1),"OVF","LDG")) -> OVF | AF40: =IF($AE40="","",IF($AE40="OVF","",$A40-COUNTIF(permit_calc!$L$3:$L$144,1)))
A41: =IF(ROW()-29>COUNTIF(permit_calc!$L$3:$L$144,1)+COUNTA($G$18:$G$25),"",ROW()-29) -> 12 | B41: =IF($A41="","",IF($AE41="OVF",INDEX(permit_calc!$B$3:$B$144,MATCH($A41,permit_calc!$N$3:$N$144,0)),IFERROR(INDEX(countries!$B:$B,MATCH($C41,countries!$D:$D,0)),$C41))) -> Niger | C41: {=IF($A41="","",IF($AE41="OVF",INDEX(permit_calc!$A$3:$A$144,MATCH($A41,permit_calc!$N$3:$N$144,0)),INDEX($U$18:$U$25,$AF41)))} -> NER | D41: =IF($A41="","",$AE41) -> OVF | E41: {=IF($A41="","",IF($AE41="OVF","",INDEX($G$18:$G$25,$AF41)))} | F41: {=IF($A41="","",IF($AE41="OVF",INDEX(permit_calc!$M$3:$M$144,MATCH($A41,permit_calc!$N$3:$N$144,0)),INDEX($A$18:$A$25,$AF41)))} -> L4 | G41: JTL | H41: {=IF($A41="","",IF($AE41="OVF",INDEX($E$18:$E$25,INDEX(permit_calc!$O$3:$O$144,MATCH($A41,permit_calc!$N$3:$N$144,0)))+INDEX($F$18:$F$25,INDEX(permit_calc!$O$3:$O$144,MATCH($A41,permit_calc!$N$3:$N$144,0))),INDEX($L$18:$L$25,$AF41)+INDEX($M$18:$M$25,$AF41)))} -> 46253.042 | I41: =IF($A41="","",IFERROR(IF(INDEX(countries!$I:$I,MATCH($C41,countries!$D:$D,0))=0,$B$12,INDEX(countries!$I:$I,MATCH($C41,countries!$D:$D,0))),$B$12)) -> 72 | J41: =IF($A41="","",$H41-$I41/24) -> 46250.042 | K41: =IF($A41="","",ROUND($J41-NOW(),1)) -> 6.4 | L41: =IF($A41="","",IF($AE41="OVF",IFERROR(INDEX(countries!$G:$G,MATCH($C41,countries!$D:$D,0)),"VERIFY"),IFERROR(INDEX(countries!$H:$H,MATCH($C41,countries!$D:$D,0)),"VERIFY"))) -> REQUIRED | M41: =IF($A41="","",IF(OR(UPPER($G41)="OWN",UPPER($G41)="EXCLUDED"),"CLIENT ARRANGING",IF($K41<0,"OVERDUE",IF($K41<1,"URGENT - FILE NOW",IF($K41<3,"DUE SOON","PENDING"))))) -> PENDING | AE41: =IF($A41="","",IF($A41<=COUNTIF(permit_calc!$L$3:$L$144,1),"OVF","LDG")) -> OVF | AF41: =IF($AE41="","",IF($AE41="OVF","",$A41-COUNTIF(permit_calc!$L$3:$L$144,1)))
A42: =IF(ROW()-29>COUNTIF(permit_calc!$L$3:$L$144,1)+COUNTA($G$18:$G$25),"",ROW()-29) -> 13 | B42: =IF($A42="","",IF($AE42="OVF",INDEX(permit_calc!$B$3:$B$144,MATCH($A42,permit_calc!$N$3:$N$144,0)),IFERROR(INDEX(countries!$B:$B,MATCH($C42,countries!$D:$D,0)),$C42))) -> Nigeria | C42: {=IF($A42="","",IF($AE42="OVF",INDEX(permit_calc!$A$3:$A$144,MATCH($A42,permit_calc!$N$3:$N$144,0)),INDEX($U$18:$U$25,$AF42)))} -> NGA | D42: =IF($A42="","",$AE42) -> OVF | E42: {=IF($A42="","",IF($AE42="OVF","",INDEX($G$18:$G$25,$AF42)))} | F42: {=IF($A42="","",IF($AE42="OVF",INDEX(permit_calc!$M$3:$M$144,MATCH($A42,permit_calc!$N$3:$N$144,0)),INDEX($A$18:$A$25,$AF42)))} -> L4 | G42: JTL | H42: {=IF($A42="","",IF($AE42="OVF",INDEX($E$18:$E$25,INDEX(permit_calc!$O$3:$O$144,MATCH($A42,permit_calc!$N$3:$N$144,0)))+INDEX($F$18:$F$25,INDEX(permit_calc!$O$3:$O$144,MATCH($A42,permit_calc!$N$3:$N$144,0))),INDEX($L$18:$L$25,$AF42)+INDEX($M$18:$M$25,$AF42)))} -> 46253.042 | I42: =IF($A42="","",IFERROR(IF(INDEX(countries!$I:$I,MATCH($C42,countries!$D:$D,0))=0,$B$12,INDEX(countries!$I:$I,MATCH($C42,countries!$D:$D,0))),$B$12)) -> 72 | J42: =IF($A42="","",$H42-$I42/24) -> 46250.042 | K42: =IF($A42="","",ROUND($J42-NOW(),1)) -> 6.4 | L42: =IF($A42="","",IF($AE42="OVF",IFERROR(INDEX(countries!$G:$G,MATCH($C42,countries!$D:$D,0)),"VERIFY"),IFERROR(INDEX(countries!$H:$H,MATCH($C42,countries!$D:$D,0)),"VERIFY"))) -> REQUIRED | M42: =IF($A42="","",IF(OR(UPPER($G42)="OWN",UPPER($G42)="EXCLUDED"),"CLIENT ARRANGING",IF($K42<0,"OVERDUE",IF($K42<1,"URGENT - FILE NOW",IF($K42<3,"DUE SOON","PENDING"))))) -> PENDING | AE42: =IF($A42="","",IF($A42<=COUNTIF(permit_calc!$L$3:$L$144,1),"OVF","LDG")) -> OVF | AF42: =IF($AE42="","",IF($AE42="OVF","",$A42-COUNTIF(permit_calc!$L$3:$L$144,1)))
A43: =IF(ROW()-29>COUNTIF(permit_calc!$L$3:$L$144,1)+COUNTA($G$18:$G$25),"",ROW()-29) -> 14 | B43: =IF($A43="","",IF($AE43="OVF",INDEX(permit_calc!$B$3:$B$144,MATCH($A43,permit_calc!$N$3:$N$144,0)),IFERROR(INDEX(countries!$B:$B,MATCH($C43,countries!$D:$D,0)),$C43))) -> Cameroon | C43: {=IF($A43="","",IF($AE43="OVF",INDEX(permit_calc!$A$3:$A$144,MATCH($A43,permit_calc!$N$3:$N$144,0)),INDEX($U$18:$U$25,$AF43)))} -> CMR | D43: =IF($A43="","",$AE43) -> OVF | E43: {=IF($A43="","",IF($AE43="OVF","",INDEX($G$18:$G$25,$AF43)))} | F43: {=IF($A43="","",IF($AE43="OVF",INDEX(permit_calc!$M$3:$M$144,MATCH($A43,permit_calc!$N$3:$N$144,0)),INDEX($A$18:$A$25,$AF43)))} -> L4 | G43: JTL | H43: {=IF($A43="","",IF($AE43="OVF",INDEX($E$18:$E$25,INDEX(permit_calc!$O$3:$O$144,MATCH($A43,permit_calc!$N$3:$N$144,0)))+INDEX($F$18:$F$25,INDEX(permit_calc!$O$3:$O$144,MATCH($A43,permit_calc!$N$3:$N$144,0))),INDEX($L$18:$L$25,$AF43)+INDEX($M$18:$M$25,$AF43)))} -> 46253.042 | I43: =IF($A43="","",IFERROR(IF(INDEX(countries!$I:$I,MATCH($C43,countries!$D:$D,0))=0,$B$12,INDEX(countries!$I:$I,MATCH($C43,countries!$D:$D,0))),$B$12)) -> 72 | J43: =IF($A43="","",$H43-$I43/24) -> 46250.042 | K43: =IF($A43="","",ROUND($J43-NOW(),1)) -> 6.4 | L43: =IF($A43="","",IF($AE43="OVF",IFERROR(INDEX(countries!$G:$G,MATCH($C43,countries!$D:$D,0)),"VERIFY"),IFERROR(INDEX(countries!$H:$H,MATCH($C43,countries!$D:$D,0)),"VERIFY"))) -> REQUIRED | M43: =IF($A43="","",IF(OR(UPPER($G43)="OWN",UPPER($G43)="EXCLUDED"),"CLIENT ARRANGING",IF($K43<0,"OVERDUE",IF($K43<1,"URGENT - FILE NOW",IF($K43<3,"DUE SOON","PENDING"))))) -> PENDING | AE43: =IF($A43="","",IF($A43<=COUNTIF(permit_calc!$L$3:$L$144,1),"OVF","LDG")) -> OVF | AF43: =IF($AE43="","",IF($AE43="OVF","",$A43-COUNTIF(permit_calc!$L$3:$L$144,1)))
A44: =IF(ROW()-29>COUNTIF(permit_calc!$L$3:$L$144,1)+COUNTA($G$18:$G$25),"",ROW()-29) -> 15 | B44: =IF($A44="","",IF($AE44="OVF",INDEX(permit_calc!$B$3:$B$144,MATCH($A44,permit_calc!$N$3:$N$144,0)),IFERROR(INDEX(countries!$B:$B,MATCH($C44,countries!$D:$D,0)),$C44))) -> Equatorial Guinea | C44: {=IF($A44="","",IF($AE44="OVF",INDEX(permit_calc!$A$3:$A$144,MATCH($A44,permit_calc!$N$3:$N$144,0)),INDEX($U$18:$U$25,$AF44)))} -> GNQ | D44: =IF($A44="","",$AE44) -> OVF | E44: {=IF($A44="","",IF($AE44="OVF","",INDEX($G$18:$G$25,$AF44)))} | F44: {=IF($A44="","",IF($AE44="OVF",INDEX(permit_calc!$M$3:$M$144,MATCH($A44,permit_calc!$N$3:$N$144,0)),INDEX($A$18:$A$25,$AF44)))} -> L4 | G44: JTL | H44: {=IF($A44="","",IF($AE44="OVF",INDEX($E$18:$E$25,INDEX(permit_calc!$O$3:$O$144,MATCH($A44,permit_calc!$N$3:$N$144,0)))+INDEX($F$18:$F$25,INDEX(permit_calc!$O$3:$O$144,MATCH($A44,permit_calc!$N$3:$N$144,0))),INDEX($L$18:$L$25,$AF44)+INDEX($M$18:$M$25,$AF44)))} -> 46253.042 | I44: =IF($A44="","",IFERROR(IF(INDEX(countries!$I:$I,MATCH($C44,countries!$D:$D,0))=0,$B$12,INDEX(countries!$I:$I,MATCH($C44,countries!$D:$D,0))),$B$12)) -> 72 | J44: =IF($A44="","",$H44-$I44/24) -> 46250.042 | K44: =IF($A44="","",ROUND($J44-NOW(),1)) -> 6.4 | L44: =IF($A44="","",IF($AE44="OVF",IFERROR(INDEX(countries!$G:$G,MATCH($C44,countries!$D:$D,0)),"VERIFY"),IFERROR(INDEX(countries!$H:$H,MATCH($C44,countries!$D:$D,0)),"VERIFY"))) -> REQUIRED | M44: =IF($A44="","",IF(OR(UPPER($G44)="OWN",UPPER($G44)="EXCLUDED"),"CLIENT ARRANGING",IF($K44<0,"OVERDUE",IF($K44<1,"URGENT - FILE NOW",IF($K44<3,"DUE SOON","PENDING"))))) -> PENDING | AE44: =IF($A44="","",IF($A44<=COUNTIF(permit_calc!$L$3:$L$144,1),"OVF","LDG")) -> OVF | AF44: =IF($AE44="","",IF($AE44="OVF","",$A44-COUNTIF(permit_calc!$L$3:$L$144,1)))
A45: =IF(ROW()-29>COUNTIF(permit_calc!$L$3:$L$144,1)+COUNTA($G$18:$G$25),"",ROW()-29) -> 16 | B45: =IF($A45="","",IF($AE45="OVF",INDEX(permit_calc!$B$3:$B$144,MATCH($A45,permit_calc!$N$3:$N$144,0)),IFERROR(INDEX(countries!$B:$B,MATCH($C45,countries!$D:$D,0)),$C45))) -> Gabon | C45: {=IF($A45="","",IF($AE45="OVF",INDEX(permit_calc!$A$3:$A$144,MATCH($A45,permit_calc!$N$3:$N$144,0)),INDEX($U$18:$U$25,$AF45)))} -> GAB | D45: =IF($A45="","",$AE45) -> OVF | E45: {=IF($A45="","",IF($AE45="OVF","",INDEX($G$18:$G$25,$AF45)))} | F45: {=IF($A45="","",IF($AE45="OVF",INDEX(permit_calc!$M$3:$M$144,MATCH($A45,permit_calc!$N$3:$N$144,0)),INDEX($A$18:$A$25,$AF45)))} -> L4 | G45: JTL | H45: {=IF($A45="","",IF($AE45="OVF",INDEX($E$18:$E$25,INDEX(permit_calc!$O$3:$O$144,MATCH($A45,permit_calc!$N$3:$N$144,0)))+INDEX($F$18:$F$25,INDEX(permit_calc!$O$3:$O$144,MATCH($A45,permit_calc!$N$3:$N$144,0))),INDEX($L$18:$L$25,$AF45)+INDEX($M$18:$M$25,$AF45)))} -> 46253.042 | I45: =IF($A45="","",IFERROR(IF(INDEX(countries!$I:$I,MATCH($C45,countries!$D:$D,0))=0,$B$12,INDEX(countries!$I:$I,MATCH($C45,countries!$D:$D,0))),$B$12)) -> 72 | J45: =IF($A45="","",$H45-$I45/24) -> 46250.042 | K45: =IF($A45="","",ROUND($J45-NOW(),1)) -> 6.4 | L45: =IF($A45="","",IF($AE45="OVF",IFERROR(INDEX(countries!$G:$G,MATCH($C45,countries!$D:$D,0)),"VERIFY"),IFERROR(INDEX(countries!$H:$H,MATCH($C45,countries!$D:$D,0)),"VERIFY"))) -> REQUIRED | M45: =IF($A45="","",IF(OR(UPPER($G45)="OWN",UPPER($G45)="EXCLUDED"),"CLIENT ARRANGING",IF($K45<0,"OVERDUE",IF($K45<1,"URGENT - FILE NOW",IF($K45<3,"DUE SOON","PENDING"))))) -> PENDING | AE45: =IF($A45="","",IF($A45<=COUNTIF(permit_calc!$L$3:$L$144,1),"OVF","LDG")) -> OVF | AF45: =IF($AE45="","",IF($AE45="OVF","",$A45-COUNTIF(permit_calc!$L$3:$L$144,1)))
A46: =IF(ROW()-29>COUNTIF(permit_calc!$L$3:$L$144,1)+COUNTA($G$18:$G$25),"",ROW()-29) -> 17 | B46: =IF($A46="","",IF($AE46="OVF",INDEX(permit_calc!$B$3:$B$144,MATCH($A46,permit_calc!$N$3:$N$144,0)),IFERROR(INDEX(countries!$B:$B,MATCH($C46,countries!$D:$D,0)),$C46))) -> Chad | C46: {=IF($A46="","",IF($AE46="OVF",INDEX(permit_calc!$A$3:$A$144,MATCH($A46,permit_calc!$N$3:$N$144,0)),INDEX($U$18:$U$25,$AF46)))} -> TCD | D46: =IF($A46="","",$AE46) -> LDG | E46: {=IF($A46="","",IF($AE46="OVF","",INDEX($G$18:$G$25,$AF46)))} -> FTTJ | F46: {=IF($A46="","",IF($AE46="OVF",INDEX(permit_calc!$M$3:$M$144,MATCH($A46,permit_calc!$N$3:$N$144,0)),INDEX($A$18:$A$25,$AF46)))} -> L1 | G46: JTL | H46: {=IF($A46="","",IF($AE46="OVF",INDEX($E$18:$E$25,INDEX(permit_calc!$O$3:$O$144,MATCH($A46,permit_calc!$N$3:$N$144,0)))+INDEX($F$18:$F$25,INDEX(permit_calc!$O$3:$O$144,MATCH($A46,permit_calc!$N$3:$N$144,0))),INDEX($L$18:$L$25,$AF46)+INDEX($M$18:$M$25,$AF46)))} -> 46248.605 | I46: =IF($A46="","",IFERROR(IF(INDEX(countries!$I:$I,MATCH($C46,countries!$D:$D,0))=0,$B$12,INDEX(countries!$I:$I,MATCH($C46,countries!$D:$D,0))),$B$12)) -> 72 | J46: =IF($A46="","",$H46-$I46/24) -> 46245.605 | K46: =IF($A46="","",ROUND($J46-NOW(),1)) -> 2 | L46: =IF($A46="","",IF($AE46="OVF",IFERROR(INDEX(countries!$G:$G,MATCH($C46,countries!$D:$D,0)),"VERIFY"),IFERROR(INDEX(countries!$H:$H,MATCH($C46,countries!$D:$D,0)),"VERIFY"))) -> REQUIRED | M46: =IF($A46="","",IF(OR(UPPER($G46)="OWN",UPPER($G46)="EXCLUDED"),"CLIENT ARRANGING",IF($K46<0,"OVERDUE",IF($K46<1,"URGENT - FILE NOW",IF($K46<3,"DUE SOON","PENDING"))))) -> DUE SOON | AE46: =IF($A46="","",IF($A46<=COUNTIF(permit_calc!$L$3:$L$144,1),"OVF","LDG")) -> LDG | AF46: =IF($AE46="","",IF($AE46="OVF","",$A46-COUNTIF(permit_calc!$L$3:$L$144,1))) -> 1
A47: =IF(ROW()-29>COUNTIF(permit_calc!$L$3:$L$144,1)+COUNTA($G$18:$G$25),"",ROW()-29) -> 18 | B47: =IF($A47="","",IF($AE47="OVF",INDEX(permit_calc!$B$3:$B$144,MATCH($A47,permit_calc!$N$3:$N$144,0)),IFERROR(INDEX(countries!$B:$B,MATCH($C47,countries!$D:$D,0)),$C47))) -> Egypt | C47: {=IF($A47="","",IF($AE47="OVF",INDEX(permit_calc!$A$3:$A$144,MATCH($A47,permit_calc!$N$3:$N$144,0)),INDEX($U$18:$U$25,$AF47)))} -> EGY | D47: =IF($A47="","",$AE47) -> LDG | E47: {=IF($A47="","",IF($AE47="OVF","",INDEX($G$18:$G$25,$AF47)))} -> HECA | F47: {=IF($A47="","",IF($AE47="OVF",INDEX(permit_calc!$M$3:$M$144,MATCH($A47,permit_calc!$N$3:$N$144,0)),INDEX($A$18:$A$25,$AF47)))} -> L2 | G47: JTL | H47: {=IF($A47="","",IF($AE47="OVF",INDEX($E$18:$E$25,INDEX(permit_calc!$O$3:$O$144,MATCH($A47,permit_calc!$N$3:$N$144,0)))+INDEX($F$18:$F$25,INDEX(permit_calc!$O$3:$O$144,MATCH($A47,permit_calc!$N$3:$N$144,0))),INDEX($L$18:$L$25,$AF47)+INDEX($M$18:$M$25,$AF47)))} -> 46250.392 | I47: =IF($A47="","",IFERROR(IF(INDEX(countries!$I:$I,MATCH($C47,countries!$D:$D,0))=0,$B$12,INDEX(countries!$I:$I,MATCH($C47,countries!$D:$D,0))),$B$12)) -> 72 | J47: =IF($A47="","",$H47-$I47/24) -> 46247.392 | K47: =IF($A47="","",ROUND($J47-NOW(),1)) -> 3.8 | L47: =IF($A47="","",IF($AE47="OVF",IFERROR(INDEX(countries!$G:$G,MATCH($C47,countries!$D:$D,0)),"VERIFY"),IFERROR(INDEX(countries!$H:$H,MATCH($C47,countries!$D:$D,0)),"VERIFY"))) -> REQUIRED | M47: =IF($A47="","",IF(OR(UPPER($G47)="OWN",UPPER($G47)="EXCLUDED"),"CLIENT ARRANGING",IF($K47<0,"OVERDUE",IF($K47<1,"URGENT - FILE NOW",IF($K47<3,"DUE SOON","PENDING"))))) -> PENDING | AE47: =IF($A47="","",IF($A47<=COUNTIF(permit_calc!$L$3:$L$144,1),"OVF","LDG")) -> LDG | AF47: =IF($AE47="","",IF($AE47="OVF","",$A47-COUNTIF(permit_calc!$L$3:$L$144,1))) -> 2
A48: =IF(ROW()-29>COUNTIF(permit_calc!$L$3:$L$144,1)+COUNTA($G$18:$G$25),"",ROW()-29) -> 19 | B48: =IF($A48="","",IF($AE48="OVF",INDEX(permit_calc!$B$3:$B$144,MATCH($A48,permit_calc!$N$3:$N$144,0)),IFERROR(INDEX(countries!$B:$B,MATCH($C48,countries!$D:$D,0)),$C48))) -> Morocco | C48: {=IF($A48="","",IF($AE48="OVF",INDEX(permit_calc!$A$3:$A$144,MATCH($A48,permit_calc!$N$3:$N$144,0)),INDEX($U$18:$U$25,$AF48)))} -> MAR | D48: =IF($A48="","",$AE48) -> LDG | E48: {=IF($A48="","",IF($AE48="OVF","",INDEX($G$18:$G$25,$AF48)))} -> GMAD | F48: {=IF($A48="","",IF($AE48="OVF",INDEX(permit_calc!$M$3:$M$144,MATCH($A48,permit_calc!$N$3:$N$144,0)),INDEX($A$18:$A$25,$AF48)))} -> L3 | G48: JTL | H48: {=IF($A48="","",IF($AE48="OVF",INDEX($E$18:$E$25,INDEX(permit_calc!$O$3:$O$144,MATCH($A48,permit_calc!$N$3:$N$144,0)))+INDEX($F$18:$F$25,INDEX(permit_calc!$O$3:$O$144,MATCH($A48,permit_calc!$N$3:$N$144,0))),INDEX($L$18:$L$25,$AF48)+INDEX($M$18:$M$25,$AF48)))} -> 46251.37 | I48: =IF($A48="","",IFERROR(IF(INDEX(countries!$I:$I,MATCH($C48,countries!$D:$D,0))=0,$B$12,INDEX(countries!$I:$I,MATCH($C48,countries!$D:$D,0))),$B$12)) -> 72 | J48: =IF($A48="","",$H48-$I48/24) -> 46248.37 | K48: =IF($A48="","",ROUND($J48-NOW(),1)) -> 4.8 | L48: =IF($A48="","",IF($AE48="OVF",IFERROR(INDEX(countries!$G:$G,MATCH($C48,countries!$D:$D,0)),"VERIFY"),IFERROR(INDEX(countries!$H:$H,MATCH($C48,countries!$D:$D,0)),"VERIFY"))) -> REQUIRED | M48: =IF($A48="","",IF(OR(UPPER($G48)="OWN",UPPER($G48)="EXCLUDED"),"CLIENT ARRANGING",IF($K48<0,"OVERDUE",IF($K48<1,"URGENT - FILE NOW",IF($K48<3,"DUE SOON","PENDING"))))) -> PENDING | AE48: =IF($A48="","",IF($A48<=COUNTIF(permit_calc!$L$3:$L$144,1),"OVF","LDG")) -> LDG | AF48: =IF($AE48="","",IF($AE48="OVF","",$A48-COUNTIF(permit_calc!$L$3:$L$144,1))) -> 3
A49: =IF(ROW()-29>COUNTIF(permit_calc!$L$3:$L$144,1)+COUNTA($G$18:$G$25),"",ROW()-29) -> 20 | B49: =IF($A49="","",IF($AE49="OVF",INDEX(permit_calc!$B$3:$B$144,MATCH($A49,permit_calc!$N$3:$N$144,0)),IFERROR(INDEX(countries!$B:$B,MATCH($C49,countries!$D:$D,0)),$C49))) -> South Africa | C49: {=IF($A49="","",IF($AE49="OVF",INDEX(permit_calc!$A$3:$A$144,MATCH($A49,permit_calc!$N$3:$N$144,0)),INDEX($U$18:$U$25,$AF49)))} -> ZAF | D49: =IF($A49="","",$AE49) -> LDG | E49: {=IF($A49="","",IF($AE49="OVF","",INDEX($G$18:$G$25,$AF49)))} -> FAOR | F49: {=IF($A49="","",IF($AE49="OVF",INDEX(permit_calc!$M$3:$M$144,MATCH($A49,permit_calc!$N$3:$N$144,0)),INDEX($A$18:$A$25,$AF49)))} -> L4 | G49: JTL | H49: {=IF($A49="","",IF($AE49="OVF",INDEX($E$18:$E$25,INDEX(permit_calc!$O$3:$O$144,MATCH($A49,permit_calc!$N$3:$N$144,0)))+INDEX($F$18:$F$25,INDEX(permit_calc!$O$3:$O$144,MATCH($A49,permit_calc!$N$3:$N$144,0))),INDEX($L$18:$L$25,$AF49)+INDEX($M$18:$M$25,$AF49)))} -> 46253.415 | I49: =IF($A49="","",IFERROR(IF(INDEX(countries!$I:$I,MATCH($C49,countries!$D:$D,0))=0,$B$12,INDEX(countries!$I:$I,MATCH($C49,countries!$D:$D,0))),$B$12)) -> 72 | J49: =IF($A49="","",$H49-$I49/24) -> 46250.415 | K49: =IF($A49="","",ROUND($J49-NOW(),1)) -> 6.8 | L49: =IF($A49="","",IF($AE49="OVF",IFERROR(INDEX(countries!$G:$G,MATCH($C49,countries!$D:$D,0)),"VERIFY"),IFERROR(INDEX(countries!$H:$H,MATCH($C49,countries!$D:$D,0)),"VERIFY"))) -> REQUIRED | M49: =IF($A49="","",IF(OR(UPPER($G49)="OWN",UPPER($G49)="EXCLUDED"),"CLIENT ARRANGING",IF($K49<0,"OVERDUE",IF($K49<1,"URGENT - FILE NOW",IF($K49<3,"DUE SOON","PENDING"))))) -> PENDING | AE49: =IF($A49="","",IF($A49<=COUNTIF(permit_calc!$L$3:$L$144,1),"OVF","LDG")) -> LDG | AF49: =IF($AE49="","",IF($AE49="OVF","",$A49-COUNTIF(permit_calc!$L$3:$L$144,1))) -> 4
... A53: =IF(ROW()-29>COUNTIF(permit_calc!$L$3:$L$144,1)+COUNTA($G$18:$G$25),"",ROW()-29) | B53: =IF($A53="","",IF($AE53="OVF",INDEX(permit_calc!$B$3:$B$144,MATCH($A53,permit_calc!$N$3:$N$144,0)),IFERROR(INDEX(countries!$B:$B,MATCH($C53,countries!$D:$D,0)),$C53))) | C53: {=IF($A53="","",IF($AE53="OVF",INDEX(permit_calc!$A$3:$A$144,MATCH($A53,permit_calc!$N$3:$N$144,0)),INDEX($U$18:$U$25,$AF53)))} | D53: =IF($A53="","",$AE53) | E53: {=IF($A53="","",IF($AE53="OVF","",INDEX($G$18:$G$25,$AF53)))} | F53: {=IF($A53="","",IF($AE53="OVF",INDEX(permit_calc!$M$3:$M$144,MATCH($A53,permit_calc!$N$3:$N$144,0)),INDEX($A$18:$A$25,$AF53)))} | G53: JTL | H53: {=IF($A53="","",IF($AE53="OVF",INDEX($E$18:$E$25,INDEX(permit_calc!$O$3:$O$144,MATCH($A53,permit_calc!$N$3:$N$144,0)))+INDEX($F$18:$F$25,INDEX(permit_calc!$O$3:$O$144,MATCH($A53,permit_calc!$N$3:$N$144,0))),INDEX($L$18:$L$25,$AF53)+INDEX($M$18:$M$25,$AF53)))} | I53: =IF($A53="","",IFERROR(IF(INDEX(countries!$I:$I,MATCH($C53,countries!$D:$D,0))=0,$B$12,INDEX(countries!$I:$I,MATCH($C53,countries!$D:$D,0))),$B$12)) | J53: =IF($A53="","",$H53-$I53/24) | K53: =IF($A53="","",ROUND($J53-NOW(),1)) | L53: =IF($A53="","",IF($AE53="OVF",IFERROR(INDEX(countries!$G:$G,MATCH($C53,countries!$D:$D,0)),"VERIFY"),IFERROR(INDEX(countries!$H:$H,MATCH($C53,countries!$D:$D,0)),"VERIFY"))) | M53: =IF($A53="","",IF(OR(UPPER($G53)="OWN",UPPER($G53)="EXCLUDED"),"CLIENT ARRANGING",IF($K53<0,"OVERDUE",IF($K53<1,"URGENT - FILE NOW",IF($K53<3,"DUE SOON","PENDING"))))) | AE53: =IF($A53="","",IF($A53<=COUNTIF(permit_calc!$L$3:$L$144,1),"OVF","LDG")) | AF53: =IF($AE53="","",IF($AE53="OVF","",$A53-COUNTIF(permit_calc!$L$3:$L$144,1)))
A54: =IF(ROW()-29>COUNTIF(permit_calc!$L$3:$L$144,1)+COUNTA($G$18:$G$25),"",ROW()-29) | B54: =IF($A54="","",IF($AE54="OVF",INDEX(permit_calc!$B$3:$B$144,MATCH($A54,permit_calc!$N$3:$N$144,0)),IFERROR(INDEX(countries!$B:$B,MATCH($C54,countries!$D:$D,0)),$C54))) | C54: {=IF($A54="","",IF($AE54="OVF",INDEX(permit_calc!$A$3:$A$144,MATCH($A54,permit_calc!$N$3:$N$144,0)),INDEX($U$18:$U$25,$AF54)))} | D54: =IF($A54="","",$AE54) | E54: {=IF($A54="","",IF($AE54="OVF","",INDEX($G$18:$G$25,$AF54)))} | F54: {=IF($A54="","",IF($AE54="OVF",INDEX(permit_calc!$M$3:$M$144,MATCH($A54,permit_calc!$N$3:$N$144,0)),INDEX($A$18:$A$25,$AF54)))} | H54: {=IF($A54="","",IF($AE54="OVF",INDEX($E$18:$E$25,INDEX(permit_calc!$O$3:$O$144,MATCH($A54,permit_calc!$N$3:$N$144,0)))+INDEX($F$18:$F$25,INDEX(permit_calc!$O$3:$O$144,MATCH($A54,permit_calc!$N$3:$N$144,0))),INDEX($L$18:$L$25,$AF54)+INDEX($M$18:$M$25,$AF54)))} | I54: =IF($A54="","",IFERROR(IF(INDEX(countries!$I:$I,MATCH($C54,countries!$D:$D,0))=0,$B$12,INDEX(countries!$I:$I,MATCH($C54,countries!$D:$D,0))),$B$12)) | J54: =IF($A54="","",$H54-$I54/24) | K54: =IF($A54="","",ROUND($J54-NOW(),1)) | L54: =IF($A54="","",IF($AE54="OVF",IFERROR(INDEX(countries!$G:$G,MATCH($C54,countries!$D:$D,0)),"VERIFY"),IFERROR(INDEX(countries!$H:$H,MATCH($C54,countries!$D:$D,0)),"VERIFY"))) | M54: =IF($A54="","",IF(OR(UPPER($G54)="OWN",UPPER($G54)="EXCLUDED"),"CLIENT ARRANGING",IF($K54<0,"OVERDUE",IF($K54<1,"URGENT - FILE NOW",IF($K54<3,"DUE SOON","PENDING"))))) | AE54: =IF($A54="","",IF($A54<=COUNTIF(permit_calc!$L$3:$L$144,1),"OVF","LDG")) | AF54: =IF($AE54="","",IF($AE54="OVF","",$A54-COUNTIF(permit_calc!$L$3:$L$144,1)))
A55: =IF(ROW()-29>COUNTIF(permit_calc!$L$3:$L$144,1)+COUNTA($G$18:$G$25),"",ROW()-29) | B55: =IF($A55="","",IF($AE55="OVF",INDEX(permit_calc!$B$3:$B$144,MATCH($A55,permit_calc!$N$3:$N$144,0)),IFERROR(INDEX(countries!$B:$B,MATCH($C55,countries!$D:$D,0)),$C55))) | C55: {=IF($A55="","",IF($AE55="OVF",INDEX(permit_calc!$A$3:$A$144,MATCH($A55,permit_calc!$N$3:$N$144,0)),INDEX($U$18:$U$25,$AF55)))} | D55: =IF($A55="","",$AE55) | E55: {=IF($A55="","",IF($AE55="OVF","",INDEX($G$18:$G$25,$AF55)))} | F55: {=IF($A55="","",IF($AE55="OVF",INDEX(permit_calc!$M$3:$M$144,MATCH($A55,permit_calc!$N$3:$N$144,0)),INDEX($A$18:$A$25,$AF55)))} | H55: {=IF($A55="","",IF($AE55="OVF",INDEX($E$18:$E$25,INDEX(permit_calc!$O$3:$O$144,MATCH($A55,permit_calc!$N$3:$N$144,0)))+INDEX($F$18:$F$25,INDEX(permit_calc!$O$3:$O$144,MATCH($A55,permit_calc!$N$3:$N$144,0))),INDEX($L$18:$L$25,$AF55)+INDEX($M$18:$M$25,$AF55)))} | I55: =IF($A55="","",IFERROR(IF(INDEX(countries!$I:$I,MATCH($C55,countries!$D:$D,0))=0,$B$12,INDEX(countries!$I:$I,MATCH($C55,countries!$D:$D,0))),$B$12)) | J55: =IF($A55="","",$H55-$I55/24) | K55: =IF($A55="","",ROUND($J55-NOW(),1)) | L55: =IF($A55="","",IF($AE55="OVF",IFERROR(INDEX(countries!$G:$G,MATCH($C55,countries!$D:$D,0)),"VERIFY"),IFERROR(INDEX(countries!$H:$H,MATCH($C55,countries!$D:$D,0)),"VERIFY"))) | M55: =IF($A55="","",IF(OR(UPPER($G55)="OWN",UPPER($G55)="EXCLUDED"),"CLIENT ARRANGING",IF($K55<0,"OVERDUE",IF($K55<1,"URGENT - FILE NOW",IF($K55<3,"DUE SOON","PENDING"))))) | AE55: =IF($A55="","",IF($A55<=COUNTIF(permit_calc!$L$3:$L$144,1),"OVF","LDG")) | AF55: =IF($AE55="","",IF($AE55="OVF","",$A55-COUNTIF(permit_calc!$L$3:$L$144,1)))
A56: =IF(ROW()-29>COUNTIF(permit_calc!$L$3:$L$144,1)+COUNTA($G$18:$G$25),"",ROW()-29) | B56: =IF($A56="","",IF($AE56="OVF",INDEX(permit_calc!$B$3:$B$144,MATCH($A56,permit_calc!$N$3:$N$144,0)),IFERROR(INDEX(countries!$B:$B,MATCH($C56,countries!$D:$D,0)),$C56))) | C56: {=IF($A56="","",IF($AE56="OVF",INDEX(permit_calc!$A$3:$A$144,MATCH($A56,permit_calc!$N$3:$N$144,0)),INDEX($U$18:$U$25,$AF56)))} | D56: =IF($A56="","",$AE56) | E56: {=IF($A56="","",IF($AE56="OVF","",INDEX($G$18:$G$25,$AF56)))} | F56: {=IF($A56="","",IF($AE56="OVF",INDEX(permit_calc!$M$3:$M$144,MATCH($A56,permit_calc!$N$3:$N$144,0)),INDEX($A$18:$A$25,$AF56)))} | H56: {=IF($A56="","",IF($AE56="OVF",INDEX($E$18:$E$25,INDEX(permit_calc!$O$3:$O$144,MATCH($A56,permit_calc!$N$3:$N$144,0)))+INDEX($F$18:$F$25,INDEX(permit_calc!$O$3:$O$144,MATCH($A56,permit_calc!$N$3:$N$144,0))),INDEX($L$18:$L$25,$AF56)+INDEX($M$18:$M$25,$AF56)))} | I56: =IF($A56="","",IFERROR(IF(INDEX(countries!$I:$I,MATCH($C56,countries!$D:$D,0))=0,$B$12,INDEX(countries!$I:$I,MATCH($C56,countries!$D:$D,0))),$B$12)) | J56: =IF($A56="","",$H56-$I56/24) | K56: =IF($A56="","",ROUND($J56-NOW(),1)) | L56: =IF($A56="","",IF($AE56="OVF",IFERROR(INDEX(countries!$G:$G,MATCH($C56,countries!$D:$D,0)),"VERIFY"),IFERROR(INDEX(countries!$H:$H,MATCH($C56,countries!$D:$D,0)),"VERIFY"))) | M56: =IF($A56="","",IF(OR(UPPER($G56)="OWN",UPPER($G56)="EXCLUDED"),"CLIENT ARRANGING",IF($K56<0,"OVERDUE",IF($K56<1,"URGENT - FILE NOW",IF($K56<3,"DUE SOON","PENDING"))))) | AE56: =IF($A56="","",IF($A56<=COUNTIF(permit_calc!$L$3:$L$144,1),"OVF","LDG")) | AF56: =IF($AE56="","",IF($AE56="OVF","",$A56-COUNTIF(permit_calc!$L$3:$L$144,1)))
A57: =IF(ROW()-29>COUNTIF(permit_calc!$L$3:$L$144,1)+COUNTA($G$18:$G$25),"",ROW()-29) | B57: =IF($A57="","",IF($AE57="OVF",INDEX(permit_calc!$B$3:$B$144,MATCH($A57,permit_calc!$N$3:$N$144,0)),IFERROR(INDEX(countries!$B:$B,MATCH($C57,countries!$D:$D,0)),$C57))) | C57: {=IF($A57="","",IF($AE57="OVF",INDEX(permit_calc!$A$3:$A$144,MATCH($A57,permit_calc!$N$3:$N$144,0)),INDEX($U$18:$U$25,$AF57)))} | D57: =IF($A57="","",$AE57) | E57: {=IF($A57="","",IF($AE57="OVF","",INDEX($G$18:$G$25,$AF57)))} | F57: {=IF($A57="","",IF($AE57="OVF",INDEX(permit_calc!$M$3:$M$144,MATCH($A57,permit_calc!$N$3:$N$144,0)),INDEX($A$18:$A$25,$AF57)))} | H57: {=IF($A57="","",IF($AE57="OVF",INDEX($E$18:$E$25,INDEX(permit_calc!$O$3:$O$144,MATCH($A57,permit_calc!$N$3:$N$144,0)))+INDEX($F$18:$F$25,INDEX(permit_calc!$O$3:$O$144,MATCH($A57,permit_calc!$N$3:$N$144,0))),INDEX($L$18:$L$25,$AF57)+INDEX($M$18:$M$25,$AF57)))} | I57: =IF($A57="","",IFERROR(IF(INDEX(countries!$I:$I,MATCH($C57,countries!$D:$D,0))=0,$B$12,INDEX(countries!$I:$I,MATCH($C57,countries!$D:$D,0))),$B$12)) | J57: =IF($A57="","",$H57-$I57/24) | K57: =IF($A57="","",ROUND($J57-NOW(),1)) | L57: =IF($A57="","",IF($AE57="OVF",IFERROR(INDEX(countries!$G:$G,MATCH($C57,countries!$D:$D,0)),"VERIFY"),IFERROR(INDEX(countries!$H:$H,MATCH($C57,countries!$D:$D,0)),"VERIFY"))) | M57: =IF($A57="","",IF(OR(UPPER($G57)="OWN",UPPER($G57)="EXCLUDED"),"CLIENT ARRANGING",IF($K57<0,"OVERDUE",IF($K57<1,"URGENT - FILE NOW",IF($K57<3,"DUE SOON","PENDING"))))) | AE57: =IF($A57="","",IF($A57<=COUNTIF(permit_calc!$L$3:$L$144,1),"OVF","LDG")) | AF57: =IF($AE57="","",IF($AE57="OVF","",$A57-COUNTIF(permit_calc!$L$3:$L$144,1)))
A58: =IF(ROW()-29>COUNTIF(permit_calc!$L$3:$L$144,1)+COUNTA($G$18:$G$25),"",ROW()-29) | B58: =IF($A58="","",IF($AE58="OVF",INDEX(permit_calc!$B$3:$B$144,MATCH($A58,permit_calc!$N$3:$N$144,0)),IFERROR(INDEX(countries!$B:$B,MATCH($C58,countries!$D:$D,0)),$C58))) | C58: {=IF($A58="","",IF($AE58="OVF",INDEX(permit_calc!$A$3:$A$144,MATCH($A58,permit_calc!$N$3:$N$144,0)),INDEX($U$18:$U$25,$AF58)))} | D58: =IF($A58="","",$AE58) | E58: {=IF($A58="","",IF($AE58="OVF","",INDEX($G$18:$G$25,$AF58)))} | F58: {=IF($A58="","",IF($AE58="OVF",INDEX(permit_calc!$M$3:$M$144,MATCH($A58,permit_calc!$N$3:$N$144,0)),INDEX($A$18:$A$25,$AF58)))} | H58: {=IF($A58="","",IF($AE58="OVF",INDEX($E$18:$E$25,INDEX(permit_calc!$O$3:$O$144,MATCH($A58,permit_calc!$N$3:$N$144,0)))+INDEX($F$18:$F$25,INDEX(permit_calc!$O$3:$O$144,MATCH($A58,permit_calc!$N$3:$N$144,0))),INDEX($L$18:$L$25,$AF58)+INDEX($M$18:$M$25,$AF58)))} | I58: =IF($A58="","",IFERROR(IF(INDEX(countries!$I:$I,MATCH($C58,countries!$D:$D,0))=0,$B$12,INDEX(countries!$I:$I,MATCH($C58,countries!$D:$D,0))),$B$12)) | J58: =IF($A58="","",$H58-$I58/24) | K58: =IF($A58="","",ROUND($J58-NOW(),1)) | L58: =IF($A58="","",IF($AE58="OVF",IFERROR(INDEX(countries!$G:$G,MATCH($C58,countries!$D:$D,0)),"VERIFY"),IFERROR(INDEX(countries!$H:$H,MATCH($C58,countries!$D:$D,0)),"VERIFY"))) | M58: =IF($A58="","",IF(OR(UPPER($G58)="OWN",UPPER($G58)="EXCLUDED"),"CLIENT ARRANGING",IF($K58<0,"OVERDUE",IF($K58<1,"URGENT - FILE NOW",IF($K58<3,"DUE SOON","PENDING"))))) | AE58: =IF($A58="","",IF($A58<=COUNTIF(permit_calc!$L$3:$L$144,1),"OVF","LDG")) | AF58: =IF($AE58="","",IF($AE58="OVF","",$A58-COUNTIF(permit_calc!$L$3:$L$144,1)))
A59: =IF(ROW()-29>COUNTIF(permit_calc!$L$3:$L$144,1)+COUNTA($G$18:$G$25),"",ROW()-29) | B59: =IF($A59="","",IF($AE59="OVF",INDEX(permit_calc!$B$3:$B$144,MATCH($A59,permit_calc!$N$3:$N$144,0)),IFERROR(INDEX(countries!$B:$B,MATCH($C59,countries!$D:$D,0)),$C59))) | C59: {=IF($A59="","",IF($AE59="OVF",INDEX(permit_calc!$A$3:$A$144,MATCH($A59,permit_calc!$N$3:$N$144,0)),INDEX($U$18:$U$25,$AF59)))} | D59: =IF($A59="","",$AE59) | E59: {=IF($A59="","",IF($AE59="OVF","",INDEX($G$18:$G$25,$AF59)))} | F59: {=IF($A59="","",IF($AE59="OVF",INDEX(permit_calc!$M$3:$M$144,MATCH($A59,permit_calc!$N$3:$N$144,0)),INDEX($A$18:$A$25,$AF59)))} | H59: {=IF($A59="","",IF($AE59="OVF",INDEX($E$18:$E$25,INDEX(permit_calc!$O$3:$O$144,MATCH($A59,permit_calc!$N$3:$N$144,0)))+INDEX($F$18:$F$25,INDEX(permit_calc!$O$3:$O$144,MATCH($A59,permit_calc!$N$3:$N$144,0))),INDEX($L$18:$L$25,$AF59)+INDEX($M$18:$M$25,$AF59)))} | I59: =IF($A59="","",IFERROR(IF(INDEX(countries!$I:$I,MATCH($C59,countries!$D:$D,0))=0,$B$12,INDEX(countries!$I:$I,MATCH($C59,countries!$D:$D,0))),$B$12)) | J59: =IF($A59="","",$H59-$I59/24) | K59: =IF($A59="","",ROUND($J59-NOW(),1)) | L59: =IF($A59="","",IF($AE59="OVF",IFERROR(INDEX(countries!$G:$G,MATCH($C59,countries!$D:$D,0)),"VERIFY"),IFERROR(INDEX(countries!$H:$H,MATCH($C59,countries!$D:$D,0)),"VERIFY"))) | M59: =IF($A59="","",IF(OR(UPPER($G59)="OWN",UPPER($G59)="EXCLUDED"),"CLIENT ARRANGING",IF($K59<0,"OVERDUE",IF($K59<1,"URGENT - FILE NOW",IF($K59<3,"DUE SOON","PENDING"))))) | AE59: =IF($A59="","",IF($A59<=COUNTIF(permit_calc!$L$3:$L$144,1),"OVF","LDG")) | AF59: =IF($AE59="","",IF($AE59="OVF","",$A59-COUNTIF(permit_calc!$L$3:$L$144,1)))
A60: =IF(ROW()-29>COUNTIF(permit_calc!$L$3:$L$144,1)+COUNTA($G$18:$G$25),"",ROW()-29) | B60: =IF($A60="","",IF($AE60="OVF",INDEX(permit_calc!$B$3:$B$144,MATCH($A60,permit_calc!$N$3:$N$144,0)),IFERROR(INDEX(countries!$B:$B,MATCH($C60,countries!$D:$D,0)),$C60))) | C60: {=IF($A60="","",IF($AE60="OVF",INDEX(permit_calc!$A$3:$A$144,MATCH($A60,permit_calc!$N$3:$N$144,0)),INDEX($U$18:$U$25,$AF60)))} | D60: =IF($A60="","",$AE60) | E60: {=IF($A60="","",IF($AE60="OVF","",INDEX($G$18:$G$25,$AF60)))} | F60: {=IF($A60="","",IF($AE60="OVF",INDEX(permit_calc!$M$3:$M$144,MATCH($A60,permit_calc!$N$3:$N$144,0)),INDEX($A$18:$A$25,$AF60)))} | H60: {=IF($A60="","",IF($AE60="OVF",INDEX($E$18:$E$25,INDEX(permit_calc!$O$3:$O$144,MATCH($A60,permit_calc!$N$3:$N$144,0)))+INDEX($F$18:$F$25,INDEX(permit_calc!$O$3:$O$144,MATCH($A60,permit_calc!$N$3:$N$144,0))),INDEX($L$18:$L$25,$AF60)+INDEX($M$18:$M$25,$AF60)))} | I60: =IF($A60="","",IFERROR(IF(INDEX(countries!$I:$I,MATCH($C60,countries!$D:$D,0))=0,$B$12,INDEX(countries!$I:$I,MATCH($C60,countries!$D:$D,0))),$B$12)) | J60: =IF($A60="","",$H60-$I60/24) | K60: =IF($A60="","",ROUND($J60-NOW(),1)) | L60: =IF($A60="","",IF($AE60="OVF",IFERROR(INDEX(countries!$G:$G,MATCH($C60,countries!$D:$D,0)),"VERIFY"),IFERROR(INDEX(countries!$H:$H,MATCH($C60,countries!$D:$D,0)),"VERIFY"))) | M60: =IF($A60="","",IF(OR(UPPER($G60)="OWN",UPPER($G60)="EXCLUDED"),"CLIENT ARRANGING",IF($K60<0,"OVERDUE",IF($K60<1,"URGENT - FILE NOW",IF($K60<3,"DUE SOON","PENDING"))))) | AE60: =IF($A60="","",IF($A60<=COUNTIF(permit_calc!$L$3:$L$144,1),"OVF","LDG")) | AF60: =IF($AE60="","",IF($AE60="OVF","",$A60-COUNTIF(permit_calc!$L$3:$L$144,1)))
A61: =IF(ROW()-29>COUNTIF(permit_calc!$L$3:$L$144,1)+COUNTA($G$18:$G$25),"",ROW()-29) | B61: =IF($A61="","",IF($AE61="OVF",INDEX(permit_calc!$B$3:$B$144,MATCH($A61,permit_calc!$N$3:$N$144,0)),IFERROR(INDEX(countries!$B:$B,MATCH($C61,countries!$D:$D,0)),$C61))) | C61: {=IF($A61="","",IF($AE61="OVF",INDEX(permit_calc!$A$3:$A$144,MATCH($A61,permit_calc!$N$3:$N$144,0)),INDEX($U$18:$U$25,$AF61)))} | D61: =IF($A61="","",$AE61) | E61: {=IF($A61="","",IF($AE61="OVF","",INDEX($G$18:$G$25,$AF61)))} | F61: {=IF($A61="","",IF($AE61="OVF",INDEX(permit_calc!$M$3:$M$144,MATCH($A61,permit_calc!$N$3:$N$144,0)),INDEX($A$18:$A$25,$AF61)))} | H61: {=IF($A61="","",IF($AE61="OVF",INDEX($E$18:$E$25,INDEX(permit_calc!$O$3:$O$144,MATCH($A61,permit_calc!$N$3:$N$144,0)))+INDEX($F$18:$F$25,INDEX(permit_calc!$O$3:$O$144,MATCH($A61,permit_calc!$N$3:$N$144,0))),INDEX($L$18:$L$25,$AF61)+INDEX($M$18:$M$25,$AF61)))} | I61: =IF($A61="","",IFERROR(IF(INDEX(countries!$I:$I,MATCH($C61,countries!$D:$D,0))=0,$B$12,INDEX(countries!$I:$I,MATCH($C61,countries!$D:$D,0))),$B$12)) | J61: =IF($A61="","",$H61-$I61/24) | K61: =IF($A61="","",ROUND($J61-NOW(),1)) | L61: =IF($A61="","",IF($AE61="OVF",IFERROR(INDEX(countries!$G:$G,MATCH($C61,countries!$D:$D,0)),"VERIFY"),IFERROR(INDEX(countries!$H:$H,MATCH($C61,countries!$D:$D,0)),"VERIFY"))) | M61: =IF($A61="","",IF(OR(UPPER($G61)="OWN",UPPER($G61)="EXCLUDED"),"CLIENT ARRANGING",IF($K61<0,"OVERDUE",IF($K61<1,"URGENT - FILE NOW",IF($K61<3,"DUE SOON","PENDING"))))) | AE61: =IF($A61="","",IF($A61<=COUNTIF(permit_calc!$L$3:$L$144,1),"OVF","LDG")) | AF61: =IF($AE61="","",IF($AE61="OVF","",$A61-COUNTIF(permit_calc!$L$3:$L$144,1)))
A62: =IF(ROW()-29>COUNTIF(permit_calc!$L$3:$L$144,1)+COUNTA($G$18:$G$25),"",ROW()-29) | B62: =IF($A62="","",IF($AE62="OVF",INDEX(permit_calc!$B$3:$B$144,MATCH($A62,permit_calc!$N$3:$N$144,0)),IFERROR(INDEX(countries!$B:$B,MATCH($C62,countries!$D:$D,0)),$C62))) | C62: {=IF($A62="","",IF($AE62="OVF",INDEX(permit_calc!$A$3:$A$144,MATCH($A62,permit_calc!$N$3:$N$144,0)),INDEX($U$18:$U$25,$AF62)))} | D62: =IF($A62="","",$AE62) | E62: {=IF($A62="","",IF($AE62="OVF","",INDEX($G$18:$G$25,$AF62)))} | F62: {=IF($A62="","",IF($AE62="OVF",INDEX(permit_calc!$M$3:$M$144,MATCH($A62,permit_calc!$N$3:$N$144,0)),INDEX($A$18:$A$25,$AF62)))} | H62: {=IF($A62="","",IF($AE62="OVF",INDEX($E$18:$E$25,INDEX(permit_calc!$O$3:$O$144,MATCH($A62,permit_calc!$N$3:$N$144,0)))+INDEX($F$18:$F$25,INDEX(permit_calc!$O$3:$O$144,MATCH($A62,permit_calc!$N$3:$N$144,0))),INDEX($L$18:$L$25,$AF62)+INDEX($M$18:$M$25,$AF62)))} | I62: =IF($A62="","",IFERROR(IF(INDEX(countries!$I:$I,MATCH($C62,countries!$D:$D,0))=0,$B$12,INDEX(countries!$I:$I,MATCH($C62,countries!$D:$D,0))),$B$12)) | J62: =IF($A62="","",$H62-$I62/24) | K62: =IF($A62="","",ROUND($J62-NOW(),1)) | L62: =IF($A62="","",IF($AE62="OVF",IFERROR(INDEX(countries!$G:$G,MATCH($C62,countries!$D:$D,0)),"VERIFY"),IFERROR(INDEX(countries!$H:$H,MATCH($C62,countries!$D:$D,0)),"VERIFY"))) | M62: =IF($A62="","",IF(OR(UPPER($G62)="OWN",UPPER($G62)="EXCLUDED"),"CLIENT ARRANGING",IF($K62<0,"OVERDUE",IF($K62<1,"URGENT - FILE NOW",IF($K62<3,"DUE SOON","PENDING"))))) | AE62: =IF($A62="","",IF($A62<=COUNTIF(permit_calc!$L$3:$L$144,1),"OVF","LDG")) | AF62: =IF($AE62="","",IF($AE62="OVF","",$A62-COUNTIF(permit_calc!$L$3:$L$144,1)))
A63: =IF(ROW()-29>COUNTIF(permit_calc!$L$3:$L$144,1)+COUNTA($G$18:$G$25),"",ROW()-29) | B63: =IF($A63="","",IF($AE63="OVF",INDEX(permit_calc!$B$3:$B$144,MATCH($A63,permit_calc!$N$3:$N$144,0)),IFERROR(INDEX(countries!$B:$B,MATCH($C63,countries!$D:$D,0)),$C63))) | C63: {=IF($A63="","",IF($AE63="OVF",INDEX(permit_calc!$A$3:$A$144,MATCH($A63,permit_calc!$N$3:$N$144,0)),INDEX($U$18:$U$25,$AF63)))} | D63: =IF($A63="","",$AE63) | E63: {=IF($A63="","",IF($AE63="OVF","",INDEX($G$18:$G$25,$AF63)))} | F63: {=IF($A63="","",IF($AE63="OVF",INDEX(permit_calc!$M$3:$M$144,MATCH($A63,permit_calc!$N$3:$N$144,0)),INDEX($A$18:$A$25,$AF63)))} | H63: {=IF($A63="","",IF($AE63="OVF",INDEX($E$18:$E$25,INDEX(permit_calc!$O$3:$O$144,MATCH($A63,permit_calc!$N$3:$N$144,0)))+INDEX($F$18:$F$25,INDEX(permit_calc!$O$3:$O$144,MATCH($A63,permit_calc!$N$3:$N$144,0))),INDEX($L$18:$L$25,$AF63)+INDEX($M$18:$M$25,$AF63)))} | I63: =IF($A63="","",IFERROR(IF(INDEX(countries!$I:$I,MATCH($C63,countries!$D:$D,0))=0,$B$12,INDEX(countries!$I:$I,MATCH($C63,countries!$D:$D,0))),$B$12)) | J63: =IF($A63="","",$H63-$I63/24) | K63: =IF($A63="","",ROUND($J63-NOW(),1)) | L63: =IF($A63="","",IF($AE63="OVF",IFERROR(INDEX(countries!$G:$G,MATCH($C63,countries!$D:$D,0)),"VERIFY"),IFERROR(INDEX(countries!$H:$H,MATCH($C63,countries!$D:$D,0)),"VERIFY"))) | M63: =IF($A63="","",IF(OR(UPPER($G63)="OWN",UPPER($G63)="EXCLUDED"),"CLIENT ARRANGING",IF($K63<0,"OVERDUE",IF($K63<1,"URGENT - FILE NOW",IF($K63<3,"DUE SOON","PENDING"))))) | AE63: =IF($A63="","",IF($A63<=COUNTIF(permit_calc!$L$3:$L$144,1),"OVF","LDG")) | AF63: =IF($AE63="","",IF($AE63="OVF","",$A63-COUNTIF(permit_calc!$L$3:$L$144,1)))
A64: =IF(ROW()-29>COUNTIF(permit_calc!$L$3:$L$144,1)+COUNTA($G$18:$G$25),"",ROW()-29) | B64: =IF($A64="","",IF($AE64="OVF",INDEX(permit_calc!$B$3:$B$144,MATCH($A64,permit_calc!$N$3:$N$144,0)),IFERROR(INDEX(countries!$B:$B,MATCH($C64,countries!$D:$D,0)),$C64))) | C64: {=IF($A64="","",IF($AE64="OVF",INDEX(permit_calc!$A$3:$A$144,MATCH($A64,permit_calc!$N$3:$N$144,0)),INDEX($U$18:$U$25,$AF64)))} | D64: =IF($A64="","",$AE64) | E64: {=IF($A64="","",IF($AE64="OVF","",INDEX($G$18:$G$25,$AF64)))} | F64: {=IF($A64="","",IF($AE64="OVF",INDEX(permit_calc!$M$3:$M$144,MATCH($A64,permit_calc!$N$3:$N$144,0)),INDEX($A$18:$A$25,$AF64)))} | H64: {=IF($A64="","",IF($AE64="OVF",INDEX($E$18:$E$25,INDEX(permit_calc!$O$3:$O$144,MATCH($A64,permit_calc!$N$3:$N$144,0)))+INDEX($F$18:$F$25,INDEX(permit_calc!$O$3:$O$144,MATCH($A64,permit_calc!$N$3:$N$144,0))),INDEX($L$18:$L$25,$AF64)+INDEX($M$18:$M$25,$AF64)))} | I64: =IF($A64="","",IFERROR(IF(INDEX(countries!$I:$I,MATCH($C64,countries!$D:$D,0))=0,$B$12,INDEX(countries!$I:$I,MATCH($C64,countries!$D:$D,0))),$B$12)) | J64: =IF($A64="","",$H64-$I64/24) | K64: =IF($A64="","",ROUND($J64-NOW(),1)) | L64: =IF($A64="","",IF($AE64="OVF",IFERROR(INDEX(countries!$G:$G,MATCH($C64,countries!$D:$D,0)),"VERIFY"),IFERROR(INDEX(countries!$H:$H,MATCH($C64,countries!$D:$D,0)),"VERIFY"))) | M64: =IF($A64="","",IF(OR(UPPER($G64)="OWN",UPPER($G64)="EXCLUDED"),"CLIENT ARRANGING",IF($K64<0,"OVERDUE",IF($K64<1,"URGENT - FILE NOW",IF($K64<3,"DUE SOON","PENDING"))))) | AE64: =IF($A64="","",IF($A64<=COUNTIF(permit_calc!$L$3:$L$144,1),"OVF","LDG")) | AF64: =IF($AE64="","",IF($AE64="OVF","",$A64-COUNTIF(permit_calc!$L$3:$L$144,1)))
A65: =IF(ROW()-29>COUNTIF(permit_calc!$L$3:$L$144,1)+COUNTA($G$18:$G$25),"",ROW()-29) | B65: =IF($A65="","",IF($AE65="OVF",INDEX(permit_calc!$B$3:$B$144,MATCH($A65,permit_calc!$N$3:$N$144,0)),IFERROR(INDEX(countries!$B:$B,MATCH($C65,countries!$D:$D,0)),$C65))) | C65: {=IF($A65="","",IF($AE65="OVF",INDEX(permit_calc!$A$3:$A$144,MATCH($A65,permit_calc!$N$3:$N$144,0)),INDEX($U$18:$U$25,$AF65)))} | D65: =IF($A65="","",$AE65) | E65: {=IF($A65="","",IF($AE65="OVF","",INDEX($G$18:$G$25,$AF65)))} | F65: {=IF($A65="","",IF($AE65="OVF",INDEX(permit_calc!$M$3:$M$144,MATCH($A65,permit_calc!$N$3:$N$144,0)),INDEX($A$18:$A$25,$AF65)))} | H65: {=IF($A65="","",IF($AE65="OVF",INDEX($E$18:$E$25,INDEX(permit_calc!$O$3:$O$144,MATCH($A65,permit_calc!$N$3:$N$144,0)))+INDEX($F$18:$F$25,INDEX(permit_calc!$O$3:$O$144,MATCH($A65,permit_calc!$N$3:$N$144,0))),INDEX($L$18:$L$25,$AF65)+INDEX($M$18:$M$25,$AF65)))} | I65: =IF($A65="","",IFERROR(IF(INDEX(countries!$I:$I,MATCH($C65,countries!$D:$D,0))=0,$B$12,INDEX(countries!$I:$I,MATCH($C65,countries!$D:$D,0))),$B$12)) | J65: =IF($A65="","",$H65-$I65/24) | K65: =IF($A65="","",ROUND($J65-NOW(),1)) | L65: =IF($A65="","",IF($AE65="OVF",IFERROR(INDEX(countries!$G:$G,MATCH($C65,countries!$D:$D,0)),"VERIFY"),IFERROR(INDEX(countries!$H:$H,MATCH($C65,countries!$D:$D,0)),"VERIFY"))) | M65: =IF($A65="","",IF(OR(UPPER($G65)="OWN",UPPER($G65)="EXCLUDED"),"CLIENT ARRANGING",IF($K65<0,"OVERDUE",IF($K65<1,"URGENT - FILE NOW",IF($K65<3,"DUE SOON","PENDING"))))) | AE65: =IF($A65="","",IF($A65<=COUNTIF(permit_calc!$L$3:$L$144,1),"OVF","LDG")) | AF65: =IF($AE65="","",IF($AE65="OVF","",$A65-COUNTIF(permit_calc!$L$3:$L$144,1)))
... A69: =IF(ROW()-29>COUNTIF(permit_calc!$L$3:$L$144,1)+COUNTA($G$18:$G$25),"",ROW()-29) | B69: =IF($A69="","",IF($AE69="OVF",INDEX(permit_calc!$B$3:$B$144,MATCH($A69,permit_calc!$N$3:$N$144,0)),IFERROR(INDEX(countries!$B:$B,MATCH($C69,countries!$D:$D,0)),$C69))) | C69: {=IF($A69="","",IF($AE69="OVF",INDEX(permit_calc!$A$3:$A$144,MATCH($A69,permit_calc!$N$3:$N$144,0)),INDEX($U$18:$U$25,$AF69)))} | D69: =IF($A69="","",$AE69) | E69: {=IF($A69="","",IF($AE69="OVF","",INDEX($G$18:$G$25,$AF69)))} | F69: {=IF($A69="","",IF($AE69="OVF",INDEX(permit_calc!$M$3:$M$144,MATCH($A69,permit_calc!$N$3:$N$144,0)),INDEX($A$18:$A$25,$AF69)))} | H69: {=IF($A69="","",IF($AE69="OVF",INDEX($E$18:$E$25,INDEX(permit_calc!$O$3:$O$144,MATCH($A69,permit_calc!$N$3:$N$144,0)))+INDEX($F$18:$F$25,INDEX(permit_calc!$O$3:$O$144,MATCH($A69,permit_calc!$N$3:$N$144,0))),INDEX($L$18:$L$25,$AF69)+INDEX($M$18:$M$25,$AF69)))} | I69: =IF($A69="","",IFERROR(IF(INDEX(countries!$I:$I,MATCH($C69,countries!$D:$D,0))=0,$B$12,INDEX(countries!$I:$I,MATCH($C69,countries!$D:$D,0))),$B$12)) | J69: =IF($A69="","",$H69-$I69/24) | K69: =IF($A69="","",ROUND($J69-NOW(),1)) | L69: =IF($A69="","",IF($AE69="OVF",IFERROR(INDEX(countries!$G:$G,MATCH($C69,countries!$D:$D,0)),"VERIFY"),IFERROR(INDEX(countries!$H:$H,MATCH($C69,countries!$D:$D,0)),"VERIFY"))) | M69: =IF($A69="","",IF(OR(UPPER($G69)="OWN",UPPER($G69)="EXCLUDED"),"CLIENT ARRANGING",IF($K69<0,"OVERDUE",IF($K69<1,"URGENT - FILE NOW",IF($K69<3,"DUE SOON","PENDING"))))) | AE69: =IF($A69="","",IF($A69<=COUNTIF(permit_calc!$L$3:$L$144,1),"OVF","LDG")) | AF69: =IF($AE69="","",IF($AE69="OVF","",$A69-COUNTIF(permit_calc!$L$3:$L$144,1)))
A70: =IF(COUNTIF(permit_calc!$L$3:$L$144,1)+COUNTA($G$18:$G$25)>40,"WARNING: more permit lines than rows available in section 3 - extend the block below row 69","")
A71: 4 · GROUND SERVICES BY STOP (one line per country on the ground · enter the provider in a service column to order it — blank means not required)
H72: =IFERROR(INDEX('SERVICE CATALOGUE'!$B$3:$B$100,MATCH(COLUMN()-7,'SERVICE CATALOGUE'!$F$3:$F$100,0)),"") -> Ground Handling | I72: =IFERROR(INDEX('SERVICE CATALOGUE'!$B$3:$B$100,MATCH(COLUMN()-7,'SERVICE CATALOGUE'!$F$3:$F$100,0)),"") -> Fuel | J72: =IFERROR(INDEX('SERVICE CATALOGUE'!$B$3:$B$100,MATCH(COLUMN()-7,'SERVICE CATALOGUE'!$F$3:$F$100,0)),"") -> Catering | K72: =IFERROR(INDEX('SERVICE CATALOGUE'!$B$3:$B$100,MATCH(COLUMN()-7,'SERVICE CATALOGUE'!$F$3:$F$100,0)),"") -> Navigation & Enroute Charges | L72: =IFERROR(INDEX('SERVICE CATALOGUE'!$B$3:$B$100,MATCH(COLUMN()-7,'SERVICE CATALOGUE'!$F$3:$F$100,0)),"") -> Slots, PPR & Parking | M72: =IFERROR(INDEX('SERVICE CATALOGUE'!$B$3:$B$100,MATCH(COLUMN()-7,'SERVICE CATALOGUE'!$F$3:$F$100,0)),"") -> Security | N72: =IFERROR(INDEX('SERVICE CATALOGUE'!$B$3:$B$100,MATCH(COLUMN()-7,'SERVICE CATALOGUE'!$F$3:$F$100,0)),"") -> Crew Services | O72: =IFERROR(INDEX('SERVICE CATALOGUE'!$B$3:$B$100,MATCH(COLUMN()-7,'SERVICE CATALOGUE'!$F$3:$F$100,0)),"") -> Flight Planning & Dispatch | ... V72: =IFERROR(INDEX('SERVICE CATALOGUE'!$B$3:$B$100,MATCH(COLUMN()-7,'SERVICE CATALOGUE'!$F$3:$F$100,0)),"") -> Pax Hotel | W72: stop and handling policy
A73: STOP | B73: COUNTRY | C73: ISO3 | D73: AIRPORT(S) | E73: LEGS | F73: FIRST ON GROUND (UTC) | G73: SERVICES ORDERED | H73: =IFERROR(INDEX('SERVICE CATALOGUE'!$C$3:$C$100,MATCH(COLUMN()-7,'SERVICE CATALOGUE'!$F$3:$F$100,0)),"") -> GH | I73: =IFERROR(INDEX('SERVICE CATALOGUE'!$C$3:$C$100,MATCH(COLUMN()-7,'SERVICE CATALOGUE'!$F$3:$F$100,0)),"") -> FUL | J73: =IFERROR(INDEX('SERVICE CATALOGUE'!$C$3:$C$100,MATCH(COLUMN()-7,'SERVICE CATALOGUE'!$F$3:$F$100,0)),"") -> CAT | K73: =IFERROR(INDEX('SERVICE CATALOGUE'!$C$3:$C$100,MATCH(COLUMN()-7,'SERVICE CATALOGUE'!$F$3:$F$100,0)),"") -> NAV | L73: =IFERROR(INDEX('SERVICE CATALOGUE'!$C$3:$C$100,MATCH(COLUMN()-7,'SERVICE CATALOGUE'!$F$3:$F$100,0)),"") -> SLT | M73: =IFERROR(INDEX('SERVICE CATALOGUE'!$C$3:$C$100,MATCH(COLUMN()-7,'SERVICE CATALOGUE'!$F$3:$F$100,0)),"") -> SEC | N73: =IFERROR(INDEX('SERVICE CATALOGUE'!$C$3:$C$100,MATCH(COLUMN()-7,'SERVICE CATALOGUE'!$F$3:$F$100,0)),"") -> CRW | O73: =IFERROR(INDEX('SERVICE CATALOGUE'!$C$3:$C$100,MATCH(COLUMN()-7,'SERVICE CATALOGUE'!$F$3:$F$100,0)),"") -> FPL | ... V73: =IFERROR(INDEX('SERVICE CATALOGUE'!$C$3:$C$100,MATCH(COLUMN()-7,'SERVICE CATALOGUE'!$F$3:$F$100,0)),"") -> PXH | W73: STOP TYPE | X73: HANDLING MANDATORY | Y73: SELF-HANDLING | Z73: PREFERRED VENDOR | AA73: VENDOR SOURCE | AB73: VENDORS AVAILABLE | AC73: STATION CONTACT | AD73: STATION EMAIL
A74: =IF(ROW()-73>SUM($AO$18:$AO$26),"",ROW()-73) -> 1 | B74: =IF($A74="","",IFERROR(INDEX(countries!$B:$B,MATCH($C74,countries!$D:$D,0)),$C74)) -> South Africa | C74: =IF($A74="","",INDEX($AK$18:$AK$26,MATCH($A74,$AP$18:$AP$26,0))) -> ZAF | D74: {=IF($A74="","",_xlfn.TEXTJOIN(", ",TRUE,IF($AK$18:$AK$26=$C74,$AL$18:$AL$26,"")))} -> FALA, FAOR | E74: {=IF($A74="","",_xlfn.TEXTJOIN(", ",TRUE,IF($AK$18:$AK$26=$C74,$AM$18:$AM$26,"")))} -> L1, L4 | F74: =IF($A74="","",_xlfn.MINIFS($AN$18:$AN$26,$AK$18:$AK$26,$C74)) -> 46248.375 | G74: =IF($A74="","",COUNTA($H74:$V74)) -> 1 | H74: JTL | W74: RON (REMAINING OVERNIGHT) | X74: =IF($A74="","",IFERROR(INDEX(countries!$L:$L,MATCH($C74,countries!$D:$D,0)),"VERIFY")) -> VERIFY | Y74: =IF($A74="","",IFERROR(INDEX(countries!$M:$M,MATCH($C74,countries!$D:$D,0)),"VERIFY")) -> VERIFY | Z74: =IF($A74="","",IFERROR(INDEX(HANDLERS!$B$4:$B$250,MATCH(TRIM(LEFT($D74&",",FIND(",",$D74&",")-1)),HANDLERS!$C$4:$C$250,0)),IFERROR(INDEX(Vendors!$B:$B,MATCH(INDEX(vendor_coverage_countries!$B:$B,MATCH(IFERROR(INDEX(countries!$C:$C,MATCH($C74,countries!$D:$D,0)),""),vendor_coverage_countries!$C:$C,0)),Vendors!$A:$A,0)),"NO VENDOR ON FILE FOR THIS STATE"))) -> ExecuJet | AA74: =IF($A74="","",IF(ISNUMBER(MATCH(TRIM(LEFT($D74&",",FIND(",",$D74&",")-1)),HANDLERS!$C$4:$C$250,0)),"HANDLERS (station "&TRIM(LEFT($D74&",",FIND(",",$D74&",")-1))&")",IF($AB74=0,"-","vendor_coverage_countries"))) -> HANDLERS (station FALA) | AB74: =IF($A74="","",COUNTIF(vendor_coverage_countries!$C:$C,IFERROR(INDEX(countries!$C:$C,MATCH($C74,countries!$D:$D,0)),""))) -> 12 | AC74: =IF($A74="","",IFERROR(INDEX(HANDLERS!$D$4:$D$250,MATCH(TRIM(LEFT($D74&",",FIND(",",$D74&",")-1)),HANDLERS!$C$4:$C$250,0)),"")) -> Wilson Thabetha | AD74: =IF($A74="","",IFERROR(INDEX(HANDLERS!$E$4:$E$250,MATCH(TRIM(LEFT($D74&",",FIND(",",$D74&",")-1)),HANDLERS!$C$4:$C$250,0)),"")) -> wilson.thabetha@execujet.com
A75: =IF(ROW()-73>SUM($AO$18:$AO$26),"",ROW()-73) -> 2 | B75: =IF($A75="","",IFERROR(INDEX(countries!$B:$B,MATCH($C75,countries!$D:$D,0)),$C75)) -> Chad | C75: =IF($A75="","",INDEX($AK$18:$AK$26,MATCH($A75,$AP$18:$AP$26,0))) -> TCD | D75: {=IF($A75="","",_xlfn.TEXTJOIN(", ",TRUE,IF($AK$18:$AK$26=$C75,$AL$18:$AL$26,"")))} -> FTTJ | E75: {=IF($A75="","",_xlfn.TEXTJOIN(", ",TRUE,IF($AK$18:$AK$26=$C75,$AM$18:$AM$26,"")))} -> L1 | F75: =IF($A75="","",_xlfn.MINIFS($AN$18:$AN$26,$AK$18:$AK$26,$C75)) -> 46248.605 | G75: =IF($A75="","",COUNTA($H75:$V75)) -> 1 | H75: JTL | W75: TECH STOP | X75: =IF($A75="","",IFERROR(INDEX(countries!$L:$L,MATCH($C75,countries!$D:$D,0)),"VERIFY")) -> VERIFY | Y75: =IF($A75="","",IFERROR(INDEX(countries!$M:$M,MATCH($C75,countries!$D:$D,0)),"VERIFY")) -> VERIFY | Z75: =IF($A75="","",IFERROR(INDEX(HANDLERS!$B$4:$B$250,MATCH(TRIM(LEFT($D75&",",FIND(",",$D75&",")-1)),HANDLERS!$C$4:$C$250,0)),IFERROR(INDEX(Vendors!$B:$B,MATCH(INDEX(vendor_coverage_countries!$B:$B,MATCH(IFERROR(INDEX(countries!$C:$C,MATCH($C75,countries!$D:$D,0)),""),vendor_coverage_countries!$C:$C,0)),Vendors!$A:$A,0)),"NO VENDOR ON FILE FOR THIS STATE"))) -> GAS | AA75: =IF($A75="","",IF(ISNUMBER(MATCH(TRIM(LEFT($D75&",",FIND(",",$D75&",")-1)),HANDLERS!$C$4:$C$250,0)),"HANDLERS (station "&TRIM(LEFT($D75&",",FIND(",",$D75&",")-1))&")",IF($AB75=0,"-","vendor_coverage_countries"))) -> HANDLERS (station FTTJ) | AB75: =IF($A75="","",COUNTIF(vendor_coverage_countries!$C:$C,IFERROR(INDEX(countries!$C:$C,MATCH($C75,countries!$D:$D,0)),""))) -> 1 | AC75: =IF($A75="","",IFERROR(INDEX(HANDLERS!$D$4:$D$250,MATCH(TRIM(LEFT($D75&",",FIND(",",$D75&",")-1)),HANDLERS!$C$4:$C$250,0)),"")) -> Youssouf Alkhali | AD75: =IF($A75="","",IFERROR(INDEX(HANDLERS!$E$4:$E$250,MATCH(TRIM(LEFT($D75&",",FIND(",",$D75&",")-1)),HANDLERS!$C$4:$C$250,0)),"")) -> alkhaliservice@gmail.com
A76: =IF(ROW()-73>SUM($AO$18:$AO$26),"",ROW()-73) -> 3 | B76: =IF($A76="","",IFERROR(INDEX(countries!$B:$B,MATCH($C76,countries!$D:$D,0)),$C76)) -> Egypt | C76: =IF($A76="","",INDEX($AK$18:$AK$26,MATCH($A76,$AP$18:$AP$26,0))) -> EGY | D76: {=IF($A76="","",_xlfn.TEXTJOIN(", ",TRUE,IF($AK$18:$AK$26=$C76,$AL$18:$AL$26,"")))} -> HECA | E76: {=IF($A76="","",_xlfn.TEXTJOIN(", ",TRUE,IF($AK$18:$AK$26=$C76,$AM$18:$AM$26,"")))} -> L2 | F76: =IF($A76="","",_xlfn.MINIFS($AN$18:$AN$26,$AK$18:$AK$26,$C76)) -> 46250.392 | G76: =IF($A76="","",COUNTA($H76:$V76)) -> 1 | H76: JTL | W76: RON (REMAINING OVERNIGHT) | X76: =IF($A76="","",IFERROR(INDEX(countries!$L:$L,MATCH($C76,countries!$D:$D,0)),"VERIFY")) -> VERIFY | Y76: =IF($A76="","",IFERROR(INDEX(countries!$M:$M,MATCH($C76,countries!$D:$D,0)),"VERIFY")) -> VERIFY | Z76: =IF($A76="","",IFERROR(INDEX(HANDLERS!$B$4:$B$250,MATCH(TRIM(LEFT($D76&",",FIND(",",$D76&",")-1)),HANDLERS!$C$4:$C$250,0)),IFERROR(INDEX(Vendors!$B:$B,MATCH(INDEX(vendor_coverage_countries!$B:$B,MATCH(IFERROR(INDEX(countries!$C:$C,MATCH($C76,countries!$D:$D,0)),""),vendor_coverage_countries!$C:$C,0)),Vendors!$A:$A,0)),"NO VENDOR ON FILE FOR THIS STATE"))) -> Egypt Jet Aviation | AA76: =IF($A76="","",IF(ISNUMBER(MATCH(TRIM(LEFT($D76&",",FIND(",",$D76&",")-1)),HANDLERS!$C$4:$C$250,0)),"HANDLERS (station "&TRIM(LEFT($D76&",",FIND(",",$D76&",")-1))&")",IF($AB76=0,"-","vendor_coverage_countries"))) -> HANDLERS (station HECA) | AB76: =IF($A76="","",COUNTIF(vendor_coverage_countries!$C:$C,IFERROR(INDEX(countries!$C:$C,MATCH($C76,countries!$D:$D,0)),""))) -> 10 | AC76: =IF($A76="","",IFERROR(INDEX(HANDLERS!$D$4:$D$250,MATCH(TRIM(LEFT($D76&",",FIND(",",$D76&",")-1)),HANDLERS!$C$4:$C$250,0)),"")) -> Ahmed Hamdy | AD76: =IF($A76="","",IFERROR(INDEX(HANDLERS!$E$4:$E$250,MATCH(TRIM(LEFT($D76&",",FIND(",",$D76&",")-1)),HANDLERS!$C$4:$C$250,0)),"")) -> ops@eja.com.eg
A77: =IF(ROW()-73>SUM($AO$18:$AO$26),"",ROW()-73) -> 4 | B77: =IF($A77="","",IFERROR(INDEX(countries!$B:$B,MATCH($C77,countries!$D:$D,0)),$C77)) -> Morocco | C77: =IF($A77="","",INDEX($AK$18:$AK$26,MATCH($A77,$AP$18:$AP$26,0))) -> MAR | D77: {=IF($A77="","",_xlfn.TEXTJOIN(", ",TRUE,IF($AK$18:$AK$26=$C77,$AL$18:$AL$26,"")))} -> GMAD | E77: {=IF($A77="","",_xlfn.TEXTJOIN(", ",TRUE,IF($AK$18:$AK$26=$C77,$AM$18:$AM$26,"")))} -> L3 | F77: =IF($A77="","",_xlfn.MINIFS($AN$18:$AN$26,$AK$18:$AK$26,$C77)) -> 46251.37 | G77: =IF($A77="","",COUNTA($H77:$V77)) -> 1 | H77: JTL | W77: TURNAROUND | X77: =IF($A77="","",IFERROR(INDEX(countries!$L:$L,MATCH($C77,countries!$D:$D,0)),"VERIFY")) -> VERIFY | Y77: =IF($A77="","",IFERROR(INDEX(countries!$M:$M,MATCH($C77,countries!$D:$D,0)),"VERIFY")) -> VERIFY | Z77: =IF($A77="","",IFERROR(INDEX(HANDLERS!$B$4:$B$250,MATCH(TRIM(LEFT($D77&",",FIND(",",$D77&",")-1)),HANDLERS!$C$4:$C$250,0)),IFERROR(INDEX(Vendors!$B:$B,MATCH(INDEX(vendor_coverage_countries!$B:$B,MATCH(IFERROR(INDEX(countries!$C:$C,MATCH($C77,countries!$D:$D,0)),""),vendor_coverage_countries!$C:$C,0)),Vendors!$A:$A,0)),"NO VENDOR ON FILE FOR THIS STATE"))) -> Swissport | AA77: =IF($A77="","",IF(ISNUMBER(MATCH(TRIM(LEFT($D77&",",FIND(",",$D77&",")-1)),HANDLERS!$C$4:$C$250,0)),"HANDLERS (station "&TRIM(LEFT($D77&",",FIND(",",$D77&",")-1))&")",IF($AB77=0,"-","vendor_coverage_countries"))) -> HANDLERS (station GMAD) | AB77: =IF($A77="","",COUNTIF(vendor_coverage_countries!$C:$C,IFERROR(INDEX(countries!$C:$C,MATCH($C77,countries!$D:$D,0)),""))) -> 7 | AC77: =IF($A77="","",IFERROR(INDEX(HANDLERS!$D$4:$D$250,MATCH(TRIM(LEFT($D77&",",FIND(",",$D77&",")-1)),HANDLERS!$C$4:$C$250,0)),"")) -> Abdellah Maaroufi | AD77: =IF($A77="","",IFERROR(INDEX(HANDLERS!$E$4:$E$250,MATCH(TRIM(LEFT($D77&",",FIND(",",$D77&",")-1)),HANDLERS!$C$4:$C$250,0)),"")) -> Abdellah.Maaroufi@swissportexecutive.com
A78: =IF(ROW()-73>SUM($AO$18:$AO$26),"",ROW()-73) | B78: =IF($A78="","",IFERROR(INDEX(countries!$B:$B,MATCH($C78,countries!$D:$D,0)),$C78)) | C78: =IF($A78="","",INDEX($AK$18:$AK$26,MATCH($A78,$AP$18:$AP$26,0))) | D78: {=IF($A78="","",_xlfn.TEXTJOIN(", ",TRUE,IF($AK$18:$AK$26=$C78,$AL$18:$AL$26,"")))} | E78: {=IF($A78="","",_xlfn.TEXTJOIN(", ",TRUE,IF($AK$18:$AK$26=$C78,$AM$18:$AM$26,"")))} | F78: =IF($A78="","",_xlfn.MINIFS($AN$18:$AN$26,$AK$18:$AK$26,$C78)) | G78: =IF($A78="","",COUNTA($H78:$V78)) | X78: =IF($A78="","",IFERROR(INDEX(countries!$L:$L,MATCH($C78,countries!$D:$D,0)),"VERIFY")) | Y78: =IF($A78="","",IFERROR(INDEX(countries!$M:$M,MATCH($C78,countries!$D:$D,0)),"VERIFY")) | Z78: =IF($A78="","",IFERROR(INDEX(HANDLERS!$B$4:$B$250,MATCH(TRIM(LEFT($D78&",",FIND(",",$D78&",")-1)),HANDLERS!$C$4:$C$250,0)),IFERROR(INDEX(Vendors!$B:$B,MATCH(INDEX(vendor_coverage_countries!$B:$B,MATCH(IFERROR(INDEX(countries!$C:$C,MATCH($C78,countries!$D:$D,0)),""),vendor_coverage_countries!$C:$C,0)),Vendors!$A:$A,0)),"NO VENDOR ON FILE FOR THIS STATE"))) | AA78: =IF($A78="","",IF(ISNUMBER(MATCH(TRIM(LEFT($D78&",",FIND(",",$D78&",")-1)),HANDLERS!$C$4:$C$250,0)),"HANDLERS (station "&TRIM(LEFT($D78&",",FIND(",",$D78&",")-1))&")",IF($AB78=0,"-","vendor_coverage_countries"))) | AB78: =IF($A78="","",COUNTIF(vendor_coverage_countries!$C:$C,IFERROR(INDEX(countries!$C:$C,MATCH($C78,countries!$D:$D,0)),""))) | AC78: =IF($A78="","",IFERROR(INDEX(HANDLERS!$D$4:$D$250,MATCH(TRIM(LEFT($D78&",",FIND(",",$D78&",")-1)),HANDLERS!$C$4:$C$250,0)),"")) | AD78: =IF($A78="","",IFERROR(INDEX(HANDLERS!$E$4:$E$250,MATCH(TRIM(LEFT($D78&",",FIND(",",$D78&",")-1)),HANDLERS!$C$4:$C$250,0)),""))
A79: =IF(ROW()-73>SUM($AO$18:$AO$26),"",ROW()-73) | B79: =IF($A79="","",IFERROR(INDEX(countries!$B:$B,MATCH($C79,countries!$D:$D,0)),$C79)) | C79: =IF($A79="","",INDEX($AK$18:$AK$26,MATCH($A79,$AP$18:$AP$26,0))) | D79: {=IF($A79="","",_xlfn.TEXTJOIN(", ",TRUE,IF($AK$18:$AK$26=$C79,$AL$18:$AL$26,"")))} | E79: {=IF($A79="","",_xlfn.TEXTJOIN(", ",TRUE,IF($AK$18:$AK$26=$C79,$AM$18:$AM$26,"")))} | F79: =IF($A79="","",_xlfn.MINIFS($AN$18:$AN$26,$AK$18:$AK$26,$C79)) | G79: =IF($A79="","",COUNTA($H79:$V79)) | X79: =IF($A79="","",IFERROR(INDEX(countries!$L:$L,MATCH($C79,countries!$D:$D,0)),"VERIFY")) | Y79: =IF($A79="","",IFERROR(INDEX(countries!$M:$M,MATCH($C79,countries!$D:$D,0)),"VERIFY")) | Z79: =IF($A79="","",IFERROR(INDEX(HANDLERS!$B$4:$B$250,MATCH(TRIM(LEFT($D79&",",FIND(",",$D79&",")-1)),HANDLERS!$C$4:$C$250,0)),IFERROR(INDEX(Vendors!$B:$B,MATCH(INDEX(vendor_coverage_countries!$B:$B,MATCH(IFERROR(INDEX(countries!$C:$C,MATCH($C79,countries!$D:$D,0)),""),vendor_coverage_countries!$C:$C,0)),Vendors!$A:$A,0)),"NO VENDOR ON FILE FOR THIS STATE"))) | AA79: =IF($A79="","",IF(ISNUMBER(MATCH(TRIM(LEFT($D79&",",FIND(",",$D79&",")-1)),HANDLERS!$C$4:$C$250,0)),"HANDLERS (station "&TRIM(LEFT($D79&",",FIND(",",$D79&",")-1))&")",IF($AB79=0,"-","vendor_coverage_countries"))) | AB79: =IF($A79="","",COUNTIF(vendor_coverage_countries!$C:$C,IFERROR(INDEX(countries!$C:$C,MATCH($C79,countries!$D:$D,0)),""))) | AC79: =IF($A79="","",IFERROR(INDEX(HANDLERS!$D$4:$D$250,MATCH(TRIM(LEFT($D79&",",FIND(",",$D79&",")-1)),HANDLERS!$C$4:$C$250,0)),"")) | AD79: =IF($A79="","",IFERROR(INDEX(HANDLERS!$E$4:$E$250,MATCH(TRIM(LEFT($D79&",",FIND(",",$D79&",")-1)),HANDLERS!$C$4:$C$250,0)),""))
A80: =IF(ROW()-73>SUM($AO$18:$AO$26),"",ROW()-73) | B80: =IF($A80="","",IFERROR(INDEX(countries!$B:$B,MATCH($C80,countries!$D:$D,0)),$C80)) | C80: =IF($A80="","",INDEX($AK$18:$AK$26,MATCH($A80,$AP$18:$AP$26,0))) | D80: {=IF($A80="","",_xlfn.TEXTJOIN(", ",TRUE,IF($AK$18:$AK$26=$C80,$AL$18:$AL$26,"")))} | E80: {=IF($A80="","",_xlfn.TEXTJOIN(", ",TRUE,IF($AK$18:$AK$26=$C80,$AM$18:$AM$26,"")))} | F80: =IF($A80="","",_xlfn.MINIFS($AN$18:$AN$26,$AK$18:$AK$26,$C80)) | G80: =IF($A80="","",COUNTA($H80:$V80)) | X80: =IF($A80="","",IFERROR(INDEX(countries!$L:$L,MATCH($C80,countries!$D:$D,0)),"VERIFY")) | Y80: =IF($A80="","",IFERROR(INDEX(countries!$M:$M,MATCH($C80,countries!$D:$D,0)),"VERIFY")) | Z80: =IF($A80="","",IFERROR(INDEX(HANDLERS!$B$4:$B$250,MATCH(TRIM(LEFT($D80&",",FIND(",",$D80&",")-1)),HANDLERS!$C$4:$C$250,0)),IFERROR(INDEX(Vendors!$B:$B,MATCH(INDEX(vendor_coverage_countries!$B:$B,MATCH(IFERROR(INDEX(countries!$C:$C,MATCH($C80,countries!$D:$D,0)),""),vendor_coverage_countries!$C:$C,0)),Vendors!$A:$A,0)),"NO VENDOR ON FILE FOR THIS STATE"))) | AA80: =IF($A80="","",IF(ISNUMBER(MATCH(TRIM(LEFT($D80&",",FIND(",",$D80&",")-1)),HANDLERS!$C$4:$C$250,0)),"HANDLERS (station "&TRIM(LEFT($D80&",",FIND(",",$D80&",")-1))&")",IF($AB80=0,"-","vendor_coverage_countries"))) | AB80: =IF($A80="","",COUNTIF(vendor_coverage_countries!$C:$C,IFERROR(INDEX(countries!$C:$C,MATCH($C80,countries!$D:$D,0)),""))) | AC80: =IF($A80="","",IFERROR(INDEX(HANDLERS!$D$4:$D$250,MATCH(TRIM(LEFT($D80&",",FIND(",",$D80&",")-1)),HANDLERS!$C$4:$C$250,0)),"")) | AD80: =IF($A80="","",IFERROR(INDEX(HANDLERS!$E$4:$E$250,MATCH(TRIM(LEFT($D80&",",FIND(",",$D80&",")-1)),HANDLERS!$C$4:$C$250,0)),""))
A81: =IF(ROW()-73>SUM($AO$18:$AO$26),"",ROW()-73) | B81: =IF($A81="","",IFERROR(INDEX(countries!$B:$B,MATCH($C81,countries!$D:$D,0)),$C81)) | C81: =IF($A81="","",INDEX($AK$18:$AK$26,MATCH($A81,$AP$18:$AP$26,0))) | D81: {=IF($A81="","",_xlfn.TEXTJOIN(", ",TRUE,IF($AK$18:$AK$26=$C81,$AL$18:$AL$26,"")))} | E81: {=IF($A81="","",_xlfn.TEXTJOIN(", ",TRUE,IF($AK$18:$AK$26=$C81,$AM$18:$AM$26,"")))} | F81: =IF($A81="","",_xlfn.MINIFS($AN$18:$AN$26,$AK$18:$AK$26,$C81)) | G81: =IF($A81="","",COUNTA($H81:$V81)) | X81: =IF($A81="","",IFERROR(INDEX(countries!$L:$L,MATCH($C81,countries!$D:$D,0)),"VERIFY")) | Y81: =IF($A81="","",IFERROR(INDEX(countries!$M:$M,MATCH($C81,countries!$D:$D,0)),"VERIFY")) | Z81: =IF($A81="","",IFERROR(INDEX(HANDLERS!$B$4:$B$250,MATCH(TRIM(LEFT($D81&",",FIND(",",$D81&",")-1)),HANDLERS!$C$4:$C$250,0)),IFERROR(INDEX(Vendors!$B:$B,MATCH(INDEX(vendor_coverage_countries!$B:$B,MATCH(IFERROR(INDEX(countries!$C:$C,MATCH($C81,countries!$D:$D,0)),""),vendor_coverage_countries!$C:$C,0)),Vendors!$A:$A,0)),"NO VENDOR ON FILE FOR THIS STATE"))) | AA81: =IF($A81="","",IF(ISNUMBER(MATCH(TRIM(LEFT($D81&",",FIND(",",$D81&",")-1)),HANDLERS!$C$4:$C$250,0)),"HANDLERS (station "&TRIM(LEFT($D81&",",FIND(",",$D81&",")-1))&")",IF($AB81=0,"-","vendor_coverage_countries"))) | AB81: =IF($A81="","",COUNTIF(vendor_coverage_countries!$C:$C,IFERROR(INDEX(countries!$C:$C,MATCH($C81,countries!$D:$D,0)),""))) | AC81: =IF($A81="","",IFERROR(INDEX(HANDLERS!$D$4:$D$250,MATCH(TRIM(LEFT($D81&",",FIND(",",$D81&",")-1)),HANDLERS!$C$4:$C$250,0)),"")) | AD81: =IF($A81="","",IFERROR(INDEX(HANDLERS!$E$4:$E$250,MATCH(TRIM(LEFT($D81&",",FIND(",",$D81&",")-1)),HANDLERS!$C$4:$C$250,0)),""))
A82: =IF(ROW()-73>SUM($AO$18:$AO$26),"",ROW()-73) | B82: =IF($A82="","",IFERROR(INDEX(countries!$B:$B,MATCH($C82,countries!$D:$D,0)),$C82)) | C82: =IF($A82="","",INDEX($AK$18:$AK$26,MATCH($A82,$AP$18:$AP$26,0))) | D82: {=IF($A82="","",_xlfn.TEXTJOIN(", ",TRUE,IF($AK$18:$AK$26=$C82,$AL$18:$AL$26,"")))} | E82: {=IF($A82="","",_xlfn.TEXTJOIN(", ",TRUE,IF($AK$18:$AK$26=$C82,$AM$18:$AM$26,"")))} | F82: =IF($A82="","",_xlfn.MINIFS($AN$18:$AN$26,$AK$18:$AK$26,$C82)) | G82: =IF($A82="","",COUNTA($H82:$V82)) | X82: =IF($A82="","",IFERROR(INDEX(countries!$L:$L,MATCH($C82,countries!$D:$D,0)),"VERIFY")) | Y82: =IF($A82="","",IFERROR(INDEX(countries!$M:$M,MATCH($C82,countries!$D:$D,0)),"VERIFY")) | Z82: =IF($A82="","",IFERROR(INDEX(HANDLERS!$B$4:$B$250,MATCH(TRIM(LEFT($D82&",",FIND(",",$D82&",")-1)),HANDLERS!$C$4:$C$250,0)),IFERROR(INDEX(Vendors!$B:$B,MATCH(INDEX(vendor_coverage_countries!$B:$B,MATCH(IFERROR(INDEX(countries!$C:$C,MATCH($C82,countries!$D:$D,0)),""),vendor_coverage_countries!$C:$C,0)),Vendors!$A:$A,0)),"NO VENDOR ON FILE FOR THIS STATE"))) | AA82: =IF($A82="","",IF(ISNUMBER(MATCH(TRIM(LEFT($D82&",",FIND(",",$D82&",")-1)),HANDLERS!$C$4:$C$250,0)),"HANDLERS (station "&TRIM(LEFT($D82&",",FIND(",",$D82&",")-1))&")",IF($AB82=0,"-","vendor_coverage_countries"))) | AB82: =IF($A82="","",COUNTIF(vendor_coverage_countries!$C:$C,IFERROR(INDEX(countries!$C:$C,MATCH($C82,countries!$D:$D,0)),""))) | AC82: =IF($A82="","",IFERROR(INDEX(HANDLERS!$D$4:$D$250,MATCH(TRIM(LEFT($D82&",",FIND(",",$D82&",")-1)),HANDLERS!$C$4:$C$250,0)),"")) | AD82: =IF($A82="","",IFERROR(INDEX(HANDLERS!$E$4:$E$250,MATCH(TRIM(LEFT($D82&",",FIND(",",$D82&",")-1)),HANDLERS!$C$4:$C$250,0)),""))
A84: Service columns are driven by the services sheet: set category = GROUND and give a ground_grid_order to add or reorder a service. Enter JTL, OWN or THIRD PARTY in a cell to order it; blank means not required. Ground handling is one service per country even when several airports are involved. For finer detail enter a sub_services code (e.g. GH-DIC for de-icing).
A86: 5 · VISA & IMMIGRATION (one line per country on the ground × each nationality on board · headcount shown in the column header) | B86: =COUNTIFS('PAX & CREW'!$B$3:$B$62,$B$5,'PAX & CREW'!$C$3:$C$62,"CREW") -> 2
A87: STOP | B87: COUNTRY | C87: ISO3 | D87: LEGS | E87: =IFERROR(INDEX($AH$18:$AH$37,MATCH(COLUMN()-4,$AJ$18:$AJ$37,0))&" ("&COUNTIFS('PAX & CREW'!$B$3:$B$62,$B$5,'PAX & CREW'!$L$3:$L$62,INDEX($AH$18:$AH$37,MATCH(COLUMN()-4,$AJ$18:$AJ$37,0)))&")","") -> United States (1) | F87: =IFERROR(INDEX($AH$18:$AH$37,MATCH(COLUMN()-4,$AJ$18:$AJ$37,0))&" ("&COUNTIFS('PAX & CREW'!$B$3:$B$62,$B$5,'PAX & CREW'!$L$3:$L$62,INDEX($AH$18:$AH$37,MATCH(COLUMN()-4,$AJ$18:$AJ$37,0)))&")","") -> South Africa (2) | G87: =IFERROR(INDEX($AH$18:$AH$37,MATCH(COLUMN()-4,$AJ$18:$AJ$37,0))&" ("&COUNTIFS('PAX & CREW'!$B$3:$B$62,$B$5,'PAX & CREW'!$L$3:$L$62,INDEX($AH$18:$AH$37,MATCH(COLUMN()-4,$AJ$18:$AJ$37,0)))&")","") -> Oman (1) | H87: =IFERROR(INDEX($AH$18:$AH$37,MATCH(COLUMN()-4,$AJ$18:$AJ$37,0))&" ("&COUNTIFS('PAX & CREW'!$B$3:$B$62,$B$5,'PAX & CREW'!$L$3:$L$62,INDEX($AH$18:$AH$37,MATCH(COLUMN()-4,$AJ$18:$AJ$37,0)))&")","") | I87: =IFERROR(INDEX($AH$18:$AH$37,MATCH(COLUMN()-4,$AJ$18:$AJ$37,0))&" ("&COUNTIFS('PAX & CREW'!$B$3:$B$62,$B$5,'PAX & CREW'!$L$3:$L$62,INDEX($AH$18:$AH$37,MATCH(COLUMN()-4,$AJ$18:$AJ$37,0)))&")","") | J87: =IFERROR(INDEX($AH$18:$AH$37,MATCH(COLUMN()-4,$AJ$18:$AJ$37,0))&" ("&COUNTIFS('PAX & CREW'!$B$3:$B$62,$B$5,'PAX & CREW'!$L$3:$L$62,INDEX($AH$18:$AH$37,MATCH(COLUMN()-4,$AJ$18:$AJ$37,0)))&")","")
A88: =IF(ROW()-87>SUM($AO$18:$AO$26),"",ROW()-87) -> 1 | B88: =IF($A88="","",IFERROR(INDEX(countries!$B:$B,MATCH($C88,countries!$D:$D,0)),$C88)) -> South Africa | C88: =IF($A88="","",INDEX($AK$18:$AK$26,MATCH($A88,$AP$18:$AP$26,0))) -> ZAF | D88: {=IF($A88="","",_xlfn.TEXTJOIN(", ",TRUE,IF($AK$18:$AK$26=$C88,$AM$18:$AM$26,"")))} -> L1, L4 | E88: {=IF(OR($A88="",E$87=""),"",_xlfn.LET(_xlpm.nat,INDEX($AH$18:$AH$37,MATCH(COLUMN()-4,$AJ$18:$AJ$37,0)),_xlpm.ctry,$B88,_xlpm.apt,IFERROR(INDEX('VISA RULES'!$E$2:$E$400,SUMPRODUCT(MATCH(1,('VISA RULES'!$B$2:$B$400=_xlpm.ctry)*('VISA RULES'!$C$2:$C$400=_xlpm.nat)*('VISA RULES'!$A$2:$A$400<>""),0))),""),_xlpm.rule,IFERROR(INDEX('VISA RULES'!$E$2:$E$400,SUMPRODUCT(MATCH(1,('VISA RULES'!$B$2:$B$400=_xlpm.ctry)*('VISA RULES'!$C$2:$C$400=_xlpm.nat)*('VISA RULES'!$A$2:$A$400=""),0))),""),_xlpm.mtx,IFERROR(INDEX('VISA MATRIX'!$B$4:$FS$145,MATCH(_xlpm.ctry,'VISA MATRIX'!$A$4:$A$145,0),MATCH(_xlpm.nat,'VISA MATRIX'!$B$3:$FS$3,0)),""),IF(_xlpm.apt<>"",_xlpm.apt&" (APT OVERRIDE)",IF(_xlpm.rule<>"",_xlpm.rule,IF(_xlpm.mtx<>"",_xlpm.mtx,"NOT ON FILE - VERIFY")))))} -> NOT REQUIRED | F88: {=IF(OR($A88="",F$87=""),"",_xlfn.LET(_xlpm.nat,INDEX($AH$18:$AH$37,MATCH(COLUMN()-4,$AJ$18:$AJ$37,0)),_xlpm.ctry,$B88,_xlpm.apt,IFERROR(INDEX('VISA RULES'!$E$2:$E$400,SUMPRODUCT(MATCH(1,('VISA RULES'!$B$2:$B$400=_xlpm.ctry)*('VISA RULES'!$C$2:$C$400=_xlpm.nat)*('VISA RULES'!$A$2:$A$400<>""),0))),""),_xlpm.rule,IFERROR(INDEX('VISA RULES'!$E$2:$E$400,SUMPRODUCT(MATCH(1,('VISA RULES'!$B$2:$B$400=_xlpm.ctry)*('VISA RULES'!$C$2:$C$400=_xlpm.nat)*('VISA RULES'!$A$2:$A$400=""),0))),""),_xlpm.mtx,IFERROR(INDEX('VISA MATRIX'!$B$4:$FS$145,MATCH(_xlpm.ctry,'VISA MATRIX'!$A$4:$A$145,0),MATCH(_xlpm.nat,'VISA MATRIX'!$B$3:$FS$3,0)),""),IF(_xlpm.apt<>"",_xlpm.apt&" (APT OVERRIDE)",IF(_xlpm.rule<>"",_xlpm.rule,IF(_xlpm.mtx<>"",_xlpm.mtx,"NOT ON FILE - VERIFY")))))} -> NOT ON FILE - VERIFY | G88: {=IF(OR($A88="",G$87=""),"",_xlfn.LET(_xlpm.nat,INDEX($AH$18:$AH$37,MATCH(COLUMN()-4,$AJ$18:$AJ$37,0)),_xlpm.ctry,$B88,_xlpm.apt,IFERROR(INDEX('VISA RULES'!$E$2:$E$400,SUMPRODUCT(MATCH(1,('VISA RULES'!$B$2:$B$400=_xlpm.ctry)*('VISA RULES'!$C$2:$C$400=_xlpm.nat)*('VISA RULES'!$A$2:$A$400<>""),0))),""),_xlpm.rule,IFERROR(INDEX('VISA RULES'!$E$2:$E$400,SUMPRODUCT(MATCH(1,('VISA RULES'!$B$2:$B$400=_xlpm.ctry)*('VISA RULES'!$C$2:$C$400=_xlpm.nat)*('VISA RULES'!$A$2:$A$400=""),0))),""),_xlpm.mtx,IFERROR(INDEX('VISA MATRIX'!$B$4:$FS$145,MATCH(_xlpm.ctry,'VISA MATRIX'!$A$4:$A$145,0),MATCH(_xlpm.nat,'VISA MATRIX'!$B$3:$FS$3,0)),""),IF(_xlpm.apt<>"",_xlpm.apt&" (APT OVERRIDE)",IF(_xlpm.rule<>"",_xlpm.rule,IF(_xlpm.mtx<>"",_xlpm.mtx,"NOT ON FILE - VERIFY")))))} -> NOT ON FILE - VERIFY | H88: {=IF(OR($A88="",H$87=""),"",_xlfn.LET(_xlpm.nat,INDEX($AH$18:$AH$37,MATCH(COLUMN()-4,$AJ$18:$AJ$37,0)),_xlpm.ctry,$B88,_xlpm.apt,IFERROR(INDEX('VISA RULES'!$E$2:$E$400,SUMPRODUCT(MATCH(1,('VISA RULES'!$B$2:$B$400=_xlpm.ctry)*('VISA RULES'!$C$2:$C$400=_xlpm.nat)*('VISA RULES'!$A$2:$A$400<>""),0))),""),_xlpm.rule,IFERROR(INDEX('VISA RULES'!$E$2:$E$400,SUMPRODUCT(MATCH(1,('VISA RULES'!$B$2:$B$400=_xlpm.ctry)*('VISA RULES'!$C$2:$C$400=_xlpm.nat)*('VISA RULES'!$A$2:$A$400=""),0))),""),_xlpm.mtx,IFERROR(INDEX('VISA MATRIX'!$B$4:$FS$145,MATCH(_xlpm.ctry,'VISA MATRIX'!$A$4:$A$145,0),MATCH(_xlpm.nat,'VISA MATRIX'!$B$3:$FS$3,0)),""),IF(_xlpm.apt<>"",_xlpm.apt&" (APT OVERRIDE)",IF(_xlpm.rule<>"",_xlpm.rule,IF(_xlpm.mtx<>"",_xlpm.mtx,"NOT ON FILE - VERIFY")))))} | I88: {=IF(OR($A88="",I$87=""),"",_xlfn.LET(_xlpm.nat,INDEX($AH$18:$AH$37,MATCH(COLUMN()-4,$AJ$18:$AJ$37,0)),_xlpm.ctry,$B88,_xlpm.apt,IFERROR(INDEX('VISA RULES'!$E$2:$E$400,SUMPRODUCT(MATCH(1,('VISA RULES'!$B$2:$B$400=_xlpm.ctry)*('VISA RULES'!$C$2:$C$400=_xlpm.nat)*('VISA RULES'!$A$2:$A$400<>""),0))),""),_xlpm.rule,IFERROR(INDEX('VISA RULES'!$E$2:$E$400,SUMPRODUCT(MATCH(1,('VISA RULES'!$B$2:$B$400=_xlpm.ctry)*('VISA RULES'!$C$2:$C$400=_xlpm.nat)*('VISA RULES'!$A$2:$A$400=""),0))),""),_xlpm.mtx,IFERROR(INDEX('VISA MATRIX'!$B$4:$FS$145,MATCH(_xlpm.ctry,'VISA MATRIX'!$A$4:$A$145,0),MATCH(_xlpm.nat,'VISA MATRIX'!$B$3:$FS$3,0)),""),IF(_xlpm.apt<>"",_xlpm.apt&" (APT OVERRIDE)",IF(_xlpm.rule<>"",_xlpm.rule,IF(_xlpm.mtx<>"",_xlpm.mtx,"NOT ON FILE - VERIFY")))))} | J88: {=IF(OR($A88="",J$87=""),"",_xlfn.LET(_xlpm.nat,INDEX($AH$18:$AH$37,MATCH(COLUMN()-4,$AJ$18:$AJ$37,0)),_xlpm.ctry,$B88,_xlpm.apt,IFERROR(INDEX('VISA RULES'!$E$2:$E$400,SUMPRODUCT(MATCH(1,('VISA RULES'!$B$2:$B$400=_xlpm.ctry)*('VISA RULES'!$C$2:$C$400=_xlpm.nat)*('VISA RULES'!$A$2:$A$400<>""),0))),""),_xlpm.rule,IFERROR(INDEX('VISA RULES'!$E$2:$E$400,SUMPRODUCT(MATCH(1,('VISA RULES'!$B$2:$B$400=_xlpm.ctry)*('VISA RULES'!$C$2:$C$400=_xlpm.nat)*('VISA RULES'!$A$2:$A$400=""),0))),""),_xlpm.mtx,IFERROR(INDEX('VISA MATRIX'!$B$4:$FS$145,MATCH(_xlpm.ctry,'VISA MATRIX'!$A$4:$A$145,0),MATCH(_xlpm.nat,'VISA MATRIX'!$B$3:$FS$3,0)),""),IF(_xlpm.apt<>"",_xlpm.apt&" (APT OVERRIDE)",IF(_xlpm.rule<>"",_xlpm.rule,IF(_xlpm.mtx<>"",_xlpm.mtx,"NOT ON FILE - VERIFY")))))}
A89: =IF(ROW()-87>SUM($AO$18:$AO$26),"",ROW()-87) -> 2 | B89: =IF($A89="","",IFERROR(INDEX(countries!$B:$B,MATCH($C89,countries!$D:$D,0)),$C89)) -> Chad | C89: =IF($A89="","",INDEX($AK$18:$AK$26,MATCH($A89,$AP$18:$AP$26,0))) -> TCD | D89: {=IF($A89="","",_xlfn.TEXTJOIN(", ",TRUE,IF($AK$18:$AK$26=$C89,$AM$18:$AM$26,"")))} -> L1 | E89: {=IF(OR($A89="",E$87=""),"",_xlfn.LET(_xlpm.nat,INDEX($AH$18:$AH$37,MATCH(COLUMN()-4,$AJ$18:$AJ$37,0)),_xlpm.ctry,$B89,_xlpm.apt,IFERROR(INDEX('VISA RULES'!$E$2:$E$400,SUMPRODUCT(MATCH(1,('VISA RULES'!$B$2:$B$400=_xlpm.ctry)*('VISA RULES'!$C$2:$C$400=_xlpm.nat)*('VISA RULES'!$A$2:$A$400<>""),0))),""),_xlpm.rule,IFERROR(INDEX('VISA RULES'!$E$2:$E$400,SUMPRODUCT(MATCH(1,('VISA RULES'!$B$2:$B$400=_xlpm.ctry)*('VISA RULES'!$C$2:$C$400=_xlpm.nat)*('VISA RULES'!$A$2:$A$400=""),0))),""),_xlpm.mtx,IFERROR(INDEX('VISA MATRIX'!$B$4:$FS$145,MATCH(_xlpm.ctry,'VISA MATRIX'!$A$4:$A$145,0),MATCH(_xlpm.nat,'VISA MATRIX'!$B$3:$FS$3,0)),""),IF(_xlpm.apt<>"",_xlpm.apt&" (APT OVERRIDE)",IF(_xlpm.rule<>"",_xlpm.rule,IF(_xlpm.mtx<>"",_xlpm.mtx,"NOT ON FILE - VERIFY")))))} -> NOT ON FILE - VERIFY | F89: {=IF(OR($A89="",F$87=""),"",_xlfn.LET(_xlpm.nat,INDEX($AH$18:$AH$37,MATCH(COLUMN()-4,$AJ$18:$AJ$37,0)),_xlpm.ctry,$B89,_xlpm.apt,IFERROR(INDEX('VISA RULES'!$E$2:$E$400,SUMPRODUCT(MATCH(1,('VISA RULES'!$B$2:$B$400=_xlpm.ctry)*('VISA RULES'!$C$2:$C$400=_xlpm.nat)*('VISA RULES'!$A$2:$A$400<>""),0))),""),_xlpm.rule,IFERROR(INDEX('VISA RULES'!$E$2:$E$400,SUMPRODUCT(MATCH(1,('VISA RULES'!$B$2:$B$400=_xlpm.ctry)*('VISA RULES'!$C$2:$C$400=_xlpm.nat)*('VISA RULES'!$A$2:$A$400=""),0))),""),_xlpm.mtx,IFERROR(INDEX('VISA MATRIX'!$B$4:$FS$145,MATCH(_xlpm.ctry,'VISA MATRIX'!$A$4:$A$145,0),MATCH(_xlpm.nat,'VISA MATRIX'!$B$3:$FS$3,0)),""),IF(_xlpm.apt<>"",_xlpm.apt&" (APT OVERRIDE)",IF(_xlpm.rule<>"",_xlpm.rule,IF(_xlpm.mtx<>"",_xlpm.mtx,"NOT ON FILE - VERIFY")))))} -> NOT ON FILE - VERIFY | G89: {=IF(OR($A89="",G$87=""),"",_xlfn.LET(_xlpm.nat,INDEX($AH$18:$AH$37,MATCH(COLUMN()-4,$AJ$18:$AJ$37,0)),_xlpm.ctry,$B89,_xlpm.apt,IFERROR(INDEX('VISA RULES'!$E$2:$E$400,SUMPRODUCT(MATCH(1,('VISA RULES'!$B$2:$B$400=_xlpm.ctry)*('VISA RULES'!$C$2:$C$400=_xlpm.nat)*('VISA RULES'!$A$2:$A$400<>""),0))),""),_xlpm.rule,IFERROR(INDEX('VISA RULES'!$E$2:$E$400,SUMPRODUCT(MATCH(1,('VISA RULES'!$B$2:$B$400=_xlpm.ctry)*('VISA RULES'!$C$2:$C$400=_xlpm.nat)*('VISA RULES'!$A$2:$A$400=""),0))),""),_xlpm.mtx,IFERROR(INDEX('VISA MATRIX'!$B$4:$FS$145,MATCH(_xlpm.ctry,'VISA MATRIX'!$A$4:$A$145,0),MATCH(_xlpm.nat,'VISA MATRIX'!$B$3:$FS$3,0)),""),IF(_xlpm.apt<>"",_xlpm.apt&" (APT OVERRIDE)",IF(_xlpm.rule<>"",_xlpm.rule,IF(_xlpm.mtx<>"",_xlpm.mtx,"NOT ON FILE - VERIFY")))))} -> NOT ON FILE - VERIFY | H89: {=IF(OR($A89="",H$87=""),"",_xlfn.LET(_xlpm.nat,INDEX($AH$18:$AH$37,MATCH(COLUMN()-4,$AJ$18:$AJ$37,0)),_xlpm.ctry,$B89,_xlpm.apt,IFERROR(INDEX('VISA RULES'!$E$2:$E$400,SUMPRODUCT(MATCH(1,('VISA RULES'!$B$2:$B$400=_xlpm.ctry)*('VISA RULES'!$C$2:$C$400=_xlpm.nat)*('VISA RULES'!$A$2:$A$400<>""),0))),""),_xlpm.rule,IFERROR(INDEX('VISA RULES'!$E$2:$E$400,SUMPRODUCT(MATCH(1,('VISA RULES'!$B$2:$B$400=_xlpm.ctry)*('VISA RULES'!$C$2:$C$400=_xlpm.nat)*('VISA RULES'!$A$2:$A$400=""),0))),""),_xlpm.mtx,IFERROR(INDEX('VISA MATRIX'!$B$4:$FS$145,MATCH(_xlpm.ctry,'VISA MATRIX'!$A$4:$A$145,0),MATCH(_xlpm.nat,'VISA MATRIX'!$B$3:$FS$3,0)),""),IF(_xlpm.apt<>"",_xlpm.apt&" (APT OVERRIDE)",IF(_xlpm.rule<>"",_xlpm.rule,IF(_xlpm.mtx<>"",_xlpm.mtx,"NOT ON FILE - VERIFY")))))} | I89: {=IF(OR($A89="",I$87=""),"",_xlfn.LET(_xlpm.nat,INDEX($AH$18:$AH$37,MATCH(COLUMN()-4,$AJ$18:$AJ$37,0)),_xlpm.ctry,$B89,_xlpm.apt,IFERROR(INDEX('VISA RULES'!$E$2:$E$400,SUMPRODUCT(MATCH(1,('VISA RULES'!$B$2:$B$400=_xlpm.ctry)*('VISA RULES'!$C$2:$C$400=_xlpm.nat)*('VISA RULES'!$A$2:$A$400<>""),0))),""),_xlpm.rule,IFERROR(INDEX('VISA RULES'!$E$2:$E$400,SUMPRODUCT(MATCH(1,('VISA RULES'!$B$2:$B$400=_xlpm.ctry)*('VISA RULES'!$C$2:$C$400=_xlpm.nat)*('VISA RULES'!$A$2:$A$400=""),0))),""),_xlpm.mtx,IFERROR(INDEX('VISA MATRIX'!$B$4:$FS$145,MATCH(_xlpm.ctry,'VISA MATRIX'!$A$4:$A$145,0),MATCH(_xlpm.nat,'VISA MATRIX'!$B$3:$FS$3,0)),""),IF(_xlpm.apt<>"",_xlpm.apt&" (APT OVERRIDE)",IF(_xlpm.rule<>"",_xlpm.rule,IF(_xlpm.mtx<>"",_xlpm.mtx,"NOT ON FILE - VERIFY")))))} | J89: {=IF(OR($A89="",J$87=""),"",_xlfn.LET(_xlpm.nat,INDEX($AH$18:$AH$37,MATCH(COLUMN()-4,$AJ$18:$AJ$37,0)),_xlpm.ctry,$B89,_xlpm.apt,IFERROR(INDEX('VISA RULES'!$E$2:$E$400,SUMPRODUCT(MATCH(1,('VISA RULES'!$B$2:$B$400=_xlpm.ctry)*('VISA RULES'!$C$2:$C$400=_xlpm.nat)*('VISA RULES'!$A$2:$A$400<>""),0))),""),_xlpm.rule,IFERROR(INDEX('VISA RULES'!$E$2:$E$400,SUMPRODUCT(MATCH(1,('VISA RULES'!$B$2:$B$400=_xlpm.ctry)*('VISA RULES'!$C$2:$C$400=_xlpm.nat)*('VISA RULES'!$A$2:$A$400=""),0))),""),_xlpm.mtx,IFERROR(INDEX('VISA MATRIX'!$B$4:$FS$145,MATCH(_xlpm.ctry,'VISA MATRIX'!$A$4:$A$145,0),MATCH(_xlpm.nat,'VISA MATRIX'!$B$3:$FS$3,0)),""),IF(_xlpm.apt<>"",_xlpm.apt&" (APT OVERRIDE)",IF(_xlpm.rule<>"",_xlpm.rule,IF(_xlpm.mtx<>"",_xlpm.mtx,"NOT ON FILE - VERIFY")))))}
A90: =IF(ROW()-87>SUM($AO$18:$AO$26),"",ROW()-87) -> 3 | B90: =IF($A90="","",IFERROR(INDEX(countries!$B:$B,MATCH($C90,countries!$D:$D,0)),$C90)) -> Egypt | C90: =IF($A90="","",INDEX($AK$18:$AK$26,MATCH($A90,$AP$18:$AP$26,0))) -> EGY | D90: {=IF($A90="","",_xlfn.TEXTJOIN(", ",TRUE,IF($AK$18:$AK$26=$C90,$AM$18:$AM$26,"")))} -> L2 | E90: {=IF(OR($A90="",E$87=""),"",_xlfn.LET(_xlpm.nat,INDEX($AH$18:$AH$37,MATCH(COLUMN()-4,$AJ$18:$AJ$37,0)),_xlpm.ctry,$B90,_xlpm.apt,IFERROR(INDEX('VISA RULES'!$E$2:$E$400,SUMPRODUCT(MATCH(1,('VISA RULES'!$B$2:$B$400=_xlpm.ctry)*('VISA RULES'!$C$2:$C$400=_xlpm.nat)*('VISA RULES'!$A$2:$A$400<>""),0))),""),_xlpm.rule,IFERROR(INDEX('VISA RULES'!$E$2:$E$400,SUMPRODUCT(MATCH(1,('VISA RULES'!$B$2:$B$400=_xlpm.ctry)*('VISA RULES'!$C$2:$C$400=_xlpm.nat)*('VISA RULES'!$A$2:$A$400=""),0))),""),_xlpm.mtx,IFERROR(INDEX('VISA MATRIX'!$B$4:$FS$145,MATCH(_xlpm.ctry,'VISA MATRIX'!$A$4:$A$145,0),MATCH(_xlpm.nat,'VISA MATRIX'!$B$3:$FS$3,0)),""),IF(_xlpm.apt<>"",_xlpm.apt&" (APT OVERRIDE)",IF(_xlpm.rule<>"",_xlpm.rule,IF(_xlpm.mtx<>"",_xlpm.mtx,"NOT ON FILE - VERIFY")))))} -> NOT ON FILE - VERIFY | F90: {=IF(OR($A90="",F$87=""),"",_xlfn.LET(_xlpm.nat,INDEX($AH$18:$AH$37,MATCH(COLUMN()-4,$AJ$18:$AJ$37,0)),_xlpm.ctry,$B90,_xlpm.apt,IFERROR(INDEX('VISA RULES'!$E$2:$E$400,SUMPRODUCT(MATCH(1,('VISA RULES'!$B$2:$B$400=_xlpm.ctry)*('VISA RULES'!$C$2:$C$400=_xlpm.nat)*('VISA RULES'!$A$2:$A$400<>""),0))),""),_xlpm.rule,IFERROR(INDEX('VISA RULES'!$E$2:$E$400,SUMPRODUCT(MATCH(1,('VISA RULES'!$B$2:$B$400=_xlpm.ctry)*('VISA RULES'!$C$2:$C$400=_xlpm.nat)*('VISA RULES'!$A$2:$A$400=""),0))),""),_xlpm.mtx,IFERROR(INDEX('VISA MATRIX'!$B$4:$FS$145,MATCH(_xlpm.ctry,'VISA MATRIX'!$A$4:$A$145,0),MATCH(_xlpm.nat,'VISA MATRIX'!$B$3:$FS$3,0)),""),IF(_xlpm.apt<>"",_xlpm.apt&" (APT OVERRIDE)",IF(_xlpm.rule<>"",_xlpm.rule,IF(_xlpm.mtx<>"",_xlpm.mtx,"NOT ON FILE - VERIFY")))))} -> NOT ON FILE - VERIFY | G90: {=IF(OR($A90="",G$87=""),"",_xlfn.LET(_xlpm.nat,INDEX($AH$18:$AH$37,MATCH(COLUMN()-4,$AJ$18:$AJ$37,0)),_xlpm.ctry,$B90,_xlpm.apt,IFERROR(INDEX('VISA RULES'!$E$2:$E$400,SUMPRODUCT(MATCH(1,('VISA RULES'!$B$2:$B$400=_xlpm.ctry)*('VISA RULES'!$C$2:$C$400=_xlpm.nat)*('VISA RULES'!$A$2:$A$400<>""),0))),""),_xlpm.rule,IFERROR(INDEX('VISA RULES'!$E$2:$E$400,SUMPRODUCT(MATCH(1,('VISA RULES'!$B$2:$B$400=_xlpm.ctry)*('VISA RULES'!$C$2:$C$400=_xlpm.nat)*('VISA RULES'!$A$2:$A$400=""),0))),""),_xlpm.mtx,IFERROR(INDEX('VISA MATRIX'!$B$4:$FS$145,MATCH(_xlpm.ctry,'VISA MATRIX'!$A$4:$A$145,0),MATCH(_xlpm.nat,'VISA MATRIX'!$B$3:$FS$3,0)),""),IF(_xlpm.apt<>"",_xlpm.apt&" (APT OVERRIDE)",IF(_xlpm.rule<>"",_xlpm.rule,IF(_xlpm.mtx<>"",_xlpm.mtx,"NOT ON FILE - VERIFY")))))} -> NOT ON FILE - VERIFY | H90: {=IF(OR($A90="",H$87=""),"",_xlfn.LET(_xlpm.nat,INDEX($AH$18:$AH$37,MATCH(COLUMN()-4,$AJ$18:$AJ$37,0)),_xlpm.ctry,$B90,_xlpm.apt,IFERROR(INDEX('VISA RULES'!$E$2:$E$400,SUMPRODUCT(MATCH(1,('VISA RULES'!$B$2:$B$400=_xlpm.ctry)*('VISA RULES'!$C$2:$C$400=_xlpm.nat)*('VISA RULES'!$A$2:$A$400<>""),0))),""),_xlpm.rule,IFERROR(INDEX('VISA RULES'!$E$2:$E$400,SUMPRODUCT(MATCH(1,('VISA RULES'!$B$2:$B$400=_xlpm.ctry)*('VISA RULES'!$C$2:$C$400=_xlpm.nat)*('VISA RULES'!$A$2:$A$400=""),0))),""),_xlpm.mtx,IFERROR(INDEX('VISA MATRIX'!$B$4:$FS$145,MATCH(_xlpm.ctry,'VISA MATRIX'!$A$4:$A$145,0),MATCH(_xlpm.nat,'VISA MATRIX'!$B$3:$FS$3,0)),""),IF(_xlpm.apt<>"",_xlpm.apt&" (APT OVERRIDE)",IF(_xlpm.rule<>"",_xlpm.rule,IF(_xlpm.mtx<>"",_xlpm.mtx,"NOT ON FILE - VERIFY")))))} | I90: {=IF(OR($A90="",I$87=""),"",_xlfn.LET(_xlpm.nat,INDEX($AH$18:$AH$37,MATCH(COLUMN()-4,$AJ$18:$AJ$37,0)),_xlpm.ctry,$B90,_xlpm.apt,IFERROR(INDEX('VISA RULES'!$E$2:$E$400,SUMPRODUCT(MATCH(1,('VISA RULES'!$B$2:$B$400=_xlpm.ctry)*('VISA RULES'!$C$2:$C$400=_xlpm.nat)*('VISA RULES'!$A$2:$A$400<>""),0))),""),_xlpm.rule,IFERROR(INDEX('VISA RULES'!$E$2:$E$400,SUMPRODUCT(MATCH(1,('VISA RULES'!$B$2:$B$400=_xlpm.ctry)*('VISA RULES'!$C$2:$C$400=_xlpm.nat)*('VISA RULES'!$A$2:$A$400=""),0))),""),_xlpm.mtx,IFERROR(INDEX('VISA MATRIX'!$B$4:$FS$145,MATCH(_xlpm.ctry,'VISA MATRIX'!$A$4:$A$145,0),MATCH(_xlpm.nat,'VISA MATRIX'!$B$3:$FS$3,0)),""),IF(_xlpm.apt<>"",_xlpm.apt&" (APT OVERRIDE)",IF(_xlpm.rule<>"",_xlpm.rule,IF(_xlpm.mtx<>"",_xlpm.mtx,"NOT ON FILE - VERIFY")))))} | J90: {=IF(OR($A90="",J$87=""),"",_xlfn.LET(_xlpm.nat,INDEX($AH$18:$AH$37,MATCH(COLUMN()-4,$AJ$18:$AJ$37,0)),_xlpm.ctry,$B90,_xlpm.apt,IFERROR(INDEX('VISA RULES'!$E$2:$E$400,SUMPRODUCT(MATCH(1,('VISA RULES'!$B$2:$B$400=_xlpm.ctry)*('VISA RULES'!$C$2:$C$400=_xlpm.nat)*('VISA RULES'!$A$2:$A$400<>""),0))),""),_xlpm.rule,IFERROR(INDEX('VISA RULES'!$E$2:$E$400,SUMPRODUCT(MATCH(1,('VISA RULES'!$B$2:$B$400=_xlpm.ctry)*('VISA RULES'!$C$2:$C$400=_xlpm.nat)*('VISA RULES'!$A$2:$A$400=""),0))),""),_xlpm.mtx,IFERROR(INDEX('VISA MATRIX'!$B$4:$FS$145,MATCH(_xlpm.ctry,'VISA MATRIX'!$A$4:$A$145,0),MATCH(_xlpm.nat,'VISA MATRIX'!$B$3:$FS$3,0)),""),IF(_xlpm.apt<>"",_xlpm.apt&" (APT OVERRIDE)",IF(_xlpm.rule<>"",_xlpm.rule,IF(_xlpm.mtx<>"",_xlpm.mtx,"NOT ON FILE - VERIFY")))))}
A91: =IF(ROW()-87>SUM($AO$18:$AO$26),"",ROW()-87) -> 4 | B91: =IF($A91="","",IFERROR(INDEX(countries!$B:$B,MATCH($C91,countries!$D:$D,0)),$C91)) -> Morocco | C91: =IF($A91="","",INDEX($AK$18:$AK$26,MATCH($A91,$AP$18:$AP$26,0))) -> MAR | D91: {=IF($A91="","",_xlfn.TEXTJOIN(", ",TRUE,IF($AK$18:$AK$26=$C91,$AM$18:$AM$26,"")))} -> L3 | E91: {=IF(OR($A91="",E$87=""),"",_xlfn.LET(_xlpm.nat,INDEX($AH$18:$AH$37,MATCH(COLUMN()-4,$AJ$18:$AJ$37,0)),_xlpm.ctry,$B91,_xlpm.apt,IFERROR(INDEX('VISA RULES'!$E$2:$E$400,SUMPRODUCT(MATCH(1,('VISA RULES'!$B$2:$B$400=_xlpm.ctry)*('VISA RULES'!$C$2:$C$400=_xlpm.nat)*('VISA RULES'!$A$2:$A$400<>""),0))),""),_xlpm.rule,IFERROR(INDEX('VISA RULES'!$E$2:$E$400,SUMPRODUCT(MATCH(1,('VISA RULES'!$B$2:$B$400=_xlpm.ctry)*('VISA RULES'!$C$2:$C$400=_xlpm.nat)*('VISA RULES'!$A$2:$A$400=""),0))),""),_xlpm.mtx,IFERROR(INDEX('VISA MATRIX'!$B$4:$FS$145,MATCH(_xlpm.ctry,'VISA MATRIX'!$A$4:$A$145,0),MATCH(_xlpm.nat,'VISA MATRIX'!$B$3:$FS$3,0)),""),IF(_xlpm.apt<>"",_xlpm.apt&" (APT OVERRIDE)",IF(_xlpm.rule<>"",_xlpm.rule,IF(_xlpm.mtx<>"",_xlpm.mtx,"NOT ON FILE - VERIFY")))))} -> NOT ON FILE - VERIFY | F91: {=IF(OR($A91="",F$87=""),"",_xlfn.LET(_xlpm.nat,INDEX($AH$18:$AH$37,MATCH(COLUMN()-4,$AJ$18:$AJ$37,0)),_xlpm.ctry,$B91,_xlpm.apt,IFERROR(INDEX('VISA RULES'!$E$2:$E$400,SUMPRODUCT(MATCH(1,('VISA RULES'!$B$2:$B$400=_xlpm.ctry)*('VISA RULES'!$C$2:$C$400=_xlpm.nat)*('VISA RULES'!$A$2:$A$400<>""),0))),""),_xlpm.rule,IFERROR(INDEX('VISA RULES'!$E$2:$E$400,SUMPRODUCT(MATCH(1,('VISA RULES'!$B$2:$B$400=_xlpm.ctry)*('VISA RULES'!$C$2:$C$400=_xlpm.nat)*('VISA RULES'!$A$2:$A$400=""),0))),""),_xlpm.mtx,IFERROR(INDEX('VISA MATRIX'!$B$4:$FS$145,MATCH(_xlpm.ctry,'VISA MATRIX'!$A$4:$A$145,0),MATCH(_xlpm.nat,'VISA MATRIX'!$B$3:$FS$3,0)),""),IF(_xlpm.apt<>"",_xlpm.apt&" (APT OVERRIDE)",IF(_xlpm.rule<>"",_xlpm.rule,IF(_xlpm.mtx<>"",_xlpm.mtx,"NOT ON FILE - VERIFY")))))} -> NOT ON FILE - VERIFY | G91: {=IF(OR($A91="",G$87=""),"",_xlfn.LET(_xlpm.nat,INDEX($AH$18:$AH$37,MATCH(COLUMN()-4,$AJ$18:$AJ$37,0)),_xlpm.ctry,$B91,_xlpm.apt,IFERROR(INDEX('VISA RULES'!$E$2:$E$400,SUMPRODUCT(MATCH(1,('VISA RULES'!$B$2:$B$400=_xlpm.ctry)*('VISA RULES'!$C$2:$C$400=_xlpm.nat)*('VISA RULES'!$A$2:$A$400<>""),0))),""),_xlpm.rule,IFERROR(INDEX('VISA RULES'!$E$2:$E$400,SUMPRODUCT(MATCH(1,('VISA RULES'!$B$2:$B$400=_xlpm.ctry)*('VISA RULES'!$C$2:$C$400=_xlpm.nat)*('VISA RULES'!$A$2:$A$400=""),0))),""),_xlpm.mtx,IFERROR(INDEX('VISA MATRIX'!$B$4:$FS$145,MATCH(_xlpm.ctry,'VISA MATRIX'!$A$4:$A$145,0),MATCH(_xlpm.nat,'VISA MATRIX'!$B$3:$FS$3,0)),""),IF(_xlpm.apt<>"",_xlpm.apt&" (APT OVERRIDE)",IF(_xlpm.rule<>"",_xlpm.rule,IF(_xlpm.mtx<>"",_xlpm.mtx,"NOT ON FILE - VERIFY")))))} -> NOT ON FILE - VERIFY | H91: {=IF(OR($A91="",H$87=""),"",_xlfn.LET(_xlpm.nat,INDEX($AH$18:$AH$37,MATCH(COLUMN()-4,$AJ$18:$AJ$37,0)),_xlpm.ctry,$B91,_xlpm.apt,IFERROR(INDEX('VISA RULES'!$E$2:$E$400,SUMPRODUCT(MATCH(1,('VISA RULES'!$B$2:$B$400=_xlpm.ctry)*('VISA RULES'!$C$2:$C$400=_xlpm.nat)*('VISA RULES'!$A$2:$A$400<>""),0))),""),_xlpm.rule,IFERROR(INDEX('VISA RULES'!$E$2:$E$400,SUMPRODUCT(MATCH(1,('VISA RULES'!$B$2:$B$400=_xlpm.ctry)*('VISA RULES'!$C$2:$C$400=_xlpm.nat)*('VISA RULES'!$A$2:$A$400=""),0))),""),_xlpm.mtx,IFERROR(INDEX('VISA MATRIX'!$B$4:$FS$145,MATCH(_xlpm.ctry,'VISA MATRIX'!$A$4:$A$145,0),MATCH(_xlpm.nat,'VISA MATRIX'!$B$3:$FS$3,0)),""),IF(_xlpm.apt<>"",_xlpm.apt&" (APT OVERRIDE)",IF(_xlpm.rule<>"",_xlpm.rule,IF(_xlpm.mtx<>"",_xlpm.mtx,"NOT ON FILE - VERIFY")))))} | I91: {=IF(OR($A91="",I$87=""),"",_xlfn.LET(_xlpm.nat,INDEX($AH$18:$AH$37,MATCH(COLUMN()-4,$AJ$18:$AJ$37,0)),_xlpm.ctry,$B91,_xlpm.apt,IFERROR(INDEX('VISA RULES'!$E$2:$E$400,SUMPRODUCT(MATCH(1,('VISA RULES'!$B$2:$B$400=_xlpm.ctry)*('VISA RULES'!$C$2:$C$400=_xlpm.nat)*('VISA RULES'!$A$2:$A$400<>""),0))),""),_xlpm.rule,IFERROR(INDEX('VISA RULES'!$E$2:$E$400,SUMPRODUCT(MATCH(1,('VISA RULES'!$B$2:$B$400=_xlpm.ctry)*('VISA RULES'!$C$2:$C$400=_xlpm.nat)*('VISA RULES'!$A$2:$A$400=""),0))),""),_xlpm.mtx,IFERROR(INDEX('VISA MATRIX'!$B$4:$FS$145,MATCH(_xlpm.ctry,'VISA MATRIX'!$A$4:$A$145,0),MATCH(_xlpm.nat,'VISA MATRIX'!$B$3:$FS$3,0)),""),IF(_xlpm.apt<>"",_xlpm.apt&" (APT OVERRIDE)",IF(_xlpm.rule<>"",_xlpm.rule,IF(_xlpm.mtx<>"",_xlpm.mtx,"NOT ON FILE - VERIFY")))))} | J91: {=IF(OR($A91="",J$87=""),"",_xlfn.LET(_xlpm.nat,INDEX($AH$18:$AH$37,MATCH(COLUMN()-4,$AJ$18:$AJ$37,0)),_xlpm.ctry,$B91,_xlpm.apt,IFERROR(INDEX('VISA RULES'!$E$2:$E$400,SUMPRODUCT(MATCH(1,('VISA RULES'!$B$2:$B$400=_xlpm.ctry)*('VISA RULES'!$C$2:$C$400=_xlpm.nat)*('VISA RULES'!$A$2:$A$400<>""),0))),""),_xlpm.rule,IFERROR(INDEX('VISA RULES'!$E$2:$E$400,SUMPRODUCT(MATCH(1,('VISA RULES'!$B$2:$B$400=_xlpm.ctry)*('VISA RULES'!$C$2:$C$400=_xlpm.nat)*('VISA RULES'!$A$2:$A$400=""),0))),""),_xlpm.mtx,IFERROR(INDEX('VISA MATRIX'!$B$4:$FS$145,MATCH(_xlpm.ctry,'VISA MATRIX'!$A$4:$A$145,0),MATCH(_xlpm.nat,'VISA MATRIX'!$B$3:$FS$3,0)),""),IF(_xlpm.apt<>"",_xlpm.apt&" (APT OVERRIDE)",IF(_xlpm.rule<>"",_xlpm.rule,IF(_xlpm.mtx<>"",_xlpm.mtx,"NOT ON FILE - VERIFY")))))}
A92: =IF(ROW()-87>SUM($AO$18:$AO$26),"",ROW()-87) | B92: =IF($A92="","",IFERROR(INDEX(countries!$B:$B,MATCH($C92,countries!$D:$D,0)),$C92)) | C92: =IF($A92="","",INDEX($AK$18:$AK$26,MATCH($A92,$AP$18:$AP$26,0))) | D92: {=IF($A92="","",_xlfn.TEXTJOIN(", ",TRUE,IF($AK$18:$AK$26=$C92,$AM$18:$AM$26,"")))} | E92: {=IF(OR($A92="",E$87=""),"",_xlfn.LET(_xlpm.nat,INDEX($AH$18:$AH$37,MATCH(COLUMN()-4,$AJ$18:$AJ$37,0)),_xlpm.ctry,$B92,_xlpm.apt,IFERROR(INDEX('VISA RULES'!$E$2:$E$400,SUMPRODUCT(MATCH(1,('VISA RULES'!$B$2:$B$400=_xlpm.ctry)*('VISA RULES'!$C$2:$C$400=_xlpm.nat)*('VISA RULES'!$A$2:$A$400<>""),0))),""),_xlpm.rule,IFERROR(INDEX('VISA RULES'!$E$2:$E$400,SUMPRODUCT(MATCH(1,('VISA RULES'!$B$2:$B$400=_xlpm.ctry)*('VISA RULES'!$C$2:$C$400=_xlpm.nat)*('VISA RULES'!$A$2:$A$400=""),0))),""),_xlpm.mtx,IFERROR(INDEX('VISA MATRIX'!$B$4:$FS$145,MATCH(_xlpm.ctry,'VISA MATRIX'!$A$4:$A$145,0),MATCH(_xlpm.nat,'VISA MATRIX'!$B$3:$FS$3,0)),""),IF(_xlpm.apt<>"",_xlpm.apt&" (APT OVERRIDE)",IF(_xlpm.rule<>"",_xlpm.rule,IF(_xlpm.mtx<>"",_xlpm.mtx,"NOT ON FILE - VERIFY")))))} | F92: {=IF(OR($A92="",F$87=""),"",_xlfn.LET(_xlpm.nat,INDEX($AH$18:$AH$37,MATCH(COLUMN()-4,$AJ$18:$AJ$37,0)),_xlpm.ctry,$B92,_xlpm.apt,IFERROR(INDEX('VISA RULES'!$E$2:$E$400,SUMPRODUCT(MATCH(1,('VISA RULES'!$B$2:$B$400=_xlpm.ctry)*('VISA RULES'!$C$2:$C$400=_xlpm.nat)*('VISA RULES'!$A$2:$A$400<>""),0))),""),_xlpm.rule,IFERROR(INDEX('VISA RULES'!$E$2:$E$400,SUMPRODUCT(MATCH(1,('VISA RULES'!$B$2:$B$400=_xlpm.ctry)*('VISA RULES'!$C$2:$C$400=_xlpm.nat)*('VISA RULES'!$A$2:$A$400=""),0))),""),_xlpm.mtx,IFERROR(INDEX('VISA MATRIX'!$B$4:$FS$145,MATCH(_xlpm.ctry,'VISA MATRIX'!$A$4:$A$145,0),MATCH(_xlpm.nat,'VISA MATRIX'!$B$3:$FS$3,0)),""),IF(_xlpm.apt<>"",_xlpm.apt&" (APT OVERRIDE)",IF(_xlpm.rule<>"",_xlpm.rule,IF(_xlpm.mtx<>"",_xlpm.mtx,"NOT ON FILE - VERIFY")))))} | G92: {=IF(OR($A92="",G$87=""),"",_xlfn.LET(_xlpm.nat,INDEX($AH$18:$AH$37,MATCH(COLUMN()-4,$AJ$18:$AJ$37,0)),_xlpm.ctry,$B92,_xlpm.apt,IFERROR(INDEX('VISA RULES'!$E$2:$E$400,SUMPRODUCT(MATCH(1,('VISA RULES'!$B$2:$B$400=_xlpm.ctry)*('VISA RULES'!$C$2:$C$400=_xlpm.nat)*('VISA RULES'!$A$2:$A$400<>""),0))),""),_xlpm.rule,IFERROR(INDEX('VISA RULES'!$E$2:$E$400,SUMPRODUCT(MATCH(1,('VISA RULES'!$B$2:$B$400=_xlpm.ctry)*('VISA RULES'!$C$2:$C$400=_xlpm.nat)*('VISA RULES'!$A$2:$A$400=""),0))),""),_xlpm.mtx,IFERROR(INDEX('VISA MATRIX'!$B$4:$FS$145,MATCH(_xlpm.ctry,'VISA MATRIX'!$A$4:$A$145,0),MATCH(_xlpm.nat,'VISA MATRIX'!$B$3:$FS$3,0)),""),IF(_xlpm.apt<>"",_xlpm.apt&" (APT OVERRIDE)",IF(_xlpm.rule<>"",_xlpm.rule,IF(_xlpm.mtx<>"",_xlpm.mtx,"NOT ON FILE - VERIFY")))))} | H92: {=IF(OR($A92="",H$87=""),"",_xlfn.LET(_xlpm.nat,INDEX($AH$18:$AH$37,MATCH(COLUMN()-4,$AJ$18:$AJ$37,0)),_xlpm.ctry,$B92,_xlpm.apt,IFERROR(INDEX('VISA RULES'!$E$2:$E$400,SUMPRODUCT(MATCH(1,('VISA RULES'!$B$2:$B$400=_xlpm.ctry)*('VISA RULES'!$C$2:$C$400=_xlpm.nat)*('VISA RULES'!$A$2:$A$400<>""),0))),""),_xlpm.rule,IFERROR(INDEX('VISA RULES'!$E$2:$E$400,SUMPRODUCT(MATCH(1,('VISA RULES'!$B$2:$B$400=_xlpm.ctry)*('VISA RULES'!$C$2:$C$400=_xlpm.nat)*('VISA RULES'!$A$2:$A$400=""),0))),""),_xlpm.mtx,IFERROR(INDEX('VISA MATRIX'!$B$4:$FS$145,MATCH(_xlpm.ctry,'VISA MATRIX'!$A$4:$A$145,0),MATCH(_xlpm.nat,'VISA MATRIX'!$B$3:$FS$3,0)),""),IF(_xlpm.apt<>"",_xlpm.apt&" (APT OVERRIDE)",IF(_xlpm.rule<>"",_xlpm.rule,IF(_xlpm.mtx<>"",_xlpm.mtx,"NOT ON FILE - VERIFY")))))} | I92: {=IF(OR($A92="",I$87=""),"",_xlfn.LET(_xlpm.nat,INDEX($AH$18:$AH$37,MATCH(COLUMN()-4,$AJ$18:$AJ$37,0)),_xlpm.ctry,$B92,_xlpm.apt,IFERROR(INDEX('VISA RULES'!$E$2:$E$400,SUMPRODUCT(MATCH(1,('VISA RULES'!$B$2:$B$400=_xlpm.ctry)*('VISA RULES'!$C$2:$C$400=_xlpm.nat)*('VISA RULES'!$A$2:$A$400<>""),0))),""),_xlpm.rule,IFERROR(INDEX('VISA RULES'!$E$2:$E$400,SUMPRODUCT(MATCH(1,('VISA RULES'!$B$2:$B$400=_xlpm.ctry)*('VISA RULES'!$C$2:$C$400=_xlpm.nat)*('VISA RULES'!$A$2:$A$400=""),0))),""),_xlpm.mtx,IFERROR(INDEX('VISA MATRIX'!$B$4:$FS$145,MATCH(_xlpm.ctry,'VISA MATRIX'!$A$4:$A$145,0),MATCH(_xlpm.nat,'VISA MATRIX'!$B$3:$FS$3,0)),""),IF(_xlpm.apt<>"",_xlpm.apt&" (APT OVERRIDE)",IF(_xlpm.rule<>"",_xlpm.rule,IF(_xlpm.mtx<>"",_xlpm.mtx,"NOT ON FILE - VERIFY")))))} | J92: {=IF(OR($A92="",J$87=""),"",_xlfn.LET(_xlpm.nat,INDEX($AH$18:$AH$37,MATCH(COLUMN()-4,$AJ$18:$AJ$37,0)),_xlpm.ctry,$B92,_xlpm.apt,IFERROR(INDEX('VISA RULES'!$E$2:$E$400,SUMPRODUCT(MATCH(1,('VISA RULES'!$B$2:$B$400=_xlpm.ctry)*('VISA RULES'!$C$2:$C$400=_xlpm.nat)*('VISA RULES'!$A$2:$A$400<>""),0))),""),_xlpm.rule,IFERROR(INDEX('VISA RULES'!$E$2:$E$400,SUMPRODUCT(MATCH(1,('VISA RULES'!$B$2:$B$400=_xlpm.ctry)*('VISA RULES'!$C$2:$C$400=_xlpm.nat)*('VISA RULES'!$A$2:$A$400=""),0))),""),_xlpm.mtx,IFERROR(INDEX('VISA MATRIX'!$B$4:$FS$145,MATCH(_xlpm.ctry,'VISA MATRIX'!$A$4:$A$145,0),MATCH(_xlpm.nat,'VISA MATRIX'!$B$3:$FS$3,0)),""),IF(_xlpm.apt<>"",_xlpm.apt&" (APT OVERRIDE)",IF(_xlpm.rule<>"",_xlpm.rule,IF(_xlpm.mtx<>"",_xlpm.mtx,"NOT ON FILE - VERIFY")))))}
A93: =IF(ROW()-87>SUM($AO$18:$AO$26),"",ROW()-87) | B93: =IF($A93="","",IFERROR(INDEX(countries!$B:$B,MATCH($C93,countries!$D:$D,0)),$C93)) | C93: =IF($A93="","",INDEX($AK$18:$AK$26,MATCH($A93,$AP$18:$AP$26,0))) | D93: {=IF($A93="","",_xlfn.TEXTJOIN(", ",TRUE,IF($AK$18:$AK$26=$C93,$AM$18:$AM$26,"")))} | E93: {=IF(OR($A93="",E$87=""),"",IF(IFERROR(INDEX('VISA MATRIX'!$B$4:$FS$145,MATCH($B93,'VISA MATRIX'!$A$4:$A$145,0),MATCH(INDEX($AH$18:$AH$37,MATCH(COLUMN()-4,$AJ$18:$AJ$37,0)),'VISA MATRIX'!$B$3:$FS$3,0)),"")<>"",IFERROR(INDEX('VISA MATRIX'!$B$4:$FS$145,MATCH($B93,'VISA MATRIX'!$A$4:$A$145,0),MATCH(INDEX($AH$18:$AH$37,MATCH(COLUMN()-4,$AJ$18:$AJ$37,0)),'VISA MATRIX'!$B$3:$FS$3,0)),""),IF(IFERROR(INDEX('VISA RULES'!$E$2:$E$400,SUMPRODUCT(MATCH(1,($B93='VISA RULES'!$B$2:$B$400)*(INDEX($AH$18:$AH$37,MATCH(COLUMN()-4,$AJ$18:$AJ$37,0))='VISA RULES'!$C$2:$C$400),0))),"")<>"",IFERROR(INDEX('VISA RULES'!$E$2:$E$400,SUMPRODUCT(MATCH(1,($B93='VISA RULES'!$B$2:$B$400)*(INDEX($AH$18:$AH$37,MATCH(COLUMN()-4,$AJ$18:$AJ$37,0))='VISA RULES'!$C$2:$C$400),0))),""),"NOT ON FILE - VERIFY")))} | F93: {=IF(OR($A93="",F$87=""),"",IF(IFERROR(INDEX('VISA MATRIX'!$B$4:$FS$145,MATCH($B93,'VISA MATRIX'!$A$4:$A$145,0),MATCH(INDEX($AH$18:$AH$37,MATCH(COLUMN()-4,$AJ$18:$AJ$37,0)),'VISA MATRIX'!$B$3:$FS$3,0)),"")<>"",IFERROR(INDEX('VISA MATRIX'!$B$4:$FS$145,MATCH($B93,'VISA MATRIX'!$A$4:$A$145,0),MATCH(INDEX($AH$18:$AH$37,MATCH(COLUMN()-4,$AJ$18:$AJ$37,0)),'VISA MATRIX'!$B$3:$FS$3,0)),""),IF(IFERROR(INDEX('VISA RULES'!$E$2:$E$400,SUMPRODUCT(MATCH(1,($B93='VISA RULES'!$B$2:$B$400)*(INDEX($AH$18:$AH$37,MATCH(COLUMN()-4,$AJ$18:$AJ$37,0))='VISA RULES'!$C$2:$C$400),0))),"")<>"",IFERROR(INDEX('VISA RULES'!$E$2:$E$400,SUMPRODUCT(MATCH(1,($B93='VISA RULES'!$B$2:$B$400)*(INDEX($AH$18:$AH$37,MATCH(COLUMN()-4,$AJ$18:$AJ$37,0))='VISA RULES'!$C$2:$C$400),0))),""),"NOT ON FILE - VERIFY")))} | G93: {=IF(OR($A93="",G$87=""),"",IF(IFERROR(INDEX('VISA MATRIX'!$B$4:$FS$145,MATCH($B93,'VISA MATRIX'!$A$4:$A$145,0),MATCH(INDEX($AH$18:$AH$37,MATCH(COLUMN()-4,$AJ$18:$AJ$37,0)),'VISA MATRIX'!$B$3:$FS$3,0)),"")<>"",IFERROR(INDEX('VISA MATRIX'!$B$4:$FS$145,MATCH($B93,'VISA MATRIX'!$A$4:$A$145,0),MATCH(INDEX($AH$18:$AH$37,MATCH(COLUMN()-4,$AJ$18:$AJ$37,0)),'VISA MATRIX'!$B$3:$FS$3,0)),""),IF(IFERROR(INDEX('VISA RULES'!$E$2:$E$400,SUMPRODUCT(MATCH(1,($B93='VISA RULES'!$B$2:$B$400)*(INDEX($AH$18:$AH$37,MATCH(COLUMN()-4,$AJ$18:$AJ$37,0))='VISA RULES'!$C$2:$C$400),0))),"")<>"",IFERROR(INDEX('VISA RULES'!$E$2:$E$400,SUMPRODUCT(MATCH(1,($B93='VISA RULES'!$B$2:$B$400)*(INDEX($AH$18:$AH$37,MATCH(COLUMN()-4,$AJ$18:$AJ$37,0))='VISA RULES'!$C$2:$C$400),0))),""),"NOT ON FILE - VERIFY")))} | H93: {=IF(OR($A93="",H$87=""),"",IF(IFERROR(INDEX('VISA MATRIX'!$B$4:$FS$145,MATCH($B93,'VISA MATRIX'!$A$4:$A$145,0),MATCH(INDEX($AH$18:$AH$37,MATCH(COLUMN()-4,$AJ$18:$AJ$37,0)),'VISA MATRIX'!$B$3:$FS$3,0)),"")<>"",IFERROR(INDEX('VISA MATRIX'!$B$4:$FS$145,MATCH($B93,'VISA MATRIX'!$A$4:$A$145,0),MATCH(INDEX($AH$18:$AH$37,MATCH(COLUMN()-4,$AJ$18:$AJ$37,0)),'VISA MATRIX'!$B$3:$FS$3,0)),""),IF(IFERROR(INDEX('VISA RULES'!$E$2:$E$400,SUMPRODUCT(MATCH(1,($B93='VISA RULES'!$B$2:$B$400)*(INDEX($AH$18:$AH$37,MATCH(COLUMN()-4,$AJ$18:$AJ$37,0))='VISA RULES'!$C$2:$C$400),0))),"")<>"",IFERROR(INDEX('VISA RULES'!$E$2:$E$400,SUMPRODUCT(MATCH(1,($B93='VISA RULES'!$B$2:$B$400)*(INDEX($AH$18:$AH$37,MATCH(COLUMN()-4,$AJ$18:$AJ$37,0))='VISA RULES'!$C$2:$C$400),0))),""),"NOT ON FILE - VERIFY")))} | I93: {=IF(OR($A93="",I$87=""),"",IF(IFERROR(INDEX('VISA MATRIX'!$B$4:$FS$145,MATCH($B93,'VISA MATRIX'!$A$4:$A$145,0),MATCH(INDEX($AH$18:$AH$37,MATCH(COLUMN()-4,$AJ$18:$AJ$37,0)),'VISA MATRIX'!$B$3:$FS$3,0)),"")<>"",IFERROR(INDEX('VISA MATRIX'!$B$4:$FS$145,MATCH($B93,'VISA MATRIX'!$A$4:$A$145,0),MATCH(INDEX($AH$18:$AH$37,MATCH(COLUMN()-4,$AJ$18:$AJ$37,0)),'VISA MATRIX'!$B$3:$FS$3,0)),""),IF(IFERROR(INDEX('VISA RULES'!$E$2:$E$400,SUMPRODUCT(MATCH(1,($B93='VISA RULES'!$B$2:$B$400)*(INDEX($AH$18:$AH$37,MATCH(COLUMN()-4,$AJ$18:$AJ$37,0))='VISA RULES'!$C$2:$C$400),0))),"")<>"",IFERROR(INDEX('VISA RULES'!$E$2:$E$400,SUMPRODUCT(MATCH(1,($B93='VISA RULES'!$B$2:$B$400)*(INDEX($AH$18:$AH$37,MATCH(COLUMN()-4,$AJ$18:$AJ$37,0))='VISA RULES'!$C$2:$C$400),0))),""),"NOT ON FILE - VERIFY")))} | J93: {=IF(OR($A93="",J$87=""),"",IF(IFERROR(INDEX('VISA MATRIX'!$B$4:$FS$145,MATCH($B93,'VISA MATRIX'!$A$4:$A$145,0),MATCH(INDEX($AH$18:$AH$37,MATCH(COLUMN()-4,$AJ$18:$AJ$37,0)),'VISA MATRIX'!$B$3:$FS$3,0)),"")<>"",IFERROR(INDEX('VISA MATRIX'!$B$4:$FS$145,MATCH($B93,'VISA MATRIX'!$A$4:$A$145,0),MATCH(INDEX($AH$18:$AH$37,MATCH(COLUMN()-4,$AJ$18:$AJ$37,0)),'VISA MATRIX'!$B$3:$FS$3,0)),""),IF(IFERROR(INDEX('VISA RULES'!$E$2:$E$400,SUMPRODUCT(MATCH(1,($B93='VISA RULES'!$B$2:$B$400)*(INDEX($AH$18:$AH$37,MATCH(COLUMN()-4,$AJ$18:$AJ$37,0))='VISA RULES'!$C$2:$C$400),0))),"")<>"",IFERROR(INDEX('VISA RULES'!$E$2:$E$400,SUMPRODUCT(MATCH(1,($B93='VISA RULES'!$B$2:$B$400)*(INDEX($AH$18:$AH$37,MATCH(COLUMN()-4,$AJ$18:$AJ$37,0))='VISA RULES'!$C$2:$C$400),0))),""),"NOT ON FILE - VERIFY")))}
A94: =IF(ROW()-87>SUM($AO$18:$AO$26),"",ROW()-87) | B94: =IF($A94="","",IFERROR(INDEX(countries!$B:$B,MATCH($C94,countries!$D:$D,0)),$C94)) | C94: =IF($A94="","",INDEX($AK$18:$AK$26,MATCH($A94,$AP$18:$AP$26,0))) | D94: {=IF($A94="","",_xlfn.TEXTJOIN(", ",TRUE,IF($AK$18:$AK$26=$C94,$AM$18:$AM$26,"")))} | E94: {=IF(OR($A94="",E$87=""),"",IF(IFERROR(INDEX('VISA MATRIX'!$B$4:$FS$145,MATCH($B94,'VISA MATRIX'!$A$4:$A$145,0),MATCH(INDEX($AH$18:$AH$37,MATCH(COLUMN()-4,$AJ$18:$AJ$37,0)),'VISA MATRIX'!$B$3:$FS$3,0)),"")<>"",IFERROR(INDEX('VISA MATRIX'!$B$4:$FS$145,MATCH($B94,'VISA MATRIX'!$A$4:$A$145,0),MATCH(INDEX($AH$18:$AH$37,MATCH(COLUMN()-4,$AJ$18:$AJ$37,0)),'VISA MATRIX'!$B$3:$FS$3,0)),""),IF(IFERROR(INDEX('VISA RULES'!$E$2:$E$400,SUMPRODUCT(MATCH(1,($B94='VISA RULES'!$B$2:$B$400)*(INDEX($AH$18:$AH$37,MATCH(COLUMN()-4,$AJ$18:$AJ$37,0))='VISA RULES'!$C$2:$C$400),0))),"")<>"",IFERROR(INDEX('VISA RULES'!$E$2:$E$400,SUMPRODUCT(MATCH(1,($B94='VISA RULES'!$B$2:$B$400)*(INDEX($AH$18:$AH$37,MATCH(COLUMN()-4,$AJ$18:$AJ$37,0))='VISA RULES'!$C$2:$C$400),0))),""),"NOT ON FILE - VERIFY")))} | F94: {=IF(OR($A94="",F$87=""),"",IF(IFERROR(INDEX('VISA MATRIX'!$B$4:$FS$145,MATCH($B94,'VISA MATRIX'!$A$4:$A$145,0),MATCH(INDEX($AH$18:$AH$37,MATCH(COLUMN()-4,$AJ$18:$AJ$37,0)),'VISA MATRIX'!$B$3:$FS$3,0)),"")<>"",IFERROR(INDEX('VISA MATRIX'!$B$4:$FS$145,MATCH($B94,'VISA MATRIX'!$A$4:$A$145,0),MATCH(INDEX($AH$18:$AH$37,MATCH(COLUMN()-4,$AJ$18:$AJ$37,0)),'VISA MATRIX'!$B$3:$FS$3,0)),""),IF(IFERROR(INDEX('VISA RULES'!$E$2:$E$400,SUMPRODUCT(MATCH(1,($B94='VISA RULES'!$B$2:$B$400)*(INDEX($AH$18:$AH$37,MATCH(COLUMN()-4,$AJ$18:$AJ$37,0))='VISA RULES'!$C$2:$C$400),0))),"")<>"",IFERROR(INDEX('VISA RULES'!$E$2:$E$400,SUMPRODUCT(MATCH(1,($B94='VISA RULES'!$B$2:$B$400)*(INDEX($AH$18:$AH$37,MATCH(COLUMN()-4,$AJ$18:$AJ$37,0))='VISA RULES'!$C$2:$C$400),0))),""),"NOT ON FILE - VERIFY")))} | G94: {=IF(OR($A94="",G$87=""),"",IF(IFERROR(INDEX('VISA MATRIX'!$B$4:$FS$145,MATCH($B94,'VISA MATRIX'!$A$4:$A$145,0),MATCH(INDEX($AH$18:$AH$37,MATCH(COLUMN()-4,$AJ$18:$AJ$37,0)),'VISA MATRIX'!$B$3:$FS$3,0)),"")<>"",IFERROR(INDEX('VISA MATRIX'!$B$4:$FS$145,MATCH($B94,'VISA MATRIX'!$A$4:$A$145,0),MATCH(INDEX($AH$18:$AH$37,MATCH(COLUMN()-4,$AJ$18:$AJ$37,0)),'VISA MATRIX'!$B$3:$FS$3,0)),""),IF(IFERROR(INDEX('VISA RULES'!$E$2:$E$400,SUMPRODUCT(MATCH(1,($B94='VISA RULES'!$B$2:$B$400)*(INDEX($AH$18:$AH$37,MATCH(COLUMN()-4,$AJ$18:$AJ$37,0))='VISA RULES'!$C$2:$C$400),0))),"")<>"",IFERROR(INDEX('VISA RULES'!$E$2:$E$400,SUMPRODUCT(MATCH(1,($B94='VISA RULES'!$B$2:$B$400)*(INDEX($AH$18:$AH$37,MATCH(COLUMN()-4,$AJ$18:$AJ$37,0))='VISA RULES'!$C$2:$C$400),0))),""),"NOT ON FILE - VERIFY")))} | H94: {=IF(OR($A94="",H$87=""),"",IF(IFERROR(INDEX('VISA MATRIX'!$B$4:$FS$145,MATCH($B94,'VISA MATRIX'!$A$4:$A$145,0),MATCH(INDEX($AH$18:$AH$37,MATCH(COLUMN()-4,$AJ$18:$AJ$37,0)),'VISA MATRIX'!$B$3:$FS$3,0)),"")<>"",IFERROR(INDEX('VISA MATRIX'!$B$4:$FS$145,MATCH($B94,'VISA MATRIX'!$A$4:$A$145,0),MATCH(INDEX($AH$18:$AH$37,MATCH(COLUMN()-4,$AJ$18:$AJ$37,0)),'VISA MATRIX'!$B$3:$FS$3,0)),""),IF(IFERROR(INDEX('VISA RULES'!$E$2:$E$400,SUMPRODUCT(MATCH(1,($B94='VISA RULES'!$B$2:$B$400)*(INDEX($AH$18:$AH$37,MATCH(COLUMN()-4,$AJ$18:$AJ$37,0))='VISA RULES'!$C$2:$C$400),0))),"")<>"",IFERROR(INDEX('VISA RULES'!$E$2:$E$400,SUMPRODUCT(MATCH(1,($B94='VISA RULES'!$B$2:$B$400)*(INDEX($AH$18:$AH$37,MATCH(COLUMN()-4,$AJ$18:$AJ$37,0))='VISA RULES'!$C$2:$C$400),0))),""),"NOT ON FILE - VERIFY")))} | I94: {=IF(OR($A94="",I$87=""),"",IF(IFERROR(INDEX('VISA MATRIX'!$B$4:$FS$145,MATCH($B94,'VISA MATRIX'!$A$4:$A$145,0),MATCH(INDEX($AH$18:$AH$37,MATCH(COLUMN()-4,$AJ$18:$AJ$37,0)),'VISA MATRIX'!$B$3:$FS$3,0)),"")<>"",IFERROR(INDEX('VISA MATRIX'!$B$4:$FS$145,MATCH($B94,'VISA MATRIX'!$A$4:$A$145,0),MATCH(INDEX($AH$18:$AH$37,MATCH(COLUMN()-4,$AJ$18:$AJ$37,0)),'VISA MATRIX'!$B$3:$FS$3,0)),""),IF(IFERROR(INDEX('VISA RULES'!$E$2:$E$400,SUMPRODUCT(MATCH(1,($B94='VISA RULES'!$B$2:$B$400)*(INDEX($AH$18:$AH$37,MATCH(COLUMN()-4,$AJ$18:$AJ$37,0))='VISA RULES'!$C$2:$C$400),0))),"")<>"",IFERROR(INDEX('VISA RULES'!$E$2:$E$400,SUMPRODUCT(MATCH(1,($B94='VISA RULES'!$B$2:$B$400)*(INDEX($AH$18:$AH$37,MATCH(COLUMN()-4,$AJ$18:$AJ$37,0))='VISA RULES'!$C$2:$C$400),0))),""),"NOT ON FILE - VERIFY")))} | J94: {=IF(OR($A94="",J$87=""),"",IF(IFERROR(INDEX('VISA MATRIX'!$B$4:$FS$145,MATCH($B94,'VISA MATRIX'!$A$4:$A$145,0),MATCH(INDEX($AH$18:$AH$37,MATCH(COLUMN()-4,$AJ$18:$AJ$37,0)),'VISA MATRIX'!$B$3:$FS$3,0)),"")<>"",IFERROR(INDEX('VISA MATRIX'!$B$4:$FS$145,MATCH($B94,'VISA MATRIX'!$A$4:$A$145,0),MATCH(INDEX($AH$18:$AH$37,MATCH(COLUMN()-4,$AJ$18:$AJ$37,0)),'VISA MATRIX'!$B$3:$FS$3,0)),""),IF(IFERROR(INDEX('VISA RULES'!$E$2:$E$400,SUMPRODUCT(MATCH(1,($B94='VISA RULES'!$B$2:$B$400)*(INDEX($AH$18:$AH$37,MATCH(COLUMN()-4,$AJ$18:$AJ$37,0))='VISA RULES'!$C$2:$C$400),0))),"")<>"",IFERROR(INDEX('VISA RULES'!$E$2:$E$400,SUMPRODUCT(MATCH(1,($B94='VISA RULES'!$B$2:$B$400)*(INDEX($AH$18:$AH$37,MATCH(COLUMN()-4,$AJ$18:$AJ$37,0))='VISA RULES'!$C$2:$C$400),0))),""),"NOT ON FILE - VERIFY")))}
A95: =IF(ROW()-87>SUM($AO$18:$AO$26),"",ROW()-87) | B95: =IF($A95="","",IFERROR(INDEX(countries!$B:$B,MATCH($C95,countries!$D:$D,0)),$C95)) | C95: =IF($A95="","",INDEX($AK$18:$AK$26,MATCH($A95,$AP$18:$AP$26,0))) | D95: {=IF($A95="","",_xlfn.TEXTJOIN(", ",TRUE,IF($AK$18:$AK$26=$C95,$AM$18:$AM$26,"")))} | E95: {=IF(OR($A95="",E$87=""),"",IF(IFERROR(INDEX('VISA MATRIX'!$B$4:$FS$145,MATCH($B95,'VISA MATRIX'!$A$4:$A$145,0),MATCH(INDEX($AH$18:$AH$37,MATCH(COLUMN()-4,$AJ$18:$AJ$37,0)),'VISA MATRIX'!$B$3:$FS$3,0)),"")<>"",IFERROR(INDEX('VISA MATRIX'!$B$4:$FS$145,MATCH($B95,'VISA MATRIX'!$A$4:$A$145,0),MATCH(INDEX($AH$18:$AH$37,MATCH(COLUMN()-4,$AJ$18:$AJ$37,0)),'VISA MATRIX'!$B$3:$FS$3,0)),""),IF(IFERROR(INDEX('VISA RULES'!$E$2:$E$400,SUMPRODUCT(MATCH(1,($B95='VISA RULES'!$B$2:$B$400)*(INDEX($AH$18:$AH$37,MATCH(COLUMN()-4,$AJ$18:$AJ$37,0))='VISA RULES'!$C$2:$C$400),0))),"")<>"",IFERROR(INDEX('VISA RULES'!$E$2:$E$400,SUMPRODUCT(MATCH(1,($B95='VISA RULES'!$B$2:$B$400)*(INDEX($AH$18:$AH$37,MATCH(COLUMN()-4,$AJ$18:$AJ$37,0))='VISA RULES'!$C$2:$C$400),0))),""),"NOT ON FILE - VERIFY")))} | F95: {=IF(OR($A95="",F$87=""),"",IF(IFERROR(INDEX('VISA MATRIX'!$B$4:$FS$145,MATCH($B95,'VISA MATRIX'!$A$4:$A$145,0),MATCH(INDEX($AH$18:$AH$37,MATCH(COLUMN()-4,$AJ$18:$AJ$37,0)),'VISA MATRIX'!$B$3:$FS$3,0)),"")<>"",IFERROR(INDEX('VISA MATRIX'!$B$4:$FS$145,MATCH($B95,'VISA MATRIX'!$A$4:$A$145,0),MATCH(INDEX($AH$18:$AH$37,MATCH(COLUMN()-4,$AJ$18:$AJ$37,0)),'VISA MATRIX'!$B$3:$FS$3,0)),""),IF(IFERROR(INDEX('VISA RULES'!$E$2:$E$400,SUMPRODUCT(MATCH(1,($B95='VISA RULES'!$B$2:$B$400)*(INDEX($AH$18:$AH$37,MATCH(COLUMN()-4,$AJ$18:$AJ$37,0))='VISA RULES'!$C$2:$C$400),0))),"")<>"",IFERROR(INDEX('VISA RULES'!$E$2:$E$400,SUMPRODUCT(MATCH(1,($B95='VISA RULES'!$B$2:$B$400)*(INDEX($AH$18:$AH$37,MATCH(COLUMN()-4,$AJ$18:$AJ$37,0))='VISA RULES'!$C$2:$C$400),0))),""),"NOT ON FILE - VERIFY")))} | G95: {=IF(OR($A95="",G$87=""),"",IF(IFERROR(INDEX('VISA MATRIX'!$B$4:$FS$145,MATCH($B95,'VISA MATRIX'!$A$4:$A$145,0),MATCH(INDEX($AH$18:$AH$37,MATCH(COLUMN()-4,$AJ$18:$AJ$37,0)),'VISA MATRIX'!$B$3:$FS$3,0)),"")<>"",IFERROR(INDEX('VISA MATRIX'!$B$4:$FS$145,MATCH($B95,'VISA MATRIX'!$A$4:$A$145,0),MATCH(INDEX($AH$18:$AH$37,MATCH(COLUMN()-4,$AJ$18:$AJ$37,0)),'VISA MATRIX'!$B$3:$FS$3,0)),""),IF(IFERROR(INDEX('VISA RULES'!$E$2:$E$400,SUMPRODUCT(MATCH(1,($B95='VISA RULES'!$B$2:$B$400)*(INDEX($AH$18:$AH$37,MATCH(COLUMN()-4,$AJ$18:$AJ$37,0))='VISA RULES'!$C$2:$C$400),0))),"")<>"",IFERROR(INDEX('VISA RULES'!$E$2:$E$400,SUMPRODUCT(MATCH(1,($B95='VISA RULES'!$B$2:$B$400)*(INDEX($AH$18:$AH$37,MATCH(COLUMN()-4,$AJ$18:$AJ$37,0))='VISA RULES'!$C$2:$C$400),0))),""),"NOT ON FILE - VERIFY")))} | H95: {=IF(OR($A95="",H$87=""),"",IF(IFERROR(INDEX('VISA MATRIX'!$B$4:$FS$145,MATCH($B95,'VISA MATRIX'!$A$4:$A$145,0),MATCH(INDEX($AH$18:$AH$37,MATCH(COLUMN()-4,$AJ$18:$AJ$37,0)),'VISA MATRIX'!$B$3:$FS$3,0)),"")<>"",IFERROR(INDEX('VISA MATRIX'!$B$4:$FS$145,MATCH($B95,'VISA MATRIX'!$A$4:$A$145,0),MATCH(INDEX($AH$18:$AH$37,MATCH(COLUMN()-4,$AJ$18:$AJ$37,0)),'VISA MATRIX'!$B$3:$FS$3,0)),""),IF(IFERROR(INDEX('VISA RULES'!$E$2:$E$400,SUMPRODUCT(MATCH(1,($B95='VISA RULES'!$B$2:$B$400)*(INDEX($AH$18:$AH$37,MATCH(COLUMN()-4,$AJ$18:$AJ$37,0))='VISA RULES'!$C$2:$C$400),0))),"")<>"",IFERROR(INDEX('VISA RULES'!$E$2:$E$400,SUMPRODUCT(MATCH(1,($B95='VISA RULES'!$B$2:$B$400)*(INDEX($AH$18:$AH$37,MATCH(COLUMN()-4,$AJ$18:$AJ$37,0))='VISA RULES'!$C$2:$C$400),0))),""),"NOT ON FILE - VERIFY")))} | I95: {=IF(OR($A95="",I$87=""),"",IF(IFERROR(INDEX('VISA MATRIX'!$B$4:$FS$145,MATCH($B95,'VISA MATRIX'!$A$4:$A$145,0),MATCH(INDEX($AH$18:$AH$37,MATCH(COLUMN()-4,$AJ$18:$AJ$37,0)),'VISA MATRIX'!$B$3:$FS$3,0)),"")<>"",IFERROR(INDEX('VISA MATRIX'!$B$4:$FS$145,MATCH($B95,'VISA MATRIX'!$A$4:$A$145,0),MATCH(INDEX($AH$18:$AH$37,MATCH(COLUMN()-4,$AJ$18:$AJ$37,0)),'VISA MATRIX'!$B$3:$FS$3,0)),""),IF(IFERROR(INDEX('VISA RULES'!$E$2:$E$400,SUMPRODUCT(MATCH(1,($B95='VISA RULES'!$B$2:$B$400)*(INDEX($AH$18:$AH$37,MATCH(COLUMN()-4,$AJ$18:$AJ$37,0))='VISA RULES'!$C$2:$C$400),0))),"")<>"",IFERROR(INDEX('VISA RULES'!$E$2:$E$400,SUMPRODUCT(MATCH(1,($B95='VISA RULES'!$B$2:$B$400)*(INDEX($AH$18:$AH$37,MATCH(COLUMN()-4,$AJ$18:$AJ$37,0))='VISA RULES'!$C$2:$C$400),0))),""),"NOT ON FILE - VERIFY")))} | J95: {=IF(OR($A95="",J$87=""),"",IF(IFERROR(INDEX('VISA MATRIX'!$B$4:$FS$145,MATCH($B95,'VISA MATRIX'!$A$4:$A$145,0),MATCH(INDEX($AH$18:$AH$37,MATCH(COLUMN()-4,$AJ$18:$AJ$37,0)),'VISA MATRIX'!$B$3:$FS$3,0)),"")<>"",IFERROR(INDEX('VISA MATRIX'!$B$4:$FS$145,MATCH($B95,'VISA MATRIX'!$A$4:$A$145,0),MATCH(INDEX($AH$18:$AH$37,MATCH(COLUMN()-4,$AJ$18:$AJ$37,0)),'VISA MATRIX'!$B$3:$FS$3,0)),""),IF(IFERROR(INDEX('VISA RULES'!$E$2:$E$400,SUMPRODUCT(MATCH(1,($B95='VISA RULES'!$B$2:$B$400)*(INDEX($AH$18:$AH$37,MATCH(COLUMN()-4,$AJ$18:$AJ$37,0))='VISA RULES'!$C$2:$C$400),0))),"")<>"",IFERROR(INDEX('VISA RULES'!$E$2:$E$400,SUMPRODUCT(MATCH(1,($B95='VISA RULES'!$B$2:$B$400)*(INDEX($AH$18:$AH$37,MATCH(COLUMN()-4,$AJ$18:$AJ$37,0))='VISA RULES'!$C$2:$C$400),0))),""),"NOT ON FILE - VERIFY")))}
A96: =IF(ROW()-87>SUM($AO$18:$AO$26),"",ROW()-87) | B96: =IF($A96="","",IFERROR(INDEX(countries!$B:$B,MATCH($C96,countries!$D:$D,0)),$C96)) | C96: =IF($A96="","",INDEX($AK$18:$AK$26,MATCH($A96,$AP$18:$AP$26,0))) | D96: {=IF($A96="","",_xlfn.TEXTJOIN(", ",TRUE,IF($AK$18:$AK$26=$C96,$AM$18:$AM$26,"")))} | E96: {=IF(OR($A96="",E$87=""),"",IF(IFERROR(INDEX('VISA MATRIX'!$B$4:$FS$145,MATCH($B96,'VISA MATRIX'!$A$4:$A$145,0),MATCH(INDEX($AH$18:$AH$37,MATCH(COLUMN()-4,$AJ$18:$AJ$37,0)),'VISA MATRIX'!$B$3:$FS$3,0)),"")<>"",IFERROR(INDEX('VISA MATRIX'!$B$4:$FS$145,MATCH($B96,'VISA MATRIX'!$A$4:$A$145,0),MATCH(INDEX($AH$18:$AH$37,MATCH(COLUMN()-4,$AJ$18:$AJ$37,0)),'VISA MATRIX'!$B$3:$FS$3,0)),""),IF(IFERROR(INDEX('VISA RULES'!$E$2:$E$400,SUMPRODUCT(MATCH(1,($B96='VISA RULES'!$B$2:$B$400)*(INDEX($AH$18:$AH$37,MATCH(COLUMN()-4,$AJ$18:$AJ$37,0))='VISA RULES'!$C$2:$C$400),0))),"")<>"",IFERROR(INDEX('VISA RULES'!$E$2:$E$400,SUMPRODUCT(MATCH(1,($B96='VISA RULES'!$B$2:$B$400)*(INDEX($AH$18:$AH$37,MATCH(COLUMN()-4,$AJ$18:$AJ$37,0))='VISA RULES'!$C$2:$C$400),0))),""),"NOT ON FILE - VERIFY")))} | F96: {=IF(OR($A96="",F$87=""),"",IF(IFERROR(INDEX('VISA MATRIX'!$B$4:$FS$145,MATCH($B96,'VISA MATRIX'!$A$4:$A$145,0),MATCH(INDEX($AH$18:$AH$37,MATCH(COLUMN()-4,$AJ$18:$AJ$37,0)),'VISA MATRIX'!$B$3:$FS$3,0)),"")<>"",IFERROR(INDEX('VISA MATRIX'!$B$4:$FS$145,MATCH($B96,'VISA MATRIX'!$A$4:$A$145,0),MATCH(INDEX($AH$18:$AH$37,MATCH(COLUMN()-4,$AJ$18:$AJ$37,0)),'VISA MATRIX'!$B$3:$FS$3,0)),""),IF(IFERROR(INDEX('VISA RULES'!$E$2:$E$400,SUMPRODUCT(MATCH(1,($B96='VISA RULES'!$B$2:$B$400)*(INDEX($AH$18:$AH$37,MATCH(COLUMN()-4,$AJ$18:$AJ$37,0))='VISA RULES'!$C$2:$C$400),0))),"")<>"",IFERROR(INDEX('VISA RULES'!$E$2:$E$400,SUMPRODUCT(MATCH(1,($B96='VISA RULES'!$B$2:$B$400)*(INDEX($AH$18:$AH$37,MATCH(COLUMN()-4,$AJ$18:$AJ$37,0))='VISA RULES'!$C$2:$C$400),0))),""),"NOT ON FILE - VERIFY")))} | G96: {=IF(OR($A96="",G$87=""),"",IF(IFERROR(INDEX('VISA MATRIX'!$B$4:$FS$145,MATCH($B96,'VISA MATRIX'!$A$4:$A$145,0),MATCH(INDEX($AH$18:$AH$37,MATCH(COLUMN()-4,$AJ$18:$AJ$37,0)),'VISA MATRIX'!$B$3:$FS$3,0)),"")<>"",IFERROR(INDEX('VISA MATRIX'!$B$4:$FS$145,MATCH($B96,'VISA MATRIX'!$A$4:$A$145,0),MATCH(INDEX($AH$18:$AH$37,MATCH(COLUMN()-4,$AJ$18:$AJ$37,0)),'VISA MATRIX'!$B$3:$FS$3,0)),""),IF(IFERROR(INDEX('VISA RULES'!$E$2:$E$400,SUMPRODUCT(MATCH(1,($B96='VISA RULES'!$B$2:$B$400)*(INDEX($AH$18:$AH$37,MATCH(COLUMN()-4,$AJ$18:$AJ$37,0))='VISA RULES'!$C$2:$C$400),0))),"")<>"",IFERROR(INDEX('VISA RULES'!$E$2:$E$400,SUMPRODUCT(MATCH(1,($B96='VISA RULES'!$B$2:$B$400)*(INDEX($AH$18:$AH$37,MATCH(COLUMN()-4,$AJ$18:$AJ$37,0))='VISA RULES'!$C$2:$C$400),0))),""),"NOT ON FILE - VERIFY")))} | H96: {=IF(OR($A96="",H$87=""),"",IF(IFERROR(INDEX('VISA MATRIX'!$B$4:$FS$145,MATCH($B96,'VISA MATRIX'!$A$4:$A$145,0),MATCH(INDEX($AH$18:$AH$37,MATCH(COLUMN()-4,$AJ$18:$AJ$37,0)),'VISA MATRIX'!$B$3:$FS$3,0)),"")<>"",IFERROR(INDEX('VISA MATRIX'!$B$4:$FS$145,MATCH($B96,'VISA MATRIX'!$A$4:$A$145,0),MATCH(INDEX($AH$18:$AH$37,MATCH(COLUMN()-4,$AJ$18:$AJ$37,0)),'VISA MATRIX'!$B$3:$FS$3,0)),""),IF(IFERROR(INDEX('VISA RULES'!$E$2:$E$400,SUMPRODUCT(MATCH(1,($B96='VISA RULES'!$B$2:$B$400)*(INDEX($AH$18:$AH$37,MATCH(COLUMN()-4,$AJ$18:$AJ$37,0))='VISA RULES'!$C$2:$C$400),0))),"")<>"",IFERROR(INDEX('VISA RULES'!$E$2:$E$400,SUMPRODUCT(MATCH(1,($B96='VISA RULES'!$B$2:$B$400)*(INDEX($AH$18:$AH$37,MATCH(COLUMN()-4,$AJ$18:$AJ$37,0))='VISA RULES'!$C$2:$C$400),0))),""),"NOT ON FILE - VERIFY")))} | I96: {=IF(OR($A96="",I$87=""),"",IF(IFERROR(INDEX('VISA MATRIX'!$B$4:$FS$145,MATCH($B96,'VISA MATRIX'!$A$4:$A$145,0),MATCH(INDEX($AH$18:$AH$37,MATCH(COLUMN()-4,$AJ$18:$AJ$37,0)),'VISA MATRIX'!$B$3:$FS$3,0)),"")<>"",IFERROR(INDEX('VISA MATRIX'!$B$4:$FS$145,MATCH($B96,'VISA MATRIX'!$A$4:$A$145,0),MATCH(INDEX($AH$18:$AH$37,MATCH(COLUMN()-4,$AJ$18:$AJ$37,0)),'VISA MATRIX'!$B$3:$FS$3,0)),""),IF(IFERROR(INDEX('VISA RULES'!$E$2:$E$400,SUMPRODUCT(MATCH(1,($B96='VISA RULES'!$B$2:$B$400)*(INDEX($AH$18:$AH$37,MATCH(COLUMN()-4,$AJ$18:$AJ$37,0))='VISA RULES'!$C$2:$C$400),0))),"")<>"",IFERROR(INDEX('VISA RULES'!$E$2:$E$400,SUMPRODUCT(MATCH(1,($B96='VISA RULES'!$B$2:$B$400)*(INDEX($AH$18:$AH$37,MATCH(COLUMN()-4,$AJ$18:$AJ$37,0))='VISA RULES'!$C$2:$C$400),0))),""),"NOT ON FILE - VERIFY")))} | J96: {=IF(OR($A96="",J$87=""),"",IF(IFERROR(INDEX('VISA MATRIX'!$B$4:$FS$145,MATCH($B96,'VISA MATRIX'!$A$4:$A$145,0),MATCH(INDEX($AH$18:$AH$37,MATCH(COLUMN()-4,$AJ$18:$AJ$37,0)),'VISA MATRIX'!$B$3:$FS$3,0)),"")<>"",IFERROR(INDEX('VISA MATRIX'!$B$4:$FS$145,MATCH($B96,'VISA MATRIX'!$A$4:$A$145,0),MATCH(INDEX($AH$18:$AH$37,MATCH(COLUMN()-4,$AJ$18:$AJ$37,0)),'VISA MATRIX'!$B$3:$FS$3,0)),""),IF(IFERROR(INDEX('VISA RULES'!$E$2:$E$400,SUMPRODUCT(MATCH(1,($B96='VISA RULES'!$B$2:$B$400)*(INDEX($AH$18:$AH$37,MATCH(COLUMN()-4,$AJ$18:$AJ$37,0))='VISA RULES'!$C$2:$C$400),0))),"")<>"",IFERROR(INDEX('VISA RULES'!$E$2:$E$400,SUMPRODUCT(MATCH(1,($B96='VISA RULES'!$B$2:$B$400)*(INDEX($AH$18:$AH$37,MATCH(COLUMN()-4,$AJ$18:$AJ$37,0))='VISA RULES'!$C$2:$C$400),0))),""),"NOT ON FILE - VERIFY")))} | K96: DOCUMENT STATUS | L96: DOCS FOLDER
A97: VISA REQUIRED ON THIS TRIP? | E97: =IF(E$87="","",IF(COUNTIF(E$88:E$96,"REQUIRED")>0,"YES",IF(COUNTIF(E$88:E$96,"NOT ON FILE - VERIFY")>0,"VERIFY",IF(COUNTIF(E$88:E$96,"VISA ON ARRIVAL")+COUNTIF(E$88:E$96,"eVISA")>0,"ON ARRIVAL / eVISA","NO")))) -> VERIFY | F97: =IF(F$87="","",IF(COUNTIF(F$88:F$96,"REQUIRED")>0,"YES",IF(COUNTIF(F$88:F$96,"NOT ON FILE - VERIFY")>0,"VERIFY",IF(COUNTIF(F$88:F$96,"VISA ON ARRIVAL")+COUNTIF(F$88:F$96,"eVISA")>0,"ON ARRIVAL / eVISA","NO")))) -> VERIFY | G97: =IF(G$87="","",IF(COUNTIF(G$88:G$96,"REQUIRED")>0,"YES",IF(COUNTIF(G$88:G$96,"NOT ON FILE - VERIFY")>0,"VERIFY",IF(COUNTIF(G$88:G$96,"VISA ON ARRIVAL")+COUNTIF(G$88:G$96,"eVISA")>0,"ON ARRIVAL / eVISA","NO")))) -> VERIFY | H97: =IF(H$87="","",IF(COUNTIF(H$88:H$96,"REQUIRED")>0,"YES",IF(COUNTIF(H$88:H$96,"NOT ON FILE - VERIFY")>0,"VERIFY",IF(COUNTIF(H$88:H$96,"VISA ON ARRIVAL")+COUNTIF(H$88:H$96,"eVISA")>0,"ON ARRIVAL / eVISA","NO")))) | I97: =IF(I$87="","",IF(COUNTIF(I$88:I$96,"REQUIRED")>0,"YES",IF(COUNTIF(I$88:I$96,"NOT ON FILE - VERIFY")>0,"VERIFY",IF(COUNTIF(I$88:I$96,"VISA ON ARRIVAL")+COUNTIF(I$88:I$96,"eVISA")>0,"ON ARRIVAL / eVISA","NO")))) | J97: =IF(J$87="","",IF(COUNTIF(J$88:J$96,"REQUIRED")>0,"YES",IF(COUNTIF(J$88:J$96,"NOT ON FILE - VERIFY")>0,"VERIFY",IF(COUNTIF(J$88:J$96,"VISA ON ARRIVAL")+COUNTIF(J$88:J$96,"eVISA")>0,"ON ARRIVAL / eVISA","NO"))))
A98: Visa status is read from the VISA MATRIX sheet (destination state x nationality), falling back to the VISA sheet for pair-specific rules with lead time, maximum stay and airport overrides. NOT ON FILE means neither source has an answer yet. Type over a cell to override for this trip only.
A100: 6 · CREW & PAX BY LEG (a person counts on a leg when their LEGS field on the PAX & CREW sheet is ALL or names that leg)
A101: LEG | B101: DEP | C101: ARR | D101: ETD (UTC) | E101: CREW | F101: PAX | G101: SOULS ON BOARD | H101: MAX PAX | I101: SEAT CHECK | J101: BILL TO
A102: {=IF(INDEX($B$18:$B$25,ROW()-101)="","",INDEX($A$18:$A$25,ROW()-101))} -> L1 | B102: {=IF($A102="","",INDEX($B$18:$B$25,ROW()-101))} -> FALA | C102: {=IF($A102="","",INDEX($G$18:$G$25,ROW()-101))} -> FTTJ | D102: {=IF($A102="","",INDEX($E$18:$E$25,ROW()-101)+INDEX($F$18:$F$25,ROW()-101))} -> 46248.375 | E102: {=IF($A102="","",SUMPRODUCT(('PAX & CREW'!$B$3:$B$62=$B$5)*('PAX & CREW'!$C$3:$C$62="CREW")*(((UPPER('PAX & CREW'!$E$3:$E$62)="ALL")+ISNUMBER(SEARCH($A102,'PAX & CREW'!$E$3:$E$62)))>0)))} -> 2 | F102: {=IF($A102="","",SUMPRODUCT(('PAX & CREW'!$B$3:$B$62=$B$5)*('PAX & CREW'!$C$3:$C$62="PAX")*(((UPPER('PAX & CREW'!$E$3:$E$62)="ALL")+ISNUMBER(SEARCH($A102,'PAX & CREW'!$E$3:$E$62)))>0)))} -> 2 | G102: =IF($A102="","",$E102+$F102) -> 4 | H102: =IF($A102="","",IFERROR(INDEX(Aircraft!$I:$I,MATCH($B$7,Aircraft!$B:$B,0)),"NOT IN FLEET")) -> 19 | I102: =IF($A102="","",IF($H102="NOT IN FLEET","CANNOT CHECK",IF($F102>$H102,"OVER CAPACITY","OK"))) -> OK | J102: {=IF($A102="","",INDEX($N$18:$N$25,ROW()-101))} -> CLI-001
A103: {=IF(INDEX($B$18:$B$25,ROW()-101)="","",INDEX($A$18:$A$25,ROW()-101))} -> L2 | B103: {=IF($A103="","",INDEX($B$18:$B$25,ROW()-101))} -> FTTJ | C103: {=IF($A103="","",INDEX($G$18:$G$25,ROW()-101))} -> HECA | D103: {=IF($A103="","",INDEX($E$18:$E$25,ROW()-101)+INDEX($F$18:$F$25,ROW()-101))} -> 46250.25 | E103: {=IF($A103="","",SUMPRODUCT(('PAX & CREW'!$B$3:$B$62=$B$5)*('PAX & CREW'!$C$3:$C$62="CREW")*(((UPPER('PAX & CREW'!$E$3:$E$62)="ALL")+ISNUMBER(SEARCH($A103,'PAX & CREW'!$E$3:$E$62)))>0)))} -> 2 | F103: {=IF($A103="","",SUMPRODUCT(('PAX & CREW'!$B$3:$B$62=$B$5)*('PAX & CREW'!$C$3:$C$62="PAX")*(((UPPER('PAX & CREW'!$E$3:$E$62)="ALL")+ISNUMBER(SEARCH($A103,'PAX & CREW'!$E$3:$E$62)))>0)))} -> 1 | G103: =IF($A103="","",$E103+$F103) -> 3 | H103: =IF($A103="","",IFERROR(INDEX(Aircraft!$I:$I,MATCH($B$7,Aircraft!$B:$B,0)),"NOT IN FLEET")) -> 19 | I103: =IF($A103="","",IF($H103="NOT IN FLEET","CANNOT CHECK",IF($F103>$H103,"OVER CAPACITY","OK"))) -> OK | J103: {=IF($A103="","",INDEX($N$18:$N$25,ROW()-101))} -> CLI-001
A104: {=IF(INDEX($B$18:$B$25,ROW()-101)="","",INDEX($A$18:$A$25,ROW()-101))} -> L3 | B104: {=IF($A104="","",INDEX($B$18:$B$25,ROW()-101))} -> HECA | C104: {=IF($A104="","",INDEX($G$18:$G$25,ROW()-101))} -> GMAD | D104: {=IF($A104="","",INDEX($E$18:$E$25,ROW()-101)+INDEX($F$18:$F$25,ROW()-101))} -> 46251.167 | E104: {=IF($A104="","",SUMPRODUCT(('PAX & CREW'!$B$3:$B$62=$B$5)*('PAX & CREW'!$C$3:$C$62="CREW")*(((UPPER('PAX & CREW'!$E$3:$E$62)="ALL")+ISNUMBER(SEARCH($A104,'PAX & CREW'!$E$3:$E$62)))>0)))} -> 2 | F104: {=IF($A104="","",SUMPRODUCT(('PAX & CREW'!$B$3:$B$62=$B$5)*('PAX & CREW'!$C$3:$C$62="PAX")*(((UPPER('PAX & CREW'!$E$3:$E$62)="ALL")+ISNUMBER(SEARCH($A104,'PAX & CREW'!$E$3:$E$62)))>0)))} -> 0 | G104: =IF($A104="","",$E104+$F104) -> 2 | H104: =IF($A104="","",IFERROR(INDEX(Aircraft!$I:$I,MATCH($B$7,Aircraft!$B:$B,0)),"NOT IN FLEET")) -> 19 | I104: =IF($A104="","",IF($H104="NOT IN FLEET","CANNOT CHECK",IF($F104>$H104,"OVER CAPACITY","OK"))) -> OK | J104: {=IF($A104="","",INDEX($N$18:$N$25,ROW()-101))} -> CLI-001
A105: {=IF(INDEX($B$18:$B$25,ROW()-101)="","",INDEX($A$18:$A$25,ROW()-101))} -> L4 | B105: {=IF($A105="","",INDEX($B$18:$B$25,ROW()-101))} -> GMAD | C105: {=IF($A105="","",INDEX($G$18:$G$25,ROW()-101))} -> FAOR | D105: {=IF($A105="","",INDEX($E$18:$E$25,ROW()-101)+INDEX($F$18:$F$25,ROW()-101))} -> 46253.042 | E105: {=IF($A105="","",SUMPRODUCT(('PAX & CREW'!$B$3:$B$62=$B$5)*('PAX & CREW'!$C$3:$C$62="CREW")*(((UPPER('PAX & CREW'!$E$3:$E$62)="ALL")+ISNUMBER(SEARCH($A105,'PAX & CREW'!$E$3:$E$62)))>0)))} -> 2 | F105: {=IF($A105="","",SUMPRODUCT(('PAX & CREW'!$B$3:$B$62=$B$5)*('PAX & CREW'!$C$3:$C$62="PAX")*(((UPPER('PAX & CREW'!$E$3:$E$62)="ALL")+ISNUMBER(SEARCH($A105,'PAX & CREW'!$E$3:$E$62)))>0)))} -> 0 | G105: =IF($A105="","",$E105+$F105) -> 2 | H105: =IF($A105="","",IFERROR(INDEX(Aircraft!$I:$I,MATCH($B$7,Aircraft!$B:$B,0)),"NOT IN FLEET")) -> 19 | I105: =IF($A105="","",IF($H105="NOT IN FLEET","CANNOT CHECK",IF($F105>$H105,"OVER CAPACITY","OK"))) -> OK | J105: {=IF($A105="","",INDEX($N$18:$N$25,ROW()-101))} -> CLI-002
A106: {=IF(INDEX($B$18:$B$25,ROW()-101)="","",INDEX($A$18:$A$25,ROW()-101))} | B106: {=IF($A106="","",INDEX($B$18:$B$25,ROW()-101))} | C106: {=IF($A106="","",INDEX($G$18:$G$25,ROW()-101))} | D106: {=IF($A106="","",INDEX($E$18:$E$25,ROW()-101)+INDEX($F$18:$F$25,ROW()-101))} | E106: {=IF($A106="","",SUMPRODUCT(('PAX & CREW'!$B$3:$B$62=$B$5)*('PAX & CREW'!$C$3:$C$62="CREW")*(((UPPER('PAX & CREW'!$E$3:$E$62)="ALL")+ISNUMBER(SEARCH($A106,'PAX & CREW'!$E$3:$E$62)))>0)))} | F106: {=IF($A106="","",SUMPRODUCT(('PAX & CREW'!$B$3:$B$62=$B$5)*('PAX & CREW'!$C$3:$C$62="PAX")*(((UPPER('PAX & CREW'!$E$3:$E$62)="ALL")+ISNUMBER(SEARCH($A106,'PAX & CREW'!$E$3:$E$62)))>0)))} | G106: =IF($A106="","",$E106+$F106) | H106: =IF($A106="","",IFERROR(INDEX(Aircraft!$I:$I,MATCH($B$7,Aircraft!$B:$B,0)),"NOT IN FLEET")) | I106: =IF($A106="","",IF($H106="NOT IN FLEET","CANNOT CHECK",IF($F106>$H106,"OVER CAPACITY","OK"))) | J106: {=IF($A106="","",INDEX($N$18:$N$25,ROW()-101))}
A107: {=IF(INDEX($B$18:$B$25,ROW()-101)="","",INDEX($A$18:$A$25,ROW()-101))} | B107: {=IF($A107="","",INDEX($B$18:$B$25,ROW()-101))} | C107: {=IF($A107="","",INDEX($G$18:$G$25,ROW()-101))} | D107: {=IF($A107="","",INDEX($E$18:$E$25,ROW()-101)+INDEX($F$18:$F$25,ROW()-101))} | E107: {=IF($A107="","",SUMPRODUCT(('PAX & CREW'!$B$3:$B$62=$B$5)*('PAX & CREW'!$C$3:$C$62="CREW")*(((UPPER('PAX & CREW'!$E$3:$E$62)="ALL")+ISNUMBER(SEARCH($A107,'PAX & CREW'!$E$3:$E$62)))>0)))} | F107: {=IF($A107="","",SUMPRODUCT(('PAX & CREW'!$B$3:$B$62=$B$5)*('PAX & CREW'!$C$3:$C$62="PAX")*(((UPPER('PAX & CREW'!$E$3:$E$62)="ALL")+ISNUMBER(SEARCH($A107,'PAX & CREW'!$E$3:$E$62)))>0)))} | G107: =IF($A107="","",$E107+$F107) | H107: =IF($A107="","",IFERROR(INDEX(Aircraft!$I:$I,MATCH($B$7,Aircraft!$B:$B,0)),"NOT IN FLEET")) | I107: =IF($A107="","",IF($H107="NOT IN FLEET","CANNOT CHECK",IF($F107>$H107,"OVER CAPACITY","OK"))) | J107: {=IF($A107="","",INDEX($N$18:$N$25,ROW()-101))}
A108: {=IF(INDEX($B$18:$B$25,ROW()-101)="","",INDEX($A$18:$A$25,ROW()-101))} | B108: {=IF($A108="","",INDEX($B$18:$B$25,ROW()-101))} | C108: {=IF($A108="","",INDEX($G$18:$G$25,ROW()-101))} | D108: {=IF($A108="","",INDEX($E$18:$E$25,ROW()-101)+INDEX($F$18:$F$25,ROW()-101))} | E108: {=IF($A108="","",SUMPRODUCT(('PAX & CREW'!$B$3:$B$62=$B$5)*('PAX & CREW'!$C$3:$C$62="CREW")*(((UPPER('PAX & CREW'!$E$3:$E$62)="ALL")+ISNUMBER(SEARCH($A108,'PAX & CREW'!$E$3:$E$62)))>0)))} | F108: {=IF($A108="","",SUMPRODUCT(('PAX & CREW'!$B$3:$B$62=$B$5)*('PAX & CREW'!$C$3:$C$62="PAX")*(((UPPER('PAX & CREW'!$E$3:$E$62)="ALL")+ISNUMBER(SEARCH($A108,'PAX & CREW'!$E$3:$E$62)))>0)))} | G108: =IF($A108="","",$E108+$F108) | H108: =IF($A108="","",IFERROR(INDEX(Aircraft!$I:$I,MATCH($B$7,Aircraft!$B:$B,0)),"NOT IN FLEET")) | I108: =IF($A108="","",IF($H108="NOT IN FLEET","CANNOT CHECK",IF($F108>$H108,"OVER CAPACITY","OK"))) | J108: {=IF($A108="","",INDEX($N$18:$N$25,ROW()-101))}
A109: {=IF(INDEX($B$18:$B$25,ROW()-101)="","",INDEX($A$18:$A$25,ROW()-101))} | B109: {=IF($A109="","",INDEX($B$18:$B$25,ROW()-101))} | C109: {=IF($A109="","",INDEX($G$18:$G$25,ROW()-101))} | D109: {=IF($A109="","",INDEX($E$18:$E$25,ROW()-101)+INDEX($F$18:$F$25,ROW()-101))} | E109: {=IF($A109="","",SUMPRODUCT(('PAX & CREW'!$B$3:$B$62=$B$5)*('PAX & CREW'!$C$3:$C$62="CREW")*(((UPPER('PAX & CREW'!$E$3:$E$62)="ALL")+ISNUMBER(SEARCH($A109,'PAX & CREW'!$E$3:$E$62)))>0)))} | F109: {=IF($A109="","",SUMPRODUCT(('PAX & CREW'!$B$3:$B$62=$B$5)*('PAX & CREW'!$C$3:$C$62="PAX")*(((UPPER('PAX & CREW'!$E$3:$E$62)="ALL")+ISNUMBER(SEARCH($A109,'PAX & CREW'!$E$3:$E$62)))>0)))} | G109: =IF($A109="","",$E109+$F109) | H109: =IF($A109="","",IFERROR(INDEX(Aircraft!$I:$I,MATCH($B$7,Aircraft!$B:$B,0)),"NOT IN FLEET")) | I109: =IF($A109="","",IF($H109="NOT IN FLEET","CANNOT CHECK",IF($F109>$H109,"OVER CAPACITY","OK"))) | J109: {=IF($A109="","",INDEX($N$18:$N$25,ROW()-101))}
A111: 7 · CREW & PAX SUMMARY (trip totals · biodata, credentials and document folders live on the PAX & CREW sheet)
A112: CREW ON BOARD (TRIP) | B112: =COUNTIFS('PAX & CREW'!$B$3:$B$62,$B$5,'PAX & CREW'!$C$3:$C$62,"CREW") -> 2
...

Sheet admin
A1: Workstation UTC offset (hrs) | B1: 0
A2: Document root path | B2: C:\Backups\InsiderTechSol\Aviation\Jetelio_v3\.LAYOUT\resources
A3: Reference lists
A4: Airport Type | B4: PPR Required | C4: Location Type | D4: Airport of Entry | E4: Fuel Types | F4: Vendor Category
A5: Civil | B5: Yes | C5: Airport | D5: Yes | E5: JET A-1 | F5: Handler
A6: Military | B6: No | C6: Airstrip | D6: No | E6: AVGAS | F6: Permit
A7: Private | B7: Prior Notice | C7: Helipad | D7: Seasonal | E7: JET A-1 + AVGAS | F7: Supervisor
A8: Joint | C8: Bulk Origin | E8: None | F8: Fuel
A9: Other | C9: Bulk Destination | F9: Catering
C10: Shipping Port | F10: Security
C11: Aircraft Carrier | F11: Transport
C12: Other | F12: Other
A14: OPERATIONAL DEFAULTS — single source of truth for every fallback
A15: Default permit lead time (hrs) — FALLBACK ONLY, not a verified figure | B15: 72
A16: Default ground service notice (hrs) | B16: 24
A17: Range reserve / safety margin (fraction of max range) | B17: 0.15
A18: Passport validity buffer beyond trip end (days) | B18: 180
A19: Document expiry alert thresholds (days before expiry) | B19: 180, 90, 30, 7
A20: Visa rule staleness limit (days since verified) | B20: 365
A21: Unverified reference data may be used for planning? | B21: NO

Sheet airports
A1: IDENTIFIERS | E1: LOCATION & CONTACT | N1: GEO & TIME | W1: OPERATIONS | AE1: INFRASTRUCTURE | AJ1: LIVE DATA | AM1: BULLETINS | AO1: DOCUMENTS | AS1: RELATED RECORDS | AU1: OTHER
A2: Airport ICAO | B2: Airport IATA | C2: FAA ID | D2: EIP ICAO | E2: Airport Name | F2: Location Type | G2: Airport Type | H2: Country | I2: City Name | J2: Location / Region | K2: Airport Address 1 | L2: Airport Address 2 | M2: Website | N2: Coordinates (DMS) | O2: Latitude (DD) | P2: Longitude (DD) | Q2: Elevation (m) | R2: Elevation (ft) | S2: Magnetic Variation | T2: Time Zone | U2: UTC Offset (hrs) | V2: Local Time (now) | W2: Airport Hours | X2: Operating Hours | Y2: Airport of Entry | Z2: PPR Required | AA2: CIQ Procedure | AB2: Arrival Slot | AC2: Departure Slot | AD2: Approaches | AE2: Runway(s) | AF2: PCN No. | AG2: Fuel Types Available | AH2: Security Rating | AI2: Alternates | AJ2: NOTAM | AK2: Airport OFP | AL2: Daily Weather | AM2: Country Bulletin | AN2: City Bulletin | AO2: Airport Charts (folder) | AP2: Runway Diagram | AQ2: Airport Images | AR2: City Map | AS2: VISA Info | AT2: Vendors | AU2: Strategic Role | AV2: Last Updated | AW2: ops_data_source | AX2: ops_data_verified_on | AY2: tech_stop_readiness
A3: OOTH | B3: TTH | E3: Thumrait Air Base | F3: Airport | G3: Military | H3: Oman | I3: Thumrait | J3: Dhofar, Oman | N3: =IF(OR($O3="",$P3=""),"",TEXT(INT(ROUND(ABS($O3)*3600,0)/3600),"00")&"°"&TEXT(INT(MOD(ROUND(ABS($O3)*3600,0),3600)/60),"00")&"′"&TEXT(MOD(ROUND(ABS($O3)*3600,0),60),"00")&"″"&IF($O3>=0,"N","S")&" "&TEXT(INT(ROUND(ABS($P3)*3600,0)/3600),"000")&"°"&TEXT(INT(MOD(ROUND(ABS($P3)*3600,0),3600)/60),"00")&"′"&TEXT(MOD(ROUND(ABS($P3)*3600,0),60),"00")&"″"&IF($P3>=0,"E","W")) -> 17°39′57″N 054°01′30″E | O3: 17.665833 | P3: 54.025 | Q3: =IF($R3="","",ROUND($R3*0.3048,0)) -> 465 | R3: 1526 | S3: 01W | T3: Asia/Muscat | U3: 4 | V3: =IF($U3="","",MOD(NOW()-admin!$B$1/24+$U3/24,1)) -> 0.77849306 | W3: H24 | X3: Open 24 hours (H24) | Y3: No | Z3: PPR | AD3: ILS, VOR/DME | AE3: One hard-surface runway 17/35 – 4,000 x 45 m | AG3: JET A-1 | AO3: =IF($A3="","",admin!$B$2&"\Charts\"&$A3) -> C:\Backups\InsiderTechSol\Aviation\Jetelio_v3\.LAYOUT\resources\Charts\OOTH | AP3: =IF($A3="","",admin!$B$2&"\RunwayDiagrams\"&$A3&".pdf") -> C:\Backups\InsiderTechSol\Aviation\Jetelio_v3\.LAYOUT\resources\RunwayDiagrams\OOTH.pdf | AQ3: =IF($A3="","",admin!$B$2&"\Images\"&$A3) -> C:\Backups\InsiderTechSol\Aviation\Jetelio_v3\.LAYOUT\resources\Images\OOTH | AR3: =IF($A3="","",admin!$B$2&"\CityMaps\"&$A3&".png") -> C:\Backups\InsiderTechSol\Aviation\Jetelio_v3\.LAYOUT\resources\CityMaps\OOTH.png | AS3: =IF($A3="","","VISA sheet") -> VISA sheet | AT3: =IF($A3="","","Vendors sheet") -> Vendors sheet | AU3: Key base for the Royal Air Force of Oman. Frequently hosts joint international and multinational military exercises. Provides strategic regional access and operations support. | AV3: =IF($A3="","",TODAY()) -> 46243 | AY3: =IF($A3="","",IF(OR(TRIM($Y3)="",TRIM($AG3)="",TRIM($X3)=""),"INCOMPLETE - NOT SELECTABLE AS TECH STOP",IF(OR($AW3="",$AX3=""),"UNVERIFIED - ADVISORY ONLY","VERIFIED"))) -> UNVERIFIED - ADVISORY ONLY
A4: OMAA | B4: AUH | E4: Zayed International Airport | F4: Airport | H4: United Arab Emirates | I4: Abu Dhabi | N4: =IF(OR($O4="",$P4=""),"",TEXT(INT(ROUND(ABS($O4)*3600,0)/3600),"00")&"°"&TEXT(INT(MOD(ROUND(ABS($O4)*3600,0),3600)/60),"00")&"′"&TEXT(MOD(ROUND(ABS($O4)*3600,0),60),"00")&"″"&IF($O4>=0,"N","S")&" "&TEXT(INT(ROUND(ABS($P4)*3600,0)/3600),"000")&"°"&TEXT(INT(MOD(ROUND(ABS($P4)*3600,0),3600)/60),"00")&"′"&TEXT(MOD(ROUND(ABS($P4)*3600,0),60),"00")&"″"&IF($P4>=0,"E","W")) -> 24°26′27″N 054°38′57″E | O4: 24.44097 | P4: 54.64924 | Q4: =IF($R4="","",ROUND($R4*0.3048,0)) -> 27 | R4: 88 | T4: Asia/Dubai | U4: 4 | V4: =IF($U4="","",MOD(NOW()-admin!$B$1/24+$U4/24,1)) -> 0.77849306 | AE4: 13L/31R 4,100x60m ASP; 13R/31L 4,106x60m ASP | AO4: =IF($A4="","",admin!$B$2&"\Charts\"&$A4) -> C:\Backups\InsiderTechSol\Aviation\Jetelio_v3\.LAYOUT\resources\Charts\OMAA | AP4: =IF($A4="","",admin!$B$2&"\RunwayDiagrams\"&$A4&".pdf") -> C:\Backups\InsiderTechSol\Aviation\Jetelio_v3\.LAYOUT\resources\RunwayDiagrams\OMAA.pdf | AQ4: =IF($A4="","",admin!$B$2&"\Images\"&$A4) -> C:\Backups\InsiderTechSol\Aviation\Jetelio_v3\.LAYOUT\resources\Images\OMAA | AR4: =IF($A4="","",admin!$B$2&"\CityMaps\"&$A4&".png") -> C:\Backups\InsiderTechSol\Aviation\Jetelio_v3\.LAYOUT\resources\CityMaps\OMAA.png | AS4: =IF($A4="","","VISA sheet") -> VISA sheet | AT4: =IF($A4="","","Vendors sheet") -> Vendors sheet | AV4: =IF($A4="","",TODAY()) -> 46243 | AY4: =IF($A4="","",IF(OR(TRIM($Y4)="",TRIM($AG4)="",TRIM($X4)=""),"INCOMPLETE - NOT SELECTABLE AS TECH STOP",IF(OR($AW4="",$AX4=""),"UNVERIFIED - ADVISORY ONLY","VERIFIED"))) -> INCOMPLETE - NOT SELECTABLE AS TECH STOP
A5: OMAD | B5: AZI | E5: Al Bateen Executive Airport | F5: Airport | H5: United Arab Emirates | I5: Abu Dhabi | N5: =IF(OR($O5="",$P5=""),"",TEXT(INT(ROUND(ABS($O5)*3600,0)/3600),"00")&"°"&TEXT(INT(MOD(ROUND(ABS($O5)*3600,0),3600)/60),"00")&"′"&TEXT(MOD(ROUND(ABS($O5)*3600,0),60),"00")&"″"&IF($O5>=0,"N","S")&" "&TEXT(INT(ROUND(ABS($P5)*3600,0)/3600),"000")&"°"&TEXT(INT(MOD(ROUND(ABS($P5)*3600,0),3600)/60),"00")&"′"&TEXT(MOD(ROUND(ABS($P5)*3600,0),60),"00")&"″"&IF($P5>=0,"E","W")) -> 24°25′37″N 054°27′36″E | O5: 24.42706 | P5: 54.45987 | Q5: =IF($R5="","",ROUND($R5*0.3048,0)) -> 5 | R5: 16 | T5: Asia/Dubai | U5: 4 | V5: =IF($U5="","",MOD(NOW()-admin!$B$1/24+$U5/24,1)) -> 0.77849306 | AE5: 13/31 3,200x46m ASP | AO5: =IF($A5="","",admin!$B$2&"\Charts\"&$A5) -> C:\Backups\InsiderTechSol\Aviation\Jetelio_v3\.LAYOUT\resources\Charts\OMAD | AP5: =IF($A5="","",admin!$B$2&"\RunwayDiagrams\"&$A5&".pdf") -> C:\Backups\InsiderTechSol\Aviation\Jetelio_v3\.LAYOUT\resources\RunwayDiagrams\OMAD.pdf | AQ5: =IF($A5="","",admin!$B$2&"\Images\"&$A5) -> C:\Backups\InsiderTechSol\Aviation\Jetelio_v3\.LAYOUT\resources\Images\OMAD | AR5: =IF($A5="","",admin!$B$2&"\CityMaps\"&$A5&".png") -> C:\Backups\InsiderTechSol\Aviation\Jetelio_v3\.LAYOUT\resources\CityMaps\OMAD.png | AS5: =IF($A5="","","VISA sheet") -> VISA sheet | AT5: =IF($A5="","","Vendors sheet") -> Vendors sheet | AV5: =IF($A5="","",TODAY()) -> 46243 | AY5: =IF($A5="","",IF(OR(TRIM($Y5)="",TRIM($AG5)="",TRIM($X5)=""),"INCOMPLETE - NOT SELECTABLE AS TECH STOP",IF(OR($AW5="",$AX5=""),"UNVERIFIED - ADVISORY ONLY","VERIFIED"))) -> INCOMPLETE - NOT SELECTABLE AS TECH STOP
A6: OAHR | B6: HEA | E6: Herat - Khwaja Abdullah Ansari International | F6: Airport | H6: Afghanistan | I6: Guzara | N6: =IF(OR($O6="",$P6=""),"",TEXT(INT(ROUND(ABS($O6)*3600,0)/3600),"00")&"°"&TEXT(INT(MOD(ROUND(ABS($O6)*3600,0),3600)/60),"00")&"′"&TEXT(MOD(ROUND(ABS($O6)*3600,0),60),"00")&"″"&IF($O6>=0,"N","S")&" "&TEXT(INT(ROUND(ABS($P6)*3600,0)/3600),"000")&"°"&TEXT(INT(MOD(ROUND(ABS($P6)*3600,0),3600)/60),"00")&"′"&TEXT(MOD(ROUND(ABS($P6)*3600,0),60),"00")&"″"&IF($P6>=0,"E","W")) -> 34°12′36″N 062°13′42″E | O6: 34.21 | P6: 62.2283 | Q6: =IF($R6="","",ROUND($R6*0.3048,0)) -> 977 | R6: 3206 | T6: Asia/Kabul | U6: 4.5 | V6: =IF($U6="","",MOD(NOW()-admin!$B$1/24+$U6/24,1)) -> 0.79932639 | AE6: 18/36 3,014x46m ASP | AO6: =IF($A6="","",admin!$B$2&"\Charts\"&$A6) -> C:\Backups\InsiderTechSol\Aviation\Jetelio_v3\.LAYOUT\resources\Charts\OAHR | AP6: =IF($A6="","",admin!$B$2&"\RunwayDiagrams\"&$A6&".pdf") -> C:\Backups\InsiderTechSol\Aviation\Jetelio_v3\.LAYOUT\resources\RunwayDiagrams\OAHR.pdf | AQ6: =IF($A6="","",admin!$B$2&"\Images\"&$A6) -> C:\Backups\InsiderTechSol\Aviation\Jetelio_v3\.LAYOUT\resources\Images\OAHR | AR6: =IF($A6="","",admin!$B$2&"\CityMaps\"&$A6&".png") -> C:\Backups\InsiderTechSol\Aviation\Jetelio_v3\.LAYOUT\resources\CityMaps\OAHR.png | AS6: =IF($A6="","","VISA sheet") -> VISA sheet | AT6: =IF($A6="","","Vendors sheet") -> Vendors sheet | AV6: =IF($A6="","",TODAY()) -> 46243 | AY6: =IF($A6="","",IF(OR(TRIM($Y6)="",TRIM($AG6)="",TRIM($X6)=""),"INCOMPLETE - NOT SELECTABLE AS TECH STOP",IF(OR($AW6="",$AX6=""),"UNVERIFIED - ADVISORY ONLY","VERIFIED"))) -> INCOMPLETE - NOT SELECTABLE AS TECH STOP
A7: OAKB | B7: KBL | E7: Kabul International Airport | F7: Airport | H7: Afghanistan | I7: Kabul | N7: =IF(OR($O7="",$P7=""),"",TEXT(INT(ROUND(ABS($O7)*3600,0)/3600),"00")&"°"&TEXT(INT(MOD(ROUND(ABS($O7)*3600,0),3600)/60),"00")&"′"&TEXT(MOD(ROUND(ABS($O7)*3600,0),60),"00")&"″"&IF($O7>=0,"N","S")&" "&TEXT(INT(ROUND(ABS($P7)*3600,0)/3600),"000")&"°"&TEXT(INT(MOD(ROUND(ABS($P7)*3600,0),3600)/60),"00")&"′"&TEXT(MOD(ROUND(ABS($P7)*3600,0),60),"00")&"″"&IF($P7>=0,"E","W")) -> 34°33′57″N 069°12′44″E | O7: 34.5659 | P7: 69.2123 | Q7: =IF($R7="","",ROUND($R7*0.3048,0)) -> 1791 | R7: 5877 | T7: Asia/Kabul | U7: 4.5 | V7: =IF($U7="","",MOD(NOW()-admin!$B$1/24+$U7/24,1)) -> 0.79932639 | AE7: 11/29 3,500x50m ASP | AO7: =IF($A7="","",admin!$B$2&"\Charts\"&$A7) -> C:\Backups\InsiderTechSol\Aviation\Jetelio_v3\.LAYOUT\resources\Charts\OAKB | AP7: =IF($A7="","",admin!$B$2&"\RunwayDiagrams\"&$A7&".pdf") -> C:\Backups\InsiderTechSol\Aviation\Jetelio_v3\.LAYOUT\resources\RunwayDiagrams\OAKB.pdf | AQ7: =IF($A7="","",admin!$B$2&"\Images\"&$A7) -> C:\Backups\InsiderTechSol\Aviation\Jetelio_v3\.LAYOUT\resources\Images\OAKB | AR7: =IF($A7="","",admin!$B$2&"\CityMaps\"&$A7&".png") -> C:\Backups\InsiderTechSol\Aviation\Jetelio_v3\.LAYOUT\resources\CityMaps\OAKB.png | AS7: =IF($A7="","","VISA sheet") -> VISA sheet | AT7: =IF($A7="","","Vendors sheet") -> Vendors sheet | AV7: =IF($A7="","",TODAY()) -> 46243 | AY7: =IF($A7="","",IF(OR(TRIM($Y7)="",TRIM($AG7)="",TRIM($X7)=""),"INCOMPLETE - NOT SELECTABLE AS TECH STOP",IF(OR($AW7="",$AX7=""),"UNVERIFIED - ADVISORY ONLY","VERIFIED"))) -> INCOMPLETE - NOT SELECTABLE AS TECH STOP
A8: TAPA | B8: ANU | E8: V. C. Bird International Airport | F8: Airport | H8: Antigua and Barbuda | I8: Osbourn | N8: =IF(OR($O8="",$P8=""),"",TEXT(INT(ROUND(ABS($O8)*3600,0)/3600),"00")&"°"&TEXT(INT(MOD(ROUND(ABS($O8)*3600,0),3600)/60),"00")&"′"&TEXT(MOD(ROUND(ABS($O8)*3600,0),60),"00")&"″"&IF($O8>=0,"N","S")&" "&TEXT(INT(ROUND(ABS($P8)*3600,0)/3600),"000")&"°"&TEXT(INT(MOD(ROUND(ABS($P8)*3600,0),3600)/60),"00")&"′"&TEXT(MOD(ROUND(ABS($P8)*3600,0),60),"00")&"″"&IF($P8>=0,"E","W")) -> 17°08′12″N 061°47′34″W | O8: 17.1367 | P8: -61.7927 | Q8: =IF($R8="","",ROUND($R8*0.3048,0)) -> 19 | R8: 62 | T8: America/Antigua | U8: -4 | V8: =IF($U8="","",MOD(NOW()-admin!$B$1/24+$U8/24,1)) -> 0.44515972 | AE8: 07/25 2,744x45m ASP | AO8: =IF($A8="","",admin!$B$2&"\Charts\"&$A8) -> C:\Backups\InsiderTechSol\Aviation\Jetelio_v3\.LAYOUT\resources\Charts\TAPA | AP8: =IF($A8="","",admin!$B$2&"\RunwayDiagrams\"&$A8&".pdf") -> C:\Backups\InsiderTechSol\Aviation\Jetelio_v3\.LAYOUT\resources\RunwayDiagrams\TAPA.pdf | AQ8: =IF($A8="","",admin!$B$2&"\Images\"&$A8) -> C:\Backups\InsiderTechSol\Aviation\Jetelio_v3\.LAYOUT\resources\Images\TAPA | AR8: =IF($A8="","",admin!$B$2&"\CityMaps\"&$A8&".png") -> C:\Backups\InsiderTechSol\Aviation\Jetelio_v3\.LAYOUT\resources\CityMaps\TAPA.png | AS8: =IF($A8="","","VISA sheet") -> VISA sheet | AT8: =IF($A8="","","Vendors sheet") -> Vendors sheet | AV8: =IF($A8="","",TODAY()) -> 46243 | AY8: =IF($A8="","",IF(OR(TRIM($Y8)="",TRIM($AG8)="",TRIM($X8)=""),"INCOMPLETE - NOT SELECTABLE AS TECH STOP",IF(OR($AW8="",$AX8=""),"UNVERIFIED - ADVISORY ONLY","VERIFIED"))) -> INCOMPLETE - NOT SELECTABLE AS TECH STOP
A9: LATI | B9: TIA | E9: Tirana International Airport Mother Teresa | F9: Airport | H9: Albania | I9: Rinas | N9: =IF(OR($O9="",$P9=""),"",TEXT(INT(ROUND(ABS($O9)*3600,0)/3600),"00")&"°"&TEXT(INT(MOD(ROUND(ABS($O9)*3600,0),3600)/60),"00")&"′"&TEXT(MOD(ROUND(ABS($O9)*3600,0),60),"00")&"″"&IF($O9>=0,"N","S")&" "&TEXT(INT(ROUND(ABS($P9)*3600,0)/3600),"000")&"°"&TEXT(INT(MOD(ROUND(ABS($P9)*3600,0),3600)/60),"00")&"′"&TEXT(MOD(ROUND(ABS($P9)*3600,0),60),"00")&"″"&IF($P9>=0,"E","W")) -> 41°24′53″N 019°43′14″E | O9: 41.4147 | P9: 19.7206 | Q9: =IF($R9="","",ROUND($R9*0.3048,0)) -> 38 | R9: 126 | T9: Europe/Tirane | U9: 1 | V9: =IF($U9="","",MOD(NOW()-admin!$B$1/24+$U9/24,1)) -> 0.65349306 | AE9: 17/35 3,000x45m ASP | AO9: =IF($A9="","",admin!$B$2&"\Charts\"&$A9) -> C:\Backups\InsiderTechSol\Aviation\Jetelio_v3\.LAYOUT\resources\Charts\LATI | AP9: =IF($A9="","",admin!$B$2&"\RunwayDiagrams\"&$A9&".pdf") -> C:\Backups\InsiderTechSol\Aviation\Jetelio_v3\.LAYOUT\resources\RunwayDiagrams\LATI.pdf | AQ9: =IF($A9="","",admin!$B$2&"\Images\"&$A9) -> C:\Backups\InsiderTechSol\Aviation\Jetelio_v3\.LAYOUT\resources\Images\LATI | AR9: =IF($A9="","",admin!$B$2&"\CityMaps\"&$A9&".png") -> C:\Backups\InsiderTechSol\Aviation\Jetelio_v3\.LAYOUT\resources\CityMaps\LATI.png | AS9: =IF($A9="","","VISA sheet") -> VISA sheet | AT9: =IF($A9="","","Vendors sheet") -> Vendors sheet | AV9: =IF($A9="","",TODAY()) -> 46243 | AY9: =IF($A9="","",IF(OR(TRIM($Y9)="",TRIM($AG9)="",TRIM($X9)=""),"INCOMPLETE - NOT SELECTABLE AS TECH STOP",IF(OR($AW9="",$AX9=""),"UNVERIFIED - ADVISORY ONLY","VERIFIED"))) -> INCOMPLETE - NOT SELECTABLE AS TECH STOP
A10: UDSG | B10: LWN | E10: Shirak International Airport | F10: Airport | H10: Armenia | I10: Gyumri | N10: =IF(OR($O10="",$P10=""),"",TEXT(INT(ROUND(ABS($O10)*3600,0)/3600),"00")&"°"&TEXT(INT(MOD(ROUND(ABS($O10)*3600,0),3600)/60),"00")&"′"&TEXT(MOD(ROUND(ABS($O10)*3600,0),60),"00")&"″"&IF($O10>=0,"N","S")&" "&TEXT(INT(ROUND(ABS($P10)*3600,0)/3600),"000")&"°"&TEXT(INT(MOD(ROUND(ABS($P10)*3600,0),3600)/60),"00")&"′"&TEXT(MOD(ROUND(ABS($P10)*3600,0),60),"00")&"″"&IF($P10>=0,"E","W")) -> 40°45′01″N 043°51′33″E | O10: 40.7504 | P10: 43.8593 | Q10: =IF($R10="","",ROUND($R10*0.3048,0)) -> 1524 | R10: 5000 | T10: Asia/Yerevan | U10: 4 | V10: =IF($U10="","",MOD(NOW()-admin!$B$1/24+$U10/24,1)) -> 0.77849306 | AE10: 02/20 3,220x45m ASP | AO10: =IF($A10="","",admin!$B$2&"\Charts\"&$A10) -> C:\Backups\InsiderTechSol\Aviation\Jetelio_v3\.LAYOUT\resources\Charts\UDSG | AP10: =IF($A10="","",admin!$B$2&"\RunwayDiagrams\"&$A10&".pdf") -> C:\Backups\InsiderTechSol\Aviation\Jetelio_v3\.LAYOUT\resources\RunwayDiagrams\UDSG.pdf | AQ10: =IF($A10="","",admin!$B$2&"\Images\"&$A10) -> C:\Backups\InsiderTechSol\Aviation\Jetelio_v3\.LAYOUT\resources\Images\UDSG | AR10: =IF($A10="","",admin!$B$2&"\CityMaps\"&$A10&".png") -> C:\Backups\InsiderTechSol\Aviation\Jetelio_v3\.LAYOUT\resources\CityMaps\UDSG.png | AS10: =IF($A10="","","VISA sheet") -> VISA sheet | AT10: =IF($A10="","","Vendors sheet") -> Vendors sheet | AV10: =IF($A10="","",TODAY()) -> 46243 | AY10: =IF($A10="","",IF(OR(TRIM($Y10)="",TRIM($AG10)="",TRIM($X10)=""),"INCOMPLETE - NOT SELECTABLE AS TECH STOP",IF(OR($AW10="",$AX10=""),"UNVERIFIED - ADVISORY ONLY","VERIFIED"))) -> INCOMPLETE - NOT SELECTABLE AS TECH STOP
A11: UDYZ | B11: EVN | E11: Zvartnots International Airport | F11: Airport | H11: Armenia | I11: Yerevan | N11: =IF(OR($O11="",$P11=""),"",TEXT(INT(ROUND(ABS($O11)*3600,0)/3600),"00")&"°"&TEXT(INT(MOD(ROUND(ABS($O11)*3600,0),3600)/60),"00")&"′"&TEXT(MOD(ROUND(ABS($O11)*3600,0),60),"00")&"″"&IF($O11>=0,"N","S")&" "&TEXT(INT(ROUND(ABS($P11)*3600,0)/3600),"000")&"°"&TEXT(INT(MOD(ROUND(ABS($P11)*3600,0),3600)/60),"00")&"′"&TEXT(MOD(ROUND(ABS($P11)*3600,0),60),"00")&"″"&IF($P11>=0,"E","W")) -> 40°08′56″N 044°23′52″E | O11: 40.14894 | P11: 44.39789 | Q11: =IF($R11="","",ROUND($R11*0.3048,0)) -> 865 | R11: 2838 | T11: Asia/Yerevan | U11: 4 | V11: =IF($U11="","",MOD(NOW()-admin!$B$1/24+$U11/24,1)) -> 0.77849306 | AE11: 08/26 3,850x56m ASP | AO11: =IF($A11="","",admin!$B$2&"\Charts\"&$A11) -> C:\Backups\InsiderTechSol\Aviation\Jetelio_v3\.LAYOUT\resources\Charts\UDYZ | AP11: =IF($A11="","",admin!$B$2&"\RunwayDiagrams\"&$A11&".pdf") -> C:\Backups\InsiderTechSol\Aviation\Jetelio_v3\.LAYOUT\resources\RunwayDiagrams\UDYZ.pdf | AQ11: =IF($A11="","",admin!$B$2&"\Images\"&$A11) -> C:\Backups\InsiderTechSol\Aviation\Jetelio_v3\.LAYOUT\resources\Images\UDYZ | AR11: =IF($A11="","",admin!$B$2&"\CityMaps\"&$A11&".png") -> C:\Backups\InsiderTechSol\Aviation\Jetelio_v3\.LAYOUT\resources\CityMaps\UDYZ.png | AS11: =IF($A11="","","VISA sheet") -> VISA sheet | AT11: =IF($A11="","","Vendors sheet") -> Vendors sheet | AV11: =IF($A11="","",TODAY()) -> 46243 | AY11: =IF($A11="","",IF(OR(TRIM($Y11)="",TRIM($AG11)="",TRIM($X11)=""),"INCOMPLETE - NOT SELECTABLE AS TECH STOP",IF(OR($AW11="",$AX11=""),"UNVERIFIED - ADVISORY ONLY","VERIFIED"))) -> INCOMPLETE - NOT SELECTABLE AS TECH STOP
A12: FNBJ | B12: NBJ | E12: Dr. Antonio Agostinho Neto International Airport | F12: Airport | H12: Angola | I12: Luanda | N12: =IF(OR($O12="",$P12=""),"",TEXT(INT(ROUND(ABS($O12)*3600,0)/3600),"00")&"°"&TEXT(INT(MOD(ROUND(ABS($O12)*3600,0),3600)/60),"00")&"′"&TEXT(MOD(ROUND(ABS($O12)*3600,0),60),"00")&"″"&IF($O12>=0,"N","S")&" "&TEXT(INT(ROUND(ABS($P12)*3600,0)/3600),"000")&"°"&TEXT(INT(MOD(ROUND(ABS($P12)*3600,0),3600)/60),"00")&"′"&TEXT(MOD(ROUND(ABS($P12)*3600,0),60),"00")&"″"&IF($P12>=0,"E","W")) -> 09°03′03″S 013°29′57″E | O12: -9.05073 | P12: 13.49908 | Q12: =IF($R12="","",ROUND($R12*0.3048,0)) -> 168 | R12: 550 | V12: =IF($U12="","",MOD(NOW()-admin!$B$1/24+$U12/24,1)) | AE12: 06L/24R 3,800x60m ASP; 06R/24L 4,000x60m PEM | AO12: =IF($A12="","",admin!$B$2&"\Charts\"&$A12) -> C:\Backups\InsiderTechSol\Aviation\Jetelio_v3\.LAYOUT\resources\Charts\FNBJ | AP12: =IF($A12="","",admin!$B$2&"\RunwayDiagrams\"&$A12&".pdf") -> C:\Backups\InsiderTechSol\Aviation\Jetelio_v3\.LAYOUT\resources\RunwayDiagrams\FNBJ.pdf | AQ12: =IF($A12="","",admin!$B$2&"\Images\"&$A12) -> C:\Backups\InsiderTechSol\Aviation\Jetelio_v3\.LAYOUT\resources\Images\FNBJ | AR12: =IF($A12="","",admin!$B$2&"\CityMaps\"&$A12&".png") -> C:\Backups\InsiderTechSol\Aviation\Jetelio_v3\.LAYOUT\resources\CityMaps\FNBJ.png | AS12: =IF($A12="","","VISA sheet") -> VISA sheet | AT12: =IF($A12="","","Vendors sheet") -> Vendors sheet | AV12: =IF($A12="","",TODAY()) -> 46243 | AY12: =IF($A12="","",IF(OR(TRIM($Y12)="",TRIM($AG12)="",TRIM($X12)=""),"INCOMPLETE - NOT SELECTABLE AS TECH STOP",IF(OR($AW12="",$AX12=""),"UNVERIFIED - ADVISORY ONLY","VERIFIED"))) -> INCOMPLETE - NOT SELECTABLE AS TECH STOP
A13: FNLU | B13: LAD | E13: Quatro de Fevereiro International Airport | F13: Airport | H13: Angola | I13: Luanda | N13: =IF(OR($O13="",$P13=""),"",TEXT(INT(ROUND(ABS($O13)*3600,0)/3600),"00")&"°"&TEXT(INT(MOD(ROUND(ABS($O13)*3600,0),3600)/60),"00")&"′"&TEXT(MOD(ROUND(ABS($O13)*3600,0),60),"00")&"″"&IF($O13>=0,"N","S")&" "&TEXT(INT(ROUND(ABS($P13)*3600,0)/3600),"000")&"°"&TEXT(INT(MOD(ROUND(ABS($P13)*3600,0),3600)/60),"00")&"′"&TEXT(MOD(ROUND(ABS($P13)*3600,0),60),"00")&"″"&IF($P13>=0,"E","W")) -> 08°51′30″S 013°13′52″E | O13: -8.85837 | P13: 13.2312 | Q13: =IF($R13="","",ROUND($R13*0.3048,0)) -> 74 | R13: 243 | T13: Africa/Luanda | U13: 1 | V13: =IF($U13="","",MOD(NOW()-admin!$B$1/24+$U13/24,1)) -> 0.65349306 | AE13: 05/23 3,716x45m ASP; 07/25 2,600x60m ASP | AO13: =IF($A13="","",admin!$B$2&"\Charts\"&$A13) -> C:\Backups\InsiderTechSol\Aviation\Jetelio_v3\.LAYOUT\resources\Charts\FNLU | AP13: =IF($A13="","",admin!$B$2&"\RunwayDiagrams\"&$A13&".pdf") -> C:\Backups\InsiderTechSol\Aviation\Jetelio_v3\.LAYOUT\resources\RunwayDiagrams\FNLU.pdf | AQ13: =IF($A13="","",admin!$B$2&"\Images\"&$A13) -> C:\Backups\InsiderTechSol\Aviation\Jetelio_v3\.LAYOUT\resources\Images\FNLU | AR13: =IF($A13="","",admin!$B$2&"\CityMaps\"&$A13&".png") -> C:\Backups\InsiderTechSol\Aviation\Jetelio_v3\.LAYOUT\resources\CityMaps\FNLU.png | AS13: =IF($A13="","","VISA sheet") -> VISA sheet | AT13: =IF($A13="","","Vendors sheet") -> Vendors sheet | AV13: =IF($A13="","",TODAY()) -> 46243 | AY13: =IF($A13="","",IF(OR(TRIM($Y13)="",TRIM($AG13)="",TRIM($X13)=""),"INCOMPLETE - NOT SELECTABLE AS TECH STOP",IF(OR($AW13="",$AX13=""),"UNVERIFIED - ADVISORY ONLY","VERIFIED"))) -> INCOMPLETE - NOT SELECTABLE AS TECH STOP
A14: SAAR | B14: ROS | E14: Rosario Islas Malvinas International Airport | F14: Airport | H14: Argentina | I14: Rosario | N14: =IF(OR($O14="",$P14=""),"",TEXT(INT(ROUND(ABS($O14)*3600,0)/3600),"00")&"°"&TEXT(INT(MOD(ROUND(ABS($O14)*3600,0),3600)/60),"00")&"′"&TEXT(MOD(ROUND(ABS($O14)*3600,0),60),"00")&"″"&IF($O14>=0,"N","S")&" "&TEXT(INT(ROUND(ABS($P14)*3600,0)/3600),"000")&"°"&TEXT(INT(MOD(ROUND(ABS($P14)*3600,0),3600)/60),"00")&"′"&TEXT(MOD(ROUND(ABS($P14)*3600,0),60),"00")&"″"&IF($P14>=0,"E","W")) -> 32°54′13″S 060°47′06″W | O14: -32.9036 | P14: -60.785 | Q14: =IF($R14="","",ROUND($R14*0.3048,0)) -> 26 | R14: 85 | T14: America/Cordoba | U14: -3 | V14: =IF($U14="","",MOD(NOW()-admin!$B$1/24+$U14/24,1)) -> 0.48682639 | AE14: 02/20 3,000x45m CON | AO14: =IF($A14="","",admin!$B$2&"\Charts\"&$A14) -> C:\Backups\InsiderTechSol\Aviation\Jetelio_v3\.LAYOUT\resources\Charts\SAAR | AP14: =IF($A14="","",admin!$B$2&"\RunwayDiagrams\"&$A14&".pdf") -> C:\Backups\InsiderTechSol\Aviation\Jetelio_v3\.LAYOUT\resources\RunwayDiagrams\SAAR.pdf | AQ14: =IF($A14="","",admin!$B$2&"\Images\"&$A14) -> C:\Backups\InsiderTechSol\Aviation\Jetelio_v3\.LAYOUT\resources\Images\SAAR | AR14: =IF($A14="","",admin!$B$2&"\CityMaps\"&$A14&".png") -> C:\Backups\InsiderTechSol\Aviation\Jetelio_v3\.LAYOUT\resources\CityMaps\SAAR.png | AS14: =IF($A14="","","VISA sheet") -> VISA sheet | AT14: =IF($A14="","","Vendors sheet") -> Vendors sheet | AV14: =IF($A14="","",TODAY()) -> 46243 | AY14: =IF($A14="","",IF(OR(TRIM($Y14)="",TRIM($AG14)="",TRIM($X14)=""),"INCOMPLETE - NOT SELECTABLE AS TECH STOP",IF(OR($AW14="",$AX14=""),"UNVERIFIED - ADVISORY ONLY","VERIFIED"))) -> INCOMPLETE - NOT SELECTABLE AS TECH STOP
A15: SABE | B15: AEP | E15: Aeroparque Jorge Newbery | F15: Airport | H15: Argentina | I15: Buenos Aires | N15: =IF(OR($O15="",$P15=""),"",TEXT(INT(ROUND(ABS($O15)*3600,0)/3600),"00")&"°"&TEXT(INT(MOD(ROUND(ABS($O15)*3600,0),3600)/60),"00")&"′"&TEXT(MOD(ROUND(ABS($O15)*3600,0),60),"00")&"″"&IF($O15>=0,"N","S")&" "&TEXT(INT(ROUND(ABS($P15)*3600,0)/3600),"000")&"°"&TEXT(INT(MOD(ROUND(ABS($P15)*3600,0),3600)/60),"00")&"′"&TEXT(MOD(ROUND(ABS($P15)*3600,0),60),"00")&"″"&IF($P15>=0,"E","W")) -> 34°33′34″S 058°24′56″W | O15: -34.55942 | P15: -58.41554 | Q15: =IF($R15="","",ROUND($R15*0.3048,0)) -> 5 | R15: 18 | T15: America/Buenos_Aires | U15: -3 | V15: =IF($U15="","",MOD(NOW()-admin!$B$1/24+$U15/24,1)) -> 0.48682639 | AE15: 13/31 2,350x45m PEM | AO15: =IF($A15="","",admin!$B$2&"\Charts\"&$A15) -> C:\Backups\InsiderTechSol\Aviation\Jetelio_v3\.LAYOUT\resources\Charts\SABE | AP15: =IF($A15="","",admin!$B$2&"\RunwayDiagrams\"&$A15&".pdf") -> C:\Backups\InsiderTechSol\Aviation\Jetelio_v3\.LAYOUT\resources\RunwayDiagrams\SABE.pdf | AQ15: =IF($A15="","",admin!$B$2&"\Images\"&$A15) -> C:\Backups\InsiderTechSol\Aviation\Jetelio_v3\.LAYOUT\resources\Images\SABE | AR15: =IF($A15="","",admin!$B$2&"\CityMaps\"&$A15&".png") -> C:\Backups\InsiderTechSol\Aviation\Jetelio_v3\.LAYOUT\resources\CityMaps\SABE.png | AS15: =IF($A15="","","VISA sheet") -> VISA sheet | AT15: =IF($A15="","","Vendors sheet") -> Vendors sheet | AV15: =IF($A15="","",TODAY()) -> 46243 | AY15: =IF($A15="","",IF(OR(TRIM($Y15)="",TRIM($AG15)="",TRIM($X15)=""),"INCOMPLETE - NOT SELECTABLE AS TECH STOP",IF(OR($AW15="",$AX15=""),"UNVERIFIED - ADVISORY ONLY","VERIFIED"))) -> INCOMPLETE - NOT SELECTABLE AS TECH STOP
A16: NSTU | B16: PPG | E16: Pago Pago International Airport | F16: Airport | H16: American Samoa | I16: Pago Pago | N16: =IF(OR($O16="",$P16=""),"",TEXT(INT(ROUND(ABS($O16)*3600,0)/3600),"00")&"°"&TEXT(INT(MOD(ROUND(ABS($O16)*3600,0),3600)/60),"00")&"′"&TEXT(MOD(ROUND(ABS($O16)*3600,0),60),"00")&"″"&IF($O16>=0,"N","S")&" "&TEXT(INT(ROUND(ABS($P16)*3600,0)/3600),"000")&"°"&TEXT(INT(MOD(ROUND(ABS($P16)*3600,0),3600)/60),"00")&"′"&TEXT(MOD(ROUND(ABS($P16)*3600,0),60),"00")&"″"&IF($P16>=0,"E","W")) -> 14°19′52″S 170°42′36″W | O16: -14.331 | P16: -170.71001 | Q16: =IF($R16="","",ROUND($R16*0.3048,0)) -> 10 | R16: 32 | T16: Pacific/Pago_Pago | U16: -11 | V16: =IF($U16="","",MOD(NOW()-admin!$B$1/24+$U16/24,1)) -> 0.15349306 | AE16: 05/23 3,048x46m ASP; 08/26 1,158x30m ASP | AO16: =IF($A16="","",admin!$B$2&"\Charts\"&$A16) -> C:\Backups\InsiderTechSol\Aviation\Jetelio_v3\.LAYOUT\resources\Charts\NSTU | AP16: =IF($A16="","",admin!$B$2&"\RunwayDiagrams\"&$A16&".pdf") -> C:\Backups\InsiderTechSol\Aviation\Jetelio_v3\.LAYOUT\resources\RunwayDiagrams\NSTU.pdf | AQ16: =IF($A16="","",admin!$B$2&"\Images\"&$A16) -> C:\Backups\InsiderTechSol\Aviation\Jetelio_v3\.LAYOUT\resources\Images\NSTU | AR16: =IF($A16="","",admin!$B$2&"\CityMaps\"&$A16&".png") -> C:\Backups\InsiderTechSol\Aviation\Jetelio_v3\.LAYOUT\resources\CityMaps\NSTU.png | AS16: =IF($A16="","","VISA sheet") -> VISA sheet | AT16: =IF($A16="","","Vendors sheet") -> Vendors sheet | AV16: =IF($A16="","",TODAY()) -> 46243 | AY16: =IF($A16="","",IF(OR(TRIM($Y16)="",TRIM($AG16)="",TRIM($X16)=""),"INCOMPLETE - NOT SELECTABLE AS TECH STOP",IF(OR($AW16="",$AX16=""),"UNVERIFIED - ADVISORY ONLY","VERIFIED"))) -> INCOMPLETE - NOT SELECTABLE AS TECH STOP
A17: LOWG | B17: GRZ | E17: Graz Airport | F17: Airport | H17: Austria | I17: Feldkirchen bei Graz | N17: =IF(OR($O17="",$P17=""),"",TEXT(INT(ROUND(ABS($O17)*3600,0)/3600),"00")&"°"&TEXT(INT(MOD(ROUND(ABS($O17)*3600,0),3600)/60),"00")&"′"&TEXT(MOD(ROUND(ABS($O17)*3600,0),60),"00")&"″"&IF($O17>=0,"N","S")&" "&TEXT(INT(ROUND(ABS($P17)*3600,0)/3600),"000")&"°"&TEXT(INT(MOD(ROUND(ABS($P17)*3600,0),3600)/60),"00")&"′"&TEXT(MOD(ROUND(ABS($P17)*3600,0),60),"00")&"″"&IF($P17>=0,"E","W")) -> 46°59′28″N 015°26′23″E | O17: 46.9911 | P17: 15.4396 | Q17: =IF($R17="","",ROUND($R17*0.3048,0)) -> 340 | R17: 1115 | T17: Europe/Vienna | U17: 1 | V17: =IF($U17="","",MOD(NOW()-admin!$B$1/24+$U17/24,1)) -> 0.65349306 | AE17: 16C/34C 3,000x45m ASP | AO17: =IF($A17="","",admin!$B$2&"\Charts\"&$A17) -> C:\Backups\InsiderTechSol\Aviation\Jetelio_v3\.LAYOUT\resources\Charts\LOWG | AP17: =IF($A17="","",admin!$B$2&"\RunwayDiagrams\"&$A17&".pdf") -> C:\Backups\InsiderTechSol\Aviation\Jetelio_v3\.LAYOUT\resources\RunwayDiagrams\LOWG.pdf | AQ17: =IF($A17="","",admin!$B$2&"\Images\"&$A17) -> C:\Backups\InsiderTechSol\Aviation\Jetelio_v3\.LAYOUT\resources\Images\LOWG | AR17: =IF($A17="","",admin!$B$2&"\CityMaps\"&$A17&".png") -> C:\Backups\InsiderTechSol\Aviation\Jetelio_v3\.LAYOUT\resources\CityMaps\LOWG.png | AS17: =IF($A17="","","VISA sheet") -> VISA sheet | AT17: =IF($A17="","","Vendors sheet") -> Vendors sheet | AV17: =IF($A17="","",TODAY()) -> 46243 | AY17: =IF($A17="","",IF(OR(TRIM($Y17)="",TRIM($AG17)="",TRIM($X17)=""),"INCOMPLETE - NOT SELECTABLE AS TECH STOP",IF(OR($AW17="",$AX17=""),"UNVERIFIED - ADVISORY ONLY","VERIFIED"))) -> INCOMPLETE - NOT SELECTABLE AS TECH STOP
A18: LOWI | B18: INN | E18: Innsbruck Airport | F18: Airport | H18: Austria | I18: Innsbruck | N18: =IF(OR($O18="",$P18=""),"",TEXT(INT(ROUND(ABS($O18)*3600,0)/3600),"00")&"°"&TEXT(INT(MOD(ROUND(ABS($O18)*3600,0),3600)/60),"00")&"′"&TEXT(MOD(ROUND(ABS($O18)*3600,0),60),"00")&"″"&IF($O18>=0,"N","S")&" "&TEXT(INT(ROUND(ABS($P18)*3600,0)/3600),"000")&"°"&TEXT(INT(MOD(ROUND(ABS($P18)*3600,0),3600)/60),"00")&"′"&TEXT(MOD(ROUND(ABS($P18)*3600,0),60),"00")&"″"&IF($P18>=0,"E","W")) -> 47°15′37″N 011°20′38″E | O18: 47.2602 | P18: 11.344 | Q18: =IF($R18="","",ROUND($R18*0.3048,0)) -> 581 | R18: 1907 | T18: Europe/Vienna | U18: 1 | V18: =IF($U18="","",MOD(NOW()-admin!$B$1/24+$U18/24,1)) -> 0.65349306 | AE18: 08/26 2,000x45m ASP | AO18: =IF($A18="","",admin!$B$2&"\Charts\"&$A18) -> C:\Backups\InsiderTechSol\Aviation\Jetelio_v3\.LAYOUT\resources\Charts\LOWI | AP18: =IF($A18="","",admin!$B$2&"\RunwayDiagrams\"&$A18&".pdf") -> C:\Backups\InsiderTechSol\Aviation\Jetelio_v3\.LAYOUT\resources\RunwayDiagrams\LOWI.pdf | AQ18: =IF($A18="","",admin!$B$2&"\Images\"&$A18) -> C:\Backups\InsiderTechSol\Aviation\Jetelio_v3\.LAYOUT\resources\Images\LOWI | AR18: =IF($A18="","",admin!$B$2&"\CityMaps\"&$A18&".png") -> C:\Backups\InsiderTechSol\Aviation\Jetelio_v3\.LAYOUT\resources\CityMaps\LOWI.png | AS18: =IF($A18="","","VISA sheet") -> VISA sheet | AT18: =IF($A18="","","Vendors sheet") -> Vendors sheet | AV18: =IF($A18="","",TODAY()) -> 46243 | AY18: =IF($A18="","",IF(OR(TRIM($Y18)="",TRIM($AG18)="",TRIM($X18)=""),"INCOMPLETE - NOT SELECTABLE AS TECH STOP",IF(OR($AW18="",$AX18=""),"UNVERIFIED - ADVISORY ONLY","VERIFIED"))) -> INCOMPLETE - NOT SELECTABLE AS TECH STOP
A19: YBBN | B19: BNE | E19: Brisbane International Airport | F19: Airport | H19: Australia | I19: Brisbane | N19: =IF(OR($O19="",$P19=""),"",TEXT(INT(ROUND(ABS($O19)*3600,0)/3600),"00")&"°"&TEXT(INT(MOD(ROUND(ABS($O19)*3600,0),3600)/60),"00")&"′"&TEXT(MOD(ROUND(ABS($O19)*3600,0),60),"00")&"″"&IF($O19>=0,"N","S")&" "&TEXT(INT(ROUND(ABS($P19)*3600,0)/3600),"000")&"°"&TEXT(INT(MOD(ROUND(ABS($P19)*3600,0),3600)/60),"00")&"′"&TEXT(MOD(ROUND(ABS($P19)*3600,0),60),"00")&"″"&IF($P19>=0,"E","W")) -> 27°23′03″S 153°07′01″E | O19: -27.3842 | P19: 153.117 | Q19: =IF($R19="","",ROUND($R19*0.3048,0)) -> 4 | R19: 13 | T19: Australia/Brisbane | U19: 10 | V19: =IF($U19="","",MOD(NOW()-admin!$B$1/24+$U19/24,1)) -> 0.028493056 | AE19: 01L/19R 3,300x60m ASP; 01R/19L 3,560x45m ASP | AO19: =IF($A19="","",admin!$B$2&"\Charts\"&$A19) -> C:\Backups\InsiderTechSol\Aviation\Jetelio_v3\.LAYOUT\resources\Charts\YBBN | AP19: =IF($A19="","",admin!$B$2&"\RunwayDiagrams\"&$A19&".pdf") -> C:\Backups\InsiderTechSol\Aviation\Jetelio_v3\.LAYOUT\resources\RunwayDiagrams\YBBN.pdf | AQ19: =IF($A19="","",admin!$B$2&"\Images\"&$A19) -> C:\Backups\InsiderTechSol\Aviation\Jetelio_v3\.LAYOUT\resources\Images\YBBN | AR19: =IF($A19="","",admin!$B$2&"\CityMaps\"&$A19&".png") -> C:\Backups\InsiderTechSol\Aviation\Jetelio_v3\.LAYOUT\resources\CityMaps\YBBN.png | AS19: =IF($A19="","","VISA sheet") -> VISA sheet | AT19: =IF($A19="","","Vendors sheet") -> Vendors sheet | AV19: =IF($A19="","",TODAY()) -> 46243 | AY19: =IF($A19="","",IF(OR(TRIM($Y19)="",TRIM($AG19)="",TRIM($X19)=""),"INCOMPLETE - NOT SELECTABLE AS TECH STOP",IF(OR($AW19="",$AX19=""),"UNVERIFIED - ADVISORY ONLY","VERIFIED"))) -> INCOMPLETE - NOT SELECTABLE AS TECH STOP
