Workbook

Sheet TRIP MANAGER
A1: TRIP MANAGER — OVERFLIGHT & LANDING PERMIT ENGINE
A2: Enter DEP ICAO, ARR ICAO, ETD and REGISTRATION for each leg. Overflown countries and permit lines below recalculate automatically.
A4: 1 · TRIP & AIRCRAFT
A5: TRIP REFERENCE | B5: JTL-2608-001 | C5: Register status → | D5: =IF($B$5="","",IFERROR(INDEX(mayfly!$C:$C,MATCH($B$5,mayfly!$A:$A,0))&" | owner: "&INDEX(mayfly!$D:$D,MATCH($B$5,mayfly!$A:$A,0))&" | legs in register: "&COUNTIF(mayfly!$A:$A,$B$5),"NOT IN THE MAYFLY REGISTER - add it there first")) | E5: BILL TO — DEFAULT (CLIENT ID) | F5: CLI-001
A6: OPERATOR | B6: JTL AVIATION, INC | C6: Operator on file for this tail → | E6: CLIENT / BILL-TO NAME | F6: =IF($F$5="","",IFERROR(INDEX(Clients!$D:$D,MATCH($F$5,Clients!$A:$A,0))&"","UNKNOWN CLIENT ID"))
A7: REGISTRATION | B7: N450GA | C7: =IF($B$7="","",IFERROR(IF(INDEX(Aircraft!$T:$T,MATCH($B$7,Aircraft!$B:$B,0))="","OPERATOR NAME NOT SET ON Operators SHEET",INDEX(Aircraft!$T:$T,MATCH($B$7,Aircraft!$B:$B,0))),"TAIL NOT IN FLEET — OPERATOR CANNOT BE VERIFIED")) | E7: BILLING ADDRESS | F7: =IF($F$5="","",IFERROR(INDEX(Clients!$E:$E,MATCH($F$5,Clients!$A:$A,0))&IF(INDEX(Clients!$F:$F,MATCH($F$5,Clients!$A:$A,0))="","",", "&INDEX(Clients!$F:$F,MATCH($F$5,Clients!$A:$A,0)))&", "&INDEX(Clients!$G:$G,MATCH($F$5,Clients!$A:$A,0))&", "&INDEX(Clients!$H:$H,MATCH($F$5,Clients!$A:$A,0)),"UNKNOWN CLIENT ID"))
A8: AIRCRAFT TYPE (ICAO) | B8: =IF($B$7="","",IFERROR(INDEX(Aircraft!$C:$C,MATCH($B$7,Aircraft!$B:$B,0)),"NOT IN FLEET")) | E8: BILLING EMAIL | F8: =IF($F$5="","",IFERROR(INDEX(Clients!$K:$K,MATCH($F$5,Clients!$A:$A,0))&"","UNKNOWN CLIENT ID"))
A9: MTOW (KG) | B9: =IF($B$7="","",IFERROR(INDEX(Aircraft!$H:$H,MATCH($B$7,Aircraft!$B:$B,0)),"NOT IN FLEET")) | E9: CURRENCY | F9: =IF($F$5="","",IFERROR(INDEX(Clients!$M:$M,MATCH($F$5,Clients!$A:$A,0))&"","UNKNOWN CLIENT ID"))
A10: BLOCK SPEED (KTS) | B10: 470 | C10: =IF($B$8="","",IFERROR("Published cruise for "&$B$8&" is "&TEXT(INDEX('AIRCRAFT PERFORMANCE'!$E:$E,MATCH($B$8,'AIRCRAFT PERFORMANCE'!$A:$A,0)),"#,##0")&" kts - indicative only","Type not in the performance table")) | E10: PAYMENT TERMS | F10: =IF($F$5="","",IFERROR(INDEX(Clients!$N:$N,MATCH($F$5,Clients!$A:$A,0))&"","UNKNOWN CLIENT ID"))
A11: TAXI / CLIMB ALLOWANCE (HRS) | B11: 0.4 | C11: Added to each leg's airborne time | E11: ACCOUNT OWNED BY OPERATOR | F11: =IF($F$5="","",IFERROR(INDEX(Clients!$B:$B,MATCH($F$5,Clients!$A:$A,0))&"","UNKNOWN CLIENT ID"))
A12: DEFAULT PERMIT LEAD TIME (HRS) | B12: 72 | C12: Used when a country has no lead time in the countries sheet | E12: ACCOUNT CHECK | F12: =IF($F$5="","",IFERROR(IF(INDEX(Clients!$B:$B,MATCH($F$5,Clients!$A:$A,0))=INDEX(Aircraft!$N:$N,MATCH($B$7,Aircraft!$B:$B,0)),"OK","BILL-TO BELONGS TO A DIFFERENT OPERATOR"),"CANNOT VERIFY - TAIL NOT IN FLEET"))
A13: TRIP DISTANCE (NM) | B13: =SUM($J$18:$J$25)
A14: TRIP EET (HRS) | B14: =ROUND(SUM($K$18:$K$25),2)
A16: 2 · LEGS (up to 8 · leg 2+ departure defaults to the previous leg's arrival, overwrite if needed)
A17: LEG | B17: DEP ICAO | C17: DEP AIRPORT | D17: DEP COUNTRY | E17: ETD DATE | F17: ETD (Z) | G17: ARR ICAO | H17: ARR AIRPORT | I17: ARR COUNTRY | J17: DIST (NM) | K17: EET (HRS) | L17: ETA DATE | M17: ETA (Z) | N17: BILL TO (LEG) | O17: DEP LAT | P17: DEP LON | Q17: ARR LAT | R17: ARR LON | S17: GC ANGLE (RAD) | T17: DEP ISO3 | U17: ARR ISO3 | V17: AVOID STATES / FIR (country name) | W17: INCLUDE STATES / FIR (country name) | X17: ROUTE CHECK | Y17: RANGE CHECK | AH17: NATIONALITY | AI17: FIRST? | AJ17: NAT RANK | AK17: GROUND ISO3 | AL17: GROUND AIRPORT | AM17: GROUND LEG | AN17: GROUND DATETIME | AO17: FIRST? | AP17: GH RANK
A18: L1 | B18: FALA | C18: =IF($B18="","",IFERROR(INDEX(airports!$E:$E,MATCH($B18,airports!$A:$A,0)),"ICAO NOT IN AIRPORTS")) | D18: =IF($B18="","",IFERROR(INDEX(airports!$H:$H,MATCH($B18,airports!$A:$A,0)),"")) | E18: 46248 | F18: 0.375 | G18: FTTJ | H18: =IF($G18="","",IFERROR(INDEX(airports!$E:$E,MATCH($G18,airports!$A:$A,0)),"ICAO NOT IN AIRPORTS")) | I18: =IF($G18="","",IFERROR(INDEX(airports!$H:$H,MATCH($G18,airports!$A:$A,0)),"")) | J18: =IF($S18="","",ROUND($S18*3440.065,0)) | K18: =IF(OR($J18="",$B$10=""),"",ROUND($J18/$B$10+$B$11,2)) | L18: =IF(OR($E18="",$K18=""),"",INT($E18+$F18+$K18/24)) | M18: =IF($L18="","",MOD($E18+$F18+$K18/24,1)) | N18: =IF($B18="","",$F$5) | O18: =IF($B18="","",IFERROR(INDEX(airports!$O:$O,MATCH($B18,airports!$A:$A,0)),"")) | P18: =IF($B18="","",IFERROR(INDEX(airports!$P:$P,MATCH($B18,airports!$A:$A,0)),"")) | Q18: =IF($G18="","",IFERROR(INDEX(airports!$O:$O,MATCH($G18,airports!$A:$A,0)),"")) | R18: =IF($G18="","",IFERROR(INDEX(airports!$P:$P,MATCH($G18,airports!$A:$A,0)),"")) | S18: =IF(OR($O18="",$Q18=""),"",ACOS(MIN(1,SIN(RADIANS($O18))*SIN(RADIANS($Q18))+COS(RADIANS($O18))*COS(RADIANS($Q18))*COS(RADIANS($R18-$P18))))) | T18: {=IF($O18="","",IFERROR(IF(INDEX(geo_grid!$B$2:$JU$231,INT(($O18+40)/0.5)+1,INT(($P18+30)/0.5)+1)="","",INDEX(geo_grid!$B$2:$JU$231,INT(($O18+40)/0.5)+1,INT(($P18+30)/0.5)+1)),"OUTSIDE GRID"))} | U18: {=IF($Q18="","",IFERROR(IF(INDEX(geo_grid!$B$2:$JU$231,INT(($Q18+40)/0.5)+1,INT(($R18+30)/0.5)+1)="","",INDEX(geo_grid!$B$2:$JU$231,INT(($Q18+40)/0.5)+1,INT(($R18+30)/0.5)+1)),"OUTSIDE GRID"))} | X18: {=IF($B18="","",IF(AND($V18="",$W18=""),"NO CONSTRAINT",TRIM(IF($V18="","",IF(SUMPRODUCT(--((ISNUMBER(SEARCH(","&permit_calc!$A$3:$A$144&",",","&SUBSTITUTE(UPPER($V18)," ","")&","))+ISNUMBER(SEARCH(","&SUBSTITUTE(UPPER(permit_calc!$B$3:$B$144)," ","")&",",","&SUBSTITUTE(UPPER($V18)," ","")&",")))>0),--(INDEX(permit_calc!$C$3:$J$144,0,ROW()-17)>0))>0,"AVOID CONFLICT - track crosses an excluded state. ",""))&IF($W18="","",IF(SUMPRODUCT(--((ISNUMBER(SEARCH(","&permit_calc!$A$3:$A$144&",",","&SUBSTITUTE(UPPER($W18)," ","")&","))+ISNUMBER(SEARCH(","&SUBSTITUTE(UPPER(permit_calc!$B$3:$B$144)," ","")&",",","&SUBSTITUTE(UPPER($W18)," ","")&",")))>0),--(INDEX(permit_calc!$C$3:$J$144,0,ROW()-17)>0))<LEN($W18)-LEN(SUBSTITUTE($W18,",",""))+1,"INCLUDE NOT ON TRACK - required state not overflown. ","")))))} | Y18: =IF($B18="","",IFERROR(IF($J18>INDEX('AIRCRAFT PERFORMANCE'!$I:$I,MATCH($B$8,'AIRCRAFT PERFORMANCE'!$A:$A,0)),"EXCEEDS PRACTICAL RANGE OF "&TEXT(INDEX('AIRCRAFT PERFORMANCE'!$I:$I,MATCH($B$8,'AIRCRAFT PERFORMANCE'!$A:$A,0)),"#,##0")&" NM - TECHNICAL STOP REQUIRED","WITHIN RANGE"),"TYPE NOT IN PERFORMANCE TABLE")) | AH18: =IFERROR(INDEX('PAX & CREW'!$L$3:$L$62,MATCH(ROW()-17,'PAX & CREW'!$AJ$3:$AJ$62,0)),"") | AI18: =IF($AH18="","",IF(COUNTIF($AH$18:$AH18,$AH18)=1,1,0)) | AJ18: =IF($AI18=1,SUM($AI$18:$AI18),"") | AK18: =IF($B$18="","",$T$18) | AL18: =IF($B$18="","",$B$18) | AM18: =IF($B$18="","","L1") | AN18: =IF($B$18="","",$E$18+$F$18) | AO18: =IF($AK18="","",IF(COUNTIF($AK$18:$AK18,$AK18)=1,1,0)) | AP18: =IF($AO18=1,SUM($AO$18:$AO18),"")
A19: L2 | B19: FTTJ | C19: =IF($B19="","",IFERROR(INDEX(airports!$E:$E,MATCH($B19,airports!$A:$A,0)),"ICAO NOT IN AIRPORTS")) | D19: =IF($B19="","",IFERROR(INDEX(airports!$H:$H,MATCH($B19,airports!$A:$A,0)),"")) | E19: 46250 | F19: 0.25 | G19: HECA | H19: =IF($G19="","",IFERROR(INDEX(airports!$E:$E,MATCH($G19,airports!$A:$A,0)),"ICAO NOT IN AIRPORTS")) | I19: =IF($G19="","",IFERROR(INDEX(airports!$H:$H,MATCH($G19,airports!$A:$A,0)),"")) | J19: =IF($S19="","",ROUND($S19*3440.065,0)) | K19: =IF(OR($J19="",$B$10=""),"",ROUND($J19/$B$10+$B$11,2)) | L19: =IF(OR($E19="",$K19=""),"",INT($E19+$F19+$K19/24)) | M19: =IF($L19="","",MOD($E19+$F19+$K19/24,1)) | N19: =IF($B19="","",$F$5) | O19: =IF($B19="","",IFERROR(INDEX(airports!$O:$O,MATCH($B19,airports!$A:$A,0)),"")) | P19: =IF($B19="","",IFERROR(INDEX(airports!$P:$P,MATCH($B19,airports!$A:$A,0)),"")) | Q19: =IF($G19="","",IFERROR(INDEX(airports!$O:$O,MATCH($G19,airports!$A:$A,0)),"")) | R19: =IF($G19="","",IFERROR(INDEX(airports!$P:$P,MATCH($G19,airports!$A:$A,0)),"")) | S19: =IF(OR($O19="",$Q19=""),"",ACOS(MIN(1,SIN(RADIANS($O19))*SIN(RADIANS($Q19))+COS(RADIANS($O19))*COS(RADIANS($Q19))*COS(RADIANS($R19-$P19))))) | T19: {=IF($O19="","",IFERROR(IF(INDEX(geo_grid!$B$2:$JU$231,INT(($O19+40)/0.5)+1,INT(($P19+30)/0.5)+1)="","",INDEX(geo_grid!$B$2:$JU$231,INT(($O19+40)/0.5)+1,INT(($P19+30)/0.5)+1)),"OUTSIDE GRID"))} | U19: {=IF($Q19="","",IFERROR(IF(INDEX(geo_grid!$B$2:$JU$231,INT(($Q19+40)/0.5)+1,INT(($R19+30)/0.5)+1)="","",INDEX(geo_grid!$B$2:$JU$231,INT(($Q19+40)/0.5)+1,INT(($R19+30)/0.5)+1)),"OUTSIDE GRID"))} | X19: {=IF($B19="","",IF(AND($V19="",$W19=""),"NO CONSTRAINT",TRIM(IF($V19="","",IF(SUMPRODUCT(--((ISNUMBER(SEARCH(","&permit_calc!$A$3:$A$144&",",","&SUBSTITUTE(UPPER($V19)," ","")&","))+ISNUMBER(SEARCH(","&SUBSTITUTE(UPPER(permit_calc!$B$3:$B$144)," ","")&",",","&SUBSTITUTE(UPPER($V19)," ","")&",")))>0),--(INDEX(permit_calc!$C$3:$J$144,0,ROW()-17)>0))>0,"AVOID CONFLICT - track crosses an excluded state. ",""))&IF($W19="","",IF(SUMPRODUCT(--((ISNUMBER(SEARCH(","&permit_calc!$A$3:$A$144&",",","&SUBSTITUTE(UPPER($W19)," ","")&","))+ISNUMBER(SEARCH(","&SUBSTITUTE(UPPER(permit_calc!$B$3:$B$144)," ","")&",",","&SUBSTITUTE(UPPER($W19)," ","")&",")))>0),--(INDEX(permit_calc!$C$3:$J$144,0,ROW()-17)>0))<LEN($W19)-LEN(SUBSTITUTE($W19,",",""))+1,"INCLUDE NOT ON TRACK - required state not overflown. ","")))))} | Y19: =IF($B19="","",IFERROR(IF($J19>INDEX('AIRCRAFT PERFORMANCE'!$I:$I,MATCH($B$8,'AIRCRAFT PERFORMANCE'!$A:$A,0)),"EXCEEDS PRACTICAL RANGE OF "&TEXT(INDEX('AIRCRAFT PERFORMANCE'!$I:$I,MATCH($B$8,'AIRCRAFT PERFORMANCE'!$A:$A,0)),"#,##0")&" NM - TECHNICAL STOP REQUIRED","WITHIN RANGE"),"TYPE NOT IN PERFORMANCE TABLE")) | AH19: =IFERROR(INDEX('PAX & CREW'!$L$3:$L$62,MATCH(ROW()-17,'PAX & CREW'!$AJ$3:$AJ$62,0)),"") | AI19: =IF($AH19="","",IF(COUNTIF($AH$18:$AH19,$AH19)=1,1,0)) | AJ19: =IF($AI19=1,SUM($AI$18:$AI19),"") | AK19: =IF($U18="","",$U18) | AL19: =IF($U18="","",$G18) | AM19: =IF($U18="","",$A18) | AN19: =IF($U18="","",$L18+$M18) | AO19: =IF($AK19="","",IF(COUNTIF($AK$18:$AK19,$AK19)=1,1,0)) | AP19: =IF($AO19=1,SUM($AO$18:$AO19),"")
A20: L3 | B20: HECA | C20: =IF($B20="","",IFERROR(INDEX(airports!$E:$E,MATCH($B20,airports!$A:$A,0)),"ICAO NOT IN AIRPORTS")) | D20: =IF($B20="","",IFERROR(INDEX(airports!$H:$H,MATCH($B20,airports!$A:$A,0)),"")) | E20: 46251 | F20: 0.16666667 | G20: GMAD | H20: =IF($G20="","",IFERROR(INDEX(airports!$E:$E,MATCH($G20,airports!$A:$A,0)),"ICAO NOT IN AIRPORTS")) | I20: =IF($G20="","",IFERROR(INDEX(airports!$H:$H,MATCH($G20,airports!$A:$A,0)),"")) | J20: =IF($S20="","",ROUND($S20*3440.065,0)) | K20: =IF(OR($J20="",$B$10=""),"",ROUND($J20/$B$10+$B$11,2)) | L20: =IF(OR($E20="",$K20=""),"",INT($E20+$F20+$K20/24)) | M20: =IF($L20="","",MOD($E20+$F20+$K20/24,1)) | N20: =IF($B20="","",$F$5) | O20: =IF($B20="","",IFERROR(INDEX(airports!$O:$O,MATCH($B20,airports!$A:$A,0)),"")) | P20: =IF($B20="","",IFERROR(INDEX(airports!$P:$P,MATCH($B20,airports!$A:$A,0)),"")) | Q20: =IF($G20="","",IFERROR(INDEX(airports!$O:$O,MATCH($G20,airports!$A:$A,0)),"")) | R20: =IF($G20="","",IFERROR(INDEX(airports!$P:$P,MATCH($G20,airports!$A:$A,0)),"")) | S20: =IF(OR($O20="",$Q20=""),"",ACOS(MIN(1,SIN(RADIANS($O20))*SIN(RADIANS($Q20))+COS(RADIANS($O20))*COS(RADIANS($Q20))*COS(RADIANS($R20-$P20))))) | T20: {=IF($O20="","",IFERROR(IF(INDEX(geo_grid!$B$2:$JU$231,INT(($O20+40)/0.5)+1,INT(($P20+30)/0.5)+1)="","",INDEX(geo_grid!$B$2:$JU$231,INT(($O20+40)/0.5)+1,INT(($P20+30)/0.5)+1)),"OUTSIDE GRID"))} | U20: {=IF($Q20="","",IFERROR(IF(INDEX(geo_grid!$B$2:$JU$231,INT(($Q20+40)/0.5)+1,INT(($R20+30)/0.5)+1)="","",INDEX(geo_grid!$B$2:$JU$231,INT(($Q20+40)/0.5)+1,INT(($R20+30)/0.5)+1)),"OUTSIDE GRID"))} | X20: {=IF($B20="","",IF(AND($V20="",$W20=""),"NO CONSTRAINT",TRIM(IF($V20="","",IF(SUMPRODUCT(--((ISNUMBER(SEARCH(","&permit_calc!$A$3:$A$144&",",","&SUBSTITUTE(UPPER($V20)," ","")&","))+ISNUMBER(SEARCH(","&SUBSTITUTE(UPPER(permit_calc!$B$3:$B$144)," ","")&",",","&SUBSTITUTE(UPPER($V20)," ","")&",")))>0),--(INDEX(permit_calc!$C$3:$J$144,0,ROW()-17)>0))>0,"AVOID CONFLICT - track crosses an excluded state. ",""))&IF($W20="","",IF(SUMPRODUCT(--((ISNUMBER(SEARCH(","&permit_calc!$A$3:$A$144&",",","&SUBSTITUTE(UPPER($W20)," ","")&","))+ISNUMBER(SEARCH(","&SUBSTITUTE(UPPER(permit_calc!$B$3:$B$144)," ","")&",",","&SUBSTITUTE(UPPER($W20)," ","")&",")))>0),--(INDEX(permit_calc!$C$3:$J$144,0,ROW()-17)>0))<LEN($W20)-LEN(SUBSTITUTE($W20,",",""))+1,"INCLUDE NOT ON TRACK - required state not overflown. ","")))))} | Y20: =IF($B20="","",IFERROR(IF($J20>INDEX('AIRCRAFT PERFORMANCE'!$I:$I,MATCH($B$8,'AIRCRAFT PERFORMANCE'!$A:$A,0)),"EXCEEDS PRACTICAL RANGE OF "&TEXT(INDEX('AIRCRAFT PERFORMANCE'!$I:$I,MATCH($B$8,'AIRCRAFT PERFORMANCE'!$A:$A,0)),"#,##0")&" NM - TECHNICAL STOP REQUIRED","WITHIN RANGE"),"TYPE NOT IN PERFORMANCE TABLE")) | AH20: =IFERROR(INDEX('PAX & CREW'!$L$3:$L$62,MATCH(ROW()-17,'PAX & CREW'!$AJ$3:$AJ$62,0)),"") | AI20: =IF($AH20="","",IF(COUNTIF($AH$18:$AH20,$AH20)=1,1,0)) | AJ20: =IF($AI20=1,SUM($AI$18:$AI20),"") | AK20: =IF($U19="","",$U19) | AL20: =IF($U19="","",$G19) | AM20: =IF($U19="","",$A19) | AN20: =IF($U19="","",$L19+$M19) | AO20: =IF($AK20="","",IF(COUNTIF($AK$18:$AK20,$AK20)=1,1,0)) | AP20: =IF($AO20=1,SUM($AO$18:$AO20),"")
A21: L4 | B21: GMAD | C21: =IF($B21="","",IFERROR(INDEX(airports!$E:$E,MATCH($B21,airports!$A:$A,0)),"ICAO NOT IN AIRPORTS")) | D21: =IF($B21="","",IFERROR(INDEX(airports!$H:$H,MATCH($B21,airports!$A:$A,0)),"")) | E21: 46253 | F21: 0.041666667 | G21: FAOR | H21: =IF($G21="","",IFERROR(INDEX(airports!$E:$E,MATCH($G21,airports!$A:$A,0)),"ICAO NOT IN AIRPORTS")) | I21: =IF($G21="","",IFERROR(INDEX(airports!$H:$H,MATCH($G21,airports!$A:$A,0)),"")) | J21: =IF($S21="","",ROUND($S21*3440.065,0)) | K21: =IF(OR($J21="",$B$10=""),"",ROUND($J21/$B$10+$B$11,2)) | L21: =IF(OR($E21="",$K21=""),"",INT($E21+$F21+$K21/24)) | M21: =IF($L21="","",MOD($E21+$F21+$K21/24,1)) | N21: CLI-002 | O21: =IF($B21="","",IFERROR(INDEX(airports!$O:$O,MATCH($B21,airports!$A:$A,0)),"")) | P21: =IF($B21="","",IFERROR(INDEX(airports!$P:$P,MATCH($B21,airports!$A:$A,0)),"")) | Q21: =IF($G21="","",IFERROR(INDEX(airports!$O:$O,MATCH($G21,airports!$A:$A,0)),"")) | R21: =IF($G21="","",IFERROR(INDEX(airports!$P:$P,MATCH($G21,airports!$A:$A,0)),"")) | S21: =IF(OR($O21="",$Q21=""),"",ACOS(MIN(1,SIN(RADIANS($O21))*SIN(RADIANS($Q21))+COS(RADIANS($O21))*COS(RADIANS($Q21))*COS(RADIANS($R21-$P21))))) | T21: {=IF($O21="","",IFERROR(IF(INDEX(geo_grid!$B$2:$JU$231,INT(($O21+40)/0.5)+1,INT(($P21+30)/0.5)+1)="","",INDEX(geo_grid!$B$2:$JU$231,INT(($O21+40)/0.5)+1,INT(($P21+30)/0.5)+1)),"OUTSIDE GRID"))} | U21: {=IF($Q21="","",IFERROR(IF(INDEX(geo_grid!$B$2:$JU$231,INT(($Q21+40)/0.5)+1,INT(($R21+30)/0.5)+1)="","",INDEX(geo_grid!$B$2:$JU$231,INT(($Q21+40)/0.5)+1,INT(($R21+30)/0.5)+1)),"OUTSIDE GRID"))} | X21: {=IF($B21="","",IF(AND($V21="",$W21=""),"NO CONSTRAINT",TRIM(IF($V21="","",IF(SUMPRODUCT(--((ISNUMBER(SEARCH(","&permit_calc!$A$3:$A$144&",",","&SUBSTITUTE(UPPER($V21)," ","")&","))+ISNUMBER(SEARCH(","&SUBSTITUTE(UPPER(permit_calc!$B$3:$B$144)," ","")&",",","&SUBSTITUTE(UPPER($V21)," ","")&",")))>0),--(INDEX(permit_calc!$C$3:$J$144,0,ROW()-17)>0))>0,"AVOID CONFLICT - track crosses an excluded state. ",""))&IF($W21="","",IF(SUMPRODUCT(--((ISNUMBER(SEARCH(","&permit_calc!$A$3:$A$144&",",","&SUBSTITUTE(UPPER($W21)," ","")&","))+ISNUMBER(SEARCH(","&SUBSTITUTE(UPPER(permit_calc!$B$3:$B$144)," ","")&",",","&SUBSTITUTE(UPPER($W21)," ","")&",")))>0),--(INDEX(permit_calc!$C$3:$J$144,0,ROW()-17)>0))<LEN($W21)-LEN(SUBSTITUTE($W21,",",""))+1,"INCLUDE NOT ON TRACK - required state not overflown. ","")))))} | Y21: =IF($B21="","",IFERROR(IF($J21>INDEX('AIRCRAFT PERFORMANCE'!$I:$I,MATCH($B$8,'AIRCRAFT PERFORMANCE'!$A:$A,0)),"EXCEEDS PRACTICAL RANGE OF "&TEXT(INDEX('AIRCRAFT PERFORMANCE'!$I:$I,MATCH($B$8,'AIRCRAFT PERFORMANCE'!$A:$A,0)),"#,##0")&" NM - TECHNICAL STOP REQUIRED","WITHIN RANGE"),"TYPE NOT IN PERFORMANCE TABLE")) | AH21: =IFERROR(INDEX('PAX & CREW'!$L$3:$L$62,MATCH(ROW()-17,'PAX & CREW'!$AJ$3:$AJ$62,0)),"") | AI21: =IF($AH21="","",IF(COUNTIF($AH$18:$AH21,$AH21)=1,1,0)) | AJ21: =IF($AI21=1,SUM($AI$18:$AI21),"") | AK21: =IF($U20="","",$U20) | AL21: =IF($U20="","",$G20) | AM21: =IF($U20="","",$A20) | AN21: =IF($U20="","",$L20+$M20) | AO21: =IF($AK21="","",IF(COUNTIF($AK$18:$AK21,$AK21)=1,1,0)) | AP21: =IF($AO21=1,SUM($AO$18:$AO21),"")
A22: L5 | C22: =IF($B22="","",IFERROR(INDEX(airports!$E:$E,MATCH($B22,airports!$A:$A,0)),"ICAO NOT IN AIRPORTS")) | D22: =IF($B22="","",IFERROR(INDEX(airports!$H:$H,MATCH($B22,airports!$A:$A,0)),"")) | H22: =IF($G22="","",IFERROR(INDEX(airports!$E:$E,MATCH($G22,airports!$A:$A,0)),"ICAO NOT IN AIRPORTS")) | I22: =IF($G22="","",IFERROR(INDEX(airports!$H:$H,MATCH($G22,airports!$A:$A,0)),"")) | J22: =IF($S22="","",ROUND($S22*3440.065,0)) | K22: =IF(OR($J22="",$B$10=""),"",ROUND($J22/$B$10+$B$11,2)) | L22: =IF(OR($E22="",$K22=""),"",INT($E22+$F22+$K22/24)) | M22: =IF($L22="","",MOD($E22+$F22+$K22/24,1)) | N22: =IF($B22="","",$F$5) | O22: =IF($B22="","",IFERROR(INDEX(airports!$O:$O,MATCH($B22,airports!$A:$A,0)),"")) | P22: =IF($B22="","",IFERROR(INDEX(airports!$P:$P,MATCH($B22,airports!$A:$A,0)),"")) | Q22: =IF($G22="","",IFERROR(INDEX(airports!$O:$O,MATCH($G22,airports!$A:$A,0)),"")) | R22: =IF($G22="","",IFERROR(INDEX(airports!$P:$P,MATCH($G22,airports!$A:$A,0)),"")) | S22: =IF(OR($O22="",$Q22=""),"",ACOS(MIN(1,SIN(RADIANS($O22))*SIN(RADIANS($Q22))+COS(RADIANS($O22))*COS(RADIANS($Q22))*COS(RADIANS($R22-$P22))))) | T22: {=IF($O22="","",IFERROR(IF(INDEX(geo_grid!$B$2:$JU$231,INT(($O22+40)/0.5)+1,INT(($P22+30)/0.5)+1)="","",INDEX(geo_grid!$B$2:$JU$231,INT(($O22+40)/0.5)+1,INT(($P22+30)/0.5)+1)),"OUTSIDE GRID"))} | U22: {=IF($Q22="","",IFERROR(IF(INDEX(geo_grid!$B$2:$JU$231,INT(($Q22+40)/0.5)+1,INT(($R22+30)/0.5)+1)="","",INDEX(geo_grid!$B$2:$JU$231,INT(($Q22+40)/0.5)+1,INT(($R22+30)/0.5)+1)),"OUTSIDE GRID"))} | X22: {=IF($B22="","",IF(AND($V22="",$W22=""),"NO CONSTRAINT",TRIM(IF($V22="","",IF(SUMPRODUCT(--((ISNUMBER(SEARCH(","&permit_calc!$A$3:$A$144&",",","&SUBSTITUTE(UPPER($V22)," ","")&","))+ISNUMBER(SEARCH(","&SUBSTITUTE(UPPER(permit_calc!$B$3:$B$144)," ","")&",",","&SUBSTITUTE(UPPER($V22)," ","")&",")))>0),--(INDEX(permit_calc!$C$3:$J$144,0,ROW()-17)>0))>0,"AVOID CONFLICT - track crosses an excluded state. ",""))&IF($W22="","",IF(SUMPRODUCT(--((ISNUMBER(SEARCH(","&permit_calc!$A$3:$A$144&",",","&SUBSTITUTE(UPPER($W22)," ","")&","))+ISNUMBER(SEARCH(","&SUBSTITUTE(UPPER(permit_calc!$B$3:$B$144)," ","")&",",","&SUBSTITUTE(UPPER($W22)," ","")&",")))>0),--(INDEX(permit_calc!$C$3:$J$144,0,ROW()-17)>0))<LEN($W22)-LEN(SUBSTITUTE($W22,",",""))+1,"INCLUDE NOT ON TRACK - required state not overflown. ","")))))} | Y22: =IF($B22="","",IFERROR(IF($J22>INDEX('AIRCRAFT PERFORMANCE'!$I:$I,MATCH($B$8,'AIRCRAFT PERFORMANCE'!$A:$A,0)),"EXCEEDS PRACTICAL RANGE OF "&TEXT(INDEX('AIRCRAFT PERFORMANCE'!$I:$I,MATCH($B$8,'AIRCRAFT PERFORMANCE'!$A:$A,0)),"#,##0")&" NM - TECHNICAL STOP REQUIRED","WITHIN RANGE"),"TYPE NOT IN PERFORMANCE TABLE")) | AH22: =IFERROR(INDEX('PAX & CREW'!$L$3:$L$62,MATCH(ROW()-17,'PAX & CREW'!$AJ$3:$AJ$62,0)),"") | AI22: =IF($AH22="","",IF(COUNTIF($AH$18:$AH22,$AH22)=1,1,0)) | AJ22: =IF($AI22=1,SUM($AI$18:$AI22),"") | AK22: =IF($U21="","",$U21) | AL22: =IF($U21="","",$G21) | AM22: =IF($U21="","",$A21) | AN22: =IF($U21="","",$L21+$M21) | AO22: =IF($AK22="","",IF(COUNTIF($AK$18:$AK22,$AK22)=1,1,0)) | AP22: =IF($AO22=1,SUM($AO$18:$AO22),"")
A23: L6 | B23: =IF($G22="","",$G22) | C23: =IF($B23="","",IFERROR(INDEX(airports!$E:$E,MATCH($B23,airports!$A:$A,0)),"ICAO NOT IN AIRPORTS")) | D23: =IF($B23="","",IFERROR(INDEX(airports!$H:$H,MATCH($B23,airports!$A:$A,0)),"")) | H23: =IF($G23="","",IFERROR(INDEX(airports!$E:$E,MATCH($G23,airports!$A:$A,0)),"ICAO NOT IN AIRPORTS")) | I23: =IF($G23="","",IFERROR(INDEX(airports!$H:$H,MATCH($G23,airports!$A:$A,0)),"")) | J23: =IF($S23="","",ROUND($S23*3440.065,0)) | K23: =IF(OR($J23="",$B$10=""),"",ROUND($J23/$B$10+$B$11,2)) | L23: =IF(OR($E23="",$K23=""),"",INT($E23+$F23+$K23/24)) | M23: =IF($L23="","",MOD($E23+$F23+$K23/24,1)) | N23: =IF($B23="","",$F$5) | O23: =IF($B23="","",IFERROR(INDEX(airports!$O:$O,MATCH($B23,airports!$A:$A,0)),"")) | P23: =IF($B23="","",IFERROR(INDEX(airports!$P:$P,MATCH($B23,airports!$A:$A,0)),"")) | Q23: =IF($G23="","",IFERROR(INDEX(airports!$O:$O,MATCH($G23,airports!$A:$A,0)),"")) | R23: =IF($G23="","",IFERROR(INDEX(airports!$P:$P,MATCH($G23,airports!$A:$A,0)),"")) | S23: =IF(OR($O23="",$Q23=""),"",ACOS(MIN(1,SIN(RADIANS($O23))*SIN(RADIANS($Q23))+COS(RADIANS($O23))*COS(RADIANS($Q23))*COS(RADIANS($R23-$P23))))) | T23: {=IF($O23="","",IFERROR(IF(INDEX(geo_grid!$B$2:$JU$231,INT(($O23+40)/0.5)+1,INT(($P23+30)/0.5)+1)="","",INDEX(geo_grid!$B$2:$JU$231,INT(($O23+40)/0.5)+1,INT(($P23+30)/0.5)+1)),"OUTSIDE GRID"))} | U23: {=IF($Q23="","",IFERROR(IF(INDEX(geo_grid!$B$2:$JU$231,INT(($Q23+40)/0.5)+1,INT(($R23+30)/0.5)+1)="","",INDEX(geo_grid!$B$2:$JU$231,INT(($Q23+40)/0.5)+1,INT(($R23+30)/0.5)+1)),"OUTSIDE GRID"))} | X23: {=IF($B23="","",IF(AND($V23="",$W23=""),"NO CONSTRAINT",TRIM(IF($V23="","",IF(SUMPRODUCT(--((ISNUMBER(SEARCH(","&permit_calc!$A$3:$A$144&",",","&SUBSTITUTE(UPPER($V23)," ","")&","))+ISNUMBER(SEARCH(","&SUBSTITUTE(UPPER(permit_calc!$B$3:$B$144)," ","")&",",","&SUBSTITUTE(UPPER($V23)," ","")&",")))>0),--(INDEX(permit_calc!$C$3:$J$144,0,ROW()-17)>0))>0,"AVOID CONFLICT - track crosses an excluded state. ",""))&IF($W23="","",IF(SUMPRODUCT(--((ISNUMBER(SEARCH(","&permit_calc!$A$3:$A$144&",",","&SUBSTITUTE(UPPER($W23)," ","")&","))+ISNUMBER(SEARCH(","&SUBSTITUTE(UPPER(permit_calc!$B$3:$B$144)," ","")&",",","&SUBSTITUTE(UPPER($W23)," ","")&",")))>0),--(INDEX(permit_calc!$C$3:$J$144,0,ROW()-17)>0))<LEN($W23)-LEN(SUBSTITUTE($W23,",",""))+1,"INCLUDE NOT ON TRACK - required state not overflown. ","")))))} | Y23: =IF($B23="","",IFERROR(IF($J23>INDEX('AIRCRAFT PERFORMANCE'!$I:$I,MATCH($B$8,'AIRCRAFT PERFORMANCE'!$A:$A,0)),"EXCEEDS PRACTICAL RANGE OF "&TEXT(INDEX('AIRCRAFT PERFORMANCE'!$I:$I,MATCH($B$8,'AIRCRAFT PERFORMANCE'!$A:$A,0)),"#,##0")&" NM - TECHNICAL STOP REQUIRED","WITHIN RANGE"),"TYPE NOT IN PERFORMANCE TABLE")) | AH23: =IFERROR(INDEX('PAX & CREW'!$L$3:$L$62,MATCH(ROW()-17,'PAX & CREW'!$AJ$3:$AJ$62,0)),"") | AI23: =IF($AH23="","",IF(COUNTIF($AH$18:$AH23,$AH23)=1,1,0)) | AJ23: =IF($AI23=1,SUM($AI$18:$AI23),"") | AK23: =IF($U22="","",$U22) | AL23: =IF($U22="","",$G22) | AM23: =IF($U22="","",$A22) | AN23: =IF($U22="","",$L22+$M22) | AO23: =IF($AK23="","",IF(COUNTIF($AK$18:$AK23,$AK23)=1,1,0)) | AP23: =IF($AO23=1,SUM($AO$18:$AO23),"")
A24: L7 | B24: =IF($G23="","",$G23) | C24: =IF($B24="","",IFERROR(INDEX(airports!$E:$E,MATCH($B24,airports!$A:$A,0)),"ICAO NOT IN AIRPORTS")) | D24: =IF($B24="","",IFERROR(INDEX(airports!$H:$H,MATCH($B24,airports!$A:$A,0)),"")) | H24: =IF($G24="","",IFERROR(INDEX(airports!$E:$E,MATCH($G24,airports!$A:$A,0)),"ICAO NOT IN AIRPORTS")) | I24: =IF($G24="","",IFERROR(INDEX(airports!$H:$H,MATCH($G24,airports!$A:$A,0)),"")) | J24: =IF($S24="","",ROUND($S24*3440.065,0)) | K24: =IF(OR($J24="",$B$10=""),"",ROUND($J24/$B$10+$B$11,2)) | L24: =IF(OR($E24="",$K24=""),"",INT($E24+$F24+$K24/24)) | M24: =IF($L24="","",MOD($E24+$F24+$K24/24,1)) | N24: =IF($B24="","",$F$5) | O24: =IF($B24="","",IFERROR(INDEX(airports!$O:$O,MATCH($B24,airports!$A:$A,0)),"")) | P24: =IF($B24="","",IFERROR(INDEX(airports!$P:$P,MATCH($B24,airports!$A:$A,0)),"")) | Q24: =IF($G24="","",IFERROR(INDEX(airports!$O:$O,MATCH($G24,airports!$A:$A,0)),"")) | R24: =IF($G24="","",IFERROR(INDEX(airports!$P:$P,MATCH($G24,airports!$A:$A,0)),"")) | S24: =IF(OR($O24="",$Q24=""),"",ACOS(MIN(1,SIN(RADIANS($O24))*SIN(RADIANS($Q24))+COS(RADIANS($O24))*COS(RADIANS($Q24))*COS(RADIANS($R24-$P24))))) | T24: {=IF($O24="","",IFERROR(IF(INDEX(geo_grid!$B$2:$JU$231,INT(($O24+40)/0.5)+1,INT(($P24+30)/0.5)+1)="","",INDEX(geo_grid!$B$2:$JU$231,INT(($O24+40)/0.5)+1,INT(($P24+30)/0.5)+1)),"OUTSIDE GRID"))} | U24: {=IF($Q24="","",IFERROR(IF(INDEX(geo_grid!$B$2:$JU$231,INT(($Q24+40)/0.5)+1,INT(($R24+30)/0.5)+1)="","",INDEX(geo_grid!$B$2:$JU$231,INT(($Q24+40)/0.5)+1,INT(($R24+30)/0.5)+1)),"OUTSIDE GRID"))} | X24: {=IF($B24="","",IF(AND($V24="",$W24=""),"NO CONSTRAINT",TRIM(IF($V24="","",IF(SUMPRODUCT(--((ISNUMBER(SEARCH(","&permit_calc!$A$3:$A$144&",",","&SUBSTITUTE(UPPER($V24)," ","")&","))+ISNUMBER(SEARCH(","&SUBSTITUTE(UPPER(permit_calc!$B$3:$B$144)," ","")&",",","&SUBSTITUTE(UPPER($V24)," ","")&",")))>0),--(INDEX(permit_calc!$C$3:$J$144,0,ROW()-17)>0))>0,"AVOID CONFLICT - track crosses an excluded state. ",""))&IF($W24="","",IF(SUMPRODUCT(--((ISNUMBER(SEARCH(","&permit_calc!$A$3:$A$144&",",","&SUBSTITUTE(UPPER($W24)," ","")&","))+ISNUMBER(SEARCH(","&SUBSTITUTE(UPPER(permit_calc!$B$3:$B$144)," ","")&",",","&SUBSTITUTE(UPPER($W24)," ","")&",")))>0),--(INDEX(permit_calc!$C$3:$J$144,0,ROW()-17)>0))<LEN($W24)-LEN(SUBSTITUTE($W24,",",""))+1,"INCLUDE NOT ON TRACK - required state not overflown. ","")))))} | Y24: =IF($B24="","",IFERROR(IF($J24>INDEX('AIRCRAFT PERFORMANCE'!$I:$I,MATCH($B$8,'AIRCRAFT PERFORMANCE'!$A:$A,0)),"EXCEEDS PRACTICAL RANGE OF "&TEXT(INDEX('AIRCRAFT PERFORMANCE'!$I:$I,MATCH($B$8,'AIRCRAFT PERFORMANCE'!$A:$A,0)),"#,##0")&" NM - TECHNICAL STOP REQUIRED","WITHIN RANGE"),"TYPE NOT IN PERFORMANCE TABLE")) | AH24: =IFERROR(INDEX('PAX & CREW'!$L$3:$L$62,MATCH(ROW()-17,'PAX & CREW'!$AJ$3:$AJ$62,0)),"") | AI24: =IF($AH24="","",IF(COUNTIF($AH$18:$AH24,$AH24)=1,1,0)) | AJ24: =IF($AI24=1,SUM($AI$18:$AI24),"") | AK24: =IF($U23="","",$U23) | AL24: =IF($U23="","",$G23) | AM24: =IF($U23="","",$A23) | AN24: =IF($U23="","",$L23+$M23) | AO24: =IF($AK24="","",IF(COUNTIF($AK$18:$AK24,$AK24)=1,1,0)) | AP24: =IF($AO24=1,SUM($AO$18:$AO24),"")
A25: L8 | B25: =IF($G24="","",$G24) | C25: =IF($B25="","",IFERROR(INDEX(airports!$E:$E,MATCH($B25,airports!$A:$A,0)),"ICAO NOT IN AIRPORTS")) | D25: =IF($B25="","",IFERROR(INDEX(airports!$H:$H,MATCH($B25,airports!$A:$A,0)),"")) | H25: =IF($G25="","",IFERROR(INDEX(airports!$E:$E,MATCH($G25,airports!$A:$A,0)),"ICAO NOT IN AIRPORTS")) | I25: =IF($G25="","",IFERROR(INDEX(airports!$H:$H,MATCH($G25,airports!$A:$A,0)),"")) | J25: =IF($S25="","",ROUND($S25*3440.065,0)) | K25: =IF(OR($J25="",$B$10=""),"",ROUND($J25/$B$10+$B$11,2)) | L25: =IF(OR($E25="",$K25=""),"",INT($E25+$F25+$K25/24)) | M25: =IF($L25="","",MOD($E25+$F25+$K25/24,1)) | N25: =IF($B25="","",$F$5) | O25: =IF($B25="","",IFERROR(INDEX(airports!$O:$O,MATCH($B25,airports!$A:$A,0)),"")) | P25: =IF($B25="","",IFERROR(INDEX(airports!$P:$P,MATCH($B25,airports!$A:$A,0)),"")) | Q25: =IF($G25="","",IFERROR(INDEX(airports!$O:$O,MATCH($G25,airports!$A:$A,0)),"")) | R25: =IF($G25="","",IFERROR(INDEX(airports!$P:$P,MATCH($G25,airports!$A:$A,0)),"")) | S25: =IF(OR($O25="",$Q25=""),"",ACOS(MIN(1,SIN(RADIANS($O25))*SIN(RADIANS($Q25))+COS(RADIANS($O25))*COS(RADIANS($Q25))*COS(RADIANS($R25-$P25))))) | T25: {=IF($O25="","",IFERROR(IF(INDEX(geo_grid!$B$2:$JU$231,INT(($O25+40)/0.5)+1,INT(($P25+30)/0.5)+1)="","",INDEX(geo_grid!$B$2:$JU$231,INT(($O25+40)/0.5)+1,INT(($P25+30)/0.5)+1)),"OUTSIDE GRID"))} | U25: {=IF($Q25="","",IFERROR(IF(INDEX(geo_grid!$B$2:$JU$231,INT(($Q25+40)/0.5)+1,INT(($R25+30)/0.5)+1)="","",INDEX(geo_grid!$B$2:$JU$231,INT(($Q25+40)/0.5)+1,INT(($R25+30)/0.5)+1)),"OUTSIDE GRID"))} | X25: {=IF($B25="","",IF(AND($V25="",$W25=""),"NO CONSTRAINT",TRIM(IF($V25="","",IF(SUMPRODUCT(--((ISNUMBER(SEARCH(","&permit_calc!$A$3:$A$144&",",","&SUBSTITUTE(UPPER($V25)," ","")&","))+ISNUMBER(SEARCH(","&SUBSTITUTE(UPPER(permit_calc!$B$3:$B$144)," ","")&",",","&SUBSTITUTE(UPPER($V25)," ","")&",")))>0),--(INDEX(permit_calc!$C$3:$J$144,0,ROW()-17)>0))>0,"AVOID CONFLICT - track crosses an excluded state. ",""))&IF($W25="","",IF(SUMPRODUCT(--((ISNUMBER(SEARCH(","&permit_calc!$A$3:$A$144&",",","&SUBSTITUTE(UPPER($W25)," ","")&","))+ISNUMBER(SEARCH(","&SUBSTITUTE(UPPER(permit_calc!$B$3:$B$144)," ","")&",",","&SUBSTITUTE(UPPER($W25)," ","")&",")))>0),--(INDEX(permit_calc!$C$3:$J$144,0,ROW()-17)>0))<LEN($W25)-LEN(SUBSTITUTE($W25,",",""))+1,"INCLUDE NOT ON TRACK - required state not overflown. ","")))))} | Y25: =IF($B25="","",IFERROR(IF($J25>INDEX('AIRCRAFT PERFORMANCE'!$I:$I,MATCH($B$8,'AIRCRAFT PERFORMANCE'!$A:$A,0)),"EXCEEDS PRACTICAL RANGE OF "&TEXT(INDEX('AIRCRAFT PERFORMANCE'!$I:$I,MATCH($B$8,'AIRCRAFT PERFORMANCE'!$A:$A,0)),"#,##0")&" NM - TECHNICAL STOP REQUIRED","WITHIN RANGE"),"TYPE NOT IN PERFORMANCE TABLE")) | AH25: =IFERROR(INDEX('PAX & CREW'!$L$3:$L$62,MATCH(ROW()-17,'PAX & CREW'!$AJ$3:$AJ$62,0)),"") | AI25: =IF($AH25="","",IF(COUNTIF($AH$18:$AH25,$AH25)=1,1,0)) | AJ25: =IF($AI25=1,SUM($AI$18:$AI25),"") | AK25: =IF($U24="","",$U24) | AL25: =IF($U24="","",$G24) | AM25: =IF($U24="","",$A24) | AN25: =IF($U24="","",$L24+$M24) | AO25: =IF($AK25="","",IF(COUNTIF($AK$18:$AK25,$AK25)=1,1,0)) | AP25: =IF($AO25=1,SUM($AO$18:$AO25),"")
A26: TOTALS | J26: =SUM($J$18:$J$25) | K26: =ROUND(SUM($K$18:$K$25),2) | L26: =IF(OR($E26="",$K26=""),"",INT($E26+$F26+$K26/24)) | M26: =IF($L26="","",MOD($E26+$F26+$K26/24,1)) | AH26: =IFERROR(INDEX('PAX & CREW'!$L$3:$L$62,MATCH(ROW()-17,'PAX & CREW'!$AJ$3:$AJ$62,0)),"") | AI26: =IF($AH26="","",IF(COUNTIF($AH$18:$AH26,$AH26)=1,1,0)) | AJ26: =IF($AI26=1,SUM($AI$18:$AI26),"") | AK26: =IF($U25="","",$U25) | AL26: =IF($U25="","",$G25) | AM26: =IF($U25="","",$A25) | AN26: =IF($U25="","",$L25+$M25) | AO26: =IF($AK26="","",IF(COUNTIF($AK$18:$AK26,$AK26)=1,1,0)) | AP26: =IF($AO26=1,SUM($AO$18:$AO26),"")
V27: Enter ISO3 codes separated by commas, e.g. LBY, SDN. FIR boundaries are approximated by state airspace — verify against the AIP. AVOID flags a conflict when the great-circle track crosses an excluded state; INCLUDE flags when a required state is not on track. Re-route by inserting a technical stop or adjusting the leg. | AH27: =IFERROR(INDEX('PAX & CREW'!$L$3:$L$62,MATCH(ROW()-17,'PAX & CREW'!$AJ$3:$AJ$62,0)),"") | AI27: =IF($AH27="","",IF(COUNTIF($AH$18:$AH27,$AH27)=1,1,0)) | AJ27: =IF($AI27=1,SUM($AI$18:$AI27),"")
A28: 3 · PERMITS (overflight for every en-route country except the leg's departure state and its destination; the destination raises a landing permit — ground services are in section 4) | AH28: =IFERROR(INDEX('PAX & CREW'!$L$3:$L$62,MATCH(ROW()-17,'PAX & CREW'!$AJ$3:$AJ$62,0)),"") | AI28: =IF($AH28="","",IF(COUNTIF($AH$18:$AH28,$AH28)=1,1,0)) | AJ28: =IF($AI28=1,SUM($AI$18:$AI28),"")
A29: # | B29: COUNTRY | C29: ISO3 | D29: PERMIT TYPE | E29: AIRPORT | F29: LEGS | G29: PROVIDER | H29: REF DATE (UTC) | I29: LEAD TIME (HRS) | J29: FILE BY (UTC) | K29: DAYS TO DEADLINE | L29: REQUIRED | M29: STATUS | AE29: ROW KIND | AF29: LEG INDEX | AH29: =IFERROR(INDEX('PAX & CREW'!$L$3:$L$62,MATCH(ROW()-17,'PAX & CREW'!$AJ$3:$AJ$62,0)),"") | AI29: =IF($AH29="","",IF(COUNTIF($AH$18:$AH29,$AH29)=1,1,0)) | AJ29: =IF($AI29=1,SUM($AI$18:$AI29),"")
A30: =IF(ROW()-29>COUNTIF(permit_calc!$L$3:$L$144,1)+COUNTA($G$18:$G$25),"",ROW()-29) | B30: =IF($A30="","",IF($AE30="OVF",INDEX(permit_calc!$B$3:$B$144,MATCH($A30,permit_calc!$N$3:$N$144,0)),IFERROR(INDEX(countries!$B:$B,MATCH($C30,countries!$D:$D,0)),$C30))) | C30: {=IF($A30="","",IF($AE30="OVF",INDEX(permit_calc!$A$3:$A$144,MATCH($A30,permit_calc!$N$3:$N$144,0)),INDEX($U$18:$U$25,$AF30)))} | D30: =IF($A30="","",$AE30) | E30: {=IF($A30="","",IF($AE30="OVF","",INDEX($G$18:$G$25,$AF30)))} | F30: {=IF($A30="","",IF($AE30="OVF",INDEX(permit_calc!$M$3:$M$144,MATCH($A30,permit_calc!$N$3:$N$144,0)),INDEX($A$18:$A$25,$AF30)))} | G30: JTL | H30: {=IF($A30="","",IF($AE30="OVF",INDEX($E$18:$E$25,INDEX(permit_calc!$O$3:$O$144,MATCH($A30,permit_calc!$N$3:$N$144,0)))+INDEX($F$18:$F$25,INDEX(permit_calc!$O$3:$O$144,MATCH($A30,permit_calc!$N$3:$N$144,0))),INDEX($L$18:$L$25,$AF30)+INDEX($M$18:$M$25,$AF30)))} | I30: =IF($A30="","",IFERROR(IF(INDEX(countries!$I:$I,MATCH($C30,countries!$D:$D,0))=0,$B$12,INDEX(countries!$I:$I,MATCH($C30,countries!$D:$D,0))),$B$12)) | J30: =IF($A30="","",$H30-$I30/24) | K30: =IF($A30="","",ROUND($J30-NOW(),1)) | L30: =IF($A30="","",IF($AE30="OVF",IFERROR(INDEX(countries!$G:$G,MATCH($C30,countries!$D:$D,0)),"VERIFY"),IFERROR(INDEX(countries!$H:$H,MATCH($C30,countries!$D:$D,0)),"VERIFY"))) | M30: =IF($A30="","",IF(OR(UPPER($G30)="OWN",UPPER($G30)="EXCLUDED"),"CLIENT ARRANGING",IF($K30<0,"OVERDUE",IF($K30<1,"URGENT - FILE NOW",IF($K30<3,"DUE SOON","PENDING"))))) | AE30: =IF($A30="","",IF($A30<=COUNTIF(permit_calc!$L$3:$L$144,1),"OVF","LDG")) | AF30: =IF($AE30="","",IF($AE30="OVF","",$A30-COUNTIF(permit_calc!$L$3:$L$144,1))) | AH30: =IFERROR(INDEX('PAX & CREW'!$L$3:$L$62,MATCH(ROW()-17,'PAX & CREW'!$AJ$3:$AJ$62,0)),"") | AI30: =IF($AH30="","",IF(COUNTIF($AH$18:$AH30,$AH30)=1,1,0)) | AJ30: =IF($AI30=1,SUM($AI$18:$AI30),"")
A31: =IF(ROW()-29>COUNTIF(permit_calc!$L$3:$L$144,1)+COUNTA($G$18:$G$25),"",ROW()-29) | B31: =IF($A31="","",IF($AE31="OVF",INDEX(permit_calc!$B$3:$B$144,MATCH($A31,permit_calc!$N$3:$N$144,0)),IFERROR(INDEX(countries!$B:$B,MATCH($C31,countries!$D:$D,0)),$C31))) | C31: {=IF($A31="","",IF($AE31="OVF",INDEX(permit_calc!$A$3:$A$144,MATCH($A31,permit_calc!$N$3:$N$144,0)),INDEX($U$18:$U$25,$AF31)))} | D31: =IF($A31="","",$AE31) | E31: {=IF($A31="","",IF($AE31="OVF","",INDEX($G$18:$G$25,$AF31)))} | F31: {=IF($A31="","",IF($AE31="OVF",INDEX(permit_calc!$M$3:$M$144,MATCH($A31,permit_calc!$N$3:$N$144,0)),INDEX($A$18:$A$25,$AF31)))} | G31: JTL | H31: {=IF($A31="","",IF($AE31="OVF",INDEX($E$18:$E$25,INDEX(permit_calc!$O$3:$O$144,MATCH($A31,permit_calc!$N$3:$N$144,0)))+INDEX($F$18:$F$25,INDEX(permit_calc!$O$3:$O$144,MATCH($A31,permit_calc!$N$3:$N$144,0))),INDEX($L$18:$L$25,$AF31)+INDEX($M$18:$M$25,$AF31)))} | I31: =IF($A31="","",IFERROR(IF(INDEX(countries!$I:$I,MATCH($C31,countries!$D:$D,0))=0,$B$12,INDEX(countries!$I:$I,MATCH($C31,countries!$D:$D,0))),$B$12)) | J31: =IF($A31="","",$H31-$I31/24) | K31: =IF($A31="","",ROUND($J31-NOW(),1)) | L31: =IF($A31="","",IF($AE31="OVF",IFERROR(INDEX(countries!$G:$G,MATCH($C31,countries!$D:$D,0)),"VERIFY"),IFERROR(INDEX(countries!$H:$H,MATCH($C31,countries!$D:$D,0)),"VERIFY"))) | M31: =IF($A31="","",IF(OR(UPPER($G31)="OWN",UPPER($G31)="EXCLUDED"),"CLIENT ARRANGING",IF($K31<0,"OVERDUE",IF($K31<1,"URGENT - FILE NOW",IF($K31<3,"DUE SOON","PENDING"))))) | AE31: =IF($A31="","",IF($A31<=COUNTIF(permit_calc!$L$3:$L$144,1),"OVF","LDG")) | AF31: =IF($AE31="","",IF($AE31="OVF","",$A31-COUNTIF(permit_calc!$L$3:$L$144,1))) | AH31: =IFERROR(INDEX('PAX & CREW'!$L$3:$L$62,MATCH(ROW()-17,'PAX & CREW'!$AJ$3:$AJ$62,0)),"") | AI31: =IF($AH31="","",IF(COUNTIF($AH$18:$AH31,$AH31)=1,1,0)) | AJ31: =IF($AI31=1,SUM($AI$18:$AI31),"")
A32: =IF(ROW()-29>COUNTIF(permit_calc!$L$3:$L$144,1)+COUNTA($G$18:$G$25),"",ROW()-29) | B32: =IF($A32="","",IF($AE32="OVF",INDEX(permit_calc!$B$3:$B$144,MATCH($A32,permit_calc!$N$3:$N$144,0)),IFERROR(INDEX(countries!$B:$B,MATCH($C32,countries!$D:$D,0)),$C32))) | C32: {=IF($A32="","",IF($AE32="OVF",INDEX(permit_calc!$A$3:$A$144,MATCH($A32,permit_calc!$N$3:$N$144,0)),INDEX($U$18:$U$25,$AF32)))} | D32: =IF($A32="","",$AE32) | E32: {=IF($A32="","",IF($AE32="OVF","",INDEX($G$18:$G$25,$AF32)))} | F32: {=IF($A32="","",IF($AE32="OVF",INDEX(permit_calc!$M$3:$M$144,MATCH($A32,permit_calc!$N$3:$N$144,0)),INDEX($A$18:$A$25,$AF32)))} | G32: JTL | H32: {=IF($A32="","",IF($AE32="OVF",INDEX($E$18:$E$25,INDEX(permit_calc!$O$3:$O$144,MATCH($A32,permit_calc!$N$3:$N$144,0)))+INDEX($F$18:$F$25,INDEX(permit_calc!$O$3:$O$144,MATCH($A32,permit_calc!$N$3:$N$144,0))),INDEX($L$18:$L$25,$AF32)+INDEX($M$18:$M$25,$AF32)))} | I32: =IF($A32="","",IFERROR(IF(INDEX(countries!$I:$I,MATCH($C32,countries!$D:$D,0))=0,$B$12,INDEX(countries!$I:$I,MATCH($C32,countries!$D:$D,0))),$B$12)) | J32: =IF($A32="","",$H32-$I32/24) | K32: =IF($A32="","",ROUND($J32-NOW(),1)) | L32: =IF($A32="","",IF($AE32="OVF",IFERROR(INDEX(countries!$G:$G,MATCH($C32,countries!$D:$D,0)),"VERIFY"),IFERROR(INDEX(countries!$H:$H,MATCH($C32,countries!$D:$D,0)),"VERIFY"))) | M32: =IF($A32="","",IF(OR(UPPER($G32)="OWN",UPPER($G32)="EXCLUDED"),"CLIENT ARRANGING",IF($K32<0,"OVERDUE",IF($K32<1,"URGENT - FILE NOW",IF($K32<3,"DUE SOON","PENDING"))))) | AE32: =IF($A32="","",IF($A32<=COUNTIF(permit_calc!$L$3:$L$144,1),"OVF","LDG")) | AF32: =IF($AE32="","",IF($AE32="OVF","",$A32-COUNTIF(permit_calc!$L$3:$L$144,1))) | AH32: =IFERROR(INDEX('PAX & CREW'!$L$3:$L$62,MATCH(ROW()-17,'PAX & CREW'!$AJ$3:$AJ$62,0)),"") | AI32: =IF($AH32="","",IF(COUNTIF($AH$18:$AH32,$AH32)=1,1,0)) | AJ32: =IF($AI32=1,SUM($AI$18:$AI32),"")
A33: =IF(ROW()-29>COUNTIF(permit_calc!$L$3:$L$144,1)+COUNTA($G$18:$G$25),"",ROW()-29) | B33: =IF($A33="","",IF($AE33="OVF",INDEX(permit_calc!$B$3:$B$144,MATCH($A33,permit_calc!$N$3:$N$144,0)),IFERROR(INDEX(countries!$B:$B,MATCH($C33,countries!$D:$D,0)),$C33))) | C33: {=IF($A33="","",IF($AE33="OVF",INDEX(permit_calc!$A$3:$A$144,MATCH($A33,permit_calc!$N$3:$N$144,0)),INDEX($U$18:$U$25,$AF33)))} | D33: =IF($A33="","",$AE33) | E33: {=IF($A33="","",IF($AE33="OVF","",INDEX($G$18:$G$25,$AF33)))} | F33: {=IF($A33="","",IF($AE33="OVF",INDEX(permit_calc!$M$3:$M$144,MATCH($A33,permit_calc!$N$3:$N$144,0)),INDEX($A$18:$A$25,$AF33)))} | G33: JTL | H33: {=IF($A33="","",IF($AE33="OVF",INDEX($E$18:$E$25,INDEX(permit_calc!$O$3:$O$144,MATCH($A33,permit_calc!$N$3:$N$144,0)))+INDEX($F$18:$F$25,INDEX(permit_calc!$O$3:$O$144,MATCH($A33,permit_calc!$N$3:$N$144,0))),INDEX($L$18:$L$25,$AF33)+INDEX($M$18:$M$25,$AF33)))} | I33: =IF($A33="","",IFERROR(IF(INDEX(countries!$I:$I,MATCH($C33,countries!$D:$D,0))=0,$B$12,INDEX(countries!$I:$I,MATCH($C33,countries!$D:$D,0))),$B$12)) | J33: =IF($A33="","",$H33-$I33/24) | K33: =IF($A33="","",ROUND($J33-NOW(),1)) | L33: =IF($A33="","",IF($AE33="OVF",IFERROR(INDEX(countries!$G:$G,MATCH($C33,countries!$D:$D,0)),"VERIFY"),IFERROR(INDEX(countries!$H:$H,MATCH($C33,countries!$D:$D,0)),"VERIFY"))) | M33: =IF($A33="","",IF(OR(UPPER($G33)="OWN",UPPER($G33)="EXCLUDED"),"CLIENT ARRANGING",IF($K33<0,"OVERDUE",IF($K33<1,"URGENT - FILE NOW",IF($K33<3,"DUE SOON","PENDING"))))) | AE33: =IF($A33="","",IF($A33<=COUNTIF(permit_calc!$L$3:$L$144,1),"OVF","LDG")) | AF33: =IF($AE33="","",IF($AE33="OVF","",$A33-COUNTIF(permit_calc!$L$3:$L$144,1))) | AH33: =IFERROR(INDEX('PAX & CREW'!$L$3:$L$62,MATCH(ROW()-17,'PAX & CREW'!$AJ$3:$AJ$62,0)),"") | AI33: =IF($AH33="","",IF(COUNTIF($AH$18:$AH33,$AH33)=1,1,0)) | AJ33: =IF($AI33=1,SUM($AI$18:$AI33),"")
A34: =IF(ROW()-29>COUNTIF(permit_calc!$L$3:$L$144,1)+COUNTA($G$18:$G$25),"",ROW()-29) | B34: =IF($A34="","",IF($AE34="OVF",INDEX(permit_calc!$B$3:$B$144,MATCH($A34,permit_calc!$N$3:$N$144,0)),IFERROR(INDEX(countries!$B:$B,MATCH($C34,countries!$D:$D,0)),$C34))) | C34: {=IF($A34="","",IF($AE34="OVF",INDEX(permit_calc!$A$3:$A$144,MATCH($A34,permit_calc!$N$3:$N$144,0)),INDEX($U$18:$U$25,$AF34)))} | D34: =IF($A34="","",$AE34) | E34: {=IF($A34="","",IF($AE34="OVF","",INDEX($G$18:$G$25,$AF34)))} | F34: {=IF($A34="","",IF($AE34="OVF",INDEX(permit_calc!$M$3:$M$144,MATCH($A34,permit_calc!$N$3:$N$144,0)),INDEX($A$18:$A$25,$AF34)))} | G34: JTL | H34: {=IF($A34="","",IF($AE34="OVF",INDEX($E$18:$E$25,INDEX(permit_calc!$O$3:$O$144,MATCH($A34,permit_calc!$N$3:$N$144,0)))+INDEX($F$18:$F$25,INDEX(permit_calc!$O$3:$O$144,MATCH($A34,permit_calc!$N$3:$N$144,0))),INDEX($L$18:$L$25,$AF34)+INDEX($M$18:$M$25,$AF34)))} | I34: =IF($A34="","",IFERROR(IF(INDEX(countries!$I:$I,MATCH($C34,countries!$D:$D,0))=0,$B$12,INDEX(countries!$I:$I,MATCH($C34,countries!$D:$D,0))),$B$12)) | J34: =IF($A34="","",$H34-$I34/24) | K34: =IF($A34="","",ROUND($J34-NOW(),1)) | L34: =IF($A34="","",IF($AE34="OVF",IFERROR(INDEX(countries!$G:$G,MATCH($C34,countries!$D:$D,0)),"VERIFY"),IFERROR(INDEX(countries!$H:$H,MATCH($C34,countries!$D:$D,0)),"VERIFY"))) | M34: =IF($A34="","",IF(OR(UPPER($G34)="OWN",UPPER($G34)="EXCLUDED"),"CLIENT ARRANGING",IF($K34<0,"OVERDUE",IF($K34<1,"URGENT - FILE NOW",IF($K34<3,"DUE SOON","PENDING"))))) | AE34: =IF($A34="","",IF($A34<=COUNTIF(permit_calc!$L$3:$L$144,1),"OVF","LDG")) | AF34: =IF($AE34="","",IF($AE34="OVF","",$A34-COUNTIF(permit_calc!$L$3:$L$144,1))) | AH34: =IFERROR(INDEX('PAX & CREW'!$L$3:$L$62,MATCH(ROW()-17,'PAX & CREW'!$AJ$3:$AJ$62,0)),"") | AI34: =IF($AH34="","",IF(COUNTIF($AH$18:$AH34,$AH34)=1,1,0)) | AJ34: =IF($AI34=1,SUM($AI$18:$AI34),"")
A35: =IF(ROW()-29>COUNTIF(permit_calc!$L$3:$L$144,1)+COUNTA($G$18:$G$25),"",ROW()-29) | B35: =IF($A35="","",IF($AE35="OVF",INDEX(permit_calc!$B$3:$B$144,MATCH($A35,permit_calc!$N$3:$N$144,0)),IFERROR(INDEX(countries!$B:$B,MATCH($C35,countries!$D:$D,0)),$C35))) | C35: {=IF($A35="","",IF($AE35="OVF",INDEX(permit_calc!$A$3:$A$144,MATCH($A35,permit_calc!$N$3:$N$144,0)),INDEX($U$18:$U$25,$AF35)))} | D35: =IF($A35="","",$AE35) | E35: {=IF($A35="","",IF($AE35="OVF","",INDEX($G$18:$G$25,$AF35)))} | F35: {=IF($A35="","",IF($AE35="OVF",INDEX(permit_calc!$M$3:$M$144,MATCH($A35,permit_calc!$N$3:$N$144,0)),INDEX($A$18:$A$25,$AF35)))} | G35: JTL | H35: {=IF($A35="","",IF($AE35="OVF",INDEX($E$18:$E$25,INDEX(permit_calc!$O$3:$O$144,MATCH($A35,permit_calc!$N$3:$N$144,0)))+INDEX($F$18:$F$25,INDEX(permit_calc!$O$3:$O$144,MATCH($A35,permit_calc!$N$3:$N$144,0))),INDEX($L$18:$L$25,$AF35)+INDEX($M$18:$M$25,$AF35)))} | I35: =IF($A35="","",IFERROR(IF(INDEX(countries!$I:$I,MATCH($C35,countries!$D:$D,0))=0,$B$12,INDEX(countries!$I:$I,MATCH($C35,countries!$D:$D,0))),$B$12)) | J35: =IF($A35="","",$H35-$I35/24) | K35: =IF($A35="","",ROUND($J35-NOW(),1)) | L35: =IF($A35="","",IF($AE35="OVF",IFERROR(INDEX(countries!$G:$G,MATCH($C35,countries!$D:$D,0)),"VERIFY"),IFERROR(INDEX(countries!$H:$H,MATCH($C35,countries!$D:$D,0)),"VERIFY"))) | M35: =IF($A35="","",IF(OR(UPPER($G35)="OWN",UPPER($G35)="EXCLUDED"),"CLIENT ARRANGING",IF($K35<0,"OVERDUE",IF($K35<1,"URGENT - FILE NOW",IF($K35<3,"DUE SOON","PENDING"))))) | AE35: =IF($A35="","",IF($A35<=COUNTIF(permit_calc!$L$3:$L$144,1),"OVF","LDG")) | AF35: =IF($AE35="","",IF($AE35="OVF","",$A35-COUNTIF(permit_calc!$L$3:$L$144,1))) | AH35: =IFERROR(INDEX('PAX & CREW'!$L$3:$L$62,MATCH(ROW()-17,'PAX & CREW'!$AJ$3:$AJ$62,0)),"") | AI35: =IF($AH35="","",IF(COUNTIF($AH$18:$AH35,$AH35)=1,1,0)) | AJ35: =IF($AI35=1,SUM($AI$18:$AI35),"")
A36: =IF(ROW()-29>COUNTIF(permit_calc!$L$3:$L$144,1)+COUNTA($G$18:$G$25),"",ROW()-29) | B36: =IF($A36="","",IF($AE36="OVF",INDEX(permit_calc!$B$3:$B$144,MATCH($A36,permit_calc!$N$3:$N$144,0)),IFERROR(INDEX(countries!$B:$B,MATCH($C36,countries!$D:$D,0)),$C36))) | C36: {=IF($A36="","",IF($AE36="OVF",INDEX(permit_calc!$A$3:$A$144,MATCH($A36,permit_calc!$N$3:$N$144,0)),INDEX($U$18:$U$25,$AF36)))} | D36: =IF($A36="","",$AE36) | E36: {=IF($A36="","",IF($AE36="OVF","",INDEX($G$18:$G$25,$AF36)))} | F36: {=IF($A36="","",IF($AE36="OVF",INDEX(permit_calc!$M$3:$M$144,MATCH($A36,permit_calc!$N$3:$N$144,0)),INDEX($A$18:$A$25,$AF36)))} | G36: JTL | H36: {=IF($A36="","",IF($AE36="OVF",INDEX($E$18:$E$25,INDEX(permit_calc!$O$3:$O$144,MATCH($A36,permit_calc!$N$3:$N$144,0)))+INDEX($F$18:$F$25,INDEX(permit_calc!$O$3:$O$144,MATCH($A36,permit_calc!$N$3:$N$144,0))),INDEX($L$18:$L$25,$AF36)+INDEX($M$18:$M$25,$AF36)))} | I36: =IF($A36="","",IFERROR(IF(INDEX(countries!$I:$I,MATCH($C36,countries!$D:$D,0))=0,$B$12,INDEX(countries!$I:$I,MATCH($C36,countries!$D:$D,0))),$B$12)) | J36: =IF($A36="","",$H36-$I36/24) | K36: =IF($A36="","",ROUND($J36-NOW(),1)) | L36: =IF($A36="","",IF($AE36="OVF",IFERROR(INDEX(countries!$G:$G,MATCH($C36,countries!$D:$D,0)),"VERIFY"),IFERROR(INDEX(countries!$H:$H,MATCH($C36,countries!$D:$D,0)),"VERIFY"))) | M36: =IF($A36="","",IF(OR(UPPER($G36)="OWN",UPPER($G36)="EXCLUDED"),"CLIENT ARRANGING",IF($K36<0,"OVERDUE",IF($K36<1,"URGENT - FILE NOW",IF($K36<3,"DUE SOON","PENDING"))))) | AE36: =IF($A36="","",IF($A36<=COUNTIF(permit_calc!$L$3:$L$144,1),"OVF","LDG")) | AF36: =IF($AE36="","",IF($AE36="OVF","",$A36-COUNTIF(permit_calc!$L$3:$L$144,1))) | AH36: =IFERROR(INDEX('PAX & CREW'!$L$3:$L$62,MATCH(ROW()-17,'PAX & CREW'!$AJ$3:$AJ$62,0)),"") | AI36: =IF($AH36="","",IF(COUNTIF($AH$18:$AH36,$AH36)=1,1,0)) | AJ36: =IF($AI36=1,SUM($AI$18:$AI36),"")
A37: =IF(ROW()-29>COUNTIF(permit_calc!$L$3:$L$144,1)+COUNTA($G$18:$G$25),"",ROW()-29) | B37: =IF($A37="","",IF($AE37="OVF",INDEX(permit_calc!$B$3:$B$144,MATCH($A37,permit_calc!$N$3:$N$144,0)),IFERROR(INDEX(countries!$B:$B,MATCH($C37,countries!$D:$D,0)),$C37))) | C37: {=IF($A37="","",IF($AE37="OVF",INDEX(permit_calc!$A$3:$A$144,MATCH($A37,permit_calc!$N$3:$N$144,0)),INDEX($U$18:$U$25,$AF37)))} | D37: =IF($A37="","",$AE37) | E37: {=IF($A37="","",IF($AE37="OVF","",INDEX($G$18:$G$25,$AF37)))} | F37: {=IF($A37="","",IF($AE37="OVF",INDEX(permit_calc!$M$3:$M$144,MATCH($A37,permit_calc!$N$3:$N$144,0)),INDEX($A$18:$A$25,$AF37)))} | G37: JTL | H37: {=IF($A37="","",IF($AE37="OVF",INDEX($E$18:$E$25,INDEX(permit_calc!$O$3:$O$144,MATCH($A37,permit_calc!$N$3:$N$144,0)))+INDEX($F$18:$F$25,INDEX(permit_calc!$O$3:$O$144,MATCH($A37,permit_calc!$N$3:$N$144,0))),INDEX($L$18:$L$25,$AF37)+INDEX($M$18:$M$25,$AF37)))} | I37: =IF($A37="","",IFERROR(IF(INDEX(countries!$I:$I,MATCH($C37,countries!$D:$D,0))=0,$B$12,INDEX(countries!$I:$I,MATCH($C37,countries!$D:$D,0))),$B$12)) | J37: =IF($A37="","",$H37-$I37/24) | K37: =IF($A37="","",ROUND($J37-NOW(),1)) | L37: =IF($A37="","",IF($AE37="OVF",IFERROR(INDEX(countries!$G:$G,MATCH($C37,countries!$D:$D,0)),"VERIFY"),IFERROR(INDEX(countries!$H:$H,MATCH($C37,countries!$D:$D,0)),"VERIFY"))) | M37: =IF($A37="","",IF(OR(UPPER($G37)="OWN",UPPER($G37)="EXCLUDED"),"CLIENT ARRANGING",IF($K37<0,"OVERDUE",IF($K37<1,"URGENT - FILE NOW",IF($K37<3,"DUE SOON","PENDING"))))) | AE37: =IF($A37="","",IF($A37<=COUNTIF(permit_calc!$L$3:$L$144,1),"OVF","LDG")) | AF37: =IF($AE37="","",IF($AE37="OVF","",$A37-COUNTIF(permit_calc!$L$3:$L$144,1))) | AH37: =IFERROR(INDEX('PAX & CREW'!$L$3:$L$62,MATCH(ROW()-17,'PAX & CREW'!$AJ$3:$AJ$62,0)),"") | AI37: =IF($AH37="","",IF(COUNTIF($AH$18:$AH37,$AH37)=1,1,0)) | AJ37: =IF($AI37=1,SUM($AI$18:$AI37),"")
A38: =IF(ROW()-29>COUNTIF(permit_calc!$L$3:$L$144,1)+COUNTA($G$18:$G$25),"",ROW()-29) | B38: =IF($A38="","",IF($AE38="OVF",INDEX(permit_calc!$B$3:$B$144,MATCH($A38,permit_calc!$N$3:$N$144,0)),IFERROR(INDEX(countries!$B:$B,MATCH($C38,countries!$D:$D,0)),$C38))) | C38: {=IF($A38="","",IF($AE38="OVF",INDEX(permit_calc!$A$3:$A$144,MATCH($A38,permit_calc!$N$3:$N$144,0)),INDEX($U$18:$U$25,$AF38)))} | D38: =IF($A38="","",$AE38) | E38: {=IF($A38="","",IF($AE38="OVF","",INDEX($G$18:$G$25,$AF38)))} | F38: {=IF($A38="","",IF($AE38="OVF",INDEX(permit_calc!$M$3:$M$144,MATCH($A38,permit_calc!$N$3:$N$144,0)),INDEX($A$18:$A$25,$AF38)))} | G38: JTL | H38: {=IF($A38="","",IF($AE38="OVF",INDEX($E$18:$E$25,INDEX(permit_calc!$O$3:$O$144,MATCH($A38,permit_calc!$N$3:$N$144,0)))+INDEX($F$18:$F$25,INDEX(permit_calc!$O$3:$O$144,MATCH($A38,permit_calc!$N$3:$N$144,0))),INDEX($L$18:$L$25,$AF38)+INDEX($M$18:$M$25,$AF38)))} | I38: =IF($A38="","",IFERROR(IF(INDEX(countries!$I:$I,MATCH($C38,countries!$D:$D,0))=0,$B$12,INDEX(countries!$I:$I,MATCH($C38,countries!$D:$D,0))),$B$12)) | J38: =IF($A38="","",$H38-$I38/24) | K38: =IF($A38="","",ROUND($J38-NOW(),1)) | L38: =IF($A38="","",IF($AE38="OVF",IFERROR(INDEX(countries!$G:$G,MATCH($C38,countries!$D:$D,0)),"VERIFY"),IFERROR(INDEX(countries!$H:$H,MATCH($C38,countries!$D:$D,0)),"VERIFY"))) | M38: =IF($A38="","",IF(OR(UPPER($G38)="OWN",UPPER($G38)="EXCLUDED"),"CLIENT ARRANGING",IF($K38<0,"OVERDUE",IF($K38<1,"URGENT - FILE NOW",IF($K38<3,"DUE SOON","PENDING"))))) | AE38: =IF($A38="","",IF($A38<=COUNTIF(permit_calc!$L$3:$L$144,1),"OVF","LDG")) | AF38: =IF($AE38="","",IF($AE38="OVF","",$A38-COUNTIF(permit_calc!$L$3:$L$144,1)))
A39: =IF(ROW()-29>COUNTIF(permit_calc!$L$3:$L$144,1)+COUNTA($G$18:$G$25),"",ROW()-29) | B39: =IF($A39="","",IF($AE39="OVF",INDEX(permit_calc!$B$3:$B$144,MATCH($A39,permit_calc!$N$3:$N$144,0)),IFERROR(INDEX(countries!$B:$B,MATCH($C39,countries!$D:$D,0)),$C39))) | C39: {=IF($A39="","",IF($AE39="OVF",INDEX(permit_calc!$A$3:$A$144,MATCH($A39,permit_calc!$N$3:$N$144,0)),INDEX($U$18:$U$25,$AF39)))} | D39: =IF($A39="","",$AE39) | E39: {=IF($A39="","",IF($AE39="OVF","",INDEX($G$18:$G$25,$AF39)))} | F39: {=IF($A39="","",IF($AE39="OVF",INDEX(permit_calc!$M$3:$M$144,MATCH($A39,permit_calc!$N$3:$N$144,0)),INDEX($A$18:$A$25,$AF39)))} | G39: JTL | H39: {=IF($A39="","",IF($AE39="OVF",INDEX($E$18:$E$25,INDEX(permit_calc!$O$3:$O$144,MATCH($A39,permit_calc!$N$3:$N$144,0)))+INDEX($F$18:$F$25,INDEX(permit_calc!$O$3:$O$144,MATCH($A39,permit_calc!$N$3:$N$144,0))),INDEX($L$18:$L$25,$AF39)+INDEX($M$18:$M$25,$AF39)))} | I39: =IF($A39="","",IFERROR(IF(INDEX(countries!$I:$I,MATCH($C39,countries!$D:$D,0))=0,$B$12,INDEX(countries!$I:$I,MATCH($C39,countries!$D:$D,0))),$B$12)) | J39: =IF($A39="","",$H39-$I39/24) | K39: =IF($A39="","",ROUND($J39-NOW(),1)) | L39: =IF($A39="","",IF($AE39="OVF",IFERROR(INDEX(countries!$G:$G,MATCH($C39,countries!$D:$D,0)),"VERIFY"),IFERROR(INDEX(countries!$H:$H,MATCH($C39,countries!$D:$D,0)),"VERIFY"))) | M39: =IF($A39="","",IF(OR(UPPER($G39)="OWN",UPPER($G39)="EXCLUDED"),"CLIENT ARRANGING",IF($K39<0,"OVERDUE",IF($K39<1,"URGENT - FILE NOW",IF($K39<3,"DUE SOON","PENDING"))))) | AE39: =IF($A39="","",IF($A39<=COUNTIF(permit_calc!$L$3:$L$144,1),"OVF","LDG")) | AF39: =IF($AE39="","",IF($AE39="OVF","",$A39-COUNTIF(permit_calc!$L$3:$L$144,1)))
A40: =IF(ROW()-29>COUNTIF(permit_calc!$L$3:$L$144,1)+COUNTA($G$18:$G$25),"",ROW()-29) | B40: =IF($A40="","",IF($AE40="OVF",INDEX(permit_calc!$B$3:$B$144,MATCH($A40,permit_calc!$N$3:$N$144,0)),IFERROR(INDEX(countries!$B:$B,MATCH($C40,countries!$D:$D,0)),$C40))) | C40: {=IF($A40="","",IF($AE40="OVF",INDEX(permit_calc!$A$3:$A$144,MATCH($A40,permit_calc!$N$3:$N$144,0)),INDEX($U$18:$U$25,$AF40)))} | D40: =IF($A40="","",$AE40) | E40: {=IF($A40="","",IF($AE40="OVF","",INDEX($G$18:$G$25,$AF40)))} | F40: {=IF($A40="","",IF($AE40="OVF",INDEX(permit_calc!$M$3:$M$144,MATCH($A40,permit_calc!$N$3:$N$144,0)),INDEX($A$18:$A$25,$AF40)))} | G40: JTL | H40: {=IF($A40="","",IF($AE40="OVF",INDEX($E$18:$E$25,INDEX(permit_calc!$O$3:$O$144,MATCH($A40,permit_calc!$N$3:$N$144,0)))+INDEX($F$18:$F$25,INDEX(permit_calc!$O$3:$O$144,MATCH($A40,permit_calc!$N$3:$N$144,0))),INDEX($L$18:$L$25,$AF40)+INDEX($M$18:$M$25,$AF40)))} | I40: =IF($A40="","",IFERROR(IF(INDEX(countries!$I:$I,MATCH($C40,countries!$D:$D,0))=0,$B$12,INDEX(countries!$I:$I,MATCH($C40,countries!$D:$D,0))),$B$12)) | J40: =IF($A40="","",$H40-$I40/24) | K40: =IF($A40="","",ROUND($J40-NOW(),1)) | L40: =IF($A40="","",IF($AE40="OVF",IFERROR(INDEX(countries!$G:$G,MATCH($C40,countries!$D:$D,0)),"VERIFY"),IFERROR(INDEX(countries!$H:$H,MATCH($C40,countries!$D:$D,0)),"VERIFY"))) | M40: =IF($A40="","",IF(OR(UPPER($G40)="OWN",UPPER($G40)="EXCLUDED"),"CLIENT ARRANGING",IF($K40<0,"OVERDUE",IF($K40<1,"URGENT - FILE NOW",IF($K40<3,"DUE SOON","PENDING"))))) | AE40: =IF($A40="","",IF($A40<=COUNTIF(permit_calc!$L$3:$L$144,1),"OVF","LDG")) | AF40: =IF($AE40="","",IF($AE40="OVF","",$A40-COUNTIF(permit_calc!$L$3:$L$144,1)))
A41: =IF(ROW()-29>COUNTIF(permit_calc!$L$3:$L$144,1)+COUNTA($G$18:$G$25),"",ROW()-29) | B41: =IF($A41="","",IF($AE41="OVF",INDEX(permit_calc!$B$3:$B$144,MATCH($A41,permit_calc!$N$3:$N$144,0)),IFERROR(INDEX(countries!$B:$B,MATCH($C41,countries!$D:$D,0)),$C41))) | C41: {=IF($A41="","",IF($AE41="OVF",INDEX(permit_calc!$A$3:$A$144,MATCH($A41,permit_calc!$N$3:$N$144,0)),INDEX($U$18:$U$25,$AF41)))} | D41: =IF($A41="","",$AE41) | E41: {=IF($A41="","",IF($AE41="OVF","",INDEX($G$18:$G$25,$AF41)))} | F41: {=IF($A41="","",IF($AE41="OVF",INDEX(permit_calc!$M$3:$M$144,MATCH($A41,permit_calc!$N$3:$N$144,0)),INDEX($A$18:$A$25,$AF41)))} | G41: JTL | H41: {=IF($A41="","",IF($AE41="OVF",INDEX($E$18:$E$25,INDEX(permit_calc!$O$3:$O$144,MATCH($A41,permit_calc!$N$3:$N$144,0)))+INDEX($F$18:$F$25,INDEX(permit_calc!$O$3:$O$144,MATCH($A41,permit_calc!$N$3:$N$144,0))),INDEX($L$18:$L$25,$AF41)+INDEX($M$18:$M$25,$AF41)))} | I41: =IF($A41="","",IFERROR(IF(INDEX(countries!$I:$I,MATCH($C41,countries!$D:$D,0))=0,$B$12,INDEX(countries!$I:$I,MATCH($C41,countries!$D:$D,0))),$B$12)) | J41: =IF($A41="","",$H41-$I41/24) | K41: =IF($A41="","",ROUND($J41-NOW(),1)) | L41: =IF($A41="","",IF($AE41="OVF",IFERROR(INDEX(countries!$G:$G,MATCH($C41,countries!$D:$D,0)),"VERIFY"),IFERROR(INDEX(countries!$H:$H,MATCH($C41,countries!$D:$D,0)),"VERIFY"))) | M41: =IF($A41="","",IF(OR(UPPER($G41)="OWN",UPPER($G41)="EXCLUDED"),"CLIENT ARRANGING",IF($K41<0,"OVERDUE",IF($K41<1,"URGENT - FILE NOW",IF($K41<3,"DUE SOON","PENDING"))))) | AE41: =IF($A41="","",IF($A41<=COUNTIF(permit_calc!$L$3:$L$144,1),"OVF","LDG")) | AF41: =IF($AE41="","",IF($AE41="OVF","",$A41-COUNTIF(permit_calc!$L$3:$L$144,1)))
A42: =IF(ROW()-29>COUNTIF(permit_calc!$L$3:$L$144,1)+COUNTA($G$18:$G$25),"",ROW()-29) | B42: =IF($A42="","",IF($AE42="OVF",INDEX(permit_calc!$B$3:$B$144,MATCH($A42,permit_calc!$N$3:$N$144,0)),IFERROR(INDEX(countries!$B:$B,MATCH($C42,countries!$D:$D,0)),$C42))) | C42: {=IF($A42="","",IF($AE42="OVF",INDEX(permit_calc!$A$3:$A$144,MATCH($A42,permit_calc!$N$3:$N$144,0)),INDEX($U$18:$U$25,$AF42)))} | D42: =IF($A42="","",$AE42) | E42: {=IF($A42="","",IF($AE42="OVF","",INDEX($G$18:$G$25,$AF42)))} | F42: {=IF($A42="","",IF($AE42="OVF",INDEX(permit_calc!$M$3:$M$144,MATCH($A42,permit_calc!$N$3:$N$144,0)),INDEX($A$18:$A$25,$AF42)))} | G42: JTL | H42: {=IF($A42="","",IF($AE42="OVF",INDEX($E$18:$E$25,INDEX(permit_calc!$O$3:$O$144,MATCH($A42,permit_calc!$N$3:$N$144,0)))+INDEX($F$18:$F$25,INDEX(permit_calc!$O$3:$O$144,MATCH($A42,permit_calc!$N$3:$N$144,0))),INDEX($L$18:$L$25,$AF42)+INDEX($M$18:$M$25,$AF42)))} | I42: =IF($A42="","",IFERROR(IF(INDEX(countries!$I:$I,MATCH($C42,countries!$D:$D,0))=0,$B$12,INDEX(countries!$I:$I,MATCH($C42,countries!$D:$D,0))),$B$12)) | J42: =IF($A42="","",$H42-$I42/24) | K42: =IF($A42="","",ROUND($J42-NOW(),1)) | L42: =IF($A42="","",IF($AE42="OVF",IFERROR(INDEX(countries!$G:$G,MATCH($C42,countries!$D:$D,0)),"VERIFY"),IFERROR(INDEX(countries!$H:$H,MATCH($C42,countries!$D:$D,0)),"VERIFY"))) | M42: =IF($A42="","",IF(OR(UPPER($G42)="OWN",UPPER($G42)="EXCLUDED"),"CLIENT ARRANGING",IF($K42<0,"OVERDUE",IF($K42<1,"URGENT - FILE NOW",IF($K42<3,"DUE SOON","PENDING"))))) | AE42: =IF($A42="","",IF($A42<=COUNTIF(permit_calc!$L$3:$L$144,1),"OVF","LDG")) | AF42: =IF($AE42="","",IF($AE42="OVF","",$A42-COUNTIF(permit_calc!$L$3:$L$144,1)))
A43: =IF(ROW()-29>COUNTIF(permit_calc!$L$3:$L$144,1)+COUNTA($G$18:$G$25),"",ROW()-29) | B43: =IF($A43="","",IF($AE43="OVF",INDEX(permit_calc!$B$3:$B$144,MATCH($A43,permit_calc!$N$3:$N$144,0)),IFERROR(INDEX(countries!$B:$B,MATCH($C43,countries!$D:$D,0)),$C43))) | C43: {=IF($A43="","",IF($AE43="OVF",INDEX(permit_calc!$A$3:$A$144,MATCH($A43,permit_calc!$N$3:$N$144,0)),INDEX($U$18:$U$25,$AF43)))} | D43: =IF($A43="","",$AE43) | E43: {=IF($A43="","",IF($AE43="OVF","",INDEX($G$18:$G$25,$AF43)))} | F43: {=IF($A43="","",IF($AE43="OVF",INDEX(permit_calc!$M$3:$M$144,MATCH($A43,permit_calc!$N$3:$N$144,0)),INDEX($A$18:$A$25,$AF43)))} | G43: JTL | H43: {=IF($A43="","",IF($AE43="OVF",INDEX($E$18:$E$25,INDEX(permit_calc!$O$3:$O$144,MATCH($A43,permit_calc!$N$3:$N$144,0)))+INDEX($F$18:$F$25,INDEX(permit_calc!$O$3:$O$144,MATCH($A43,permit_calc!$N$3:$N$144,0))),INDEX($L$18:$L$25,$AF43)+INDEX($M$18:$M$25,$AF43)))} | I43: =IF($A43="","",IFERROR(IF(INDEX(countries!$I:$I,MATCH($C43,countries!$D:$D,0))=0,$B$12,INDEX(countries!$I:$I,MATCH($C43,countries!$D:$D,0))),$B$12)) | J43: =IF($A43="","",$H43-$I43/24) | K43: =IF($A43="","",ROUND($J43-NOW(),1)) | L43: =IF($A43="","",IF($AE43="OVF",IFERROR(INDEX(countries!$G:$G,MATCH($C43,countries!$D:$D,0)),"VERIFY"),IFERROR(INDEX(countries!$H:$H,MATCH($C43,countries!$D:$D,0)),"VERIFY"))) | M43: =IF($A43="","",IF(OR(UPPER($G43)="OWN",UPPER($G43)="EXCLUDED"),"CLIENT ARRANGING",IF($K43<0,"OVERDUE",IF($K43<1,"URGENT - FILE NOW",IF($K43<3,"DUE SOON","PENDING"))))) | AE43: =IF($A43="","",IF($A43<=COUNTIF(permit_calc!$L$3:$L$144,1),"OVF","LDG")) | AF43: =IF($AE43="","",IF($AE43="OVF","",$A43-COUNTIF(permit_calc!$L$3:$L$144,1)))
A44: =IF(ROW()-29>COUNTIF(permit_calc!$L$3:$L$144,1)+COUNTA($G$18:$G$25),"",ROW()-29) | B44: =IF($A44="","",IF($AE44="OVF",INDEX(permit_calc!$B$3:$B$144,MATCH($A44,permit_calc!$N$3:$N$144,0)),IFERROR(INDEX(countries!$B:$B,MATCH($C44,countries!$D:$D,0)),$C44))) | C44: {=IF($A44="","",IF($AE44="OVF",INDEX(permit_calc!$A$3:$A$144,MATCH($A44,permit_calc!$N$3:$N$144,0)),INDEX($U$18:$U$25,$AF44)))} | D44: =IF($A44="","",$AE44) | E44: {=IF($A44="","",IF($AE44="OVF","",INDEX($G$18:$G$25,$AF44)))} | F44: {=IF($A44="","",IF($AE44="OVF",INDEX(permit_calc!$M$3:$M$144,MATCH($A44,permit_calc!$N$3:$N$144,0)),INDEX($A$18:$A$25,$AF44)))} | G44: JTL | H44: {=IF($A44="","",IF($AE44="OVF",INDEX($E$18:$E$25,INDEX(permit_calc!$O$3:$O$144,MATCH($A44,permit_calc!$N$3:$N$144,0)))+INDEX($F$18:$F$25,INDEX(permit_calc!$O$3:$O$144,MATCH($A44,permit_calc!$N$3:$N$144,0))),INDEX($L$18:$L$25,$AF44)+INDEX($M$18:$M$25,$AF44)))} | I44: =IF($A44="","",IFERROR(IF(INDEX(countries!$I:$I,MATCH($C44,countries!$D:$D,0))=0,$B$12,INDEX(countries!$I:$I,MATCH($C44,countries!$D:$D,0))),$B$12)) | J44: =IF($A44="","",$H44-$I44/24) | K44: =IF($A44="","",ROUND($J44-NOW(),1)) | L44: =IF($A44="","",IF($AE44="OVF",IFERROR(INDEX(countries!$G:$G,MATCH($C44,countries!$D:$D,0)),"VERIFY"),IFERROR(INDEX(countries!$H:$H,MATCH($C44,countries!$D:$D,0)),"VERIFY"))) | M44: =IF($A44="","",IF(OR(UPPER($G44)="OWN",UPPER($G44)="EXCLUDED"),"CLIENT ARRANGING",IF($K44<0,"OVERDUE",IF($K44<1,"URGENT - FILE NOW",IF($K44<3,"DUE SOON","PENDING"))))) | AE44: =IF($A44="","",IF($A44<=COUNTIF(permit_calc!$L$3:$L$144,1),"OVF","LDG")) | AF44: =IF($AE44="","",IF($AE44="OVF","",$A44-COUNTIF(permit_calc!$L$3:$L$144,1)))
A45: =IF(ROW()-29>COUNTIF(permit_calc!$L$3:$L$144,1)+COUNTA($G$18:$G$25),"",ROW()-29) | B45: =IF($A45="","",IF($AE45="OVF",INDEX(permit_calc!$B$3:$B$144,MATCH($A45,permit_calc!$N$3:$N$144,0)),IFERROR(INDEX(countries!$B:$B,MATCH($C45,countries!$D:$D,0)),$C45))) | C45: {=IF($A45="","",IF($AE45="OVF",INDEX(permit_calc!$A$3:$A$144,MATCH($A45,permit_calc!$N$3:$N$144,0)),INDEX($U$18:$U$25,$AF45)))} | D45: =IF($A45="","",$AE45) | E45: {=IF($A45="","",IF($AE45="OVF","",INDEX($G$18:$G$25,$AF45)))} | F45: {=IF($A45="","",IF($AE45="OVF",INDEX(permit_calc!$M$3:$M$144,MATCH($A45,permit_calc!$N$3:$N$144,0)),INDEX($A$18:$A$25,$AF45)))} | G45: JTL | H45: {=IF($A45="","",IF($AE45="OVF",INDEX($E$18:$E$25,INDEX(permit_calc!$O$3:$O$144,MATCH($A45,permit_calc!$N$3:$N$144,0)))+INDEX($F$18:$F$25,INDEX(permit_calc!$O$3:$O$144,MATCH($A45,permit_calc!$N$3:$N$144,0))),INDEX($L$18:$L$25,$AF45)+INDEX($M$18:$M$25,$AF45)))} | I45: =IF($A45="","",IFERROR(IF(INDEX(countries!$I:$I,MATCH($C45,countries!$D:$D,0))=0,$B$12,INDEX(countries!$I:$I,MATCH($C45,countries!$D:$D,0))),$B$12)) | J45: =IF($A45="","",$H45-$I45/24) | K45: =IF($A45="","",ROUND($J45-NOW(),1)) | L45: =IF($A45="","",IF($AE45="OVF",IFERROR(INDEX(countries!$G:$G,MATCH($C45,countries!$D:$D,0)),"VERIFY"),IFERROR(INDEX(countries!$H:$H,MATCH($C45,countries!$D:$D,0)),"VERIFY"))) | M45: =IF($A45="","",IF(OR(UPPER($G45)="OWN",UPPER($G45)="EXCLUDED"),"CLIENT ARRANGING",IF($K45<0,"OVERDUE",IF($K45<1,"URGENT - FILE NOW",IF($K45<3,"DUE SOON","PENDING"))))) | AE45: =IF($A45="","",IF($A45<=COUNTIF(permit_calc!$L$3:$L$144,1),"OVF","LDG")) | AF45: =IF($AE45="","",IF($AE45="OVF","",$A45-COUNTIF(permit_calc!$L$3:$L$144,1)))
A46: =IF(ROW()-29>COUNTIF(permit_calc!$L$3:$L$144,1)+COUNTA($G$18:$G$25),"",ROW()-29) | B46: =IF($A46="","",IF($AE46="OVF",INDEX(permit_calc!$B$3:$B$144,MATCH($A46,permit_calc!$N$3:$N$144,0)),IFERROR(INDEX(countries!$B:$B,MATCH($C46,countries!$D:$D,0)),$C46))) | C46: {=IF($A46="","",IF($AE46="OVF",INDEX(permit_calc!$A$3:$A$144,MATCH($A46,permit_calc!$N$3:$N$144,0)),INDEX($U$18:$U$25,$AF46)))} | D46: =IF($A46="","",$AE46) | E46: {=IF($A46="","",IF($AE46="OVF","",INDEX($G$18:$G$25,$AF46)))} | F46: {=IF($A46="","",IF($AE46="OVF",INDEX(permit_calc!$M$3:$M$144,MATCH($A46,permit_calc!$N$3:$N$144,0)),INDEX($A$18:$A$25,$AF46)))} | G46: JTL | H46: {=IF($A46="","",IF($AE46="OVF",INDEX($E$18:$E$25,INDEX(permit_calc!$O$3:$O$144,MATCH($A46,permit_calc!$N$3:$N$144,0)))+INDEX($F$18:$F$25,INDEX(permit_calc!$O$3:$O$144,MATCH($A46,permit_calc!$N$3:$N$144,0))),INDEX($L$18:$L$25,$AF46)+INDEX($M$18:$M$25,$AF46)))} | I46: =IF($A46="","",IFERROR(IF(INDEX(countries!$I:$I,MATCH($C46,countries!$D:$D,0))=0,$B$12,INDEX(countries!$I:$I,MATCH($C46,countries!$D:$D,0))),$B$12)) | J46: =IF($A46="","",$H46-$I46/24) | K46: =IF($A46="","",ROUND($J46-NOW(),1)) | L46: =IF($A46="","",IF($AE46="OVF",IFERROR(INDEX(countries!$G:$G,MATCH($C46,countries!$D:$D,0)),"VERIFY"),IFERROR(INDEX(countries!$H:$H,MATCH($C46,countries!$D:$D,0)),"VERIFY"))) | M46: =IF($A46="","",IF(OR(UPPER($G46)="OWN",UPPER($G46)="EXCLUDED"),"CLIENT ARRANGING",IF($K46<0,"OVERDUE",IF($K46<1,"URGENT - FILE NOW",IF($K46<3,"DUE SOON","PENDING"))))) | AE46: =IF($A46="","",IF($A46<=COUNTIF(permit_calc!$L$3:$L$144,1),"OVF","LDG")) | AF46: =IF($AE46="","",IF($AE46="OVF","",$A46-COUNTIF(permit_calc!$L$3:$L$144,1)))
A47: =IF(ROW()-29>COUNTIF(permit_calc!$L$3:$L$144,1)+COUNTA($G$18:$G$25),"",ROW()-29) | B47: =IF($A47="","",IF($AE47="OVF",INDEX(permit_calc!$B$3:$B$144,MATCH($A47,permit_calc!$N$3:$N$144,0)),IFERROR(INDEX(countries!$B:$B,MATCH($C47,countries!$D:$D,0)),$C47))) | C47: {=IF($A47="","",IF($AE47="OVF",INDEX(permit_calc!$A$3:$A$144,MATCH($A47,permit_calc!$N$3:$N$144,0)),INDEX($U$18:$U$25,$AF47)))} | D47: =IF($A47="","",$AE47) | E47: {=IF($A47="","",IF($AE47="OVF","",INDEX($G$18:$G$25,$AF47)))} | F47: {=IF($A47="","",IF($AE47="OVF",INDEX(permit_calc!$M$3:$M$144,MATCH($A47,permit_calc!$N$3:$N$144,0)),INDEX($A$18:$A$25,$AF47)))} | G47: JTL | H47: {=IF($A47="","",IF($AE47="OVF",INDEX($E$18:$E$25,INDEX(permit_calc!$O$3:$O$144,MATCH($A47,permit_calc!$N$3:$N$144,0)))+INDEX($F$18:$F$25,INDEX(permit_calc!$O$3:$O$144,MATCH($A47,permit_calc!$N$3:$N$144,0))),INDEX($L$18:$L$25,$AF47)+INDEX($M$18:$M$25,$AF47)))} | I47: =IF($A47="","",IFERROR(IF(INDEX(countries!$I:$I,MATCH($C47,countries!$D:$D,0))=0,$B$12,INDEX(countries!$I:$I,MATCH($C47,countries!$D:$D,0))),$B$12)) | J47: =IF($A47="","",$H47-$I47/24) | K47: =IF($A47="","",ROUND($J47-NOW(),1)) | L47: =IF($A47="","",IF($AE47="OVF",IFERROR(INDEX(countries!$G:$G,MATCH($C47,countries!$D:$D,0)),"VERIFY"),IFERROR(INDEX(countries!$H:$H,MATCH($C47,countries!$D:$D,0)),"VERIFY"))) | M47: =IF($A47="","",IF(OR(UPPER($G47)="OWN",UPPER($G47)="EXCLUDED"),"CLIENT ARRANGING",IF($K47<0,"OVERDUE",IF($K47<1,"URGENT - FILE NOW",IF($K47<3,"DUE SOON","PENDING"))))) | AE47: =IF($A47="","",IF($A47<=COUNTIF(permit_calc!$L$3:$L$144,1),"OVF","LDG")) | AF47: =IF($AE47="","",IF($AE47="OVF","",$A47-COUNTIF(permit_calc!$L$3:$L$144,1)))
A48: =IF(ROW()-29>COUNTIF(permit_calc!$L$3:$L$144,1)+COUNTA($G$18:$G$25),"",ROW()-29) | B48: =IF($A48="","",IF($AE48="OVF",INDEX(permit_calc!$B$3:$B$144,MATCH($A48,permit_calc!$N$3:$N$144,0)),IFERROR(INDEX(countries!$B:$B,MATCH($C48,countries!$D:$D,0)),$C48))) | C48: {=IF($A48="","",IF($AE48="OVF",INDEX(permit_calc!$A$3:$A$144,MATCH($A48,permit_calc!$N$3:$N$144,0)),INDEX($U$18:$U$25,$AF48)))} | D48: =IF($A48="","",$AE48) | E48: {=IF($A48="","",IF($AE48="OVF","",INDEX($G$18:$G$25,$AF48)))} | F48: {=IF($A48="","",IF($AE48="OVF",INDEX(permit_calc!$M$3:$M$144,MATCH($A48,permit_calc!$N$3:$N$144,0)),INDEX($A$18:$A$25,$AF48)))} | G48: JTL | H48: {=IF($A48="","",IF($AE48="OVF",INDEX($E$18:$E$25,INDEX(permit_calc!$O$3:$O$144,MATCH($A48,permit_calc!$N$3:$N$144,0)))+INDEX($F$18:$F$25,INDEX(permit_calc!$O$3:$O$144,MATCH($A48,permit_calc!$N$3:$N$144,0))),INDEX($L$18:$L$25,$AF48)+INDEX($M$18:$M$25,$AF48)))} | I48: =IF($A48="","",IFERROR(IF(INDEX(countries!$I:$I,MATCH($C48,countries!$D:$D,0))=0,$B$12,INDEX(countries!$I:$I,MATCH($C48,countries!$D:$D,0))),$B$12)) | J48: =IF($A48="","",$H48-$I48/24) | K48: =IF($A48="","",ROUND($J48-NOW(),1)) | L48: =IF($A48="","",IF($AE48="OVF",IFERROR(INDEX(countries!$G:$G,MATCH($C48,countries!$D:$D,0)),"VERIFY"),IFERROR(INDEX(countries!$H:$H,MATCH($C48,countries!$D:$D,0)),"VERIFY"))) | M48: =IF($A48="","",IF(OR(UPPER($G48)="OWN",UPPER($G48)="EXCLUDED"),"CLIENT ARRANGING",IF($K48<0,"OVERDUE",IF($K48<1,"URGENT - FILE NOW",IF($K48<3,"DUE SOON","PENDING"))))) | AE48: =IF($A48="","",IF($A48<=COUNTIF(permit_calc!$L$3:$L$144,1),"OVF","LDG")) | AF48: =IF($AE48="","",IF($AE48="OVF","",$A48-COUNTIF(permit_calc!$L$3:$L$144,1)))
A49: =IF(ROW()-29>COUNTIF(permit_calc!$L$3:$L$144,1)+COUNTA($G$18:$G$25),"",ROW()-29) | B49: =IF($A49="","",IF($AE49="OVF",INDEX(permit_calc!$B$3:$B$144,MATCH($A49,permit_calc!$N$3:$N$144,0)),IFERROR(INDEX(countries!$B:$B,MATCH($C49,countries!$D:$D,0)),$C49))) | C49: {=IF($A49="","",IF($AE49="OVF",INDEX(permit_calc!$A$3:$A$144,MATCH($A49,permit_calc!$N$3:$N$144,0)),INDEX($U$18:$U$25,$AF49)))} | D49: =IF($A49="","",$AE49) | E49: {=IF($A49="","",IF($AE49="OVF","",INDEX($G$18:$G$25,$AF49)))} | F49: {=IF($A49="","",IF($AE49="OVF",INDEX(permit_calc!$M$3:$M$144,MATCH($A49,permit_calc!$N$3:$N$144,0)),INDEX($A$18:$A$25,$AF49)))} | G49: JTL | H49: {=IF($A49="","",IF($AE49="OVF",INDEX($E$18:$E$25,INDEX(permit_calc!$O$3:$O$144,MATCH($A49,permit_calc!$N$3:$N$144,0)))+INDEX($F$18:$F$25,INDEX(permit_calc!$O$3:$O$144,MATCH($A49,permit_calc!$N$3:$N$144,0))),INDEX($L$18:$L$25,$AF49)+INDEX($M$18:$M$25,$AF49)))} | I49: =IF($A49="","",IFERROR(IF(INDEX(countries!$I:$I,MATCH($C49,countries!$D:$D,0))=0,$B$12,INDEX(countries!$I:$I,MATCH($C49,countries!$D:$D,0))),$B$12)) | J49: =IF($A49="","",$H49-$I49/24) | K49: =IF($A49="","",ROUND($J49-NOW(),1)) | L49: =IF($A49="","",IF($AE49="OVF",IFERROR(INDEX(countries!$G:$G,MATCH($C49,countries!$D:$D,0)),"VERIFY"),IFERROR(INDEX(countries!$H:$H,MATCH($C49,countries!$D:$D,0)),"VERIFY"))) | M49: =IF($A49="","",IF(OR(UPPER($G49)="OWN",UPPER($G49)="EXCLUDED"),"CLIENT ARRANGING",IF($K49<0,"OVERDUE",IF($K49<1,"URGENT - FILE NOW",IF($K49<3,"DUE SOON","PENDING"))))) | AE49: =IF($A49="","",IF($A49<=COUNTIF(permit_calc!$L$3:$L$144,1),"OVF","LDG")) | AF49: =IF($AE49="","",IF($AE49="OVF","",$A49-COUNTIF(permit_calc!$L$3:$L$144,1)))
... A53: =IF(ROW()-29>COUNTIF(permit_calc!$L$3:$L$144,1)+COUNTA($G$18:$G$25),"",ROW()-29) | B53: =IF($A53="","",IF($AE53="OVF",INDEX(permit_calc!$B$3:$B$144,MATCH($A53,permit_calc!$N$3:$N$144,0)),IFERROR(INDEX(countries!$B:$B,MATCH($C53,countries!$D:$D,0)),$C53))) | C53: {=IF($A53="","",IF($AE53="OVF",INDEX(permit_calc!$A$3:$A$144,MATCH($A53,permit_calc!$N$3:$N$144,0)),INDEX($U$18:$U$25,$AF53)))} | D53: =IF($A53="","",$AE53) | E53: {=IF($A53="","",IF($AE53="OVF","",INDEX($G$18:$G$25,$AF53)))} | F53: {=IF($A53="","",IF($AE53="OVF",INDEX(permit_calc!$M$3:$M$144,MATCH($A53,permit_calc!$N$3:$N$144,0)),INDEX($A$18:$A$25,$AF53)))} | G53: JTL | H53: {=IF($A53="","",IF($AE53="OVF",INDEX($E$18:$E$25,INDEX(permit_calc!$O$3:$O$144,MATCH($A53,permit_calc!$N$3:$N$144,0)))+INDEX($F$18:$F$25,INDEX(permit_calc!$O$3:$O$144,MATCH($A53,permit_calc!$N$3:$N$144,0))),INDEX($L$18:$L$25,$AF53)+INDEX($M$18:$M$25,$AF53)))} | I53: =IF($A53="","",IFERROR(IF(INDEX(countries!$I:$I,MATCH($C53,countries!$D:$D,0))=0,$B$12,INDEX(countries!$I:$I,MATCH($C53,countries!$D:$D,0))),$B$12)) | J53: =IF($A53="","",$H53-$I53/24) | K53: =IF($A53="","",ROUND($J53-NOW(),1)) | L53: =IF($A53="","",IF($AE53="OVF",IFERROR(INDEX(countries!$G:$G,MATCH($C53,countries!$D:$D,0)),"VERIFY"),IFERROR(INDEX(countries!$H:$H,MATCH($C53,countries!$D:$D,0)),"VERIFY"))) | M53: =IF($A53="","",IF(OR(UPPER($G53)="OWN",UPPER($G53)="EXCLUDED"),"CLIENT ARRANGING",IF($K53<0,"OVERDUE",IF($K53<1,"URGENT - FILE NOW",IF($K53<3,"DUE SOON","PENDING"))))) | AE53: =IF($A53="","",IF($A53<=COUNTIF(permit_calc!$L$3:$L$144,1),"OVF","LDG")) | AF53: =IF($AE53="","",IF($AE53="OVF","",$A53-COUNTIF(permit_calc!$L$3:$L$144,1)))
A54: =IF(ROW()-29>COUNTIF(permit_calc!$L$3:$L$144,1)+COUNTA($G$18:$G$25),"",ROW()-29) | B54: =IF($A54="","",IF($AE54="OVF",INDEX(permit_calc!$B$3:$B$144,MATCH($A54,permit_calc!$N$3:$N$144,0)),IFERROR(INDEX(countries!$B:$B,MATCH($C54,countries!$D:$D,0)),$C54))) | C54: {=IF($A54="","",IF($AE54="OVF",INDEX(permit_calc!$A$3:$A$144,MATCH($A54,permit_calc!$N$3:$N$144,0)),INDEX($U$18:$U$25,$AF54)))} | D54: =IF($A54="","",$AE54) | E54: {=IF($A54="","",IF($AE54="OVF","",INDEX($G$18:$G$25,$AF54)))} | F54: {=IF($A54="","",IF($AE54="OVF",INDEX(permit_calc!$M$3:$M$144,MATCH($A54,permit_calc!$N$3:$N$144,0)),INDEX($A$18:$A$25,$AF54)))} | H54: {=IF($A54="","",IF($AE54="OVF",INDEX($E$18:$E$25,INDEX(permit_calc!$O$3:$O$144,MATCH($A54,permit_calc!$N$3:$N$144,0)))+INDEX($F$18:$F$25,INDEX(permit_calc!$O$3:$O$144,MATCH($A54,permit_calc!$N$3:$N$144,0))),INDEX($L$18:$L$25,$AF54)+INDEX($M$18:$M$25,$AF54)))} | I54: =IF($A54="","",IFERROR(IF(INDEX(countries!$I:$I,MATCH($C54,countries!$D:$D,0))=0,$B$12,INDEX(countries!$I:$I,MATCH($C54,countries!$D:$D,0))),$B$12)) | J54: =IF($A54="","",$H54-$I54/24) | K54: =IF($A54="","",ROUND($J54-NOW(),1)) | L54: =IF($A54="","",IF($AE54="OVF",IFERROR(INDEX(countries!$G:$G,MATCH($C54,countries!$D:$D,0)),"VERIFY"),IFERROR(INDEX(countries!$H:$H,MATCH($C54,countries!$D:$D,0)),"VERIFY"))) | M54: =IF($A54="","",IF(OR(UPPER($G54)="OWN",UPPER($G54)="EXCLUDED"),"CLIENT ARRANGING",IF($K54<0,"OVERDUE",IF($K54<1,"URGENT - FILE NOW",IF($K54<3,"DUE SOON","PENDING"))))) | AE54: =IF($A54="","",IF($A54<=COUNTIF(permit_calc!$L$3:$L$144,1),"OVF","LDG")) | AF54: =IF($AE54="","",IF($AE54="OVF","",$A54-COUNTIF(permit_calc!$L$3:$L$144,1)))
A55: =IF(ROW()-29>COUNTIF(permit_calc!$L$3:$L$144,1)+COUNTA($G$18:$G$25),"",ROW()-29) | B55: =IF($A55="","",IF($AE55="OVF",INDEX(permit_calc!$B$3:$B$144,MATCH($A55,permit_calc!$N$3:$N$144,0)),IFERROR(INDEX(countries!$B:$B,MATCH($C55,countries!$D:$D,0)),$C55))) | C55: {=IF($A55="","",IF($AE55="OVF",INDEX(permit_calc!$A$3:$A$144,MATCH($A55,permit_calc!$N$3:$N$144,0)),INDEX($U$18:$U$25,$AF55)))} | D55: =IF($A55="","",$AE55) | E55: {=IF($A55="","",IF($AE55="OVF","",INDEX($G$18:$G$25,$AF55)))} | F55: {=IF($A55="","",IF($AE55="OVF",INDEX(permit_calc!$M$3:$M$144,MATCH($A55,permit_calc!$N$3:$N$144,0)),INDEX($A$18:$A$25,$AF55)))} | H55: {=IF($A55="","",IF($AE55="OVF",INDEX($E$18:$E$25,INDEX(permit_calc!$O$3:$O$144,MATCH($A55,permit_calc!$N$3:$N$144,0)))+INDEX($F$18:$F$25,INDEX(permit_calc!$O$3:$O$144,MATCH($A55,permit_calc!$N$3:$N$144,0))),INDEX($L$18:$L$25,$AF55)+INDEX($M$18:$M$25,$AF55)))} | I55: =IF($A55="","",IFERROR(IF(INDEX(countries!$I:$I,MATCH($C55,countries!$D:$D,0))=0,$B$12,INDEX(countries!$I:$I,MATCH($C55,countries!$D:$D,0))),$B$12)) | J55: =IF($A55="","",$H55-$I55/24) | K55: =IF($A55="","",ROUND($J55-NOW(),1)) | L55: =IF($A55="","",IF($AE55="OVF",IFERROR(INDEX(countries!$G:$G,MATCH($C55,countries!$D:$D,0)),"VERIFY"),IFERROR(INDEX(countries!$H:$H,MATCH($C55,countries!$D:$D,0)),"VERIFY"))) | M55: =IF($A55="","",IF(OR(UPPER($G55)="OWN",UPPER($G55)="EXCLUDED"),"CLIENT ARRANGING",IF($K55<0,"OVERDUE",IF($K55<1,"URGENT - FILE NOW",IF($K55<3,"DUE SOON","PENDING"))))) | AE55: =IF($A55="","",IF($A55<=COUNTIF(permit_calc!$L$3:$L$144,1),"OVF","LDG")) | AF55: =IF($AE55="","",IF($AE55="OVF","",$A55-COUNTIF(permit_calc!$L$3:$L$144,1)))
A56: =IF(ROW()-29>COUNTIF(permit_calc!$L$3:$L$144,1)+COUNTA($G$18:$G$25),"",ROW()-29) | B56: =IF($A56="","",IF($AE56="OVF",INDEX(permit_calc!$B$3:$B$144,MATCH($A56,permit_calc!$N$3:$N$144,0)),IFERROR(INDEX(countries!$B:$B,MATCH($C56,countries!$D:$D,0)),$C56))) | C56: {=IF($A56="","",IF($AE56="OVF",INDEX(permit_calc!$A$3:$A$144,MATCH($A56,permit_calc!$N$3:$N$144,0)),INDEX($U$18:$U$25,$AF56)))} | D56: =IF($A56="","",$AE56) | E56: {=IF($A56="","",IF($AE56="OVF","",INDEX($G$18:$G$25,$AF56)))} | F56: {=IF($A56="","",IF($AE56="OVF",INDEX(permit_calc!$M$3:$M$144,MATCH($A56,permit_calc!$N$3:$N$144,0)),INDEX($A$18:$A$25,$AF56)))} | H56: {=IF($A56="","",IF($AE56="OVF",INDEX($E$18:$E$25,INDEX(permit_calc!$O$3:$O$144,MATCH($A56,permit_calc!$N$3:$N$144,0)))+INDEX($F$18:$F$25,INDEX(permit_calc!$O$3:$O$144,MATCH($A56,permit_calc!$N$3:$N$144,0))),INDEX($L$18:$L$25,$AF56)+INDEX($M$18:$M$25,$AF56)))} | I56: =IF($A56="","",IFERROR(IF(INDEX(countries!$I:$I,MATCH($C56,countries!$D:$D,0))=0,$B$12,INDEX(countries!$I:$I,MATCH($C56,countries!$D:$D,0))),$B$12)) | J56: =IF($A56="","",$H56-$I56/24) | K56: =IF($A56="","",ROUND($J56-NOW(),1)) | L56: =IF($A56="","",IF($AE56="OVF",IFERROR(INDEX(countries!$G:$G,MATCH($C56,countries!$D:$D,0)),"VERIFY"),IFERROR(INDEX(countries!$H:$H,MATCH($C56,countries!$D:$D,0)),"VERIFY"))) | M56: =IF($A56="","",IF(OR(UPPER($G56)="OWN",UPPER($G56)="EXCLUDED"),"CLIENT ARRANGING",IF($K56<0,"OVERDUE",IF($K56<1,"URGENT - FILE NOW",IF($K56<3,"DUE SOON","PENDING"))))) | AE56: =IF($A56="","",IF($A56<=COUNTIF(permit_calc!$L$3:$L$144,1),"OVF","LDG")) | AF56: =IF($AE56="","",IF($AE56="OVF","",$A56-COUNTIF(permit_calc!$L$3:$L$144,1)))
A57: =IF(ROW()-29>COUNTIF(permit_calc!$L$3:$L$144,1)+COUNTA($G$18:$G$25),"",ROW()-29) | B57: =IF($A57="","",IF($AE57="OVF",INDEX(permit_calc!$B$3:$B$144,MATCH($A57,permit_calc!$N$3:$N$144,0)),IFERROR(INDEX(countries!$B:$B,MATCH($C57,countries!$D:$D,0)),$C57))) | C57: {=IF($A57="","",IF($AE57="OVF",INDEX(permit_calc!$A$3:$A$144,MATCH($A57,permit_calc!$N$3:$N$144,0)),INDEX($U$18:$U$25,$AF57)))} | D57: =IF($A57="","",$AE57) | E57: {=IF($A57="","",IF($AE57="OVF","",INDEX($G$18:$G$25,$AF57)))} | F57: {=IF($A57="","",IF($AE57="OVF",INDEX(permit_calc!$M$3:$M$144,MATCH($A57,permit_calc!$N$3:$N$144,0)),INDEX($A$18:$A$25,$AF57)))} | H57: {=IF($A57="","",IF($AE57="OVF",INDEX($E$18:$E$25,INDEX(permit_calc!$O$3:$O$144,MATCH($A57,permit_calc!$N$3:$N$144,0)))+INDEX($F$18:$F$25,INDEX(permit_calc!$O$3:$O$144,MATCH($A57,permit_calc!$N$3:$N$144,0))),INDEX($L$18:$L$25,$AF57)+INDEX($M$18:$M$25,$AF57)))} | I57: =IF($A57="","",IFERROR(IF(INDEX(countries!$I:$I,MATCH($C57,countries!$D:$D,0))=0,$B$12,INDEX(countries!$I:$I,MATCH($C57,countries!$D:$D,0))),$B$12)) | J57: =IF($A57="","",$H57-$I57/24) | K57: =IF($A57="","",ROUND($J57-NOW(),1)) | L57: =IF($A57="","",IF($AE57="OVF",IFERROR(INDEX(countries!$G:$G,MATCH($C57,countries!$D:$D,0)),"VERIFY"),IFERROR(INDEX(countries!$H:$H,MATCH($C57,countries!$D:$D,0)),"VERIFY"))) | M57: =IF($A57="","",IF(OR(UPPER($G57)="OWN",UPPER($G57)="EXCLUDED"),"CLIENT ARRANGING",IF($K57<0,"OVERDUE",IF($K57<1,"URGENT - FILE NOW",IF($K57<3,"DUE SOON","PENDING"))))) | AE57: =IF($A57="","",IF($A57<=COUNTIF(permit_calc!$L$3:$L$144,1),"OVF","LDG")) | AF57: =IF($AE57="","",IF($AE57="OVF","",$A57-COUNTIF(permit_calc!$L$3:$L$144,1)))
A58: =IF(ROW()-29>COUNTIF(permit_calc!$L$3:$L$144,1)+COUNTA($G$18:$G$25),"",ROW()-29) | B58: =IF($A58="","",IF($AE58="OVF",INDEX(permit_calc!$B$3:$B$144,MATCH($A58,permit_calc!$N$3:$N$144,0)),IFERROR(INDEX(countries!$B:$B,MATCH($C58,countries!$D:$D,0)),$C58))) | C58: {=IF($A58="","",IF($AE58="OVF",INDEX(permit_calc!$A$3:$A$144,MATCH($A58,permit_calc!$N$3:$N$144,0)),INDEX($U$18:$U$25,$AF58)))} | D58: =IF($A58="","",$AE58) | E58: {=IF($A58="","",IF($AE58="OVF","",INDEX($G$18:$G$25,$AF58)))} | F58: {=IF($A58="","",IF($AE58="OVF",INDEX(permit_calc!$M$3:$M$144,MATCH($A58,permit_calc!$N$3:$N$144,0)),INDEX($A$18:$A$25,$AF58)))} | H58: {=IF($A58="","",IF($AE58="OVF",INDEX($E$18:$E$25,INDEX(permit_calc!$O$3:$O$144,MATCH($A58,permit_calc!$N$3:$N$144,0)))+INDEX($F$18:$F$25,INDEX(permit_calc!$O$3:$O$144,MATCH($A58,permit_calc!$N$3:$N$144,0))),INDEX($L$18:$L$25,$AF58)+INDEX($M$18:$M$25,$AF58)))} | I58: =IF($A58="","",IFERROR(IF(INDEX(countries!$I:$I,MATCH($C58,countries!$D:$D,0))=0,$B$12,INDEX(countries!$I:$I,MATCH($C58,countries!$D:$D,0))),$B$12)) | J58: =IF($A58="","",$H58-$I58/24) | K58: =IF($A58="","",ROUND($J58-NOW(),1)) | L58: =IF($A58="","",IF($AE58="OVF",IFERROR(INDEX(countries!$G:$G,MATCH($C58,countries!$D:$D,0)),"VERIFY"),IFERROR(INDEX(countries!$H:$H,MATCH($C58,countries!$D:$D,0)),"VERIFY"))) | M58: =IF($A58="","",IF(OR(UPPER($G58)="OWN",UPPER($G58)="EXCLUDED"),"CLIENT ARRANGING",IF($K58<0,"OVERDUE",IF($K58<1,"URGENT - FILE NOW",IF($K58<3,"DUE SOON","PENDING"))))) | AE58: =IF($A58="","",IF($A58<=COUNTIF(permit_calc!$L$3:$L$144,1),"OVF","LDG")) | AF58: =IF($AE58="","",IF($AE58="OVF","",$A58-COUNTIF(permit_calc!$L$3:$L$144,1)))
A59: =IF(ROW()-29>COUNTIF(permit_calc!$L$3:$L$144,1)+COUNTA($G$18:$G$25),"",ROW()-29) | B59: =IF($A59="","",IF($AE59="OVF",INDEX(permit_calc!$B$3:$B$144,MATCH($A59,permit_calc!$N$3:$N$144,0)),IFERROR(INDEX(countries!$B:$B,MATCH($C59,countries!$D:$D,0)),$C59))) | C59: {=IF($A59="","",IF($AE59="OVF",INDEX(permit_calc!$A$3:$A$144,MATCH($A59,permit_calc!$N$3:$N$144,0)),INDEX($U$18:$U$25,$AF59)))} | D59: =IF($A59="","",$AE59) | E59: {=IF($A59="","",IF($AE59="OVF","",INDEX($G$18:$G$25,$AF59)))} | F59: {=IF($A59="","",IF($AE59="OVF",INDEX(permit_calc!$M$3:$M$144,MATCH($A59,permit_calc!$N$3:$N$144,0)),INDEX($A$18:$A$25,$AF59)))} | H59: {=IF($A59="","",IF($AE59="OVF",INDEX($E$18:$E$25,INDEX(permit_calc!$O$3:$O$144,MATCH($A59,permit_calc!$N$3:$N$144,0)))+INDEX($F$18:$F$25,INDEX(permit_calc!$O$3:$O$144,MATCH($A59,permit_calc!$N$3:$N$144,0))),INDEX($L$18:$L$25,$AF59)+INDEX($M$18:$M$25,$AF59)))} | I59: =IF($A59="","",IFERROR(IF(INDEX(countries!$I:$I,MATCH($C59,countries!$D:$D,0))=0,$B$12,INDEX(countries!$I:$I,MATCH($C59,countries!$D:$D,0))),$B$12)) | J59: =IF($A59="","",$H59-$I59/24) | K59: =IF($A59="","",ROUND($J59-NOW(),1)) | L59: =IF($A59="","",IF($AE59="OVF",IFERROR(INDEX(countries!$G:$G,MATCH($C59,countries!$D:$D,0)),"VERIFY"),IFERROR(INDEX(countries!$H:$H,MATCH($C59,countries!$D:$D,0)),"VERIFY"))) | M59: =IF($A59="","",IF(OR(UPPER($G59)="OWN",UPPER($G59)="EXCLUDED"),"CLIENT ARRANGING",IF($K59<0,"OVERDUE",IF($K59<1,"URGENT - FILE NOW",IF($K59<3,"DUE SOON","PENDING"))))) | AE59: =IF($A59="","",IF($A59<=COUNTIF(permit_calc!$L$3:$L$144,1),"OVF","LDG")) | AF59: =IF($AE59="","",IF($AE59="OVF","",$A59-COUNTIF(permit_calc!$L$3:$L$144,1)))
A60: =IF(ROW()-29>COUNTIF(permit_calc!$L$3:$L$144,1)+COUNTA($G$18:$G$25),"",ROW()-29) | B60: =IF($A60="","",IF($AE60="OVF",INDEX(permit_calc!$B$3:$B$144,MATCH($A60,permit_calc!$N$3:$N$144,0)),IFERROR(INDEX(countries!$B:$B,MATCH($C60,countries!$D:$D,0)),$C60))) | C60: {=IF($A60="","",IF($AE60="OVF",INDEX(permit_calc!$A$3:$A$144,MATCH($A60,permit_calc!$N$3:$N$144,0)),INDEX($U$18:$U$25,$AF60)))} | D60: =IF($A60="","",$AE60) | E60: {=IF($A60="","",IF($AE60="OVF","",INDEX($G$18:$G$25,$AF60)))} | F60: {=IF($A60="","",IF($AE60="OVF",INDEX(permit_calc!$M$3:$M$144,MATCH($A60,permit_calc!$N$3:$N$144,0)),INDEX($A$18:$A$25,$AF60)))} | H60: {=IF($A60="","",IF($AE60="OVF",INDEX($E$18:$E$25,INDEX(permit_calc!$O$3:$O$144,MATCH($A60,permit_calc!$N$3:$N$144,0)))+INDEX($F$18:$F$25,INDEX(permit_calc!$O$3:$O$144,MATCH($A60,permit_calc!$N$3:$N$144,0))),INDEX($L$18:$L$25,$AF60)+INDEX($M$18:$M$25,$AF60)))} | I60: =IF($A60="","",IFERROR(IF(INDEX(countries!$I:$I,MATCH($C60,countries!$D:$D,0))=0,$B$12,INDEX(countries!$I:$I,MATCH($C60,countries!$D:$D,0))),$B$12)) | J60: =IF($A60="","",$H60-$I60/24) | K60: =IF($A60="","",ROUND($J60-NOW(),1)) | L60: =IF($A60="","",IF($AE60="OVF",IFERROR(INDEX(countries!$G:$G,MATCH($C60,countries!$D:$D,0)),"VERIFY"),IFERROR(INDEX(countries!$H:$H,MATCH($C60,countries!$D:$D,0)),"VERIFY"))) | M60: =IF($A60="","",IF(OR(UPPER($G60)="OWN",UPPER($G60)="EXCLUDED"),"CLIENT ARRANGING",IF($K60<0,"OVERDUE",IF($K60<1,"URGENT - FILE NOW",IF($K60<3,"DUE SOON","PENDING"))))) | AE60: =IF($A60="","",IF($A60<=COUNTIF(permit_calc!$L$3:$L$144,1),"OVF","LDG")) | AF60: =IF($AE60="","",IF($AE60="OVF","",$A60-COUNTIF(permit_calc!$L$3:$L$144,1)))
A61: =IF(ROW()-29>COUNTIF(permit_calc!$L$3:$L$144,1)+COUNTA($G$18:$G$25),"",ROW()-29) | B61: =IF($A61="","",IF($AE61="OVF",INDEX(permit_calc!$B$3:$B$144,MATCH($A61,permit_calc!$N$3:$N$144,0)),IFERROR(INDEX(countries!$B:$B,MATCH($C61,countries!$D:$D,0)),$C61))) | C61: {=IF($A61="","",IF($AE61="OVF",INDEX(permit_calc!$A$3:$A$144,MATCH($A61,permit_calc!$N$3:$N$144,0)),INDEX($U$18:$U$25,$AF61)))} | D61: =IF($A61="","",$AE61) | E61: {=IF($A61="","",IF($AE61="OVF","",INDEX($G$18:$G$25,$AF61)))} | F61: {=IF($A61="","",IF($AE61="OVF",INDEX(permit_calc!$M$3:$M$144,MATCH($A61,permit_calc!$N$3:$N$144,0)),INDEX($A$18:$A$25,$AF61)))} | H61: {=IF($A61="","",IF($AE61="OVF",INDEX($E$18:$E$25,INDEX(permit_calc!$O$3:$O$144,MATCH($A61,permit_calc!$N$3:$N$144,0)))+INDEX($F$18:$F$25,INDEX(permit_calc!$O$3:$O$144,MATCH($A61,permit_calc!$N$3:$N$144,0))),INDEX($L$18:$L$25,$AF61)+INDEX($M$18:$M$25,$AF61)))} | I61: =IF($A61="","",IFERROR(IF(INDEX(countries!$I:$I,MATCH($C61,countries!$D:$D,0))=0,$B$12,INDEX(countries!$I:$I,MATCH($C61,countries!$D:$D,0))),$B$12)) | J61: =IF($A61="","",$H61-$I61/24) | K61: =IF($A61="","",ROUND($J61-NOW(),1)) | L61: =IF($A61="","",IF($AE61="OVF",IFERROR(INDEX(countries!$G:$G,MATCH($C61,countries!$D:$D,0)),"VERIFY"),IFERROR(INDEX(countries!$H:$H,MATCH($C61,countries!$D:$D,0)),"VERIFY"))) | M61: =IF($A61="","",IF(OR(UPPER($G61)="OWN",UPPER($G61)="EXCLUDED"),"CLIENT ARRANGING",IF($K61<0,"OVERDUE",IF($K61<1,"URGENT - FILE NOW",IF($K61<3,"DUE SOON","PENDING"))))) | AE61: =IF($A61="","",IF($A61<=COUNTIF(permit_calc!$L$3:$L$144,1),"OVF","LDG")) | AF61: =IF($AE61="","",IF($AE61="OVF","",$A61-COUNTIF(permit_calc!$L$3:$L$144,1)))
A62: =IF(ROW()-29>COUNTIF(permit_calc!$L$3:$L$144,1)+COUNTA($G$18:$G$25),"",ROW()-29) | B62: =IF($A62="","",IF($AE62="OVF",INDEX(permit_calc!$B$3:$B$144,MATCH($A62,permit_calc!$N$3:$N$144,0)),IFERROR(INDEX(countries!$B:$B,MATCH($C62,countries!$D:$D,0)),$C62))) | C62: {=IF($A62="","",IF($AE62="OVF",INDEX(permit_calc!$A$3:$A$144,MATCH($A62,permit_calc!$N$3:$N$144,0)),INDEX($U$18:$U$25,$AF62)))} | D62: =IF($A62="","",$AE62) | E62: {=IF($A62="","",IF($AE62="OVF","",INDEX($G$18:$G$25,$AF62)))} | F62: {=IF($A62="","",IF($AE62="OVF",INDEX(permit_calc!$M$3:$M$144,MATCH($A62,permit_calc!$N$3:$N$144,0)),INDEX($A$18:$A$25,$AF62)))} | H62: {=IF($A62="","",IF($AE62="OVF",INDEX($E$18:$E$25,INDEX(permit_calc!$O$3:$O$144,MATCH($A62,permit_calc!$N$3:$N$144,0)))+INDEX($F$18:$F$25,INDEX(permit_calc!$O$3:$O$144,MATCH($A62,permit_calc!$N$3:$N$144,0))),INDEX($L$18:$L$25,$AF62)+INDEX($M$18:$M$25,$AF62)))} | I62: =IF($A62="","",IFERROR(IF(INDEX(countries!$I:$I,MATCH($C62,countries!$D:$D,0))=0,$B$12,INDEX(countries!$I:$I,MATCH($C62,countries!$D:$D,0))),$B$12)) | J62: =IF($A62="","",$H62-$I62/24) | K62: =IF($A62="","",ROUND($J62-NOW(),1)) | L62: =IF($A62="","",IF($AE62="OVF",IFERROR(INDEX(countries!$G:$G,MATCH($C62,countries!$D:$D,0)),"VERIFY"),IFERROR(INDEX(countries!$H:$H,MATCH($C62,countries!$D:$D,0)),"VERIFY"))) | M62: =IF($A62="","",IF(OR(UPPER($G62)="OWN",UPPER($G62)="EXCLUDED"),"CLIENT ARRANGING",IF($K62<0,"OVERDUE",IF($K62<1,"URGENT - FILE NOW",IF($K62<3,"DUE SOON","PENDING"))))) | AE62: =IF($A62="","",IF($A62<=COUNTIF(permit_calc!$L$3:$L$144,1),"OVF","LDG")) | AF62: =IF($AE62="","",IF($AE62="OVF","",$A62-COUNTIF(permit_calc!$L$3:$L$144,1)))
A63: =IF(ROW()-29>COUNTIF(permit_calc!$L$3:$L$144,1)+COUNTA($G$18:$G$25),"",ROW()-29) | B63: =IF($A63="","",IF($AE63="OVF",INDEX(permit_calc!$B$3:$B$144,MATCH($A63,permit_calc!$N$3:$N$144,0)),IFERROR(INDEX(countries!$B:$B,MATCH($C63,countries!$D:$D,0)),$C63))) | C63: {=IF($A63="","",IF($AE63="OVF",INDEX(permit_calc!$A$3:$A$144,MATCH($A63,permit_calc!$N$3:$N$144,0)),INDEX($U$18:$U$25,$AF63)))} | D63: =IF($A63="","",$AE63) | E63: {=IF($A63="","",IF($AE63="OVF","",INDEX($G$18:$G$25,$AF63)))} | F63: {=IF($A63="","",IF($AE63="OVF",INDEX(permit_calc!$M$3:$M$144,MATCH($A63,permit_calc!$N$3:$N$144,0)),INDEX($A$18:$A$25,$AF63)))} | H63: {=IF($A63="","",IF($AE63="OVF",INDEX($E$18:$E$25,INDEX(permit_calc!$O$3:$O$144,MATCH($A63,permit_calc!$N$3:$N$144,0)))+INDEX($F$18:$F$25,INDEX(permit_calc!$O$3:$O$144,MATCH($A63,permit_calc!$N$3:$N$144,0))),INDEX($L$18:$L$25,$AF63)+INDEX($M$18:$M$25,$AF63)))} | I63: =IF($A63="","",IFERROR(IF(INDEX(countries!$I:$I,MATCH($C63,countries!$D:$D,0))=0,$B$12,INDEX(countries!$I:$I,MATCH($C63,countries!$D:$D,0))),$B$12)) | J63: =IF($A63="","",$H63-$I63/24) | K63: =IF($A63="","",ROUND($J63-NOW(),1)) | L63: =IF($A63="","",IF($AE63="OVF",IFERROR(INDEX(countries!$G:$G,MATCH($C63,countries!$D:$D,0)),"VERIFY"),IFERROR(INDEX(countries!$H:$H,MATCH($C63,countries!$D:$D,0)),"VERIFY"))) | M63: =IF($A63="","",IF(OR(UPPER($G63)="OWN",UPPER($G63)="EXCLUDED"),"CLIENT ARRANGING",IF($K63<0,"OVERDUE",IF($K63<1,"URGENT - FILE NOW",IF($K63<3,"DUE SOON","PENDING"))))) | AE63: =IF($A63="","",IF($A63<=COUNTIF(permit_calc!$L$3:$L$144,1),"OVF","LDG")) | AF63: =IF($AE63="","",IF($AE63="OVF","",$A63-COUNTIF(permit_calc!$L$3:$L$144,1)))
A64: =IF(ROW()-29>COUNTIF(permit_calc!$L$3:$L$144,1)+COUNTA($G$18:$G$25),"",ROW()-29) | B64: =IF($A64="","",IF($AE64="OVF",INDEX(permit_calc!$B$3:$B$144,MATCH($A64,permit_calc!$N$3:$N$144,0)),IFERROR(INDEX(countries!$B:$B,MATCH($C64,countries!$D:$D,0)),$C64))) | C64: {=IF($A64="","",IF($AE64="OVF",INDEX(permit_calc!$A$3:$A$144,MATCH($A64,permit_calc!$N$3:$N$144,0)),INDEX($U$18:$U$25,$AF64)))} | D64: =IF($A64="","",$AE64) | E64: {=IF($A64="","",IF($AE64="OVF","",INDEX($G$18:$G$25,$AF64)))} | F64: {=IF($A64="","",IF($AE64="OVF",INDEX(permit_calc!$M$3:$M$144,MATCH($A64,permit_calc!$N$3:$N$144,0)),INDEX($A$18:$A$25,$AF64)))} | H64: {=IF($A64="","",IF($AE64="OVF",INDEX($E$18:$E$25,INDEX(permit_calc!$O$3:$O$144,MATCH($A64,permit_calc!$N$3:$N$144,0)))+INDEX($F$18:$F$25,INDEX(permit_calc!$O$3:$O$144,MATCH($A64,permit_calc!$N$3:$N$144,0))),INDEX($L$18:$L$25,$AF64)+INDEX($M$18:$M$25,$AF64)))} | I64: =IF($A64="","",IFERROR(IF(INDEX(countries!$I:$I,MATCH($C64,countries!$D:$D,0))=0,$B$12,INDEX(countries!$I:$I,MATCH($C64,countries!$D:$D,0))),$B$12)) | J64: =IF($A64="","",$H64-$I64/24) | K64: =IF($A64="","",ROUND($J64-NOW(),1)) | L64: =IF($A64="","",IF($AE64="OVF",IFERROR(INDEX(countries!$G:$G,MATCH($C64,countries!$D:$D,0)),"VERIFY"),IFERROR(INDEX(countries!$H:$H,MATCH($C64,countries!$D:$D,0)),"VERIFY"))) | M64: =IF($A64="","",IF(OR(UPPER($G64)="OWN",UPPER($G64)="EXCLUDED"),"CLIENT ARRANGING",IF($K64<0,"OVERDUE",IF($K64<1,"URGENT - FILE NOW",IF($K64<3,"DUE SOON","PENDING"))))) | AE64: =IF($A64="","",IF($A64<=COUNTIF(permit_calc!$L$3:$L$144,1),"OVF","LDG")) | AF64: =IF($AE64="","",IF($AE64="OVF","",$A64-COUNTIF(permit_calc!$L$3:$L$144,1)))
A65: =IF(ROW()-29>COUNTIF(permit_calc!$L$3:$L$144,1)+COUNTA($G$18:$G$25),"",ROW()-29) | B65: =IF($A65="","",IF($AE65="OVF",INDEX(permit_calc!$B$3:$B$144,MATCH($A65,permit_calc!$N$3:$N$144,0)),IFERROR(INDEX(countries!$B:$B,MATCH($C65,countries!$D:$D,0)),$C65))) | C65: {=IF($A65="","",IF($AE65="OVF",INDEX(permit_calc!$A$3:$A$144,MATCH($A65,permit_calc!$N$3:$N$144,0)),INDEX($U$18:$U$25,$AF65)))} | D65: =IF($A65="","",$AE65) | E65: {=IF($A65="","",IF($AE65="OVF","",INDEX($G$18:$G$25,$AF65)))} | F65: {=IF($A65="","",IF($AE65="OVF",INDEX(permit_calc!$M$3:$M$144,MATCH($A65,permit_calc!$N$3:$N$144,0)),INDEX($A$18:$A$25,$AF65)))} | H65: {=IF($A65="","",IF($AE65="OVF",INDEX($E$18:$E$25,INDEX(permit_calc!$O$3:$O$144,MATCH($A65,permit_calc!$N$3:$N$144,0)))+INDEX($F$18:$F$25,INDEX(permit_calc!$O$3:$O$144,MATCH($A65,permit_calc!$N$3:$N$144,0))),INDEX($L$18:$L$25,$AF65)+INDEX($M$18:$M$25,$AF65)))} | I65: =IF($A65="","",IFERROR(IF(INDEX(countries!$I:$I,MATCH($C65,countries!$D:$D,0))=0,$B$12,INDEX(countries!$I:$I,MATCH($C65,countries!$D:$D,0))),$B$12)) | J65: =IF($A65="","",$H65-$I65/24) | K65: =IF($A65="","",ROUND($J65-NOW(),1)) | L65: =IF($A65="","",IF($AE65="OVF",IFERROR(INDEX(countries!$G:$G,MATCH($C65,countries!$D:$D,0)),"VERIFY"),IFERROR(INDEX(countries!$H:$H,MATCH($C65,countries!$D:$D,0)),"VERIFY"))) | M65: =IF($A65="","",IF(OR(UPPER($G65)="OWN",UPPER($G65)="EXCLUDED"),"CLIENT ARRANGING",IF($K65<0,"OVERDUE",IF($K65<1,"URGENT - FILE NOW",IF($K65<3,"DUE SOON","PENDING"))))) | AE65: =IF($A65="","",IF($A65<=COUNTIF(permit_calc!$L$3:$L$144,1),"OVF","LDG")) | AF65: =IF($AE65="","",IF($AE65="OVF","",$A65-COUNTIF(permit_calc!$L$3:$L$144,1)))
... A69: =IF(ROW()-29>COUNTIF(permit_calc!$L$3:$L$144,1)+COUNTA($G$18:$G$25),"",ROW()-29) | B69: =IF($A69="","",IF($AE69="OVF",INDEX(permit_calc!$B$3:$B$144,MATCH($A69,permit_calc!$N$3:$N$144,0)),IFERROR(INDEX(countries!$B:$B,MATCH($C69,countries!$D:$D,0)),$C69))) | C69: {=IF($A69="","",IF($AE69="OVF",INDEX(permit_calc!$A$3:$A$144,MATCH($A69,permit_calc!$N$3:$N$144,0)),INDEX($U$18:$U$25,$AF69)))} | D69: =IF($A69="","",$AE69) | E69: {=IF($A69="","",IF($AE69="OVF","",INDEX($G$18:$G$25,$AF69)))} | F69: {=IF($A69="","",IF($AE69="OVF",INDEX(permit_calc!$M$3:$M$144,MATCH($A69,permit_calc!$N$3:$N$144,0)),INDEX($A$18:$A$25,$AF69)))} | H69: {=IF($A69="","",IF($AE69="OVF",INDEX($E$18:$E$25,INDEX(permit_calc!$O$3:$O$144,MATCH($A69,permit_calc!$N$3:$N$144,0)))+INDEX($F$18:$F$25,INDEX(permit_calc!$O$3:$O$144,MATCH($A69,permit_calc!$N$3:$N$144,0))),INDEX($L$18:$L$25,$AF69)+INDEX($M$18:$M$25,$AF69)))} | I69: =IF($A69="","",IFERROR(IF(INDEX(countries!$I:$I,MATCH($C69,countries!$D:$D,0))=0,$B$12,INDEX(countries!$I:$I,MATCH($C69,countries!$D:$D,0))),$B$12)) | J69: =IF($A69="","",$H69-$I69/24) | K69: =IF($A69="","",ROUND($J69-NOW(),1)) | L69: =IF($A69="","",IF($AE69="OVF",IFERROR(INDEX(countries!$G:$G,MATCH($C69,countries!$D:$D,0)),"VERIFY"),IFERROR(INDEX(countries!$H:$H,MATCH($C69,countries!$D:$D,0)),"VERIFY"))) | M69: =IF($A69="","",IF(OR(UPPER($G69)="OWN",UPPER($G69)="EXCLUDED"),"CLIENT ARRANGING",IF($K69<0,"OVERDUE",IF($K69<1,"URGENT - FILE NOW",IF($K69<3,"DUE SOON","PENDING"))))) | AE69: =IF($A69="","",IF($A69<=COUNTIF(permit_calc!$L$3:$L$144,1),"OVF","LDG")) | AF69: =IF($AE69="","",IF($AE69="OVF","",$A69-COUNTIF(permit_calc!$L$3:$L$144,1)))
A70: =IF(COUNTIF(permit_calc!$L$3:$L$144,1)+COUNTA($G$18:$G$25)>40,"WARNING: more permit lines than rows available in section 3 - extend the block below row 69","")
A71: 4 · GROUND SERVICES BY STOP (one line per country on the ground · enter the provider in a service column to order it — blank means not required)
H72: =IFERROR(INDEX('SERVICE CATALOGUE'!$B$3:$B$100,MATCH(COLUMN()-7,'SERVICE CATALOGUE'!$F$3:$F$100,0)),"") | I72: =IFERROR(INDEX('SERVICE CATALOGUE'!$B$3:$B$100,MATCH(COLUMN()-7,'SERVICE CATALOGUE'!$F$3:$F$100,0)),"") | J72: =IFERROR(INDEX('SERVICE CATALOGUE'!$B$3:$B$100,MATCH(COLUMN()-7,'SERVICE CATALOGUE'!$F$3:$F$100,0)),"") | K72: =IFERROR(INDEX('SERVICE CATALOGUE'!$B$3:$B$100,MATCH(COLUMN()-7,'SERVICE CATALOGUE'!$F$3:$F$100,0)),"") | L72: =IFERROR(INDEX('SERVICE CATALOGUE'!$B$3:$B$100,MATCH(COLUMN()-7,'SERVICE CATALOGUE'!$F$3:$F$100,0)),"") | M72: =IFERROR(INDEX('SERVICE CATALOGUE'!$B$3:$B$100,MATCH(COLUMN()-7,'SERVICE CATALOGUE'!$F$3:$F$100,0)),"") | N72: =IFERROR(INDEX('SERVICE CATALOGUE'!$B$3:$B$100,MATCH(COLUMN()-7,'SERVICE CATALOGUE'!$F$3:$F$100,0)),"") | O72: =IFERROR(INDEX('SERVICE CATALOGUE'!$B$3:$B$100,MATCH(COLUMN()-7,'SERVICE CATALOGUE'!$F$3:$F$100,0)),"") | ... V72: =IFERROR(INDEX('SERVICE CATALOGUE'!$B$3:$B$100,MATCH(COLUMN()-7,'SERVICE CATALOGUE'!$F$3:$F$100,0)),"") | W72: stop and handling policy
A73: STOP | B73: COUNTRY | C73: ISO3 | D73: AIRPORT(S) | E73: LEGS | F73: FIRST ON GROUND (UTC) | G73: SERVICES ORDERED | H73: =IFERROR(INDEX('SERVICE CATALOGUE'!$C$3:$C$100,MATCH(COLUMN()-7,'SERVICE CATALOGUE'!$F$3:$F$100,0)),"") | I73: =IFERROR(INDEX('SERVICE CATALOGUE'!$C$3:$C$100,MATCH(COLUMN()-7,'SERVICE CATALOGUE'!$F$3:$F$100,0)),"") | J73: =IFERROR(INDEX('SERVICE CATALOGUE'!$C$3:$C$100,MATCH(COLUMN()-7,'SERVICE CATALOGUE'!$F$3:$F$100,0)),"") | K73: =IFERROR(INDEX('SERVICE CATALOGUE'!$C$3:$C$100,MATCH(COLUMN()-7,'SERVICE CATALOGUE'!$F$3:$F$100,0)),"") | L73: =IFERROR(INDEX('SERVICE CATALOGUE'!$C$3:$C$100,MATCH(COLUMN()-7,'SERVICE CATALOGUE'!$F$3:$F$100,0)),"") | M73: =IFERROR(INDEX('SERVICE CATALOGUE'!$C$3:$C$100,MATCH(COLUMN()-7,'SERVICE CATALOGUE'!$F$3:$F$100,0)),"") | N73: =IFERROR(INDEX('SERVICE CATALOGUE'!$C$3:$C$100,MATCH(COLUMN()-7,'SERVICE CATALOGUE'!$F$3:$F$100,0)),"") | O73: =IFERROR(INDEX('SERVICE CATALOGUE'!$C$3:$C$100,MATCH(COLUMN()-7,'SERVICE CATALOGUE'!$F$3:$F$100,0)),"") | ... V73: =IFERROR(INDEX('SERVICE CATALOGUE'!$C$3:$C$100,MATCH(COLUMN()-7,'SERVICE CATALOGUE'!$F$3:$F$100,0)),"") | W73: STOP TYPE | X73: HANDLING MANDATORY | Y73: SELF-HANDLING | Z73: PREFERRED VENDOR | AA73: VENDOR SOURCE | AB73: VENDORS AVAILABLE | AC73: STATION CONTACT | AD73: STATION EMAIL
A74: =IF(ROW()-73>SUM($AO$18:$AO$26),"",ROW()-73) | B74: =IF($A74="","",IFERROR(INDEX(countries!$B:$B,MATCH($C74,countries!$D:$D,0)),$C74)) | C74: =IF($A74="","",INDEX($AK$18:$AK$26,MATCH($A74,$AP$18:$AP$26,0))) | D74: {=IF($A74="","",_xlfn.TEXTJOIN(", ",TRUE,IF($AK$18:$AK$26=$C74,$AL$18:$AL$26,"")))} | E74: {=IF($A74="","",_xlfn.TEXTJOIN(", ",TRUE,IF($AK$18:$AK$26=$C74,$AM$18:$AM$26,"")))} | F74: =IF($A74="","",_xlfn.MINIFS($AN$18:$AN$26,$AK$18:$AK$26,$C74)) | G74: =IF($A74="","",COUNTA($H74:$V74)) | H74: JTL | W74: RON (REMAINING OVERNIGHT) | X74: =IF($A74="","",IFERROR(INDEX(countries!$L:$L,MATCH($C74,countries!$D:$D,0)),"VERIFY")) | Y74: =IF($A74="","",IFERROR(INDEX(countries!$M:$M,MATCH($C74,countries!$D:$D,0)),"VERIFY")) | Z74: =IF($A74="","",IFERROR(INDEX(HANDLERS!$B$4:$B$250,MATCH(TRIM(LEFT($D74&",",FIND(",",$D74&",")-1)),HANDLERS!$C$4:$C$250,0)),IFERROR(INDEX(Vendors!$B:$B,MATCH(INDEX(vendor_coverage_countries!$B:$B,MATCH(IFERROR(INDEX(countries!$C:$C,MATCH($C74,countries!$D:$D,0)),""),vendor_coverage_countries!$C:$C,0)),Vendors!$A:$A,0)),"NO VENDOR ON FILE FOR THIS STATE"))) | AA74: =IF($A74="","",IF(ISNUMBER(MATCH(TRIM(LEFT($D74&",",FIND(",",$D74&",")-1)),HANDLERS!$C$4:$C$250,0)),"HANDLERS (station "&TRIM(LEFT($D74&",",FIND(",",$D74&",")-1))&")",IF($AB74=0,"-","vendor_coverage_countries"))) | AB74: =IF($A74="","",COUNTIF(vendor_coverage_countries!$C:$C,IFERROR(INDEX(countries!$C:$C,MATCH($C74,countries!$D:$D,0)),""))) | AC74: =IF($A74="","",IFERROR(INDEX(HANDLERS!$D$4:$D$250,MATCH(TRIM(LEFT($D74&",",FIND(",",$D74&",")-1)),HANDLERS!$C$4:$C$250,0)),"")) | AD74: =IF($A74="","",IFERROR(INDEX(HANDLERS!$E$4:$E$250,MATCH(TRIM(LEFT($D74&",",FIND(",",$D74&",")-1)),HANDLERS!$C$4:$C$250,0)),""))
A75: =IF(ROW()-73>SUM($AO$18:$AO$26),"",ROW()-73) | B75: =IF($A75="","",IFERROR(INDEX(countries!$B:$B,MATCH($C75,countries!$D:$D,0)),$C75)) | C75: =IF($A75="","",INDEX($AK$18:$AK$26,MATCH($A75,$AP$18:$AP$26,0))) | D75: {=IF($A75="","",_xlfn.TEXTJOIN(", ",TRUE,IF($AK$18:$AK$26=$C75,$AL$18:$AL$26,"")))} | E75: {=IF($A75="","",_xlfn.TEXTJOIN(", ",TRUE,IF($AK$18:$AK$26=$C75,$AM$18:$AM$26,"")))} | F75: =IF($A75="","",_xlfn.MINIFS($AN$18:$AN$26,$AK$18:$AK$26,$C75)) | G75: =IF($A75="","",COUNTA($H75:$V75)) | H75: JTL | W75: TECH STOP | X75: =IF($A75="","",IFERROR(INDEX(countries!$L:$L,MATCH($C75,countries!$D:$D,0)),"VERIFY")) | Y75: =IF($A75="","",IFERROR(INDEX(countries!$M:$M,MATCH($C75,countries!$D:$D,0)),"VERIFY")) | Z75: =IF($A75="","",IFERROR(INDEX(HANDLERS!$B$4:$B$250,MATCH(TRIM(LEFT($D75&",",FIND(",",$D75&",")-1)),HANDLERS!$C$4:$C$250,0)),IFERROR(INDEX(Vendors!$B:$B,MATCH(INDEX(vendor_coverage_countries!$B:$B,MATCH(IFERROR(INDEX(countries!$C:$C,MATCH($C75,countries!$D:$D,0)),""),vendor_coverage_countries!$C:$C,0)),Vendors!$A:$A,0)),"NO VENDOR ON FILE FOR THIS STATE"))) | AA75: =IF($A75="","",IF(ISNUMBER(MATCH(TRIM(LEFT($D75&",",FIND(",",$D75&",")-1)),HANDLERS!$C$4:$C$250,0)),"HANDLERS (station "&TRIM(LEFT($D75&",",FIND(",",$D75&",")-1))&")",IF($AB75=0,"-","vendor_coverage_countries"))) | AB75: =IF($A75="","",COUNTIF(vendor_coverage_countries!$C:$C,IFERROR(INDEX(countries!$C:$C,MATCH($C75,countries!$D:$D,0)),""))) | AC75: =IF($A75="","",IFERROR(INDEX(HANDLERS!$D$4:$D$250,MATCH(TRIM(LEFT($D75&",",FIND(",",$D75&",")-1)),HANDLERS!$C$4:$C$250,0)),"")) | AD75: =IF($A75="","",IFERROR(INDEX(HANDLERS!$E$4:$E$250,MATCH(TRIM(LEFT($D75&",",FIND(",",$D75&",")-1)),HANDLERS!$C$4:$C$250,0)),""))
A76: =IF(ROW()-73>SUM($AO$18:$AO$26),"",ROW()-73) | B76: =IF($A76="","",IFERROR(INDEX(countries!$B:$B,MATCH($C76,countries!$D:$D,0)),$C76)) | C76: =IF($A76="","",INDEX($AK$18:$AK$26,MATCH($A76,$AP$18:$AP$26,0))) | D76: {=IF($A76="","",_xlfn.TEXTJOIN(", ",TRUE,IF($AK$18:$AK$26=$C76,$AL$18:$AL$26,"")))} | E76: {=IF($A76="","",_xlfn.TEXTJOIN(", ",TRUE,IF($AK$18:$AK$26=$C76,$AM$18:$AM$26,"")))} | F76: =IF($A76="","",_xlfn.MINIFS($AN$18:$AN$26,$AK$18:$AK$26,$C76)) | G76: =IF($A76="","",COUNTA($H76:$V76)) | H76: JTL | W76: RON (REMAINING OVERNIGHT) | X76: =IF($A76="","",IFERROR(INDEX(countries!$L:$L,MATCH($C76,countries!$D:$D,0)),"VERIFY")) | Y76: =IF($A76="","",IFERROR(INDEX(countries!$M:$M,MATCH($C76,countries!$D:$D,0)),"VERIFY")) | Z76: =IF($A76="","",IFERROR(INDEX(HANDLERS!$B$4:$B$250,MATCH(TRIM(LEFT($D76&",",FIND(",",$D76&",")-1)),HANDLERS!$C$4:$C$250,0)),IFERROR(INDEX(Vendors!$B:$B,MATCH(INDEX(vendor_coverage_countries!$B:$B,MATCH(IFERROR(INDEX(countries!$C:$C,MATCH($C76,countries!$D:$D,0)),""),vendor_coverage_countries!$C:$C,0)),Vendors!$A:$A,0)),"NO VENDOR ON FILE FOR THIS STATE"))) | AA76: =IF($A76="","",IF(ISNUMBER(MATCH(TRIM(LEFT($D76&",",FIND(",",$D76&",")-1)),HANDLERS!$C$4:$C$250,0)),"HANDLERS (station "&TRIM(LEFT($D76&",",FIND(",",$D76&",")-1))&")",IF($AB76=0,"-","vendor_coverage_countries"))) | AB76: =IF($A76="","",COUNTIF(vendor_coverage_countries!$C:$C,IFERROR(INDEX(countries!$C:$C,MATCH($C76,countries!$D:$D,0)),""))) | AC76: =IF($A76="","",IFERROR(INDEX(HANDLERS!$D$4:$D$250,MATCH(TRIM(LEFT($D76&",",FIND(",",$D76&",")-1)),HANDLERS!$C$4:$C$250,0)),"")) | AD76: =IF($A76="","",IFERROR(INDEX(HANDLERS!$E$4:$E$250,MATCH(TRIM(LEFT($D76&",",FIND(",",$D76&",")-1)),HANDLERS!$C$4:$C$250,0)),""))
A77: =IF(ROW()-73>SUM($AO$18:$AO$26),"",ROW()-73) | B77: =IF($A77="","",IFERROR(INDEX(countries!$B:$B,MATCH($C77,countries!$D:$D,0)),$C77)) | C77: =IF($A77="","",INDEX($AK$18:$AK$26,MATCH($A77,$AP$18:$AP$26,0))) | D77: {=IF($A77="","",_xlfn.TEXTJOIN(", ",TRUE,IF($AK$18:$AK$26=$C77,$AL$18:$AL$26,"")))} | E77: {=IF($A77="","",_xlfn.TEXTJOIN(", ",TRUE,IF($AK$18:$AK$26=$C77,$AM$18:$AM$26,"")))} | F77: =IF($A77="","",_xlfn.MINIFS($AN$18:$AN$26,$AK$18:$AK$26,$C77)) | G77: =IF($A77="","",COUNTA($H77:$V77)) | H77: JTL | W77: TURNAROUND | X77: =IF($A77="","",IFERROR(INDEX(countries!$L:$L,MATCH($C77,countries!$D:$D,0)),"VERIFY")) | Y77: =IF($A77="","",IFERROR(INDEX(countries!$M:$M,MATCH($C77,countries!$D:$D,0)),"VERIFY")) | Z77: =IF($A77="","",IFERROR(INDEX(HANDLERS!$B$4:$B$250,MATCH(TRIM(LEFT($D77&",",FIND(",",$D77&",")-1)),HANDLERS!$C$4:$C$250,0)),IFERROR(INDEX(Vendors!$B:$B,MATCH(INDEX(vendor_coverage_countries!$B:$B,MATCH(IFERROR(INDEX(countries!$C:$C,MATCH($C77,countries!$D:$D,0)),""),vendor_coverage_countries!$C:$C,0)),Vendors!$A:$A,0)),"NO VENDOR ON FILE FOR THIS STATE"))) | AA77: =IF($A77="","",IF(ISNUMBER(MATCH(TRIM(LEFT($D77&",",FIND(",",$D77&",")-1)),HANDLERS!$C$4:$C$250,0)),"HANDLERS (station "&TRIM(LEFT($D77&",",FIND(",",$D77&",")-1))&")",IF($AB77=0,"-","vendor_coverage_countries"))) | AB77: =IF($A77="","",COUNTIF(vendor_coverage_countries!$C:$C,IFERROR(INDEX(countries!$C:$C,MATCH($C77,countries!$D:$D,0)),""))) | AC77: =IF($A77="","",IFERROR(INDEX(HANDLERS!$D$4:$D$250,MATCH(TRIM(LEFT($D77&",",FIND(",",$D77&",")-1)),HANDLERS!$C$4:$C$250,0)),"")) | AD77: =IF($A77="","",IFERROR(INDEX(HANDLERS!$E$4:$E$250,MATCH(TRIM(LEFT($D77&",",FIND(",",$D77&",")-1)),HANDLERS!$C$4:$C$250,0)),""))
A78: =IF(ROW()-73>SUM($AO$18:$AO$26),"",ROW()-73) | B78: =IF($A78="","",IFERROR(INDEX(countries!$B:$B,MATCH($C78,countries!$D:$D,0)),$C78)) | C78: =IF($A78="","",INDEX($AK$18:$AK$26,MATCH($A78,$AP$18:$AP$26,0))) | D78: {=IF($A78="","",_xlfn.TEXTJOIN(", ",TRUE,IF($AK$18:$AK$26=$C78,$AL$18:$AL$26,"")))} | E78: {=IF($A78="","",_xlfn.TEXTJOIN(", ",TRUE,IF($AK$18:$AK$26=$C78,$AM$18:$AM$26,"")))} | F78: =IF($A78="","",_xlfn.MINIFS($AN$18:$AN$26,$AK$18:$AK$26,$C78)) | G78: =IF($A78="","",COUNTA($H78:$V78)) | X78: =IF($A78="","",IFERROR(INDEX(countries!$L:$L,MATCH($C78,countries!$D:$D,0)),"VERIFY")) | Y78: =IF($A78="","",IFERROR(INDEX(countries!$M:$M,MATCH($C78,countries!$D:$D,0)),"VERIFY")) | Z78: =IF($A78="","",IFERROR(INDEX(HANDLERS!$B$4:$B$250,MATCH(TRIM(LEFT($D78&",",FIND(",",$D78&",")-1)),HANDLERS!$C$4:$C$250,0)),IFERROR(INDEX(Vendors!$B:$B,MATCH(INDEX(vendor_coverage_countries!$B:$B,MATCH(IFERROR(INDEX(countries!$C:$C,MATCH($C78,countries!$D:$D,0)),""),vendor_coverage_countries!$C:$C,0)),Vendors!$A:$A,0)),"NO VENDOR ON FILE FOR THIS STATE"))) | AA78: =IF($A78="","",IF(ISNUMBER(MATCH(TRIM(LEFT($D78&",",FIND(",",$D78&",")-1)),HANDLERS!$C$4:$C$250,0)),"HANDLERS (station "&TRIM(LEFT($D78&",",FIND(",",$D78&",")-1))&")",IF($AB78=0,"-","vendor_coverage_countries"))) | AB78: =IF($A78="","",COUNTIF(vendor_coverage_countries!$C:$C,IFERROR(INDEX(countries!$C:$C,MATCH($C78,countries!$D:$D,0)),""))) | AC78: =IF($A78="","",IFERROR(INDEX(HANDLERS!$D$4:$D$250,MATCH(TRIM(LEFT($D78&",",FIND(",",$D78&",")-1)),HANDLERS!$C$4:$C$250,0)),"")) | AD78: =IF($A78="","",IFERROR(INDEX(HANDLERS!$E$4:$E$250,MATCH(TRIM(LEFT($D78&",",FIND(",",$D78&",")-1)),HANDLERS!$C$4:$C$250,0)),""))
A79: =IF(ROW()-73>SUM($AO$18:$AO$26),"",ROW()-73) | B79: =IF($A79="","",IFERROR(INDEX(countries!$B:$B,MATCH($C79,countries!$D:$D,0)),$C79)) | C79: =IF($A79="","",INDEX($AK$18:$AK$26,MATCH($A79,$AP$18:$AP$26,0))) | D79: {=IF($A79="","",_xlfn.TEXTJOIN(", ",TRUE,IF($AK$18:$AK$26=$C79,$AL$18:$AL$26,"")))} | E79: {=IF($A79="","",_xlfn.TEXTJOIN(", ",TRUE,IF($AK$18:$AK$26=$C79,$AM$18:$AM$26,"")))} | F79: =IF($A79="","",_xlfn.MINIFS($AN$18:$AN$26,$AK$18:$AK$26,$C79)) | G79: =IF($A79="","",COUNTA($H79:$V79)) | X79: =IF($A79="","",IFERROR(INDEX(countries!$L:$L,MATCH($C79,countries!$D:$D,0)),"VERIFY")) | Y79: =IF($A79="","",IFERROR(INDEX(countries!$M:$M,MATCH($C79,countries!$D:$D,0)),"VERIFY")) | Z79: =IF($A79="","",IFERROR(INDEX(HANDLERS!$B$4:$B$250,MATCH(TRIM(LEFT($D79&",",FIND(",",$D79&",")-1)),HANDLERS!$C$4:$C$250,0)),IFERROR(INDEX(Vendors!$B:$B,MATCH(INDEX(vendor_coverage_countries!$B:$B,MATCH(IFERROR(INDEX(countries!$C:$C,MATCH($C79,countries!$D:$D,0)),""),vendor_coverage_countries!$C:$C,0)),Vendors!$A:$A,0)),"NO VENDOR ON FILE FOR THIS STATE"))) | AA79: =IF($A79="","",IF(ISNUMBER(MATCH(TRIM(LEFT($D79&",",FIND(",",$D79&",")-1)),HANDLERS!$C$4:$C$250,0)),"HANDLERS (station "&TRIM(LEFT($D79&",",FIND(",",$D79&",")-1))&")",IF($AB79=0,"-","vendor_coverage_countries"))) | AB79: =IF($A79="","",COUNTIF(vendor_coverage_countries!$C:$C,IFERROR(INDEX(countries!$C:$C,MATCH($C79,countries!$D:$D,0)),""))) | AC79: =IF($A79="","",IFERROR(INDEX(HANDLERS!$D$4:$D$250,MATCH(TRIM(LEFT($D79&",",FIND(",",$D79&",")-1)),HANDLERS!$C$4:$C$250,0)),"")) | AD79: =IF($A79="","",IFERROR(INDEX(HANDLERS!$E$4:$E$250,MATCH(TRIM(LEFT($D79&",",FIND(",",$D79&",")-1)),HANDLERS!$C$4:$C$250,0)),""))
A80: =IF(ROW()-73>SUM($AO$18:$AO$26),"",ROW()-73) | B80: =IF($A80="","",IFERROR(INDEX(countries!$B:$B,MATCH($C80,countries!$D:$D,0)),$C80)) | C80: =IF($A80="","",INDEX($AK$18:$AK$26,MATCH($A80,$AP$18:$AP$26,0))) | D80: {=IF($A80="","",_xlfn.TEXTJOIN(", ",TRUE,IF($AK$18:$AK$26=$C80,$AL$18:$AL$26,"")))} | E80: {=IF($A80="","",_xlfn.TEXTJOIN(", ",TRUE,IF($AK$18:$AK$26=$C80,$AM$18:$AM$26,"")))} | F80: =IF($A80="","",_xlfn.MINIFS($AN$18:$AN$26,$AK$18:$AK$26,$C80)) | G80: =IF($A80="","",COUNTA($H80:$V80)) | X80: =IF($A80="","",IFERROR(INDEX(countries!$L:$L,MATCH($C80,countries!$D:$D,0)),"VERIFY")) | Y80: =IF($A80="","",IFERROR(INDEX(countries!$M:$M,MATCH($C80,countries!$D:$D,0)),"VERIFY")) | Z80: =IF($A80="","",IFERROR(INDEX(HANDLERS!$B$4:$B$250,MATCH(TRIM(LEFT($D80&",",FIND(",",$D80&",")-1)),HANDLERS!$C$4:$C$250,0)),IFERROR(INDEX(Vendors!$B:$B,MATCH(INDEX(vendor_coverage_countries!$B:$B,MATCH(IFERROR(INDEX(countries!$C:$C,MATCH($C80,countries!$D:$D,0)),""),vendor_coverage_countries!$C:$C,0)),Vendors!$A:$A,0)),"NO VENDOR ON FILE FOR THIS STATE"))) | AA80: =IF($A80="","",IF(ISNUMBER(MATCH(TRIM(LEFT($D80&",",FIND(",",$D80&",")-1)),HANDLERS!$C$4:$C$250,0)),"HANDLERS (station "&TRIM(LEFT($D80&",",FIND(",",$D80&",")-1))&")",IF($AB80=0,"-","vendor_coverage_countries"))) | AB80: =IF($A80="","",COUNTIF(vendor_coverage_countries!$C:$C,IFERROR(INDEX(countries!$C:$C,MATCH($C80,countries!$D:$D,0)),""))) | AC80: =IF($A80="","",IFERROR(INDEX(HANDLERS!$D$4:$D$250,MATCH(TRIM(LEFT($D80&",",FIND(",",$D80&",")-1)),HANDLERS!$C$4:$C$250,0)),"")) | AD80: =IF($A80="","",IFERROR(INDEX(HANDLERS!$E$4:$E$250,MATCH(TRIM(LEFT($D80&",",FIND(",",$D80&",")-1)),HANDLERS!$C$4:$C$250,0)),""))
A81: =IF(ROW()-73>SUM($AO$18:$AO$26),"",ROW()-73) | B81: =IF($A81="","",IFERROR(INDEX(countries!$B:$B,MATCH($C81,countries!$D:$D,0)),$C81)) | C81: =IF($A81="","",INDEX($AK$18:$AK$26,MATCH($A81,$AP$18:$AP$26,0))) | D81: {=IF($A81="","",_xlfn.TEXTJOIN(", ",TRUE,IF($AK$18:$AK$26=$C81,$AL$18:$AL$26,"")))} | E81: {=IF($A81="","",_xlfn.TEXTJOIN(", ",TRUE,IF($AK$18:$AK$26=$C81,$AM$18:$AM$26,"")))} | F81: =IF($A81="","",_xlfn.MINIFS($AN$18:$AN$26,$AK$18:$AK$26,$C81)) | G81: =IF($A81="","",COUNTA($H81:$V81)) | X81: =IF($A81="","",IFERROR(INDEX(countries!$L:$L,MATCH($C81,countries!$D:$D,0)),"VERIFY")) | Y81: =IF($A81="","",IFERROR(INDEX(countries!$M:$M,MATCH($C81,countries!$D:$D,0)),"VERIFY")) | Z81: =IF($A81="","",IFERROR(INDEX(HANDLERS!$B$4:$B$250,MATCH(TRIM(LEFT($D81&",",FIND(",",$D81&",")-1)),HANDLERS!$C$4:$C$250,0)),IFERROR(INDEX(Vendors!$B:$B,MATCH(INDEX(vendor_coverage_countries!$B:$B,MATCH(IFERROR(INDEX(countries!$C:$C,MATCH($C81,countries!$D:$D,0)),""),vendor_coverage_countries!$C:$C,0)),Vendors!$A:$A,0)),"NO VENDOR ON FILE FOR THIS STATE"))) | AA81: =IF($A81="","",IF(ISNUMBER(MATCH(TRIM(LEFT($D81&",",FIND(",",$D81&",")-1)),HANDLERS!$C$4:$C$250,0)),"HANDLERS (station "&TRIM(LEFT($D81&",",FIND(",",$D81&",")-1))&")",IF($AB81=0,"-","vendor_coverage_countries"))) | AB81: =IF($A81="","",COUNTIF(vendor_coverage_countries!$C:$C,IFERROR(INDEX(countries!$C:$C,MATCH($C81,countries!$D:$D,0)),""))) | AC81: =IF($A81="","",IFERROR(INDEX(HANDLERS!$D$4:$D$250,MATCH(TRIM(LEFT($D81&",",FIND(",",$D81&",")-1)),HANDLERS!$C$4:$C$250,0)),"")) | AD81: =IF($A81="","",IFERROR(INDEX(HANDLERS!$E$4:$E$250,MATCH(TRIM(LEFT($D81&",",FIND(",",$D81&",")-1)),HANDLERS!$C$4:$C$250,0)),""))
A82: =IF(ROW()-73>SUM($AO$18:$AO$26),"",ROW()-73) | B82: =IF($A82="","",IFERROR(INDEX(countries!$B:$B,MATCH($C82,countries!$D:$D,0)),$C82)) | C82: =IF($A82="","",INDEX($AK$18:$AK$26,MATCH($A82,$AP$18:$AP$26,0))) | D82: {=IF($A82="","",_xlfn.TEXTJOIN(", ",TRUE,IF($AK$18:$AK$26=$C82,$AL$18:$AL$26,"")))} | E82: {=IF($A82="","",_xlfn.TEXTJOIN(", ",TRUE,IF($AK$18:$AK$26=$C82,$AM$18:$AM$26,"")))} | F82: =IF($A82="","",_xlfn.MINIFS($AN$18:$AN$26,$AK$18:$AK$26,$C82)) | G82: =IF($A82="","",COUNTA($H82:$V82)) | X82: =IF($A82="","",IFERROR(INDEX(countries!$L:$L,MATCH($C82,countries!$D:$D,0)),"VERIFY")) | Y82: =IF($A82="","",IFERROR(INDEX(countries!$M:$M,MATCH($C82,countries!$D:$D,0)),"VERIFY")) | Z82: =IF($A82="","",IFERROR(INDEX(HANDLERS!$B$4:$B$250,MATCH(TRIM(LEFT($D82&",",FIND(",",$D82&",")-1)),HANDLERS!$C$4:$C$250,0)),IFERROR(INDEX(Vendors!$B:$B,MATCH(INDEX(vendor_coverage_countries!$B:$B,MATCH(IFERROR(INDEX(countries!$C:$C,MATCH($C82,countries!$D:$D,0)),""),vendor_coverage_countries!$C:$C,0)),Vendors!$A:$A,0)),"NO VENDOR ON FILE FOR THIS STATE"))) | AA82: =IF($A82="","",IF(ISNUMBER(MATCH(TRIM(LEFT($D82&",",FIND(",",$D82&",")-1)),HANDLERS!$C$4:$C$250,0)),"HANDLERS (station "&TRIM(LEFT($D82&",",FIND(",",$D82&",")-1))&")",IF($AB82=0,"-","vendor_coverage_countries"))) | AB82: =IF($A82="","",COUNTIF(vendor_coverage_countries!$C:$C,IFERROR(INDEX(countries!$C:$C,MATCH($C82,countries!$D:$D,0)),""))) | AC82: =IF($A82="","",IFERROR(INDEX(HANDLERS!$D$4:$D$250,MATCH(TRIM(LEFT($D82&",",FIND(",",$D82&",")-1)),HANDLERS!$C$4:$C$250,0)),"")) | AD82: =IF($A82="","",IFERROR(INDEX(HANDLERS!$E$4:$E$250,MATCH(TRIM(LEFT($D82&",",FIND(",",$D82&",")-1)),HANDLERS!$C$4:$C$250,0)),""))
A84: Service columns are driven by the services sheet: set category = GROUND and give a ground_grid_order to add or reorder a service. Enter JTL, OWN or THIRD PARTY in a cell to order it; blank means not required. Ground handling is one service per country even when several airports are involved. For finer detail enter a sub_services code (e.g. GH-DIC for de-icing).
A86: 5 · VISA & IMMIGRATION (one line per country on the ground × each nationality on board · headcount shown in the column header) | B86: =COUNTIFS('PAX & CREW'!$B$3:$B$62,$B$5,'PAX & CREW'!$C$3:$C$62,"CREW")
A87: STOP | B87: COUNTRY | C87: ISO3 | D87: LEGS | E87: =IFERROR(INDEX($AH$18:$AH$37,MATCH(COLUMN()-4,$AJ$18:$AJ$37,0))&" ("&COUNTIFS('PAX & CREW'!$B$3:$B$62,$B$5,'PAX & CREW'!$L$3:$L$62,INDEX($AH$18:$AH$37,MATCH(COLUMN()-4,$AJ$18:$AJ$37,0)))&")","") | F87: =IFERROR(INDEX($AH$18:$AH$37,MATCH(COLUMN()-4,$AJ$18:$AJ$37,0))&" ("&COUNTIFS('PAX & CREW'!$B$3:$B$62,$B$5,'PAX & CREW'!$L$3:$L$62,INDEX($AH$18:$AH$37,MATCH(COLUMN()-4,$AJ$18:$AJ$37,0)))&")","") | G87: =IFERROR(INDEX($AH$18:$AH$37,MATCH(COLUMN()-4,$AJ$18:$AJ$37,0))&" ("&COUNTIFS('PAX & CREW'!$B$3:$B$62,$B$5,'PAX & CREW'!$L$3:$L$62,INDEX($AH$18:$AH$37,MATCH(COLUMN()-4,$AJ$18:$AJ$37,0)))&")","") | H87: =IFERROR(INDEX($AH$18:$AH$37,MATCH(COLUMN()-4,$AJ$18:$AJ$37,0))&" ("&COUNTIFS('PAX & CREW'!$B$3:$B$62,$B$5,'PAX & CREW'!$L$3:$L$62,INDEX($AH$18:$AH$37,MATCH(COLUMN()-4,$AJ$18:$AJ$37,0)))&")","") | I87: =IFERROR(INDEX($AH$18:$AH$37,MATCH(COLUMN()-4,$AJ$18:$AJ$37,0))&" ("&COUNTIFS('PAX & CREW'!$B$3:$B$62,$B$5,'PAX & CREW'!$L$3:$L$62,INDEX($AH$18:$AH$37,MATCH(COLUMN()-4,$AJ$18:$AJ$37,0)))&")","") | J87: =IFERROR(INDEX($AH$18:$AH$37,MATCH(COLUMN()-4,$AJ$18:$AJ$37,0))&" ("&COUNTIFS('PAX & CREW'!$B$3:$B$62,$B$5,'PAX & CREW'!$L$3:$L$62,INDEX($AH$18:$AH$37,MATCH(COLUMN()-4,$AJ$18:$AJ$37,0)))&")","")
A88: =IF(ROW()-87>SUM($AO$18:$AO$26),"",ROW()-87) | B88: =IF($A88="","",IFERROR(INDEX(countries!$B:$B,MATCH($C88,countries!$D:$D,0)),$C88)) | C88: =IF($A88="","",INDEX($AK$18:$AK$26,MATCH($A88,$AP$18:$AP$26,0))) | D88: {=IF($A88="","",_xlfn.TEXTJOIN(", ",TRUE,IF($AK$18:$AK$26=$C88,$AM$18:$AM$26,"")))} | E88: {=IF(OR($A88="",E$87=""),"",_xlfn.LET(_xlpm.nat,INDEX($AH$18:$AH$37,MATCH(COLUMN()-4,$AJ$18:$AJ$37,0)),_xlpm.ctry,$B88,_xlpm.apt,IFERROR(INDEX('VISA RULES'!$E$2:$E$400,SUMPRODUCT(MATCH(1,('VISA RULES'!$B$2:$B$400=_xlpm.ctry)*('VISA RULES'!$C$2:$C$400=_xlpm.nat)*('VISA RULES'!$A$2:$A$400<>""),0))),""),_xlpm.rule,IFERROR(INDEX('VISA RULES'!$E$2:$E$400,SUMPRODUCT(MATCH(1,('VISA RULES'!$B$2:$B$400=_xlpm.ctry)*('VISA RULES'!$C$2:$C$400=_xlpm.nat)*('VISA RULES'!$A$2:$A$400=""),0))),""),_xlpm.mtx,IFERROR(INDEX('VISA MATRIX'!$B$4:$FS$145,MATCH(_xlpm.ctry,'VISA MATRIX'!$A$4:$A$145,0),MATCH(_xlpm.nat,'VISA MATRIX'!$B$3:$FS$3,0)),""),IF(_xlpm.apt<>"",_xlpm.apt&" (APT OVERRIDE)",IF(_xlpm.rule<>"",_xlpm.rule,IF(_xlpm.mtx<>"",_xlpm.mtx,"NOT ON FILE - VERIFY")))))} | F88: {=IF(OR($A88="",F$87=""),"",_xlfn.LET(_xlpm.nat,INDEX($AH$18:$AH$37,MATCH(COLUMN()-4,$AJ$18:$AJ$37,0)),_xlpm.ctry,$B88,_xlpm.apt,IFERROR(INDEX('VISA RULES'!$E$2:$E$400,SUMPRODUCT(MATCH(1,('VISA RULES'!$B$2:$B$400=_xlpm.ctry)*('VISA RULES'!$C$2:$C$400=_xlpm.nat)*('VISA RULES'!$A$2:$A$400<>""),0))),""),_xlpm.rule,IFERROR(INDEX('VISA RULES'!$E$2:$E$400,SUMPRODUCT(MATCH(1,('VISA RULES'!$B$2:$B$400=_xlpm.ctry)*('VISA RULES'!$C$2:$C$400=_xlpm.nat)*('VISA RULES'!$A$2:$A$400=""),0))),""),_xlpm.mtx,IFERROR(INDEX('VISA MATRIX'!$B$4:$FS$145,MATCH(_xlpm.ctry,'VISA MATRIX'!$A$4:$A$145,0),MATCH(_xlpm.nat,'VISA MATRIX'!$B$3:$FS$3,0)),""),IF(_xlpm.apt<>"",_xlpm.apt&" (APT OVERRIDE)",IF(_xlpm.rule<>"",_xlpm.rule,IF(_xlpm.mtx<>"",_xlpm.mtx,"NOT ON FILE - VERIFY")))))} | G88: {=IF(OR($A88="",G$87=""),"",_xlfn.LET(_xlpm.nat,INDEX($AH$18:$AH$37,MATCH(COLUMN()-4,$AJ$18:$AJ$37,0)),_xlpm.ctry,$B88,_xlpm.apt,IFERROR(INDEX('VISA RULES'!$E$2:$E$400,SUMPRODUCT(MATCH(1,('VISA RULES'!$B$2:$B$400=_xlpm.ctry)*('VISA RULES'!$C$2:$C$400=_xlpm.nat)*('VISA RULES'!$A$2:$A$400<>""),0))),""),_xlpm.rule,IFERROR(INDEX('VISA RULES'!$E$2:$E$400,SUMPRODUCT(MATCH(1,('VISA RULES'!$B$2:$B$400=_xlpm.ctry)*('VISA RULES'!$C$2:$C$400=_xlpm.nat)*('VISA RULES'!$A$2:$A$400=""),0))),""),_xlpm.mtx,IFERROR(INDEX('VISA MATRIX'!$B$4:$FS$145,MATCH(_xlpm.ctry,'VISA MATRIX'!$A$4:$A$145,0),MATCH(_xlpm.nat,'VISA MATRIX'!$B$3:$FS$3,0)),""),IF(_xlpm.apt<>"",_xlpm.apt&" (APT OVERRIDE)",IF(_xlpm.rule<>"",_xlpm.rule,IF(_xlpm.mtx<>"",_xlpm.mtx,"NOT ON FILE - VERIFY")))))} | H88: {=IF(OR($A88="",H$87=""),"",_xlfn.LET(_xlpm.nat,INDEX($AH$18:$AH$37,MATCH(COLUMN()-4,$AJ$18:$AJ$37,0)),_xlpm.ctry,$B88,_xlpm.apt,IFERROR(INDEX('VISA RULES'!$E$2:$E$400,SUMPRODUCT(MATCH(1,('VISA RULES'!$B$2:$B$400=_xlpm.ctry)*('VISA RULES'!$C$2:$C$400=_xlpm.nat)*('VISA RULES'!$A$2:$A$400<>""),0))),""),_xlpm.rule,IFERROR(INDEX('VISA RULES'!$E$2:$E$400,SUMPRODUCT(MATCH(1,('VISA RULES'!$B$2:$B$400=_xlpm.ctry)*('VISA RULES'!$C$2:$C$400=_xlpm.nat)*('VISA RULES'!$A$2:$A$400=""),0))),""),_xlpm.mtx,IFERROR(INDEX('VISA MATRIX'!$B$4:$FS$145,MATCH(_xlpm.ctry,'VISA MATRIX'!$A$4:$A$145,0),MATCH(_xlpm.nat,'VISA MATRIX'!$B$3:$FS$3,0)),""),IF(_xlpm.apt<>"",_xlpm.apt&" (APT OVERRIDE)",IF(_xlpm.rule<>"",_xlpm.rule,IF(_xlpm.mtx<>"",_xlpm.mtx,"NOT ON FILE - VERIFY")))))} | I88: {=IF(OR($A88="",I$87=""),"",_xlfn.LET(_xlpm.nat,INDEX($AH$18:$AH$37,MATCH(COLUMN()-4,$AJ$18:$AJ$37,0)),_xlpm.ctry,$B88,_xlpm.apt,IFERROR(INDEX('VISA RULES'!$E$2:$E$400,SUMPRODUCT(MATCH(1,('VISA RULES'!$B$2:$B$400=_xlpm.ctry)*('VISA RULES'!$C$2:$C$400=_xlpm.nat)*('VISA RULES'!$A$2:$A$400<>""),0))),""),_xlpm.rule,IFERROR(INDEX('VISA RULES'!$E$2:$E$400,SUMPRODUCT(MATCH(1,('VISA RULES'!$B$2:$B$400=_xlpm.ctry)*('VISA RULES'!$C$2:$C$400=_xlpm.nat)*('VISA RULES'!$A$2:$A$400=""),0))),""),_xlpm.mtx,IFERROR(INDEX('VISA MATRIX'!$B$4:$FS$145,MATCH(_xlpm.ctry,'VISA MATRIX'!$A$4:$A$145,0),MATCH(_xlpm.nat,'VISA MATRIX'!$B$3:$FS$3,0)),""),IF(_xlpm.apt<>"",_xlpm.apt&" (APT OVERRIDE)",IF(_xlpm.rule<>"",_xlpm.rule,IF(_xlpm.mtx<>"",_xlpm.mtx,"NOT ON FILE - VERIFY")))))} | J88: {=IF(OR($A88="",J$87=""),"",_xlfn.LET(_xlpm.nat,INDEX($AH$18:$AH$37,MATCH(COLUMN()-4,$AJ$18:$AJ$37,0)),_xlpm.ctry,$B88,_xlpm.apt,IFERROR(INDEX('VISA RULES'!$E$2:$E$400,SUMPRODUCT(MATCH(1,('VISA RULES'!$B$2:$B$400=_xlpm.ctry)*('VISA RULES'!$C$2:$C$400=_xlpm.nat)*('VISA RULES'!$A$2:$A$400<>""),0))),""),_xlpm.rule,IFERROR(INDEX('VISA RULES'!$E$2:$E$400,SUMPRODUCT(MATCH(1,('VISA RULES'!$B$2:$B$400=_xlpm.ctry)*('VISA RULES'!$C$2:$C$400=_xlpm.nat)*('VISA RULES'!$A$2:$A$400=""),0))),""),_xlpm.mtx,IFERROR(INDEX('VISA MATRIX'!$B$4:$FS$145,MATCH(_xlpm.ctry,'VISA MATRIX'!$A$4:$A$145,0),MATCH(_xlpm.nat,'VISA MATRIX'!$B$3:$FS$3,0)),""),IF(_xlpm.apt<>"",_xlpm.apt&" (APT OVERRIDE)",IF(_xlpm.rule<>"",_xlpm.rule,IF(_xlpm.mtx<>"",_xlpm.mtx,"NOT ON FILE - VERIFY")))))}
A89: =IF(ROW()-87>SUM($AO$18:$AO$26),"",ROW()-87) | B89: =IF($A89="","",IFERROR(INDEX(countries!$B:$B,MATCH($C89,countries!$D:$D,0)),$C89)) | C89: =IF($A89="","",INDEX($AK$18:$AK$26,MATCH($A89,$AP$18:$AP$26,0))) | D89: {=IF($A89="","",_xlfn.TEXTJOIN(", ",TRUE,IF($AK$18:$AK$26=$C89,$AM$18:$AM$26,"")))} | E89: {=IF(OR($A89="",E$87=""),"",_xlfn.LET(_xlpm.nat,INDEX($AH$18:$AH$37,MATCH(COLUMN()-4,$AJ$18:$AJ$37,0)),_xlpm.ctry,$B89,_xlpm.apt,IFERROR(INDEX('VISA RULES'!$E$2:$E$400,SUMPRODUCT(MATCH(1,('VISA RULES'!$B$2:$B$400=_xlpm.ctry)*('VISA RULES'!$C$2:$C$400=_xlpm.nat)*('VISA RULES'!$A$2:$A$400<>""),0))),""),_xlpm.rule,IFERROR(INDEX('VISA RULES'!$E$2:$E$400,SUMPRODUCT(MATCH(1,('VISA RULES'!$B$2:$B$400=_xlpm.ctry)*('VISA RULES'!$C$2:$C$400=_xlpm.nat)*('VISA RULES'!$A$2:$A$400=""),0))),""),_xlpm.mtx,IFERROR(INDEX('VISA MATRIX'!$B$4:$FS$145,MATCH(_xlpm.ctry,'VISA MATRIX'!$A$4:$A$145,0),MATCH(_xlpm.nat,'VISA MATRIX'!$B$3:$FS$3,0)),""),IF(_xlpm.apt<>"",_xlpm.apt&" (APT OVERRIDE)",IF(_xlpm.rule<>"",_xlpm.rule,IF(_xlpm.mtx<>"",_xlpm.mtx,"NOT ON FILE - VERIFY")))))} | F89: {=IF(OR($A89="",F$87=""),"",_xlfn.LET(_xlpm.nat,INDEX($AH$18:$AH$37,MATCH(COLUMN()-4,$AJ$18:$AJ$37,0)),_xlpm.ctry,$B89,_xlpm.apt,IFERROR(INDEX('VISA RULES'!$E$2:$E$400,SUMPRODUCT(MATCH(1,('VISA RULES'!$B$2:$B$400=_xlpm.ctry)*('VISA RULES'!$C$2:$C$400=_xlpm.nat)*('VISA RULES'!$A$2:$A$400<>""),0))),""),_xlpm.rule,IFERROR(INDEX('VISA RULES'!$E$2:$E$400,SUMPRODUCT(MATCH(1,('VISA RULES'!$B$2:$B$400=_xlpm.ctry)*('VISA RULES'!$C$2:$C$400=_xlpm.nat)*('VISA RULES'!$A$2:$A$400=""),0))),""),_xlpm.mtx,IFERROR(INDEX('VISA MATRIX'!$B$4:$FS$145,MATCH(_xlpm.ctry,'VISA MATRIX'!$A$4:$A$145,0),MATCH(_xlpm.nat,'VISA MATRIX'!$B$3:$FS$3,0)),""),IF(_xlpm.apt<>"",_xlpm.apt&" (APT OVERRIDE)",IF(_xlpm.rule<>"",_xlpm.rule,IF(_xlpm.mtx<>"",_xlpm.mtx,"NOT ON FILE - VERIFY")))))} | G89: {=IF(OR($A89="",G$87=""),"",_xlfn.LET(_xlpm.nat,INDEX($AH$18:$AH$37,MATCH(COLUMN()-4,$AJ$18:$AJ$37,0)),_xlpm.ctry,$B89,_xlpm.apt,IFERROR(INDEX('VISA RULES'!$E$2:$E$400,SUMPRODUCT(MATCH(1,('VISA RULES'!$B$2:$B$400=_xlpm.ctry)*('VISA RULES'!$C$2:$C$400=_xlpm.nat)*('VISA RULES'!$A$2:$A$400<>""),0))),""),_xlpm.rule,IFERROR(INDEX('VISA RULES'!$E$2:$E$400,SUMPRODUCT(MATCH(1,('VISA RULES'!$B$2:$B$400=_xlpm.ctry)*('VISA RULES'!$C$2:$C$400=_xlpm.nat)*('VISA RULES'!$A$2:$A$400=""),0))),""),_xlpm.mtx,IFERROR(INDEX('VISA MATRIX'!$B$4:$FS$145,MATCH(_xlpm.ctry,'VISA MATRIX'!$A$4:$A$145,0),MATCH(_xlpm.nat,'VISA MATRIX'!$B$3:$FS$3,0)),""),IF(_xlpm.apt<>"",_xlpm.apt&" (APT OVERRIDE)",IF(_xlpm.rule<>"",_xlpm.rule,IF(_xlpm.mtx<>"",_xlpm.mtx,"NOT ON FILE - VERIFY")))))} | H89: {=IF(OR($A89="",H$87=""),"",_xlfn.LET(_xlpm.nat,INDEX($AH$18:$AH$37,MATCH(COLUMN()-4,$AJ$18:$AJ$37,0)),_xlpm.ctry,$B89,_xlpm.apt,IFERROR(INDEX('VISA RULES'!$E$2:$E$400,SUMPRODUCT(MATCH(1,('VISA RULES'!$B$2:$B$400=_xlpm.ctry)*('VISA RULES'!$C$2:$C$400=_xlpm.nat)*('VISA RULES'!$A$2:$A$400<>""),0))),""),_xlpm.rule,IFERROR(INDEX('VISA RULES'!$E$2:$E$400,SUMPRODUCT(MATCH(1,('VISA RULES'!$B$2:$B$400=_xlpm.ctry)*('VISA RULES'!$C$2:$C$400=_xlpm.nat)*('VISA RULES'!$A$2:$A$400=""),0))),""),_xlpm.mtx,IFERROR(INDEX('VISA MATRIX'!$B$4:$FS$145,MATCH(_xlpm.ctry,'VISA MATRIX'!$A$4:$A$145,0),MATCH(_xlpm.nat,'VISA MATRIX'!$B$3:$FS$3,0)),""),IF(_xlpm.apt<>"",_xlpm.apt&" (APT OVERRIDE)",IF(_xlpm.rule<>"",_xlpm.rule,IF(_xlpm.mtx<>"",_xlpm.mtx,"NOT ON FILE - VERIFY")))))} | I89: {=IF(OR($A89="",I$87=""),"",_xlfn.LET(_xlpm.nat,INDEX($AH$18:$AH$37,MATCH(COLUMN()-4,$AJ$18:$AJ$37,0)),_xlpm.ctry,$B89,_xlpm.apt,IFERROR(INDEX('VISA RULES'!$E$2:$E$400,SUMPRODUCT(MATCH(1,('VISA RULES'!$B$2:$B$400=_xlpm.ctry)*('VISA RULES'!$C$2:$C$400=_xlpm.nat)*('VISA RULES'!$A$2:$A$400<>""),0))),""),_xlpm.rule,IFERROR(INDEX('VISA RULES'!$E$2:$E$400,SUMPRODUCT(MATCH(1,('VISA RULES'!$B$2:$B$400=_xlpm.ctry)*('VISA RULES'!$C$2:$C$400=_xlpm.nat)*('VISA RULES'!$A$2:$A$400=""),0))),""),_xlpm.mtx,IFERROR(INDEX('VISA MATRIX'!$B$4:$FS$145,MATCH(_xlpm.ctry,'VISA MATRIX'!$A$4:$A$145,0),MATCH(_xlpm.nat,'VISA MATRIX'!$B$3:$FS$3,0)),""),IF(_xlpm.apt<>"",_xlpm.apt&" (APT OVERRIDE)",IF(_xlpm.rule<>"",_xlpm.rule,IF(_xlpm.mtx<>"",_xlpm.mtx,"NOT ON FILE - VERIFY")))))} | J89: {=IF(OR($A89="",J$87=""),"",_xlfn.LET(_xlpm.nat,INDEX($AH$18:$AH$37,MATCH(COLUMN()-4,$AJ$18:$AJ$37,0)),_xlpm.ctry,$B89,_xlpm.apt,IFERROR(INDEX('VISA RULES'!$E$2:$E$400,SUMPRODUCT(MATCH(1,('VISA RULES'!$B$2:$B$400=_xlpm.ctry)*('VISA RULES'!$C$2:$C$400=_xlpm.nat)*('VISA RULES'!$A$2:$A$400<>""),0))),""),_xlpm.rule,IFERROR(INDEX('VISA RULES'!$E$2:$E$400,SUMPRODUCT(MATCH(1,('VISA RULES'!$B$2:$B$400=_xlpm.ctry)*('VISA RULES'!$C$2:$C$400=_xlpm.nat)*('VISA RULES'!$A$2:$A$400=""),0))),""),_xlpm.mtx,IFERROR(INDEX('VISA MATRIX'!$B$4:$FS$145,MATCH(_xlpm.ctry,'VISA MATRIX'!$A$4:$A$145,0),MATCH(_xlpm.nat,'VISA MATRIX'!$B$3:$FS$3,0)),""),IF(_xlpm.apt<>"",_xlpm.apt&" (APT OVERRIDE)",IF(_xlpm.rule<>"",_xlpm.rule,IF(_xlpm.mtx<>"",_xlpm.mtx,"NOT ON FILE - VERIFY")))))}
A90: =IF(ROW()-87>SUM($AO$18:$AO$26),"",ROW()-87) | B90: =IF($A90="","",IFERROR(INDEX(countries!$B:$B,MATCH($C90,countries!$D:$D,0)),$C90)) | C90: =IF($A90="","",INDEX($AK$18:$AK$26,MATCH($A90,$AP$18:$AP$26,0))) | D90: {=IF($A90="","",_xlfn.TEXTJOIN(", ",TRUE,IF($AK$18:$AK$26=$C90,$AM$18:$AM$26,"")))} | E90: {=IF(OR($A90="",E$87=""),"",_xlfn.LET(_xlpm.nat,INDEX($AH$18:$AH$37,MATCH(COLUMN()-4,$AJ$18:$AJ$37,0)),_xlpm.ctry,$B90,_xlpm.apt,IFERROR(INDEX('VISA RULES'!$E$2:$E$400,SUMPRODUCT(MATCH(1,('VISA RULES'!$B$2:$B$400=_xlpm.ctry)*('VISA RULES'!$C$2:$C$400=_xlpm.nat)*('VISA RULES'!$A$2:$A$400<>""),0))),""),_xlpm.rule,IFERROR(INDEX('VISA RULES'!$E$2:$E$400,SUMPRODUCT(MATCH(1,('VISA RULES'!$B$2:$B$400=_xlpm.ctry)*('VISA RULES'!$C$2:$C$400=_xlpm.nat)*('VISA RULES'!$A$2:$A$400=""),0))),""),_xlpm.mtx,IFERROR(INDEX('VISA MATRIX'!$B$4:$FS$145,MATCH(_xlpm.ctry,'VISA MATRIX'!$A$4:$A$145,0),MATCH(_xlpm.nat,'VISA MATRIX'!$B$3:$FS$3,0)),""),IF(_xlpm.apt<>"",_xlpm.apt&" (APT OVERRIDE)",IF(_xlpm.rule<>"",_xlpm.rule,IF(_xlpm.mtx<>"",_xlpm.mtx,"NOT ON FILE - VERIFY")))))} | F90: {=IF(OR($A90="",F$87=""),"",_xlfn.LET(_xlpm.nat,INDEX($AH$18:$AH$37,MATCH(COLUMN()-4,$AJ$18:$AJ$37,0)),_xlpm.ctry,$B90,_xlpm.apt,IFERROR(INDEX('VISA RULES'!$E$2:$E$400,SUMPRODUCT(MATCH(1,('VISA RULES'!$B$2:$B$400=_xlpm.ctry)*('VISA RULES'!$C$2:$C$400=_xlpm.nat)*('VISA RULES'!$A$2:$A$400<>""),0))),""),_xlpm.rule,IFERROR(INDEX('VISA RULES'!$E$2:$E$400,SUMPRODUCT(MATCH(1,('VISA RULES'!$B$2:$B$400=_xlpm.ctry)*('VISA RULES'!$C$2:$C$400=_xlpm.nat)*('VISA RULES'!$A$2:$A$400=""),0))),""),_xlpm.mtx,IFERROR(INDEX('VISA MATRIX'!$B$4:$FS$145,MATCH(_xlpm.ctry,'VISA MATRIX'!$A$4:$A$145,0),MATCH(_xlpm.nat,'VISA MATRIX'!$B$3:$FS$3,0)),""),IF(_xlpm.apt<>"",_xlpm.apt&" (APT OVERRIDE)",IF(_xlpm.rule<>"",_xlpm.rule,IF(_xlpm.mtx<>"",_xlpm.mtx,"NOT ON FILE - VERIFY")))))} | G90: {=IF(OR($A90="",G$87=""),"",_xlfn.LET(_xlpm.nat,INDEX($AH$18:$AH$37,MATCH(COLUMN()-4,$AJ$18:$AJ$37,0)),_xlpm.ctry,$B90,_xlpm.apt,IFERROR(INDEX('VISA RULES'!$E$2:$E$400,SUMPRODUCT(MATCH(1,('VISA RULES'!$B$2:$B$400=_xlpm.ctry)*('VISA RULES'!$C$2:$C$400=_xlpm.nat)*('VISA RULES'!$A$2:$A$400<>""),0))),""),_xlpm.rule,IFERROR(INDEX('VISA RULES'!$E$2:$E$400,SUMPRODUCT(MATCH(1,('VISA RULES'!$B$2:$B$400=_xlpm.ctry)*('VISA RULES'!$C$2:$C$400=_xlpm.nat)*('VISA RULES'!$A$2:$A$400=""),0))),""),_xlpm.mtx,IFERROR(INDEX('VISA MATRIX'!$B$4:$FS$145,MATCH(_xlpm.ctry,'VISA MATRIX'!$A$4:$A$145,0),MATCH(_xlpm.nat,'VISA MATRIX'!$B$3:$FS$3,0)),""),IF(_xlpm.apt<>"",_xlpm.apt&" (APT OVERRIDE)",IF(_xlpm.rule<>"",_xlpm.rule,IF(_xlpm.mtx<>"",_xlpm.mtx,"NOT ON FILE - VERIFY")))))} | H90: {=IF(OR($A90="",H$87=""),"",_xlfn.LET(_xlpm.nat,INDEX($AH$18:$AH$37,MATCH(COLUMN()-4,$AJ$18:$AJ$37,0)),_xlpm.ctry,$B90,_xlpm.apt,IFERROR(INDEX('VISA RULES'!$E$2:$E$400,SUMPRODUCT(MATCH(1,('VISA RULES'!$B$2:$B$400=_xlpm.ctry)*('VISA RULES'!$C$2:$C$400=_xlpm.nat)*('VISA RULES'!$A$2:$A$400<>""),0))),""),_xlpm.rule,IFERROR(INDEX('VISA RULES'!$E$2:$E$400,SUMPRODUCT(MATCH(1,('VISA RULES'!$B$2:$B$400=_xlpm.ctry)*('VISA RULES'!$C$2:$C$400=_xlpm.nat)*('VISA RULES'!$A$2:$A$400=""),0))),""),_xlpm.mtx,IFERROR(INDEX('VISA MATRIX'!$B$4:$FS$145,MATCH(_xlpm.ctry,'VISA MATRIX'!$A$4:$A$145,0),MATCH(_xlpm.nat,'VISA MATRIX'!$B$3:$FS$3,0)),""),IF(_xlpm.apt<>"",_xlpm.apt&" (APT OVERRIDE)",IF(_xlpm.rule<>"",_xlpm.rule,IF(_xlpm.mtx<>"",_xlpm.mtx,"NOT ON FILE - VERIFY")))))} | I90: {=IF(OR($A90="",I$87=""),"",_xlfn.LET(_xlpm.nat,INDEX($AH$18:$AH$37,MATCH(COLUMN()-4,$AJ$18:$AJ$37,0)),_xlpm.ctry,$B90,_xlpm.apt,IFERROR(INDEX('VISA RULES'!$E$2:$E$400,SUMPRODUCT(MATCH(1,('VISA RULES'!$B$2:$B$400=_xlpm.ctry)*('VISA RULES'!$C$2:$C$400=_xlpm.nat)*('VISA RULES'!$A$2:$A$400<>""),0))),""),_xlpm.rule,IFERROR(INDEX('VISA RULES'!$E$2:$E$400,SUMPRODUCT(MATCH(1,('VISA RULES'!$B$2:$B$400=_xlpm.ctry)*('VISA RULES'!$C$2:$C$400=_xlpm.nat)*('VISA RULES'!$A$2:$A$400=""),0))),""),_xlpm.mtx,IFERROR(INDEX('VISA MATRIX'!$B$4:$FS$145,MATCH(_xlpm.ctry,'VISA MATRIX'!$A$4:$A$145,0),MATCH(_xlpm.nat,'VISA MATRIX'!$B$3:$FS$3,0)),""),IF(_xlpm.apt<>"",_xlpm.apt&" (APT OVERRIDE)",IF(_xlpm.rule<>"",_xlpm.rule,IF(_xlpm.mtx<>"",_xlpm.mtx,"NOT ON FILE - VERIFY")))))} | J90: {=IF(OR($A90="",J$87=""),"",_xlfn.LET(_xlpm.nat,INDEX($AH$18:$AH$37,MATCH(COLUMN()-4,$AJ$18:$AJ$37,0)),_xlpm.ctry,$B90,_xlpm.apt,IFERROR(INDEX('VISA RULES'!$E$2:$E$400,SUMPRODUCT(MATCH(1,('VISA RULES'!$B$2:$B$400=_xlpm.ctry)*('VISA RULES'!$C$2:$C$400=_xlpm.nat)*('VISA RULES'!$A$2:$A$400<>""),0))),""),_xlpm.rule,IFERROR(INDEX('VISA RULES'!$E$2:$E$400,SUMPRODUCT(MATCH(1,('VISA RULES'!$B$2:$B$400=_xlpm.ctry)*('VISA RULES'!$C$2:$C$400=_xlpm.nat)*('VISA RULES'!$A$2:$A$400=""),0))),""),_xlpm.mtx,IFERROR(INDEX('VISA MATRIX'!$B$4:$FS$145,MATCH(_xlpm.ctry,'VISA MATRIX'!$A$4:$A$145,0),MATCH(_xlpm.nat,'VISA MATRIX'!$B$3:$FS$3,0)),""),IF(_xlpm.apt<>"",_xlpm.apt&" (APT OVERRIDE)",IF(_xlpm.rule<>"",_xlpm.rule,IF(_xlpm.mtx<>"",_xlpm.mtx,"NOT ON FILE - VERIFY")))))}
A91: =IF(ROW()-87>SUM($AO$18:$AO$26),"",ROW()-87) | B91: =IF($A91="","",IFERROR(INDEX(countries!$B:$B,MATCH($C91,countries!$D:$D,0)),$C91)) | C91: =IF($A91="","",INDEX($AK$18:$AK$26,MATCH($A91,$AP$18:$AP$26,0))) | D91: {=IF($A91="","",_xlfn.TEXTJOIN(", ",TRUE,IF($AK$18:$AK$26=$C91,$AM$18:$AM$26,"")))} | E91: {=IF(OR($A91="",E$87=""),"",_xlfn.LET(_xlpm.nat,INDEX($AH$18:$AH$37,MATCH(COLUMN()-4,$AJ$18:$AJ$37,0)),_xlpm.ctry,$B91,_xlpm.apt,IFERROR(INDEX('VISA RULES'!$E$2:$E$400,SUMPRODUCT(MATCH(1,('VISA RULES'!$B$2:$B$400=_xlpm.ctry)*('VISA RULES'!$C$2:$C$400=_xlpm.nat)*('VISA RULES'!$A$2:$A$400<>""),0))),""),_xlpm.rule,IFERROR(INDEX('VISA RULES'!$E$2:$E$400,SUMPRODUCT(MATCH(1,('VISA RULES'!$B$2:$B$400=_xlpm.ctry)*('VISA RULES'!$C$2:$C$400=_xlpm.nat)*('VISA RULES'!$A$2:$A$400=""),0))),""),_xlpm.mtx,IFERROR(INDEX('VISA MATRIX'!$B$4:$FS$145,MATCH(_xlpm.ctry,'VISA MATRIX'!$A$4:$A$145,0),MATCH(_xlpm.nat,'VISA MATRIX'!$B$3:$FS$3,0)),""),IF(_xlpm.apt<>"",_xlpm.apt&" (APT OVERRIDE)",IF(_xlpm.rule<>"",_xlpm.rule,IF(_xlpm.mtx<>"",_xlpm.mtx,"NOT ON FILE - VERIFY")))))} | F91: {=IF(OR($A91="",F$87=""),"",_xlfn.LET(_xlpm.nat,INDEX($AH$18:$AH$37,MATCH(COLUMN()-4,$AJ$18:$AJ$37,0)),_xlpm.ctry,$B91,_xlpm.apt,IFERROR(INDEX('VISA RULES'!$E$2:$E$400,SUMPRODUCT(MATCH(1,('VISA RULES'!$B$2:$B$400=_xlpm.ctry)*('VISA RULES'!$C$2:$C$400=_xlpm.nat)*('VISA RULES'!$A$2:$A$400<>""),0))),""),_xlpm.rule,IFERROR(INDEX('VISA RULES'!$E$2:$E$400,SUMPRODUCT(MATCH(1,('VISA RULES'!$B$2:$B$400=_xlpm.ctry)*('VISA RULES'!$C$2:$C$400=_xlpm.nat)*('VISA RULES'!$A$2:$A$400=""),0))),""),_xlpm.mtx,IFERROR(INDEX('VISA MATRIX'!$B$4:$FS$145,MATCH(_xlpm.ctry,'VISA MATRIX'!$A$4:$A$145,0),MATCH(_xlpm.nat,'VISA MATRIX'!$B$3:$FS$3,0)),""),IF(_xlpm.apt<>"",_xlpm.apt&" (APT OVERRIDE)",IF(_xlpm.rule<>"",_xlpm.rule,IF(_xlpm.mtx<>"",_xlpm.mtx,"NOT ON FILE - VERIFY")))))} | G91: {=IF(OR($A91="",G$87=""),"",_xlfn.LET(_xlpm.nat,INDEX($AH$18:$AH$37,MATCH(COLUMN()-4,$AJ$18:$AJ$37,0)),_xlpm.ctry,$B91,_xlpm.apt,IFERROR(INDEX('VISA RULES'!$E$2:$E$400,SUMPRODUCT(MATCH(1,('VISA RULES'!$B$2:$B$400=_xlpm.ctry)*('VISA RULES'!$C$2:$C$400=_xlpm.nat)*('VISA RULES'!$A$2:$A$400<>""),0))),""),_xlpm.rule,IFERROR(INDEX('VISA RULES'!$E$2:$E$400,SUMPRODUCT(MATCH(1,('VISA RULES'!$B$2:$B$400=_xlpm.ctry)*('VISA RULES'!$C$2:$C$400=_xlpm.nat)*('VISA RULES'!$A$2:$A$400=""),0))),""),_xlpm.mtx,IFERROR(INDEX('VISA MATRIX'!$B$4:$FS$145,MATCH(_xlpm.ctry,'VISA MATRIX'!$A$4:$A$145,0),MATCH(_xlpm.nat,'VISA MATRIX'!$B$3:$FS$3,0)),""),IF(_xlpm.apt<>"",_xlpm.apt&" (APT OVERRIDE)",IF(_xlpm.rule<>"",_xlpm.rule,IF(_xlpm.mtx<>"",_xlpm.mtx,"NOT ON FILE - VERIFY")))))} | H91: {=IF(OR($A91="",H$87=""),"",_xlfn.LET(_xlpm.nat,INDEX($AH$18:$AH$37,MATCH(COLUMN()-4,$AJ$18:$AJ$37,0)),_xlpm.ctry,$B91,_xlpm.apt,IFERROR(INDEX('VISA RULES'!$E$2:$E$400,SUMPRODUCT(MATCH(1,('VISA RULES'!$B$2:$B$400=_xlpm.ctry)*('VISA RULES'!$C$2:$C$400=_xlpm.nat)*('VISA RULES'!$A$2:$A$400<>""),0))),""),_xlpm.rule,IFERROR(INDEX('VISA RULES'!$E$2:$E$400,SUMPRODUCT(MATCH(1,('VISA RULES'!$B$2:$B$400=_xlpm.ctry)*('VISA RULES'!$C$2:$C$400=_xlpm.nat)*('VISA RULES'!$A$2:$A$400=""),0))),""),_xlpm.mtx,IFERROR(INDEX('VISA MATRIX'!$B$4:$FS$145,MATCH(_xlpm.ctry,'VISA MATRIX'!$A$4:$A$145,0),MATCH(_xlpm.nat,'VISA MATRIX'!$B$3:$FS$3,0)),""),IF(_xlpm.apt<>"",_xlpm.apt&" (APT OVERRIDE)",IF(_xlpm.rule<>"",_xlpm.rule,IF(_xlpm.mtx<>"",_xlpm.mtx,"NOT ON FILE - VERIFY")))))} | I91: {=IF(OR($A91="",I$87=""),"",_xlfn.LET(_xlpm.nat,INDEX($AH$18:$AH$37,MATCH(COLUMN()-4,$AJ$18:$AJ$37,0)),_xlpm.ctry,$B91,_xlpm.apt,IFERROR(INDEX('VISA RULES'!$E$2:$E$400,SUMPRODUCT(MATCH(1,('VISA RULES'!$B$2:$B$400=_xlpm.ctry)*('VISA RULES'!$C$2:$C$400=_xlpm.nat)*('VISA RULES'!$A$2:$A$400<>""),0))),""),_xlpm.rule,IFERROR(INDEX('VISA RULES'!$E$2:$E$400,SUMPRODUCT(MATCH(1,('VISA RULES'!$B$2:$B$400=_xlpm.ctry)*('VISA RULES'!$C$2:$C$400=_xlpm.nat)*('VISA RULES'!$A$2:$A$400=""),0))),""),_xlpm.mtx,IFERROR(INDEX('VISA MATRIX'!$B$4:$FS$145,MATCH(_xlpm.ctry,'VISA MATRIX'!$A$4:$A$145,0),MATCH(_xlpm.nat,'VISA MATRIX'!$B$3:$FS$3,0)),""),IF(_xlpm.apt<>"",_xlpm.apt&" (APT OVERRIDE)",IF(_xlpm.rule<>"",_xlpm.rule,IF(_xlpm.mtx<>"",_xlpm.mtx,"NOT ON FILE - VERIFY")))))} | J91: {=IF(OR($A91="",J$87=""),"",_xlfn.LET(_xlpm.nat,INDEX($AH$18:$AH$37,MATCH(COLUMN()-4,$AJ$18:$AJ$37,0)),_xlpm.ctry,$B91,_xlpm.apt,IFERROR(INDEX('VISA RULES'!$E$2:$E$400,SUMPRODUCT(MATCH(1,('VISA RULES'!$B$2:$B$400=_xlpm.ctry)*('VISA RULES'!$C$2:$C$400=_xlpm.nat)*('VISA RULES'!$A$2:$A$400<>""),0))),""),_xlpm.rule,IFERROR(INDEX('VISA RULES'!$E$2:$E$400,SUMPRODUCT(MATCH(1,('VISA RULES'!$B$2:$B$400=_xlpm.ctry)*('VISA RULES'!$C$2:$C$400=_xlpm.nat)*('VISA RULES'!$A$2:$A$400=""),0))),""),_xlpm.mtx,IFERROR(INDEX('VISA MATRIX'!$B$4:$FS$145,MATCH(_xlpm.ctry,'VISA MATRIX'!$A$4:$A$145,0),MATCH(_xlpm.nat,'VISA MATRIX'!$B$3:$FS$3,0)),""),IF(_xlpm.apt<>"",_xlpm.apt&" (APT OVERRIDE)",IF(_xlpm.rule<>"",_xlpm.rule,IF(_xlpm.mtx<>"",_xlpm.mtx,"NOT ON FILE - VERIFY")))))}
A92: =IF(ROW()-87>SUM($AO$18:$AO$26),"",ROW()-87) | B92: =IF($A92="","",IFERROR(INDEX(countries!$B:$B,MATCH($C92,countries!$D:$D,0)),$C92)) | C92: =IF($A92="","",INDEX($AK$18:$AK$26,MATCH($A92,$AP$18:$AP$26,0))) | D92: {=IF($A92="","",_xlfn.TEXTJOIN(", ",TRUE,IF($AK$18:$AK$26=$C92,$AM$18:$AM$26,"")))} | E92: {=IF(OR($A92="",E$87=""),"",_xlfn.LET(_xlpm.nat,INDEX($AH$18:$AH$37,MATCH(COLUMN()-4,$AJ$18:$AJ$37,0)),_xlpm.ctry,$B92,_xlpm.apt,IFERROR(INDEX('VISA RULES'!$E$2:$E$400,SUMPRODUCT(MATCH(1,('VISA RULES'!$B$2:$B$400=_xlpm.ctry)*('VISA RULES'!$C$2:$C$400=_xlpm.nat)*('VISA RULES'!$A$2:$A$400<>""),0))),""),_xlpm.rule,IFERROR(INDEX('VISA RULES'!$E$2:$E$400,SUMPRODUCT(MATCH(1,('VISA RULES'!$B$2:$B$400=_xlpm.ctry)*('VISA RULES'!$C$2:$C$400=_xlpm.nat)*('VISA RULES'!$A$2:$A$400=""),0))),""),_xlpm.mtx,IFERROR(INDEX('VISA MATRIX'!$B$4:$FS$145,MATCH(_xlpm.ctry,'VISA MATRIX'!$A$4:$A$145,0),MATCH(_xlpm.nat,'VISA MATRIX'!$B$3:$FS$3,0)),""),IF(_xlpm.apt<>"",_xlpm.apt&" (APT OVERRIDE)",IF(_xlpm.rule<>"",_xlpm.rule,IF(_xlpm.mtx<>"",_xlpm.mtx,"NOT ON FILE - VERIFY")))))} | F92: {=IF(OR($A92="",F$87=""),"",_xlfn.LET(_xlpm.nat,INDEX($AH$18:$AH$37,MATCH(COLUMN()-4,$AJ$18:$AJ$37,0)),_xlpm.ctry,$B92,_xlpm.apt,IFERROR(INDEX('VISA RULES'!$E$2:$E$400,SUMPRODUCT(MATCH(1,('VISA RULES'!$B$2:$B$400=_xlpm.ctry)*('VISA RULES'!$C$2:$C$400=_xlpm.nat)*('VISA RULES'!$A$2:$A$400<>""),0))),""),_xlpm.rule,IFERROR(INDEX('VISA RULES'!$E$2:$E$400,SUMPRODUCT(MATCH(1,('VISA RULES'!$B$2:$B$400=_xlpm.ctry)*('VISA RULES'!$C$2:$C$400=_xlpm.nat)*('VISA RULES'!$A$2:$A$400=""),0))),""),_xlpm.mtx,IFERROR(INDEX('VISA MATRIX'!$B$4:$FS$145,MATCH(_xlpm.ctry,'VISA MATRIX'!$A$4:$A$145,0),MATCH(_xlpm.nat,'VISA MATRIX'!$B$3:$FS$3,0)),""),IF(_xlpm.apt<>"",_xlpm.apt&" (APT OVERRIDE)",IF(_xlpm.rule<>"",_xlpm.rule,IF(_xlpm.mtx<>"",_xlpm.mtx,"NOT ON FILE - VERIFY")))))} | G92: {=IF(OR($A92="",G$87=""),"",_xlfn.LET(_xlpm.nat,INDEX($AH$18:$AH$37,MATCH(COLUMN()-4,$AJ$18:$AJ$37,0)),_xlpm.ctry,$B92,_xlpm.apt,IFERROR(INDEX('VISA RULES'!$E$2:$E$400,SUMPRODUCT(MATCH(1,('VISA RULES'!$B$2:$B$400=_xlpm.ctry)*('VISA RULES'!$C$2:$C$400=_xlpm.nat)*('VISA RULES'!$A$2:$A$400<>""),0))),""),_xlpm.rule,IFERROR(INDEX('VISA RULES'!$E$2:$E$400,SUMPRODUCT(MATCH(1,('VISA RULES'!$B$2:$B$400=_xlpm.ctry)*('VISA RULES'!$C$2:$C$400=_xlpm.nat)*('VISA RULES'!$A$2:$A$400=""),0))),""),_xlpm.mtx,IFERROR(INDEX('VISA MATRIX'!$B$4:$FS$145,MATCH(_xlpm.ctry,'VISA MATRIX'!$A$4:$A$145,0),MATCH(_xlpm.nat,'VISA MATRIX'!$B$3:$FS$3,0)),""),IF(_xlpm.apt<>"",_xlpm.apt&" (APT OVERRIDE)",IF(_xlpm.rule<>"",_xlpm.rule,IF(_xlpm.mtx<>"",_xlpm.mtx,"NOT ON FILE - VERIFY")))))} | H92: {=IF(OR($A92="",H$87=""),"",_xlfn.LET(_xlpm.nat,INDEX($AH$18:$AH$37,MATCH(COLUMN()-4,$AJ$18:$AJ$37,0)),_xlpm.ctry,$B92,_xlpm.apt,IFERROR(INDEX('VISA RULES'!$E$2:$E$400,SUMPRODUCT(MATCH(1,('VISA RULES'!$B$2:$B$400=_xlpm.ctry)*('VISA RULES'!$C$2:$C$400=_xlpm.nat)*('VISA RULES'!$A$2:$A$400<>""),0))),""),_xlpm.rule,IFERROR(INDEX('VISA RULES'!$E$2:$E$400,SUMPRODUCT(MATCH(1,('VISA RULES'!$B$2:$B$400=_xlpm.ctry)*('VISA RULES'!$C$2:$C$400=_xlpm.nat)*('VISA RULES'!$A$2:$A$400=""),0))),""),_xlpm.mtx,IFERROR(INDEX('VISA MATRIX'!$B$4:$FS$145,MATCH(_xlpm.ctry,'VISA MATRIX'!$A$4:$A$145,0),MATCH(_xlpm.nat,'VISA MATRIX'!$B$3:$FS$3,0)),""),IF(_xlpm.apt<>"",_xlpm.apt&" (APT OVERRIDE)",IF(_xlpm.rule<>"",_xlpm.rule,IF(_xlpm.mtx<>"",_xlpm.mtx,"NOT ON FILE - VERIFY")))))} | I92: {=IF(OR($A92="",I$87=""),"",_xlfn.LET(_xlpm.nat,INDEX($AH$18:$AH$37,MATCH(COLUMN()-4,$AJ$18:$AJ$37,0)),_xlpm.ctry,$B92,_xlpm.apt,IFERROR(INDEX('VISA RULES'!$E$2:$E$400,SUMPRODUCT(MATCH(1,('VISA RULES'!$B$2:$B$400=_xlpm.ctry)*('VISA RULES'!$C$2:$C$400=_xlpm.nat)*('VISA RULES'!$A$2:$A$400<>""),0))),""),_xlpm.rule,IFERROR(INDEX('VISA RULES'!$E$2:$E$400,SUMPRODUCT(MATCH(1,('VISA RULES'!$B$2:$B$400=_xlpm.ctry)*('VISA RULES'!$C$2:$C$400=_xlpm.nat)*('VISA RULES'!$A$2:$A$400=""),0))),""),_xlpm.mtx,IFERROR(INDEX('VISA MATRIX'!$B$4:$FS$145,MATCH(_xlpm.ctry,'VISA MATRIX'!$A$4:$A$145,0),MATCH(_xlpm.nat,'VISA MATRIX'!$B$3:$FS$3,0)),""),IF(_xlpm.apt<>"",_xlpm.apt&" (APT OVERRIDE)",IF(_xlpm.rule<>"",_xlpm.rule,IF(_xlpm.mtx<>"",_xlpm.mtx,"NOT ON FILE - VERIFY")))))} | J92: {=IF(OR($A92="",J$87=""),"",_xlfn.LET(_xlpm.nat,INDEX($AH$18:$AH$37,MATCH(COLUMN()-4,$AJ$18:$AJ$37,0)),_xlpm.ctry,$B92,_xlpm.apt,IFERROR(INDEX('VISA RULES'!$E$2:$E$400,SUMPRODUCT(MATCH(1,('VISA RULES'!$B$2:$B$400=_xlpm.ctry)*('VISA RULES'!$C$2:$C$400=_xlpm.nat)*('VISA RULES'!$A$2:$A$400<>""),0))),""),_xlpm.rule,IFERROR(INDEX('VISA RULES'!$E$2:$E$400,SUMPRODUCT(MATCH(1,('VISA RULES'!$B$2:$B$400=_xlpm.ctry)*('VISA RULES'!$C$2:$C$400=_xlpm.nat)*('VISA RULES'!$A$2:$A$400=""),0))),""),_xlpm.mtx,IFERROR(INDEX('VISA MATRIX'!$B$4:$FS$145,MATCH(_xlpm.ctry,'VISA MATRIX'!$A$4:$A$145,0),MATCH(_xlpm.nat,'VISA MATRIX'!$B$3:$FS$3,0)),""),IF(_xlpm.apt<>"",_xlpm.apt&" (APT OVERRIDE)",IF(_xlpm.rule<>"",_xlpm.rule,IF(_xlpm.mtx<>"",_xlpm.mtx,"NOT ON FILE - VERIFY")))))}
A93: =IF(ROW()-87>SUM($AO$18:$AO$26),"",ROW()-87) | B93: =IF($A93="","",IFERROR(INDEX(countries!$B:$B,MATCH($C93,countries!$D:$D,0)),$C93)) | C93: =IF($A93="","",INDEX($AK$18:$AK$26,MATCH($A93,$AP$18:$AP$26,0))) | D93: {=IF($A93="","",_xlfn.TEXTJOIN(", ",TRUE,IF($AK$18:$AK$26=$C93,$AM$18:$AM$26,"")))} | E93: {=IF(OR($A93="",E$87=""),"",IF(IFERROR(INDEX('VISA MATRIX'!$B$4:$FS$145,MATCH($B93,'VISA MATRIX'!$A$4:$A$145,0),MATCH(INDEX($AH$18:$AH$37,MATCH(COLUMN()-4,$AJ$18:$AJ$37,0)),'VISA MATRIX'!$B$3:$FS$3,0)),"")<>"",IFERROR(INDEX('VISA MATRIX'!$B$4:$FS$145,MATCH($B93,'VISA MATRIX'!$A$4:$A$145,0),MATCH(INDEX($AH$18:$AH$37,MATCH(COLUMN()-4,$AJ$18:$AJ$37,0)),'VISA MATRIX'!$B$3:$FS$3,0)),""),IF(IFERROR(INDEX('VISA RULES'!$E$2:$E$400,SUMPRODUCT(MATCH(1,($B93='VISA RULES'!$B$2:$B$400)*(INDEX($AH$18:$AH$37,MATCH(COLUMN()-4,$AJ$18:$AJ$37,0))='VISA RULES'!$C$2:$C$400),0))),"")<>"",IFERROR(INDEX('VISA RULES'!$E$2:$E$400,SUMPRODUCT(MATCH(1,($B93='VISA RULES'!$B$2:$B$400)*(INDEX($AH$18:$AH$37,MATCH(COLUMN()-4,$AJ$18:$AJ$37,0))='VISA RULES'!$C$2:$C$400),0))),""),"NOT ON FILE - VERIFY")))} | F93: {=IF(OR($A93="",F$87=""),"",IF(IFERROR(INDEX('VISA MATRIX'!$B$4:$FS$145,MATCH($B93,'VISA MATRIX'!$A$4:$A$145,0),MATCH(INDEX($AH$18:$AH$37,MATCH(COLUMN()-4,$AJ$18:$AJ$37,0)),'VISA MATRIX'!$B$3:$FS$3,0)),"")<>"",IFERROR(INDEX('VISA MATRIX'!$B$4:$FS$145,MATCH($B93,'VISA MATRIX'!$A$4:$A$145,0),MATCH(INDEX($AH$18:$AH$37,MATCH(COLUMN()-4,$AJ$18:$AJ$37,0)),'VISA MATRIX'!$B$3:$FS$3,0)),""),IF(IFERROR(INDEX('VISA RULES'!$E$2:$E$400,SUMPRODUCT(MATCH(1,($B93='VISA RULES'!$B$2:$B$400)*(INDEX($AH$18:$AH$37,MATCH(COLUMN()-4,$AJ$18:$AJ$37,0))='VISA RULES'!$C$2:$C$400),0))),"")<>"",IFERROR(INDEX('VISA RULES'!$E$2:$E$400,SUMPRODUCT(MATCH(1,($B93='VISA RULES'!$B$2:$B$400)*(INDEX($AH$18:$AH$37,MATCH(COLUMN()-4,$AJ$18:$AJ$37,0))='VISA RULES'!$C$2:$C$400),0))),""),"NOT ON FILE - VERIFY")))} | G93: {=IF(OR($A93="",G$87=""),"",IF(IFERROR(INDEX('VISA MATRIX'!$B$4:$FS$145,MATCH($B93,'VISA MATRIX'!$A$4:$A$145,0),MATCH(INDEX($AH$18:$AH$37,MATCH(COLUMN()-4,$AJ$18:$AJ$37,0)),'VISA MATRIX'!$B$3:$FS$3,0)),"")<>"",IFERROR(INDEX('VISA MATRIX'!$B$4:$FS$145,MATCH($B93,'VISA MATRIX'!$A$4:$A$145,0),MATCH(INDEX($AH$18:$AH$37,MATCH(COLUMN()-4,$AJ$18:$AJ$37,0)),'VISA MATRIX'!$B$3:$FS$3,0)),""),IF(IFERROR(INDEX('VISA RULES'!$E$2:$E$400,SUMPRODUCT(MATCH(1,($B93='VISA RULES'!$B$2:$B$400)*(INDEX($AH$18:$AH$37,MATCH(COLUMN()-4,$AJ$18:$AJ$37,0))='VISA RULES'!$C$2:$C$400),0))),"")<>"",IFERROR(INDEX('VISA RULES'!$E$2:$E$400,SUMPRODUCT(MATCH(1,($B93='VISA RULES'!$B$2:$B$400)*(INDEX($AH$18:$AH$37,MATCH(COLUMN()-4,$AJ$18:$AJ$37,0))='VISA RULES'!$C$2:$C$400),0))),""),"NOT ON FILE - VERIFY")))} | H93: {=IF(OR($A93="",H$87=""),"",IF(IFERROR(INDEX('VISA MATRIX'!$B$4:$FS$145,MATCH($B93,'VISA MATRIX'!$A$4:$A$145,0),MATCH(INDEX($AH$18:$AH$37,MATCH(COLUMN()-4,$AJ$18:$AJ$37,0)),'VISA MATRIX'!$B$3:$FS$3,0)),"")<>"",IFERROR(INDEX('VISA MATRIX'!$B$4:$FS$145,MATCH($B93,'VISA MATRIX'!$A$4:$A$145,0),MATCH(INDEX($AH$18:$AH$37,MATCH(COLUMN()-4,$AJ$18:$AJ$37,0)),'VISA MATRIX'!$B$3:$FS$3,0)),""),IF(IFERROR(INDEX('VISA RULES'!$E$2:$E$400,SUMPRODUCT(MATCH(1,($B93='VISA RULES'!$B$2:$B$400)*(INDEX($AH$18:$AH$37,MATCH(COLUMN()-4,$AJ$18:$AJ$37,0))='VISA RULES'!$C$2:$C$400),0))),"")<>"",IFERROR(INDEX('VISA RULES'!$E$2:$E$400,SUMPRODUCT(MATCH(1,($B93='VISA RULES'!$B$2:$B$400)*(INDEX($AH$18:$AH$37,MATCH(COLUMN()-4,$AJ$18:$AJ$37,0))='VISA RULES'!$C$2:$C$400),0))),""),"NOT ON FILE - VERIFY")))} | I93: {=IF(OR($A93="",I$87=""),"",IF(IFERROR(INDEX('VISA MATRIX'!$B$4:$FS$145,MATCH($B93,'VISA MATRIX'!$A$4:$A$145,0),MATCH(INDEX($AH$18:$AH$37,MATCH(COLUMN()-4,$AJ$18:$AJ$37,0)),'VISA MATRIX'!$B$3:$FS$3,0)),"")<>"",IFERROR(INDEX('VISA MATRIX'!$B$4:$FS$145,MATCH($B93,'VISA MATRIX'!$A$4:$A$145,0),MATCH(INDEX($AH$18:$AH$37,MATCH(COLUMN()-4,$AJ$18:$AJ$37,0)),'VISA MATRIX'!$B$3:$FS$3,0)),""),IF(IFERROR(INDEX('VISA RULES'!$E$2:$E$400,SUMPRODUCT(MATCH(1,($B93='VISA RULES'!$B$2:$B$400)*(INDEX($AH$18:$AH$37,MATCH(COLUMN()-4,$AJ$18:$AJ$37,0))='VISA RULES'!$C$2:$C$400),0))),"")<>"",IFERROR(INDEX('VISA RULES'!$E$2:$E$400,SUMPRODUCT(MATCH(1,($B93='VISA RULES'!$B$2:$B$400)*(INDEX($AH$18:$AH$37,MATCH(COLUMN()-4,$AJ$18:$AJ$37,0))='VISA RULES'!$C$2:$C$400),0))),""),"NOT ON FILE - VERIFY")))} | J93: {=IF(OR($A93="",J$87=""),"",IF(IFERROR(INDEX('VISA MATRIX'!$B$4:$FS$145,MATCH($B93,'VISA MATRIX'!$A$4:$A$145,0),MATCH(INDEX($AH$18:$AH$37,MATCH(COLUMN()-4,$AJ$18:$AJ$37,0)),'VISA MATRIX'!$B$3:$FS$3,0)),"")<>"",IFERROR(INDEX('VISA MATRIX'!$B$4:$FS$145,MATCH($B93,'VISA MATRIX'!$A$4:$A$145,0),MATCH(INDEX($AH$18:$AH$37,MATCH(COLUMN()-4,$AJ$18:$AJ$37,0)),'VISA MATRIX'!$B$3:$FS$3,0)),""),IF(IFERROR(INDEX('VISA RULES'!$E$2:$E$400,SUMPRODUCT(MATCH(1,($B93='VISA RULES'!$B$2:$B$400)*(INDEX($AH$18:$AH$37,MATCH(COLUMN()-4,$AJ$18:$AJ$37,0))='VISA RULES'!$C$2:$C$400),0))),"")<>"",IFERROR(INDEX('VISA RULES'!$E$2:$E$400,SUMPRODUCT(MATCH(1,($B93='VISA RULES'!$B$2:$B$400)*(INDEX($AH$18:$AH$37,MATCH(COLUMN()-4,$AJ$18:$AJ$37,0))='VISA RULES'!$C$2:$C$400),0))),""),"NOT ON FILE - VERIFY")))}
A94: =IF(ROW()-87>SUM($AO$18:$AO$26),"",ROW()-87) | B94: =IF($A94="","",IFERROR(INDEX(countries!$B:$B,MATCH($C94,countries!$D:$D,0)),$C94)) | C94: =IF($A94="","",INDEX($AK$18:$AK$26,MATCH($A94,$AP$18:$AP$26,0))) | D94: {=IF($A94="","",_xlfn.TEXTJOIN(", ",TRUE,IF($AK$18:$AK$26=$C94,$AM$18:$AM$26,"")))} | E94: {=IF(OR($A94="",E$87=""),"",IF(IFERROR(INDEX('VISA MATRIX'!$B$4:$FS$145,MATCH($B94,'VISA MATRIX'!$A$4:$A$145,0),MATCH(INDEX($AH$18:$AH$37,MATCH(COLUMN()-4,$AJ$18:$AJ$37,0)),'VISA MATRIX'!$B$3:$FS$3,0)),"")<>"",IFERROR(INDEX('VISA MATRIX'!$B$4:$FS$145,MATCH($B94,'VISA MATRIX'!$A$4:$A$145,0),MATCH(INDEX($AH$18:$AH$37,MATCH(COLUMN()-4,$AJ$18:$AJ$37,0)),'VISA MATRIX'!$B$3:$FS$3,0)),""),IF(IFERROR(INDEX('VISA RULES'!$E$2:$E$400,SUMPRODUCT(MATCH(1,($B94='VISA RULES'!$B$2:$B$400)*(INDEX($AH$18:$AH$37,MATCH(COLUMN()-4,$AJ$18:$AJ$37,0))='VISA RULES'!$C$2:$C$400),0))),"")<>"",IFERROR(INDEX('VISA RULES'!$E$2:$E$400,SUMPRODUCT(MATCH(1,($B94='VISA RULES'!$B$2:$B$400)*(INDEX($AH$18:$AH$37,MATCH(COLUMN()-4,$AJ$18:$AJ$37,0))='VISA RULES'!$C$2:$C$400),0))),""),"NOT ON FILE - VERIFY")))} | F94: {=IF(OR($A94="",F$87=""),"",IF(IFERROR(INDEX('VISA MATRIX'!$B$4:$FS$145,MATCH($B94,'VISA MATRIX'!$A$4:$A$145,0),MATCH(INDEX($AH$18:$AH$37,MATCH(COLUMN()-4,$AJ$18:$AJ$37,0)),'VISA MATRIX'!$B$3:$FS$3,0)),"")<>"",IFERROR(INDEX('VISA MATRIX'!$B$4:$FS$145,MATCH($B94,'VISA MATRIX'!$A$4:$A$145,0),MATCH(INDEX($AH$18:$AH$37,MATCH(COLUMN()-4,$AJ$18:$AJ$37,0)),'VISA MATRIX'!$B$3:$FS$3,0)),""),IF(IFERROR(INDEX('VISA RULES'!$E$2:$E$400,SUMPRODUCT(MATCH(1,($B94='VISA RULES'!$B$2:$B$400)*(INDEX($AH$18:$AH$37,MATCH(COLUMN()-4,$AJ$18:$AJ$37,0))='VISA RULES'!$C$2:$C$400),0))),"")<>"",IFERROR(INDEX('VISA RULES'!$E$2:$E$400,SUMPRODUCT(MATCH(1,($B94='VISA RULES'!$B$2:$B$400)*(INDEX($AH$18:$AH$37,MATCH(COLUMN()-4,$AJ$18:$AJ$37,0))='VISA RULES'!$C$2:$C$400),0))),""),"NOT ON FILE - VERIFY")))} | G94: {=IF(OR($A94="",G$87=""),"",IF(IFERROR(INDEX('VISA MATRIX'!$B$4:$FS$145,MATCH($B94,'VISA MATRIX'!$A$4:$A$145,0),MATCH(INDEX($AH$18:$AH$37,MATCH(COLUMN()-4,$AJ$18:$AJ$37,0)),'VISA MATRIX'!$B$3:$FS$3,0)),"")<>"",IFERROR(INDEX('VISA MATRIX'!$B$4:$FS$145,MATCH($B94,'VISA MATRIX'!$A$4:$A$145,0),MATCH(INDEX($AH$18:$AH$37,MATCH(COLUMN()-4,$AJ$18:$AJ$37,0)),'VISA MATRIX'!$B$3:$FS$3,0)),""),IF(IFERROR(INDEX('VISA RULES'!$E$2:$E$400,SUMPRODUCT(MATCH(1,($B94='VISA RULES'!$B$2:$B$400)*(INDEX($AH$18:$AH$37,MATCH(COLUMN()-4,$AJ$18:$AJ$37,0))='VISA RULES'!$C$2:$C$400),0))),"")<>"",IFERROR(INDEX('VISA RULES'!$E$2:$E$400,SUMPRODUCT(MATCH(1,($B94='VISA RULES'!$B$2:$B$400)*(INDEX($AH$18:$AH$37,MATCH(COLUMN()-4,$AJ$18:$AJ$37,0))='VISA RULES'!$C$2:$C$400),0))),""),"NOT ON FILE - VERIFY")))} | H94: {=IF(OR($A94="",H$87=""),"",IF(IFERROR(INDEX('VISA MATRIX'!$B$4:$FS$145,MATCH($B94,'VISA MATRIX'!$A$4:$A$145,0),MATCH(INDEX($AH$18:$AH$37,MATCH(COLUMN()-4,$AJ$18:$AJ$37,0)),'VISA MATRIX'!$B$3:$FS$3,0)),"")<>"",IFERROR(INDEX('VISA MATRIX'!$B$4:$FS$145,MATCH($B94,'VISA MATRIX'!$A$4:$A$145,0),MATCH(INDEX($AH$18:$AH$37,MATCH(COLUMN()-4,$AJ$18:$AJ$37,0)),'VISA MATRIX'!$B$3:$FS$3,0)),""),IF(IFERROR(INDEX('VISA RULES'!$E$2:$E$400,SUMPRODUCT(MATCH(1,($B94='VISA RULES'!$B$2:$B$400)*(INDEX($AH$18:$AH$37,MATCH(COLUMN()-4,$AJ$18:$AJ$37,0))='VISA RULES'!$C$2:$C$400),0))),"")<>"",IFERROR(INDEX('VISA RULES'!$E$2:$E$400,SUMPRODUCT(MATCH(1,($B94='VISA RULES'!$B$2:$B$400)*(INDEX($AH$18:$AH$37,MATCH(COLUMN()-4,$AJ$18:$AJ$37,0))='VISA RULES'!$C$2:$C$400),0))),""),"NOT ON FILE - VERIFY")))} | I94: {=IF(OR($A94="",I$87=""),"",IF(IFERROR(INDEX('VISA MATRIX'!$B$4:$FS$145,MATCH($B94,'VISA MATRIX'!$A$4:$A$145,0),MATCH(INDEX($AH$18:$AH$37,MATCH(COLUMN()-4,$AJ$18:$AJ$37,0)),'VISA MATRIX'!$B$3:$FS$3,0)),"")<>"",IFERROR(INDEX('VISA MATRIX'!$B$4:$FS$145,MATCH($B94,'VISA MATRIX'!$A$4:$A$145,0),MATCH(INDEX($AH$18:$AH$37,MATCH(COLUMN()-4,$AJ$18:$AJ$37,0)),'VISA MATRIX'!$B$3:$FS$3,0)),""),IF(IFERROR(INDEX('VISA RULES'!$E$2:$E$400,SUMPRODUCT(MATCH(1,($B94='VISA RULES'!$B$2:$B$400)*(INDEX($AH$18:$AH$37,MATCH(COLUMN()-4,$AJ$18:$AJ$37,0))='VISA RULES'!$C$2:$C$400),0))),"")<>"",IFERROR(INDEX('VISA RULES'!$E$2:$E$400,SUMPRODUCT(MATCH(1,($B94='VISA RULES'!$B$2:$B$400)*(INDEX($AH$18:$AH$37,MATCH(COLUMN()-4,$AJ$18:$AJ$37,0))='VISA RULES'!$C$2:$C$400),0))),""),"NOT ON FILE - VERIFY")))} | J94: {=IF(OR($A94="",J$87=""),"",IF(IFERROR(INDEX('VISA MATRIX'!$B$4:$FS$145,MATCH($B94,'VISA MATRIX'!$A$4:$A$145,0),MATCH(INDEX($AH$18:$AH$37,MATCH(COLUMN()-4,$AJ$18:$AJ$37,0)),'VISA MATRIX'!$B$3:$FS$3,0)),"")<>"",IFERROR(INDEX('VISA MATRIX'!$B$4:$FS$145,MATCH($B94,'VISA MATRIX'!$A$4:$A$145,0),MATCH(INDEX($AH$18:$AH$37,MATCH(COLUMN()-4,$AJ$18:$AJ$37,0)),'VISA MATRIX'!$B$3:$FS$3,0)),""),IF(IFERROR(INDEX('VISA RULES'!$E$2:$E$400,SUMPRODUCT(MATCH(1,($B94='VISA RULES'!$B$2:$B$400)*(INDEX($AH$18:$AH$37,MATCH(COLUMN()-4,$AJ$18:$AJ$37,0))='VISA RULES'!$C$2:$C$400),0))),"")<>"",IFERROR(INDEX('VISA RULES'!$E$2:$E$400,SUMPRODUCT(MATCH(1,($B94='VISA RULES'!$B$2:$B$400)*(INDEX($AH$18:$AH$37,MATCH(COLUMN()-4,$AJ$18:$AJ$37,0))='VISA RULES'!$C$2:$C$400),0))),""),"NOT ON FILE - VERIFY")))}
A95: =IF(ROW()-87>SUM($AO$18:$AO$26),"",ROW()-87) | B95: =IF($A95="","",IFERROR(INDEX(countries!$B:$B,MATCH($C95,countries!$D:$D,0)),$C95)) | C95: =IF($A95="","",INDEX($AK$18:$AK$26,MATCH($A95,$AP$18:$AP$26,0))) | D95: {=IF($A95="","",_xlfn.TEXTJOIN(", ",TRUE,IF($AK$18:$AK$26=$C95,$AM$18:$AM$26,"")))} | E95: {=IF(OR($A95="",E$87=""),"",IF(IFERROR(INDEX('VISA MATRIX'!$B$4:$FS$145,MATCH($B95,'VISA MATRIX'!$A$4:$A$145,0),MATCH(INDEX($AH$18:$AH$37,MATCH(COLUMN()-4,$AJ$18:$AJ$37,0)),'VISA MATRIX'!$B$3:$FS$3,0)),"")<>"",IFERROR(INDEX('VISA MATRIX'!$B$4:$FS$145,MATCH($B95,'VISA MATRIX'!$A$4:$A$145,0),MATCH(INDEX($AH$18:$AH$37,MATCH(COLUMN()-4,$AJ$18:$AJ$37,0)),'VISA MATRIX'!$B$3:$FS$3,0)),""),IF(IFERROR(INDEX('VISA RULES'!$E$2:$E$400,SUMPRODUCT(MATCH(1,($B95='VISA RULES'!$B$2:$B$400)*(INDEX($AH$18:$AH$37,MATCH(COLUMN()-4,$AJ$18:$AJ$37,0))='VISA RULES'!$C$2:$C$400),0))),"")<>"",IFERROR(INDEX('VISA RULES'!$E$2:$E$400,SUMPRODUCT(MATCH(1,($B95='VISA RULES'!$B$2:$B$400)*(INDEX($AH$18:$AH$37,MATCH(COLUMN()-4,$AJ$18:$AJ$37,0))='VISA RULES'!$C$2:$C$400),0))),""),"NOT ON FILE - VERIFY")))} | F95: {=IF(OR($A95="",F$87=""),"",IF(IFERROR(INDEX('VISA MATRIX'!$B$4:$FS$145,MATCH($B95,'VISA MATRIX'!$A$4:$A$145,0),MATCH(INDEX($AH$18:$AH$37,MATCH(COLUMN()-4,$AJ$18:$AJ$37,0)),'VISA MATRIX'!$B$3:$FS$3,0)),"")<>"",IFERROR(INDEX('VISA MATRIX'!$B$4:$FS$145,MATCH($B95,'VISA MATRIX'!$A$4:$A$145,0),MATCH(INDEX($AH$18:$AH$37,MATCH(COLUMN()-4,$AJ$18:$AJ$37,0)),'VISA MATRIX'!$B$3:$FS$3,0)),""),IF(IFERROR(INDEX('VISA RULES'!$E$2:$E$400,SUMPRODUCT(MATCH(1,($B95='VISA RULES'!$B$2:$B$400)*(INDEX($AH$18:$AH$37,MATCH(COLUMN()-4,$AJ$18:$AJ$37,0))='VISA RULES'!$C$2:$C$400),0))),"")<>"",IFERROR(INDEX('VISA RULES'!$E$2:$E$400,SUMPRODUCT(MATCH(1,($B95='VISA RULES'!$B$2:$B$400)*(INDEX($AH$18:$AH$37,MATCH(COLUMN()-4,$AJ$18:$AJ$37,0))='VISA RULES'!$C$2:$C$400),0))),""),"NOT ON FILE - VERIFY")))} | G95: {=IF(OR($A95="",G$87=""),"",IF(IFERROR(INDEX('VISA MATRIX'!$B$4:$FS$145,MATCH($B95,'VISA MATRIX'!$A$4:$A$145,0),MATCH(INDEX($AH$18:$AH$37,MATCH(COLUMN()-4,$AJ$18:$AJ$37,0)),'VISA MATRIX'!$B$3:$FS$3,0)),"")<>"",IFERROR(INDEX('VISA MATRIX'!$B$4:$FS$145,MATCH($B95,'VISA MATRIX'!$A$4:$A$145,0),MATCH(INDEX($AH$18:$AH$37,MATCH(COLUMN()-4,$AJ$18:$AJ$37,0)),'VISA MATRIX'!$B$3:$FS$3,0)),""),IF(IFERROR(INDEX('VISA RULES'!$E$2:$E$400,SUMPRODUCT(MATCH(1,($B95='VISA RULES'!$B$2:$B$400)*(INDEX($AH$18:$AH$37,MATCH(COLUMN()-4,$AJ$18:$AJ$37,0))='VISA RULES'!$C$2:$C$400),0))),"")<>"",IFERROR(INDEX('VISA RULES'!$E$2:$E$400,SUMPRODUCT(MATCH(1,($B95='VISA RULES'!$B$2:$B$400)*(INDEX($AH$18:$AH$37,MATCH(COLUMN()-4,$AJ$18:$AJ$37,0))='VISA RULES'!$C$2:$C$400),0))),""),"NOT ON FILE - VERIFY")))} | H95: {=IF(OR($A95="",H$87=""),"",IF(IFERROR(INDEX('VISA MATRIX'!$B$4:$FS$145,MATCH($B95,'VISA MATRIX'!$A$4:$A$145,0),MATCH(INDEX($AH$18:$AH$37,MATCH(COLUMN()-4,$AJ$18:$AJ$37,0)),'VISA MATRIX'!$B$3:$FS$3,0)),"")<>"",IFERROR(INDEX('VISA MATRIX'!$B$4:$FS$145,MATCH($B95,'VISA MATRIX'!$A$4:$A$145,0),MATCH(INDEX($AH$18:$AH$37,MATCH(COLUMN()-4,$AJ$18:$AJ$37,0)),'VISA MATRIX'!$B$3:$FS$3,0)),""),IF(IFERROR(INDEX('VISA RULES'!$E$2:$E$400,SUMPRODUCT(MATCH(1,($B95='VISA RULES'!$B$2:$B$400)*(INDEX($AH$18:$AH$37,MATCH(COLUMN()-4,$AJ$18:$AJ$37,0))='VISA RULES'!$C$2:$C$400),0))),"")<>"",IFERROR(INDEX('VISA RULES'!$E$2:$E$400,SUMPRODUCT(MATCH(1,($B95='VISA RULES'!$B$2:$B$400)*(INDEX($AH$18:$AH$37,MATCH(COLUMN()-4,$AJ$18:$AJ$37,0))='VISA RULES'!$C$2:$C$400),0))),""),"NOT ON FILE - VERIFY")))} | I95: {=IF(OR($A95="",I$87=""),"",IF(IFERROR(INDEX('VISA MATRIX'!$B$4:$FS$145,MATCH($B95,'VISA MATRIX'!$A$4:$A$145,0),MATCH(INDEX($AH$18:$AH$37,MATCH(COLUMN()-4,$AJ$18:$AJ$37,0)),'VISA MATRIX'!$B$3:$FS$3,0)),"")<>"",IFERROR(INDEX('VISA MATRIX'!$B$4:$FS$145,MATCH($B95,'VISA MATRIX'!$A$4:$A$145,0),MATCH(INDEX($AH$18:$AH$37,MATCH(COLUMN()-4,$AJ$18:$AJ$37,0)),'VISA MATRIX'!$B$3:$FS$3,0)),""),IF(IFERROR(INDEX('VISA RULES'!$E$2:$E$400,SUMPRODUCT(MATCH(1,($B95='VISA RULES'!$B$2:$B$400)*(INDEX($AH$18:$AH$37,MATCH(COLUMN()-4,$AJ$18:$AJ$37,0))='VISA RULES'!$C$2:$C$400),0))),"")<>"",IFERROR(INDEX('VISA RULES'!$E$2:$E$400,SUMPRODUCT(MATCH(1,($B95='VISA RULES'!$B$2:$B$400)*(INDEX($AH$18:$AH$37,MATCH(COLUMN()-4,$AJ$18:$AJ$37,0))='VISA RULES'!$C$2:$C$400),0))),""),"NOT ON FILE - VERIFY")))} | J95: {=IF(OR($A95="",J$87=""),"",IF(IFERROR(INDEX('VISA MATRIX'!$B$4:$FS$145,MATCH($B95,'VISA MATRIX'!$A$4:$A$145,0),MATCH(INDEX($AH$18:$AH$37,MATCH(COLUMN()-4,$AJ$18:$AJ$37,0)),'VISA MATRIX'!$B$3:$FS$3,0)),"")<>"",IFERROR(INDEX('VISA MATRIX'!$B$4:$FS$145,MATCH($B95,'VISA MATRIX'!$A$4:$A$145,0),MATCH(INDEX($AH$18:$AH$37,MATCH(COLUMN()-4,$AJ$18:$AJ$37,0)),'VISA MATRIX'!$B$3:$FS$3,0)),""),IF(IFERROR(INDEX('VISA RULES'!$E$2:$E$400,SUMPRODUCT(MATCH(1,($B95='VISA RULES'!$B$2:$B$400)*(INDEX($AH$18:$AH$37,MATCH(COLUMN()-4,$AJ$18:$AJ$37,0))='VISA RULES'!$C$2:$C$400),0))),"")<>"",IFERROR(INDEX('VISA RULES'!$E$2:$E$400,SUMPRODUCT(MATCH(1,($B95='VISA RULES'!$B$2:$B$400)*(INDEX($AH$18:$AH$37,MATCH(COLUMN()-4,$AJ$18:$AJ$37,0))='VISA RULES'!$C$2:$C$400),0))),""),"NOT ON FILE - VERIFY")))}
A96: =IF(ROW()-87>SUM($AO$18:$AO$26),"",ROW()-87) | B96: =IF($A96="","",IFERROR(INDEX(countries!$B:$B,MATCH($C96,countries!$D:$D,0)),$C96)) | C96: =IF($A96="","",INDEX($AK$18:$AK$26,MATCH($A96,$AP$18:$AP$26,0))) | D96: {=IF($A96="","",_xlfn.TEXTJOIN(", ",TRUE,IF($AK$18:$AK$26=$C96,$AM$18:$AM$26,"")))} | E96: {=IF(OR($A96="",E$87=""),"",IF(IFERROR(INDEX('VISA MATRIX'!$B$4:$FS$145,MATCH($B96,'VISA MATRIX'!$A$4:$A$145,0),MATCH(INDEX($AH$18:$AH$37,MATCH(COLUMN()-4,$AJ$18:$AJ$37,0)),'VISA MATRIX'!$B$3:$FS$3,0)),"")<>"",IFERROR(INDEX('VISA MATRIX'!$B$4:$FS$145,MATCH($B96,'VISA MATRIX'!$A$4:$A$145,0),MATCH(INDEX($AH$18:$AH$37,MATCH(COLUMN()-4,$AJ$18:$AJ$37,0)),'VISA MATRIX'!$B$3:$FS$3,0)),""),IF(IFERROR(INDEX('VISA RULES'!$E$2:$E$400,SUMPRODUCT(MATCH(1,($B96='VISA RULES'!$B$2:$B$400)*(INDEX($AH$18:$AH$37,MATCH(COLUMN()-4,$AJ$18:$AJ$37,0))='VISA RULES'!$C$2:$C$400),0))),"")<>"",IFERROR(INDEX('VISA RULES'!$E$2:$E$400,SUMPRODUCT(MATCH(1,($B96='VISA RULES'!$B$2:$B$400)*(INDEX($AH$18:$AH$37,MATCH(COLUMN()-4,$AJ$18:$AJ$37,0))='VISA RULES'!$C$2:$C$400),0))),""),"NOT ON FILE - VERIFY")))} | F96: {=IF(OR($A96="",F$87=""),"",IF(IFERROR(INDEX('VISA MATRIX'!$B$4:$FS$145,MATCH($B96,'VISA MATRIX'!$A$4:$A$145,0),MATCH(INDEX($AH$18:$AH$37,MATCH(COLUMN()-4,$AJ$18:$AJ$37,0)),'VISA MATRIX'!$B$3:$FS$3,0)),"")<>"",IFERROR(INDEX('VISA MATRIX'!$B$4:$FS$145,MATCH($B96,'VISA MATRIX'!$A$4:$A$145,0),MATCH(INDEX($AH$18:$AH$37,MATCH(COLUMN()-4,$AJ$18:$AJ$37,0)),'VISA MATRIX'!$B$3:$FS$3,0)),""),IF(IFERROR(INDEX('VISA RULES'!$E$2:$E$400,SUMPRODUCT(MATCH(1,($B96='VISA RULES'!$B$2:$B$400)*(INDEX($AH$18:$AH$37,MATCH(COLUMN()-4,$AJ$18:$AJ$37,0))='VISA RULES'!$C$2:$C$400),0))),"")<>"",IFERROR(INDEX('VISA RULES'!$E$2:$E$400,SUMPRODUCT(MATCH(1,($B96='VISA RULES'!$B$2:$B$400)*(INDEX($AH$18:$AH$37,MATCH(COLUMN()-4,$AJ$18:$AJ$37,0))='VISA RULES'!$C$2:$C$400),0))),""),"NOT ON FILE - VERIFY")))} | G96: {=IF(OR($A96="",G$87=""),"",IF(IFERROR(INDEX('VISA MATRIX'!$B$4:$FS$145,MATCH($B96,'VISA MATRIX'!$A$4:$A$145,0),MATCH(INDEX($AH$18:$AH$37,MATCH(COLUMN()-4,$AJ$18:$AJ$37,0)),'VISA MATRIX'!$B$3:$FS$3,0)),"")<>"",IFERROR(INDEX('VISA MATRIX'!$B$4:$FS$145,MATCH($B96,'VISA MATRIX'!$A$4:$A$145,0),MATCH(INDEX($AH$18:$AH$37,MATCH(COLUMN()-4,$AJ$18:$AJ$37,0)),'VISA MATRIX'!$B$3:$FS$3,0)),""),IF(IFERROR(INDEX('VISA RULES'!$E$2:$E$400,SUMPRODUCT(MATCH(1,($B96='VISA RULES'!$B$2:$B$400)*(INDEX($AH$18:$AH$37,MATCH(COLUMN()-4,$AJ$18:$AJ$37,0))='VISA RULES'!$C$2:$C$400),0))),"")<>"",IFERROR(INDEX('VISA RULES'!$E$2:$E$400,SUMPRODUCT(MATCH(1,($B96='VISA RULES'!$B$2:$B$400)*(INDEX($AH$18:$AH$37,MATCH(COLUMN()-4,$AJ$18:$AJ$37,0))='VISA RULES'!$C$2:$C$400),0))),""),"NOT ON FILE - VERIFY")))} | H96: {=IF(OR($A96="",H$87=""),"",IF(IFERROR(INDEX('VISA MATRIX'!$B$4:$FS$145,MATCH($B96,'VISA MATRIX'!$A$4:$A$145,0),MATCH(INDEX($AH$18:$AH$37,MATCH(COLUMN()-4,$AJ$18:$AJ$37,0)),'VISA MATRIX'!$B$3:$FS$3,0)),"")<>"",IFERROR(INDEX('VISA MATRIX'!$B$4:$FS$145,MATCH($B96,'VISA MATRIX'!$A$4:$A$145,0),MATCH(INDEX($AH$18:$AH$37,MATCH(COLUMN()-4,$AJ$18:$AJ$37,0)),'VISA MATRIX'!$B$3:$FS$3,0)),""),IF(IFERROR(INDEX('VISA RULES'!$E$2:$E$400,SUMPRODUCT(MATCH(1,($B96='VISA RULES'!$B$2:$B$400)*(INDEX($AH$18:$AH$37,MATCH(COLUMN()-4,$AJ$18:$AJ$37,0))='VISA RULES'!$C$2:$C$400),0))),"")<>"",IFERROR(INDEX('VISA RULES'!$E$2:$E$400,SUMPRODUCT(MATCH(1,($B96='VISA RULES'!$B$2:$B$400)*(INDEX($AH$18:$AH$37,MATCH(COLUMN()-4,$AJ$18:$AJ$37,0))='VISA RULES'!$C$2:$C$400),0))),""),"NOT ON FILE - VERIFY")))} | I96: {=IF(OR($A96="",I$87=""),"",IF(IFERROR(INDEX('VISA MATRIX'!$B$4:$FS$145,MATCH($B96,'VISA MATRIX'!$A$4:$A$145,0),MATCH(INDEX($AH$18:$AH$37,MATCH(COLUMN()-4,$AJ$18:$AJ$37,0)),'VISA MATRIX'!$B$3:$FS$3,0)),"")<>"",IFERROR(INDEX('VISA MATRIX'!$B$4:$FS$145,MATCH($B96,'VISA MATRIX'!$A$4:$A$145,0),MATCH(INDEX($AH$18:$AH$37,MATCH(COLUMN()-4,$AJ$18:$AJ$37,0)),'VISA MATRIX'!$B$3:$FS$3,0)),""),IF(IFERROR(INDEX('VISA RULES'!$E$2:$E$400,SUMPRODUCT(MATCH(1,($B96='VISA RULES'!$B$2:$B$400)*(INDEX($AH$18:$AH$37,MATCH(COLUMN()-4,$AJ$18:$AJ$37,0))='VISA RULES'!$C$2:$C$400),0))),"")<>"",IFERROR(INDEX('VISA RULES'!$E$2:$E$400,SUMPRODUCT(MATCH(1,($B96='VISA RULES'!$B$2:$B$400)*(INDEX($AH$18:$AH$37,MATCH(COLUMN()-4,$AJ$18:$AJ$37,0))='VISA RULES'!$C$2:$C$400),0))),""),"NOT ON FILE - VERIFY")))} | J96: {=IF(OR($A96="",J$87=""),"",IF(IFERROR(INDEX('VISA MATRIX'!$B$4:$FS$145,MATCH($B96,'VISA MATRIX'!$A$4:$A$145,0),MATCH(INDEX($AH$18:$AH$37,MATCH(COLUMN()-4,$AJ$18:$AJ$37,0)),'VISA MATRIX'!$B$3:$FS$3,0)),"")<>"",IFERROR(INDEX('VISA MATRIX'!$B$4:$FS$145,MATCH($B96,'VISA MATRIX'!$A$4:$A$145,0),MATCH(INDEX($AH$18:$AH$37,MATCH(COLUMN()-4,$AJ$18:$AJ$37,0)),'VISA MATRIX'!$B$3:$FS$3,0)),""),IF(IFERROR(INDEX('VISA RULES'!$E$2:$E$400,SUMPRODUCT(MATCH(1,($B96='VISA RULES'!$B$2:$B$400)*(INDEX($AH$18:$AH$37,MATCH(COLUMN()-4,$AJ$18:$AJ$37,0))='VISA RULES'!$C$2:$C$400),0))),"")<>"",IFERROR(INDEX('VISA RULES'!$E$2:$E$400,SUMPRODUCT(MATCH(1,($B96='VISA RULES'!$B$2:$B$400)*(INDEX($AH$18:$AH$37,MATCH(COLUMN()-4,$AJ$18:$AJ$37,0))='VISA RULES'!$C$2:$C$400),0))),""),"NOT ON FILE - VERIFY")))} | K96: DOCUMENT STATUS | L96: DOCS FOLDER
A97: VISA REQUIRED ON THIS TRIP? | E97: =IF(E$87="","",IF(COUNTIF(E$88:E$96,"REQUIRED")>0,"YES",IF(COUNTIF(E$88:E$96,"NOT ON FILE - VERIFY")>0,"VERIFY",IF(COUNTIF(E$88:E$96,"VISA ON ARRIVAL")+COUNTIF(E$88:E$96,"eVISA")>0,"ON ARRIVAL / eVISA","NO")))) | F97: =IF(F$87="","",IF(COUNTIF(F$88:F$96,"REQUIRED")>0,"YES",IF(COUNTIF(F$88:F$96,"NOT ON FILE - VERIFY")>0,"VERIFY",IF(COUNTIF(F$88:F$96,"VISA ON ARRIVAL")+COUNTIF(F$88:F$96,"eVISA")>0,"ON ARRIVAL / eVISA","NO")))) | G97: =IF(G$87="","",IF(COUNTIF(G$88:G$96,"REQUIRED")>0,"YES",IF(COUNTIF(G$88:G$96,"NOT ON FILE - VERIFY")>0,"VERIFY",IF(COUNTIF(G$88:G$96,"VISA ON ARRIVAL")+COUNTIF(G$88:G$96,"eVISA")>0,"ON ARRIVAL / eVISA","NO")))) | H97: =IF(H$87="","",IF(COUNTIF(H$88:H$96,"REQUIRED")>0,"YES",IF(COUNTIF(H$88:H$96,"NOT ON FILE - VERIFY")>0,"VERIFY",IF(COUNTIF(H$88:H$96,"VISA ON ARRIVAL")+COUNTIF(H$88:H$96,"eVISA")>0,"ON ARRIVAL / eVISA","NO")))) | I97: =IF(I$87="","",IF(COUNTIF(I$88:I$96,"REQUIRED")>0,"YES",IF(COUNTIF(I$88:I$96,"NOT ON FILE - VERIFY")>0,"VERIFY",IF(COUNTIF(I$88:I$96,"VISA ON ARRIVAL")+COUNTIF(I$88:I$96,"eVISA")>0,"ON ARRIVAL / eVISA","NO")))) | J97: =IF(J$87="","",IF(COUNTIF(J$88:J$96,"REQUIRED")>0,"YES",IF(COUNTIF(J$88:J$96,"NOT ON FILE - VERIFY")>0,"VERIFY",IF(COUNTIF(J$88:J$96,"VISA ON ARRIVAL")+COUNTIF(J$88:J$96,"eVISA")>0,"ON ARRIVAL / eVISA","NO"))))
A98: Visa status is read from the VISA MATRIX sheet (destination state x nationality), falling back to the VISA sheet for pair-specific rules with lead time, maximum stay and airport overrides. NOT ON FILE means neither source has an answer yet. Type over a cell to override for this trip only.
A100: 6 · CREW & PAX BY LEG (a person counts on a leg when their LEGS field on the PAX & CREW sheet is ALL or names that leg)
A101: LEG | B101: DEP | C101: ARR | D101: ETD (UTC) | E101: CREW | F101: PAX | G101: SOULS ON BOARD | H101: MAX PAX | I101: SEAT CHECK | J101: BILL TO
A102: {=IF(INDEX($B$18:$B$25,ROW()-101)="","",INDEX($A$18:$A$25,ROW()-101))} | B102: {=IF($A102="","",INDEX($B$18:$B$25,ROW()-101))} | C102: {=IF($A102="","",INDEX($G$18:$G$25,ROW()-101))} | D102: {=IF($A102="","",INDEX($E$18:$E$25,ROW()-101)+INDEX($F$18:$F$25,ROW()-101))} | E102: {=IF($A102="","",SUMPRODUCT(('PAX & CREW'!$B$3:$B$62=$B$5)*('PAX & CREW'!$C$3:$C$62="CREW")*(((UPPER('PAX & CREW'!$E$3:$E$62)="ALL")+ISNUMBER(SEARCH($A102,'PAX & CREW'!$E$3:$E$62)))>0)))} | F102: {=IF($A102="","",SUMPRODUCT(('PAX & CREW'!$B$3:$B$62=$B$5)*('PAX & CREW'!$C$3:$C$62="PAX")*(((UPPER('PAX & CREW'!$E$3:$E$62)="ALL")+ISNUMBER(SEARCH($A102,'PAX & CREW'!$E$3:$E$62)))>0)))} | G102: =IF($A102="","",$E102+$F102) | H102: =IF($A102="","",IFERROR(INDEX(Aircraft!$I:$I,MATCH($B$7,Aircraft!$B:$B,0)),"NOT IN FLEET")) | I102: =IF($A102="","",IF($H102="NOT IN FLEET","CANNOT CHECK",IF($F102>$H102,"OVER CAPACITY","OK"))) | J102: {=IF($A102="","",INDEX($N$18:$N$25,ROW()-101))}
A103: {=IF(INDEX($B$18:$B$25,ROW()-101)="","",INDEX($A$18:$A$25,ROW()-101))} | B103: {=IF($A103="","",INDEX($B$18:$B$25,ROW()-101))} | C103: {=IF($A103="","",INDEX($G$18:$G$25,ROW()-101))} | D103: {=IF($A103="","",INDEX($E$18:$E$25,ROW()-101)+INDEX($F$18:$F$25,ROW()-101))} | E103: {=IF($A103="","",SUMPRODUCT(('PAX & CREW'!$B$3:$B$62=$B$5)*('PAX & CREW'!$C$3:$C$62="CREW")*(((UPPER('PAX & CREW'!$E$3:$E$62)="ALL")+ISNUMBER(SEARCH($A103,'PAX & CREW'!$E$3:$E$62)))>0)))} | F103: {=IF($A103="","",SUMPRODUCT(('PAX & CREW'!$B$3:$B$62=$B$5)*('PAX & CREW'!$C$3:$C$62="PAX")*(((UPPER('PAX & CREW'!$E$3:$E$62)="ALL")+ISNUMBER(SEARCH($A103,'PAX & CREW'!$E$3:$E$62)))>0)))} | G103: =IF($A103="","",$E103+$F103) | H103: =IF($A103="","",IFERROR(INDEX(Aircraft!$I:$I,MATCH($B$7,Aircraft!$B:$B,0)),"NOT IN FLEET")) | I103: =IF($A103="","",IF($H103="NOT IN FLEET","CANNOT CHECK",IF($F103>$H103,"OVER CAPACITY","OK"))) | J103: {=IF($A103="","",INDEX($N$18:$N$25,ROW()-101))}
A104: {=IF(INDEX($B$18:$B$25,ROW()-101)="","",INDEX($A$18:$A$25,ROW()-101))} | B104: {=IF($A104="","",INDEX($B$18:$B$25,ROW()-101))} | C104: {=IF($A104="","",INDEX($G$18:$G$25,ROW()-101))} | D104: {=IF($A104="","",INDEX($E$18:$E$25,ROW()-101)+INDEX($F$18:$F$25,ROW()-101))} | E104: {=IF($A104="","",SUMPRODUCT(('PAX & CREW'!$B$3:$B$62=$B$5)*('PAX & CREW'!$C$3:$C$62="CREW")*(((UPPER('PAX & CREW'!$E$3:$E$62)="ALL")+ISNUMBER(SEARCH($A104,'PAX & CREW'!$E$3:$E$62)))>0)))} | F104: {=IF($A104="","",SUMPRODUCT(('PAX & CREW'!$B$3:$B$62=$B$5)*('PAX & CREW'!$C$3:$C$62="PAX")*(((UPPER('PAX & CREW'!$E$3:$E$62)="ALL")+ISNUMBER(SEARCH($A104,'PAX & CREW'!$E$3:$E$62)))>0)))} | G104: =IF($A104="","",$E104+$F104) | H104: =IF($A104="","",IFERROR(INDEX(Aircraft!$I:$I,MATCH($B$7,Aircraft!$B:$B,0)),"NOT IN FLEET")) | I104: =IF($A104="","",IF($H104="NOT IN FLEET","CANNOT CHECK",IF($F104>$H104,"OVER CAPACITY","OK"))) | J104: {=IF($A104="","",INDEX($N$18:$N$25,ROW()-101))}
A105: {=IF(INDEX($B$18:$B$25,ROW()-101)="","",INDEX($A$18:$A$25,ROW()-101))} | B105: {=IF($A105="","",INDEX($B$18:$B$25,ROW()-101))} | C105: {=IF($A105="","",INDEX($G$18:$G$25,ROW()-101))} | D105: {=IF($A105="","",INDEX($E$18:$E$25,ROW()-101)+INDEX($F$18:$F$25,ROW()-101))} | E105: {=IF($A105="","",SUMPRODUCT(('PAX & CREW'!$B$3:$B$62=$B$5)*('PAX & CREW'!$C$3:$C$62="CREW")*(((UPPER('PAX & CREW'!$E$3:$E$62)="ALL")+ISNUMBER(SEARCH($A105,'PAX & CREW'!$E$3:$E$62)))>0)))} | F105: {=IF($A105="","",SUMPRODUCT(('PAX & CREW'!$B$3:$B$62=$B$5)*('PAX & CREW'!$C$3:$C$62="PAX")*(((UPPER('PAX & CREW'!$E$3:$E$62)="ALL")+ISNUMBER(SEARCH($A105,'PAX & CREW'!$E$3:$E$62)))>0)))} | G105: =IF($A105="","",$E105+$F105) | H105: =IF($A105="","",IFERROR(INDEX(Aircraft!$I:$I,MATCH($B$7,Aircraft!$B:$B,0)),"NOT IN FLEET")) | I105: =IF($A105="","",IF($H105="NOT IN FLEET","CANNOT CHECK",IF($F105>$H105,"OVER CAPACITY","OK"))) | J105: {=IF($A105="","",INDEX($N$18:$N$25,ROW()-101))}
A106: {=IF(INDEX($B$18:$B$25,ROW()-101)="","",INDEX($A$18:$A$25,ROW()-101))} | B106: {=IF($A106="","",INDEX($B$18:$B$25,ROW()-101))} | C106: {=IF($A106="","",INDEX($G$18:$G$25,ROW()-101))} | D106: {=IF($A106="","",INDEX($E$18:$E$25,ROW()-101)+INDEX($F$18:$F$25,ROW()-101))} | E106: {=IF($A106="","",SUMPRODUCT(('PAX & CREW'!$B$3:$B$62=$B$5)*('PAX & CREW'!$C$3:$C$62="CREW")*(((UPPER('PAX & CREW'!$E$3:$E$62)="ALL")+ISNUMBER(SEARCH($A106,'PAX & CREW'!$E$3:$E$62)))>0)))} | F106: {=IF($A106="","",SUMPRODUCT(('PAX & CREW'!$B$3:$B$62=$B$5)*('PAX & CREW'!$C$3:$C$62="PAX")*(((UPPER('PAX & CREW'!$E$3:$E$62)="ALL")+ISNUMBER(SEARCH($A106,'PAX & CREW'!$E$3:$E$62)))>0)))} | G106: =IF($A106="","",$E106+$F106) | H106: =IF($A106="","",IFERROR(INDEX(Aircraft!$I:$I,MATCH($B$7,Aircraft!$B:$B,0)),"NOT IN FLEET")) | I106: =IF($A106="","",IF($H106="NOT IN FLEET","CANNOT CHECK",IF($F106>$H106,"OVER CAPACITY","OK"))) | J106: {=IF($A106="","",INDEX($N$18:$N$25,ROW()-101))}
A107: {=IF(INDEX($B$18:$B$25,ROW()-101)="","",INDEX($A$18:$A$25,ROW()-101))} | B107: {=IF($A107="","",INDEX($B$18:$B$25,ROW()-101))} | C107: {=IF($A107="","",INDEX($G$18:$G$25,ROW()-101))} | D107: {=IF($A107="","",INDEX($E$18:$E$25,ROW()-101)+INDEX($F$18:$F$25,ROW()-101))} | E107: {=IF($A107="","",SUMPRODUCT(('PAX & CREW'!$B$3:$B$62=$B$5)*('PAX & CREW'!$C$3:$C$62="CREW")*(((UPPER('PAX & CREW'!$E$3:$E$62)="ALL")+ISNUMBER(SEARCH($A107,'PAX & CREW'!$E$3:$E$62)))>0)))} | F107: {=IF($A107="","",SUMPRODUCT(('PAX & CREW'!$B$3:$B$62=$B$5)*('PAX & CREW'!$C$3:$C$62="PAX")*(((UPPER('PAX & CREW'!$E$3:$E$62)="ALL")+ISNUMBER(SEARCH($A107,'PAX & CREW'!$E$3:$E$62)))>0)))} | G107: =IF($A107="","",$E107+$F107) | H107: =IF($A107="","",IFERROR(INDEX(Aircraft!$I:$I,MATCH($B$7,Aircraft!$B:$B,0)),"NOT IN FLEET")) | I107: =IF($A107="","",IF($H107="NOT IN FLEET","CANNOT CHECK",IF($F107>$H107,"OVER CAPACITY","OK"))) | J107: {=IF($A107="","",INDEX($N$18:$N$25,ROW()-101))}
A108: {=IF(INDEX($B$18:$B$25,ROW()-101)="","",INDEX($A$18:$A$25,ROW()-101))} | B108: {=IF($A108="","",INDEX($B$18:$B$25,ROW()-101))} | C108: {=IF($A108="","",INDEX($G$18:$G$25,ROW()-101))} | D108: {=IF($A108="","",INDEX($E$18:$E$25,ROW()-101)+INDEX($F$18:$F$25,ROW()-101))} | E108: {=IF($A108="","",SUMPRODUCT(('PAX & CREW'!$B$3:$B$62=$B$5)*('PAX & CREW'!$C$3:$C$62="CREW")*(((UPPER('PAX & CREW'!$E$3:$E$62)="ALL")+ISNUMBER(SEARCH($A108,'PAX & CREW'!$E$3:$E$62)))>0)))} | F108: {=IF($A108="","",SUMPRODUCT(('PAX & CREW'!$B$3:$B$62=$B$5)*('PAX & CREW'!$C$3:$C$62="PAX")*(((UPPER('PAX & CREW'!$E$3:$E$62)="ALL")+ISNUMBER(SEARCH($A108,'PAX & CREW'!$E$3:$E$62)))>0)))} | G108: =IF($A108="","",$E108+$F108) | H108: =IF($A108="","",IFERROR(INDEX(Aircraft!$I:$I,MATCH($B$7,Aircraft!$B:$B,0)),"NOT IN FLEET")) | I108: =IF($A108="","",IF($H108="NOT IN FLEET","CANNOT CHECK",IF($F108>$H108,"OVER CAPACITY","OK"))) | J108: {=IF($A108="","",INDEX($N$18:$N$25,ROW()-101))}
A109: {=IF(INDEX($B$18:$B$25,ROW()-101)="","",INDEX($A$18:$A$25,ROW()-101))} | B109: {=IF($A109="","",INDEX($B$18:$B$25,ROW()-101))} | C109: {=IF($A109="","",INDEX($G$18:$G$25,ROW()-101))} | D109: {=IF($A109="","",INDEX($E$18:$E$25,ROW()-101)+INDEX($F$18:$F$25,ROW()-101))} | E109: {=IF($A109="","",SUMPRODUCT(('PAX & CREW'!$B$3:$B$62=$B$5)*('PAX & CREW'!$C$3:$C$62="CREW")*(((UPPER('PAX & CREW'!$E$3:$E$62)="ALL")+ISNUMBER(SEARCH($A109,'PAX & CREW'!$E$3:$E$62)))>0)))} | F109: {=IF($A109="","",SUMPRODUCT(('PAX & CREW'!$B$3:$B$62=$B$5)*('PAX & CREW'!$C$3:$C$62="PAX")*(((UPPER('PAX & CREW'!$E$3:$E$62)="ALL")+ISNUMBER(SEARCH($A109,'PAX & CREW'!$E$3:$E$62)))>0)))} | G109: =IF($A109="","",$E109+$F109) | H109: =IF($A109="","",IFERROR(INDEX(Aircraft!$I:$I,MATCH($B$7,Aircraft!$B:$B,0)),"NOT IN FLEET")) | I109: =IF($A109="","",IF($H109="NOT IN FLEET","CANNOT CHECK",IF($F109>$H109,"OVER CAPACITY","OK"))) | J109: {=IF($A109="","",INDEX($N$18:$N$25,ROW()-101))}
A111: 7 · CREW & PAX SUMMARY (trip totals · biodata, credentials and document folders live on the PAX & CREW sheet)
A112: CREW ON BOARD (TRIP) | B112: =COUNTIFS('PAX & CREW'!$B$3:$B$62,$B$5,'PAX & CREW'!$C$3:$C$62,"CREW")
...

Sheet admin
A1: Workstation UTC offset (hrs) | B1: 0
A2: Document root path | B2: C:\Backups\InsiderTechSol\Aviation\Jetelio_v3\.LAYOUT\resources
A3: Reference lists
A4: Airport Type | B4: PPR Required | C4: Location Type | D4: Airport of Entry | E4: Fuel Types | F4: Vendor Category
A5: Civil | B5: Yes | C5: Airport | D5: Yes | E5: JET A-1 | F5: Handler
A6: Military | B6: No | C6: Airstrip | D6: No | E6: AVGAS | F6: Permit
A7: Private | B7: Prior Notice | C7: Helipad | D7: Seasonal | E7: JET A-1 + AVGAS | F7: Supervisor
A8: Joint | C8: Bulk Origin | E8: None | F8: Fuel
A9: Other | C9: Bulk Destination | F9: Catering
C10: Shipping Port | F10: Security
C11: Aircraft Carrier | F11: Transport
C12: Other | F12: Other
A14: OPERATIONAL DEFAULTS — single source of truth for every fallback
A15: Default permit lead time (hrs) — FALLBACK ONLY, not a verified figure | B15: 72
A16: Default ground service notice (hrs) | B16: 24
A17: Range reserve / safety margin (fraction of max range) | B17: 0.15
A18: Passport validity buffer beyond trip end (days) | B18: 180
A19: Document expiry alert thresholds (days before expiry) | B19: 180,90,30,7
A20: Visa rule staleness limit (days since verified) | B20: 365
A21: Unverified reference data may be used for planning? | B21: NO

Sheet airports
A1: IDENTIFIERS | E1: LOCATION & CONTACT | N1: GEO & TIME | W1: OPERATIONS | AE1: INFRASTRUCTURE | AJ1: LIVE DATA | AM1: BULLETINS | AO1: DOCUMENTS | AS1: RELATED RECORDS | AU1: OTHER
A2: Airport ICAO | B2: Airport IATA | C2: FAA ID | D2: EIP ICAO | E2: Airport Name | F2: Location Type | G2: Airport Type | H2: Country | I2: City Name | J2: Location / Region | K2: Airport Address 1 | L2: Airport Address 2 | M2: Website | N2: Coordinates (DMS) | O2: Latitude (DD) | P2: Longitude (DD) | Q2: Elevation (m) | R2: Elevation (ft) | S2: Magnetic Variation | T2: Time Zone | U2: UTC Offset (hrs) | V2: Local Time (now) | W2: Airport Hours | X2: Operating Hours | Y2: Airport of Entry | Z2: PPR Required | AA2: CIQ Procedure | AB2: Arrival Slot | AC2: Departure Slot | AD2: Approaches | AE2: Runway(s) | AF2: PCN No. | AG2: Fuel Types Available | AH2: Security Rating | AI2: Alternates | AJ2: NOTAM | AK2: Airport OFP | AL2: Daily Weather | AM2: Country Bulletin | AN2: City Bulletin | AO2: Airport Charts (folder) | AP2: Runway Diagram | AQ2: Airport Images | AR2: City Map | AS2: VISA Info | AT2: Vendors | AU2: Strategic Role | AV2: Last Updated | AW2: ops_data_source | AX2: ops_data_verified_on | AY2: tech_stop_readiness
A3: AGGH | B3: HIR | E3: Honiara International Airport | I3: Honiara | O3: -9.428 | P3: 160.05499 | R3: 28 | T3: Pacific/Guadalcanal
A4: AYNZ | B4: LAE | E4: Nadzab Tomodachi International Airport | I4: Lae | O4: -6.56799 | P4: 146.72654 | R4: 239 | T4: Pacific/Port_Moresby
A5: AYPY | B5: POM | E5: Port Moresby Jacksons International Airport | I5: Port Moresby | O5: -9.44338 | P5: 147.22 | R5: 146 | T5: Pacific/Port_Moresby
A6: BGGH | B6: GOH | E6: Nuuk International Airport | H6: Greenland | I6: Nuuk | O6: 64.19107 | P6: -51.67914 | R6: 283 | T6: America/Godthab
A7: BIAR | B7: AEY | E7: Akureyri International Airport | H7: Iceland | I7: Akureyri | O7: 65.65657 | P7: -18.07202 | R7: 6 | T7: Atlantic/Reykjavik
A8: BIKF | B8: KEF | E8: Keflavik International Airport | H8: Iceland | I8: Reykjavík | O8: 63.985 | P8: -22.6056 | R8: 171 | T8: Atlantic/Reykjavik
A9: BKPR | B9: PRN | E9: Priština Adem Jashari International Airport | H9: Kosovo | I9: Prishtina | O9: 42.5728 | P9: 21.0358 | R9: 1789 | T9: Europe/Belgrade
A10: CYEG | B10: YEG | E10: Edmonton International Airport | I10: Edmonton | O10: 53.3097 | P10: -113.58 | R10: 2373 | T10: America/Edmonton
A11: CYHZ | B11: YHZ | E11: Halifax / Stanfield International Airport | I11: Halifax | O11: 44.8808 | P11: -63.5086 | R11: 477 | T11: America/Halifax
A12: DAAE | B12: BJA | E12: Soummam–Abane Ramdane Airport | H12: Algeria | I12: Béjaïa | O12: 36.71255 | P12: 5.06991 | R12: 20 | T12: Africa/Algiers
A13: DAAG | B13: ALG | E13: Houari Boumediene Airport | H13: Algeria | I13: Algiers | O13: 36.69389 | P13: 3.21453 | R13: 82 | T13: Africa/Algiers
A14: DBBB | B14: COO | E14: Cotonou Cadjehoun International Airport | H14: Benin | I14: Cotonou | O14: 6.35723 | P14: 2.38435 | R14: 19 | T14: Africa/Porto-Novo
A15: DFFD | B15: OUA | E15: Ouagadougou Thomas Sankara International Airport | H15: Burkina Faso | I15: Ouagadougou | O15: 12.3532 | P15: -1.51242 | R15: 1037 | T15: Africa/Ouagadougou
A16: DFOO | B16: BOY | E16: Bobo Dioulasso Airport | H16: Burkina Faso | I16: Bobo Dioulasso | O16: 11.1601 | P16: -4.33097 | R16: 1511 | T16: Africa/Ouagadougou
A17: DGAA | B17: ACC | E17: Kotoka International Airport | H17: Ghana | I17: Accra | O17: 5.60519 | P17: -0.16679 | R17: 205 | T17: Africa/Accra
A18: DGLE | B18: TML | E18: Yakubu Tali International Airport | H18: Ghana | I18: Tamale | O18: 9.55391 | P18: -0.86606 | R18: 553 | T18: Africa/Accra
A19: DIAP | B19: ABJ | E19: Félix-Houphouët-Boigny International Airport | H19: Côte d'Ivoire | I19: Abidjan | O19: 5.26139 | P19: -3.92629 | R19: 21 | T19: Africa/Abidjan
A20: DIYO | B20: ASK | E20: Yamoussoukro International Airport | H20: Côte d'Ivoire | I20: Yamoussoukro | O20: 6.90317 | P20: -5.36558 | R20: 699 | T20: Africa/Abidjan
A21: DNAA | B21: ABV | E21: Nnamdi Azikiwe International Airport | H21: Nigeria | I21: Abuja | O21: 9.00679 | P21: 7.26317 | R21: 1123 | T21: Africa/Lagos
A22: DNAS | B22: ABB | E22: Asaba International Airport | H22: Nigeria | I22: Asaba | O22: 6.20417 | P22: 6.66528 | R22: 305 | T22: Africa/Lagos
A23: DNMM | B23: LOS | E23: Murtala Muhammed International Airport | H23: Nigeria | I23: Lagos | O23: 6.57737 | P23: 3.32116 | R23: 135 | T23: Africa/Lagos
... A39: EGLF | B39: FAB | E39: Farnborough Airport | H39: United Kingdom | I39: Farnborough | O39: 51.2758 | P39: -0.77633 | R39: 238 | T39: Europe/London
A40: EGNS | B40: IOM | E40: Isle of Man Airport | I40: Castletown | O40: 54.08308 | P40: -4.62387 | R40: 52 | T40: Europe/Isle_of_Man
A41: EGPK | B41: PIK | E41: Glasgow Prestwick Airport | H41: United Kingdom | I41: Prestwick | O41: 55.5015 | P41: -4.57718 | R41: 65 | T41: Europe/London
A42: EGYP | B42: MPN | E42: Mount Pleasant Airport / RAF Mount Pleasant | I42: Mount Pleasant | O42: -51.82264 | P42: -58.44578 | R42: 244 | T42: Atlantic/Stanley
A43: EHAM | B43: AMS | E43: Amsterdam Airport Schiphol | H43: Netherlands | I43: Amsterdam | O43: 52.3086 | P43: 4.76389 | R43: -11 | T43: Europe/Amsterdam
A44: EHBK | B44: MST | E44: Maastricht Aachen Airport | H44: Netherlands | I44: Maastricht | O44: 50.91109 | P44: 5.7694 | R44: 375 | T44: Europe/Amsterdam
A45: EICK | B45: ORK | E45: Cork International Airport | H45: Ireland | I45: Cork | O45: 51.8413 | P45: -8.49111 | R45: 502 | T45: Europe/Dublin
A46: EIDW | B46: DUB | E46: Dublin Airport | H46: Ireland | I46: Dublin | O46: 53.42871 | P46: -6.26212 | R46: 242 | T46: Europe/Dublin
A47: EKAH | B47: AAR | E47: Aarhus Airport | H47: Denmark | I47: Aarhus | O47: 56.30333 | P47: 10.61829 | R47: 82 | T47: Europe/Copenhagen
A48: EKBI | B48: BLL | E48: Billund Airport | H48: Denmark | I48: Billund | O48: 55.74034 | P48: 9.15702 | R48: 247 | T48: Europe/Copenhagen
A49: EKVG | B49: FAE | E49: Vágar Airport | I49: Vágar | O49: 62.06326 | P49: -7.27578 | R49: 280 | T49: Atlantic/Faeroe
A50: ELLX | B50: LUX | E50: Luxembourg-Findel International Airport | H50: Luxembourg | I50: Luxembourg | O50: 49.62685 | P50: 6.21213 | R50: 1234 | T50: Europe/Luxembourg
A51: ENAL | B51: AES | E51: Ålesund Airport | H51: Norway | I51: Ålesund | O51: 62.56044 | P51: 6.11085 | R51: 69 | T51: Europe/Oslo
A52: ENBO | B52: BOO | E52: Bodø Airport | H52: Norway | I52: Bodø | O52: 67.2692 | P52: 14.3653 | R52: 42 | T52: Europe/Oslo
A53: EPGD | B53: GDN | E53: Gdańsk Lech Wałęsa Airport | H53: Poland | I53: Gdańsk | O53: 54.3776 | P53: 18.4662 | R53: 489 | T53: Europe/Warsaw
A54: EPKK | B54: KRK | E54: Kraków John Paul II International Airport | H54: Poland | I54: Balice | O54: 50.0777 | P54: 19.7848 | R54: 791 | T54: Europe/Warsaw
A55: ESGG | B55: GOT | E55: Göteborg Landvetter Airport | H55: Sweden | I55: Göteborg | O55: 57.6628 | P55: 12.2798 | R55: 506 | T55: Europe/Stockholm
A56: ESKN | B56: NYO | E56: Stockholm Skavsta Airport | H56: Sweden | I56: Nyköping | O56: 58.78966 | P56: 16.91148 | R56: 140 | T56: Europe/Stockholm
A57: EVLA | B57: LPX | E57: Liepāja International Airport | H57: Latvia | I57: Liepāja | O57: 56.5175 | P57: 21.0969 | R57: 16 | T57: Europe/Riga
A58: EVRA | B58: RIX | E58: Riga International Airport | H58: Latvia | I58: Riga | O58: 56.92075 | P58: 23.97071 | R58: 36 | T58: Europe/Riga
A59: EYKA | B59: KUN | E59: Kaunas International Airport | H59: Lithuania | I59: Kaunas | O59: 54.96397 | P59: 24.08582 | R59: 256 | T59: Europe/Vilnius
A60: EYPA | B60: PLQ | E60: Palanga International Airport | H60: Lithuania | I60: Palanga | O60: 55.9732 | P60: 21.0939 | R60: 33 | T60: Europe/Vilnius
A61: FABL | B61: BFN | E61: Bram Fischer International Airport | H61: South Africa | I61: Bloemfontein | O61: -29.0927 | P61: 26.3024 | R61: 4457 | T61: Africa/Johannesburg
... A71: FCPP | B71: PNR | E71: Antonio Agostinho-Neto International Airport | H71: Republic of the Congo | I71: Pointe Noire | O71: -4.81603 | P71: 11.8866 | R71: 55 | T71: Africa/Brazzaville
A72: FDSK | B72: SHO | E72: King Mswati III International Airport | H72: Eswatini | I72: Mpaka | O72: -26.35861 | P72: 31.71694 | R72: 1092
A73: FEFF | B73: BGF | E73: Bangui M'Poko International Airport | H73: Central African Republic | I73: Bangui | O73: 4.39848 | P73: 18.5188 | R73: 1208 | T73: Africa/Bangui
A74: FGBT | B74: BSG | E74: Bata International Airport | H74: Equatorial Guinea | I74: Bata | O74: 1.90547 | P74: 9.80568 | R74: 13 | T74: Africa/Malabo
A75: FGCO | B75: OCS | E75: Corisco International Airport | H75: Equatorial Guinea | I75: Corisco Island | O75: 0.91094 | P75: 9.33027 | R75: 55
A76: FGSL | B76: SSG | E76: Malabo International Airport | H76: Equatorial Guinea | I76: Malabo | O76: 3.75527 | P76: 8.70872 | R76: 76 | T76: Africa/Malabo
A77: FIMP | B77: MRU | E77: Sir Seewoosagur Ramgoolam International Airport | H77: Mauritius | I77: Plaine Magnien | O77: -20.4302 | P77: 57.6836 | R77: 186 | T77: Indian/Mauritius
A78: FKKD | B78: DLA | E78: Douala International Airport | H78: Cameroon | I78: Douala | O78: 4.00608 | P78: 9.71948 | R78: 33 | T78: Africa/Douala
A79: FKKR | B79: GOU | E79: Garoua International Airport | H79: Cameroon | I79: Garoua | O79: 9.33479 | P79: 13.37213 | R79: 794 | T79: Africa/Douala
A80: FLHN | B80: LVI | E80: Harry Mwanga Nkumbula International Airport | H80: Zambia | I80: Livingstone | O80: -17.82152 | P80: 25.81964 | R80: 3302
A81: FLKK | B81: LUN | E81: Kenneth Kaunda International Airport | H81: Zambia | I81: Lusaka | O81: -15.33083 | P81: 28.45272 | R81: 3779
A82: FMCH | B82: HAH | E82: Prince Said Ibrahim International Airport | H82: Comoros | I82: Moroni | O82: -11.5337 | P82: 43.2719 | R82: 93 | T82: Indian/Comoro
A83: FMCZ | B83: DZA | E83: Dzaoudzi Pamandzi International Airport | H83: Mayotte | I83: Dzaoudzi | O83: -12.80932 | P83: 45.28182 | R83: 23 | T83: Indian/Mayotte
A84: FMEE | B84: RUN | E84: Roland Garros Airport | H84: Réunion | I84: Sainte-Marie | O84: -20.89009 | P84: 55.51889 | R84: 66 | T84: Indian/Reunion
A85: FMEP | B85: ZSE | E85: Saint-Pierre Pierrefonds Airport | H85: Réunion | I85: Saint-Pierre | O85: -21.31936 | P85: 55.42251 | R85: 59 | T85: Indian/Reunion
A86: FMMI | B86: TNR | E86: Ivato International Airport | H86: Madagascar | I86: Antananarivo | O86: -18.7969 | P86: 47.4788 | R86: 4198 | T86: Indian/Antananarivo
A87: FMMT | B87: TMM | E87: Toamasina Ambalamanasy Airport | H87: Madagascar | I87: Toamasina | O87: -18.11354 | P87: 49.39226 | R87: 22 | T87: Indian/Antananarivo
A88: FNBJ | B88: NBJ | E88: Dr. Antonio Agostinho Neto International Airport | H88: Angola | I88: Luanda | O88: -9.05073 | P88: 13.49908 | R88: 550
A89: FNLU | B89: LAD | E89: Quatro de Fevereiro International Airport | H89: Angola | I89: Luanda | O89: -8.85837 | P89: 13.2312 | R89: 243 | T89: Africa/Luanda
A90: FOOG | B90: POG | E90: Port Gentil International Airport | H90: Gabon | I90: Port Gentil | O90: -0.71174 | P90: 8.75438 | R90: 13 | T90: Africa/Libreville
A91: FOOL | B91: LBV | E91: Libreville Leon M'ba International Airport | H91: Gabon | I91: Libreville | O91: 0.45895 | P91: 9.41214 | R91: 39 | T91: Africa/Libreville
A92: FPST | B92: TMS | E92: São Tomé International Airport | I92: São Tomé | O92: 0.37817 | P92: 6.71215 | R92: 33 | T92: Africa/Sao_Tome
A93: FQBR | B93: BEW | E93: Beira International Airport | H93: Mozambique | I93: Beira | O93: -19.7964 | P93: 34.9076 | R93: 33 | T93: Africa/Maputo
A94: FQMA | B94: MPM | E94: Maputo Airport | H94: Mozambique | I94: Maputo | O94: -25.9208 | P94: 32.5726 | R94: 145 | T94: Africa/Maputo
A95: FSIA | B95: SEZ | E95: Seychelles International Airport | H95: Seychelles | I95: Victoria | O95: -4.67434 | P95: 55.5218 | R95: 10 | T95: Indian/Mahe
A96: FTTJ | B96: NDJ | E96: N'Djamena International Airport | H96: Chad | I96: N'Djamena | O96: 12.1337 | P96: 15.034 | R96: 968 | T96: Africa/Ndjamena
A97: FVFA | B97: VFA | E97: Victoria Falls International Airport | H97: Zimbabwe | I97: Victoria Falls | O97: -18.09744 | P97: 25.83687 | R97: 3490 | T97: Africa/Harare
A98: FVJN | B98: BUQ | E98: Joshua Mqabuko Nkomo International Airport | H98: Zimbabwe | I98: Bulawayo | O98: -20.01628 | P98: 28.6229 | R98: 4359
A99: FVRG | B99: HRE | E99: Robert Gabriel Mugabe International Airport | H99: Zimbabwe | I99: Harare | O99: -17.9318 | P99: 31.0928 | R99: 4887 | T99: Africa/Harare
A100: FWCL | B100: BLZ | E100: Chileka International Airport | H100: Malawi | I100: Blantyre | O100: -15.67719 | P100: 34.97232 | R100: 2555 | T100: Africa/Blantyre
A101: FWKI | B101: LLW | E101: Kamuzu International Airport | H101: Malawi | I101: Lumbadzi | O101: -13.7894 | P101: 33.781 | R101: 4035 | T101: Africa/Blantyre
A102: FXMM | B102: MSU | E102: Moshoeshoe I International Airport | H102: Lesotho | I102: Maseru | O102: -29.45628 | P102: 27.55446 | R102: 5348 | T102: Africa/Maseru
A103: FYWE | B103: ERS | E103: Eros Airport | H103: Namibia | I103: Windhoek | O103: -22.60492 | P103: 17.079 | R103: 5575 | T103: Africa/Windhoek
A104: FYWH | B104: WDH | E104: Hosea Kutako International Airport | H104: Namibia | I104: Windhoek | O104: -22.4799 | P104: 17.4709 | R104: 5640 | T104: Africa/Windhoek
A105: FZAA | B105: FIH | E105: Ndjili International Airport | H105: Democratic Republic of the Congo | I105: Kinshasa | O105: -4.38575 | P105: 15.4446 | R105: 1027 | T105: Africa/Kinshasa
A106: FZIC | B106: FKI | E106: Bangoka International Airport | H106: Democratic Republic of the Congo | I106: Kisangani | O106: 0.48164 | P106: 25.338 | R106: 1417 | T106: Africa/Lubumbashi
A107: GABS | B107: BKO | E107: Modibo Keita International Airport | H107: Mali | I107: Bamako | O107: 12.5335 | P107: -7.94994 | R107: 1247 | T107: Africa/Bamako
A108: GATB | B108: TOM | E108: Tombouktou Airport | H108: Mali | I108: Timbuktu | O108: 16.7305 | P108: -3.00758 | R108: 863 | T108: Africa/Bamako
A109: GBYD | B109: BJL | E109: Banjul International Airport | H109: Gambia | I109: Banjul | O109: 13.338 | P109: -16.6522 | R109: 95 | T109: Africa/Banjul
A110: GCFV | B110: FUE | E110: Fuerteventura Airport | H110: Spain | I110: El Matorral | O110: 28.4527 | P110: -13.8638 | R110: 85 | T110: Atlantic/Canary
... A119: GMMN | B119: CMN | E119: Mohammed V International Airport | H119: Morocco | I119: Casablanca | O119: 33.3675 | P119: -7.58997 | R119: 656 | T119: Africa/Casablanca
A120: GOBD | B120: DSS | E120: Blaise Diagne International Airport | H120: Senegal | I120: Dakar | O120: 14.67088 | P120: -17.07283 | R120: 290
A121: GOOY | B121: DKR | E121: Léopold Sédar Senghor International Airport | H121: Senegal | I121: Dakar | O121: 14.74234 | P121: -17.47922 | R121: 85 | T121: Africa/Dakar
A122: GQNO | B122: NKC | E122: Nouakchott–Oumtounsy International Airport | H122: Mauritania | I122: Nouakchott | O122: 18.31 | P122: -15.96972 | R122: 9 | T122: Africa/Nouakchott
A123: GQPP | B123: NDB | E123: Nouadhibou International Airport | H123: Mauritania | I123: Nouadhibou | O123: 20.9324 | P123: -17.0302 | R123: 24 | T123: Africa/Nouakchott
A124: GUCY | B124: CKY | E124: Ahmed Sékou Touré International Airport | H124: Guinea | I124: Conakry | O124: 9.57689 | P124: -13.612 | R124: 72 | T124: Africa/Conakry
A125: GVAC | B125: SID | E125: Amílcar Cabral International Airport | H125: Cape Verde | I125: Espargos | O125: 16.7414 | P125: -22.9494 | R125: 177 | T125: Atlantic/Cape_Verde
A126: GVBA | B126: BVC | E126: Aristides Pereira International Airport | H126: Cape Verde | I126: Rabil | O126: 16.1365 | P126: -22.8889 | R126: 69 | T126: Atlantic/Cape_Verde
A127: HAAB | B127: ADD | E127: Addis Ababa Bole International Airport | H127: Ethiopia | I127: Addis Ababa | O127: 8.97789 | P127: 38.7993 | R127: 7630 | T127: Africa/Addis_Ababa
A128: HADR | B128: DIR | E128: Aba Tenna Dejazmach Yilma International Airport | H128: Ethiopia | I128: Dire Dawa | O128: 9.62355 | P128: 41.85503 | R128: 3827 | T128: Africa/Addis_Ababa
A129: HBBA | B129: BJM | E129: Bujumbura Melchior Ndadaye International Airport | H129: Burundi | I129: Bujumbura | O129: -3.32402 | P129: 29.3185 | R129: 2582 | T129: Africa/Bujumbura
A130: HCMF | B130: BSA | E130: Bender Qassim International Airport | H130: Somalia | I130: Bosaso | O130: 11.27524 | P130: 49.13923 | R130: 3 | T130: Africa/Mogadishu
A131: HCMH | B131: HGA | E131: Egal International Airport | H131: Somalia | I131: Hargeisa | O131: 9.51408 | P131: 44.08347 | R131: 4471 | T131: Africa/Mogadishu
A132: HCMM | B132: MGQ | E132: Aden Adde International Airport | H132: Somalia | I132: Mogadishu | O132: 2.01444 | P132: 45.3047 | R132: 29 | T132: Africa/Mogadishu
...

Sheet VISA RULES
A1: Airport ICAO (optional) | B1: Country | C1: Nationality | D1: Visa Type | E1: Required? | F1: Lead Time (days) | G1: Max Stay (days) | H1: Notes / Conditions

Sheet Vendors
A1: vendor_id | B1: company_name | C1: legal_name | D1: tax_id_vat | E1: website | F1: account_type | G1: credit_rating_status | H1: is_active | I1: primary_contact | J1: email | K1: phone_24_7 | L1: sita_address | M1: aftn_address | N1: payment_terms | O1: currency | P1: notes | Q1: created_at | R1: updated_at | S1: countries_covered | T1: countries_covered_list | U1: primary_icao | V1: airports_covered | X1: questionnaire_sent_on | Y1: questionnaire_returned_on | Z1: services_offered_codes | AA1: stations_covered | AB1: caa_direct_account_states | AC1: approved_by | AD1: approved_on | AE1: capability_status | AF1: preference_rank
A2: VND-001 | B2: ZAS Z AVIATION SERVICES | AE2: PENDING
A3: VND-002 | B3: NILE VALLEY AVIATION | AE3: PENDING
A4: VND-003 | B4: CLEOPATRA AVIATION | AE4: PENDING
A5: VND-004 | B5: NATIONAL AVIATION | AE5: PENDING
A6: VND-005 | B6: EGYPT JET AVIATION | AE6: PENDING
A7: VND-006 | B7: TIGER AVIATION SERVICES | AE7: PENDING
A8: VND-007 | B8: AIR SERVICES TOURISM L.L.C. | AE8: PENDING
A9: VND-008 | B9: JETEX FLIGHT SUPPORT | AE9: PENDING
A10: VND-009 | B10: JET AVIATION (EMEA) | AE10: PENDING
A11: VND-010 | B11: AVIARY | AE11: PENDING
A12: VND-011 | B12: MENZIES | AE12: PENDING
A13: VND-012 | B13: EXECUJET | AE13: PENDING
... A137: VND-136 | B137: ASG BUSINESS AVIATION LLC | AE137: PENDING

Sheet SERVICE CATALOGUE
A1: SERVICE CATALOGUE — services and sub-services in one table. Rows 2-18 are the 17 top-level services (referenced by the ground-services grid on TRIP MANAGER). Rows 19-70 are the 52 sub-services, each hanging off a parent by code prefix.
A2: id | B2: name | C2: code | D2: description | E2: category | F2: ground_grid_order | G2: level | H2: parent_service_id | I2: mapping_audit
A3: CAT | B3: Catering | C3: CAT | D3: Crew, VIP and bonded stores | E3: GROUND | F3: 3 | G3: SERVICE
A4: CIQ | B4: Customs & Immigration | C4: CIQ | D4: Clearance, facilitation and health/quarantine | E4: GROUND | F4: 11 | G4: SERVICE
A5: CRH | B5: Crew Hotel | C5: CRH | D5: Crew Hotel | E5: GROUND | F5: 14 | G5: SERVICE
A6: CRT | B6: Crew transport | C6: CRT | D6: Crew VIP Transport | E6: GROUND | F6: 12 | G6: SERVICE
A7: CRW | B7: Crew Services | C7: CRW | D7: HOTAC, transport, visas and immigration liaison | E7: GROUND | F7: 7 | G7: SERVICE
A8: FPL | B8: Flight Planning & Dispatch | C8: FPL | D8: OFP, weather, NOTAM and ATC filing | E8: GROUND | F8: 8 | G8: SERVICE
A9: FUL | B9: Fuel | C9: FUL | D9: Uplift, release and defueling | E9: GROUND | F9: 2 | G9: SERVICE
A10: GH | B10: Ground Handling | C10: GH | D10: Ramp, passenger and aircraft servicing at the station | E10: GROUND | F10: 1 | G10: SERVICE
A11: LDG | B11: Landing Permits | C11: LDG | D11: Regulatory clearances filed with the state CAA | E11: PERMIT | G11: SERVICE
A12: MED | B12: Medical & Medevac | C12: MED | D12: Medevac coordination and patient transfer | E12: GROUND | F12: 10 | G12: SERVICE
A13: MRO | B13: Maintenance | C13: MRO | D13: Line maintenance, AOG and parts logistics | E13: GROUND | F13: 9 | G13: SERVICE
A14: NAV | B14: Navigation & Enroute Charges | C14: NAV | D14: Enroute and terminal navigation charge handling | E14: GROUND | F14: 4 | G14: SERVICE
A15: OVF | B15: Overflight Permits | C15: OVF | D15: Regulatory clearances filed with the state CAA | E15: PERMIT | G15: SERVICE
A16: PXH | B16: Pax Hotel | C16: PXH | D16: Pax Hotel | E16: GROUND | F16: 15 | G16: SERVICE
A17: PXT | B17: Pax transport | C17: PXT | D17: Pax transportation | E17: GROUND | F17: 13 | G17: SERVICE
A18: SEC | B18: Security | C18: SEC | D18: Aircraft guarding, screening and risk assessment | E18: GROUND | F18: 6 | G18: SERVICE
A19: SLT | B19: Slots, PPR & Parking | C19: SLT | D19: Airport slot, PPR and stand allocation | E19: GROUND | F19: 5 | G19: SERVICE
A20: CAT-BND | B20: Bonded Stores & Duty-Free | C20: CAT-BND | G20: SUB-SERVICE | H20: CAT
A21: CAT-CRW | B21: Crew Catering | C21: CAT-CRW | G21: SUB-SERVICE | H21: CAT
A22: CAT-SPL | B22: Special Dietary (Halal/Kosher/Allergen) | C22: CAT-SPL | G22: SUB-SERVICE | H22: CAT
A23: CAT-VIP | B23: VIP / Premium Catering | C23: CAT-VIP | G23: SUB-SERVICE | H23: CAT
A24: CIQ-CUS | B24: Customs Clearance | C24: CIQ-CUS | G24: SUB-SERVICE | H24: CIQ
A25: CIQ-HLT | B25: Health / Quarantine Clearance | C25: CIQ-HLT | G25: SUB-SERVICE | H25: CIQ
A26: CIQ-IMM | B26: Immigration Facilitation | C26: CIQ-IMM | G26: SUB-SERVICE | H26: CIQ
A27: CIQ-VOA | B27: Visa on Arrival Support | C27: CIQ-VOA | G27: SUB-SERVICE | H27: CIQ
A28: CRW-HTL | B28: Hotel Accommodation (HOTAC) | C28: CRW-HTL | G28: SUB-SERVICE | H28: CRW
A29: CRW-IMM | B29: Immigration Liaison | C29: CRW-IMM | G29: SUB-SERVICE | H29: CRW
A30: CRW-VIS | B30: Crew Visa & Documentation | C30: CRW-VIS | G30: SUB-SERVICE | H30: CRW
A31: FPL-ALT | B31: Alternate & Fuel Analysis | C31: FPL-ALT | G31: SUB-SERVICE | H31: FPL
... A37: FUL-JTA | B37: Jet A-1 Uplift | C37: FUL-JTA | G37: SUB-SERVICE | H37: FUL
A38: FUL-REL | B38: Fuel Release / Carnet | C38: FUL-REL | D38: Third-party release against card or contract | G38: SUB-SERVICE | H38: FUL
A39: GH-CGO | B39: Cargo & Baggage Handling | C39: GH-CGO | G39: SUB-SERVICE | H39: GH
A40: GH-DIC | B40: De-icing / Anti-icing | C40: GH-DIC | D40: Seasonal, Type I-IV fluids | G40: SUB-SERVICE | H40: GH
A41: GH-HGR | B41: Hangarage & Parking | C41: GH-HGR | D41: Overnight and long-stay | G41: SUB-SERVICE | H41: GH
A42: GH-LAV | B42: Lavatory & Potable Water | C42: GH-LAV | G42: SUB-SERVICE | H42: GH
A43: GH-LNG | B43: Passenger & VIP Lounge | C43: GH-LNG | D43: Terminal or FBO lounge access | G43: SUB-SERVICE | H43: GH
A44: GH-RMP | B44: Ramp Handling | C44: GH-RMP | D44: Marshalling, chocks, GPU, ASU, towing | G44: SUB-SERVICE | H44: GH
A45: GH-TRP | B45: Crew & Passenger Transport | C45: GH-TRP | D45: Airside and landside transfers | G45: SUB-SERVICE | H45: GH
A46: MED-AMB | B46: Ambulance Transfer | C46: MED-AMB | G46: SUB-SERVICE | H46: MED
A47: MED-CRD | B47: Medevac Coordination | C47: MED-CRD | G47: SUB-SERVICE | H47: MED
A48: MED-ESC | B48: Medical Escort / Doctor on Board | C48: MED-ESC | G48: SUB-SERVICE | H48: MED
A49: MRO-AOG | B49: AOG Support | C49: MRO-AOG | G49: SUB-SERVICE | H49: MRO
A50: MRO-LIN | B50: Line Maintenance | C50: MRO-LIN | D50: Transit and daily checks | G50: SUB-SERVICE | H50: MRO
A51: MRO-PRT | B51: Parts Logistics & Customs | C51: MRO-PRT | G51: SUB-SERVICE | H51: MRO
A52: NAV-ENR | B52: Enroute Navigation Charges | C52: NAV-ENR | G52: SUB-SERVICE | H52: NAV
A53: NAV-STL | B53: Charge Settlement & Reconciliation | C53: NAV-STL | D53: Payment on behalf of operator | G53: SUB-SERVICE | H53: NAV
A54: NAV-TRM | B54: Terminal Navigation Charges | C54: NAV-TRM | G54: SUB-SERVICE | H54: NAV
A55: PRM-AMB | B55: Ambulance / Medevac Permit | C55: PRM-AMB | D55: Priority handling | G55: SUB-SERVICE | H55: OVF
A56: PRM-BLK | B56: Block / Annual Permit | C56: PRM-BLK | D56: Multi-movement standing approval | G56: SUB-SERVICE | H56: OVF
A57: PRM-CAB | B57: Cabotage Approval | C57: PRM-CAB | D57: Domestic sector on foreign registration | G57: SUB-SERVICE | H57: OVF
A58: PRM-CHT | B58: Charter / Traffic Right Approval | C58: PRM-CHT | D58: Commercial charter authorisation | G58: SUB-SERVICE | H58: OVF
A59: PRM-DGR | B59: Dangerous Goods / Special Cargo Permit | C59: PRM-DGR | G59: SUB-SERVICE | H59: OVF
A60: PRM-DIP | B60: Diplomatic Clearance | C60: PRM-DIP | D60: State/VIP and government aircraft | G60: SUB-SERVICE | H60: OVF
A61: PRM-LND | B61: Landing Permit | C61: PRM-LND | D61: Standard landing clearance | G61: SUB-SERVICE | H61: LDG
A62: PRM-LND-EMG | B62: Short-Notice Landing Permit | C62: PRM-LND-EMG | D62: Filed inside standard lead time | G62: SUB-SERVICE | H62: LDG
A63: PRM-OVF | B63: Overflight Permit | C63: PRM-OVF | D63: Standard enroute clearance | G63: SUB-SERVICE | H63: OVF
A64: SEC-EP | B64: Executive Protection | C64: SEC-EP | D64: Close protection for principals | G64: SUB-SERVICE | H64: SEC
A65: SEC-GRD | B65: Aircraft Guarding | C65: SEC-GRD | D65: Static guard, 24h or overnight | G65: SUB-SERVICE | H65: SEC
A66: SEC-RSK | B66: Security Risk Assessment | C66: SEC-RSK | D66: Station threat brief | G66: SUB-SERVICE | H66: SEC
A67: SEC-SCR | B67: Passenger & Baggage Screening | C67: SEC-SCR | G67: SUB-SERVICE | H67: SEC
A68: SLT-CUR | B68: Curfew / Night Dispensation | C68: SLT-CUR | G68: SUB-SERVICE | H68: SLT
A69: SLT-PPR | B69: PPR Request | C69: SLT-PPR | D69: Prior permission required | G69: SUB-SERVICE | H69: SLT
A70: SLT-SLT | B70: Airport Slot Request | C70: SLT-SLT | D70: Level 2/3 coordinated airports | G70: SUB-SERVICE | H70: SLT
A71: SLT-STD | B71: Stand / Parking Allocation | C71: SLT-STD | G71: SUB-SERVICE | H71: SLT

Sheet vendor_coverage_airports
A1: id | B1: vendor_id | C1: icao_code | D1: is_primary_handler | E1: fbo_facility_name | F1: sita_address | G1: aftn_address | H1: vhf_frequency | I1: airport_name_lookup | J1: country_iso_code | K1: data_confidence
A2: VCA-0001 | B2: VND-001 | C2: HECA | D2: NO
A3: VCA-0002 | B3: VND-002 | C3: HECA | D3: NO
A4: VCA-0003 | B4: VND-003 | C4: HECA | D4: NO
A5: VCA-0004 | B5: VND-004 | C5: HECA | D5: NO
A6: VCA-0005 | B6: VND-005 | C6: HECA | D6: NO
A7: VCA-0006 | B7: VND-006 | C7: HECA | D7: NO
A8: VCA-0007 | B8: VND-007 | C8: HECA | D8: NO
A9: VCA-0008 | B9: VND-008 | C9: HECA | D9: NO
A10: VCA-0009 | B10: VND-009 | C10: HECA | D10: NO
A11: VCA-0010 | B11: VND-010 | C11: HECA | D11: NO
A12: VCA-0011 | B12: VND-011 | C12: FAOR | D12: NO
A13: VCA-0012 | B13: VND-012 | C13: FAOR | D13: NO
... A296: VCA-0295 | B296: VND-115 | C296: OAKB | D296: NO

Sheet vendor_coverage_countries
A1: id | B1: vendor_id | C1: country_iso_code | D1: has_caa_direct_account | E1: service_scope | F1: country_name_lookup
A2: VCC-0001 | B2: VND-001 | C2: EG | D2: NO | E2: Ground Handling / Trip Support
A3: VCC-0002 | B3: VND-002 | C3: EG | D3: NO | E3: Ground Handling / Trip Support
A4: VCC-0003 | B4: VND-003 | C4: EG | D4: NO | E4: Ground Handling / Trip Support
A5: VCC-0004 | B5: VND-004 | C5: EG | D5: NO | E5: Ground Handling / Trip Support
A6: VCC-0005 | B6: VND-005 | C6: EG | D6: NO | E6: Ground Handling / Trip Support
A7: VCC-0006 | B7: VND-006 | C7: EG | D7: NO | E7: Ground Handling / Trip Support
A8: VCC-0007 | B8: VND-007 | C8: EG | D8: NO | E8: Ground Handling / Trip Support
A9: VCC-0008 | B9: VND-008 | C9: EG | D9: NO | E9: Ground Handling / Trip Support
A10: VCC-0009 | B10: VND-009 | C10: EG | D10: NO | E10: Ground Handling / Trip Support
A11: VCC-0010 | B11: VND-010 | C11: EG | D11: NO | E11: Ground Handling / Trip Support
A12: VCC-0011 | B12: VND-011 | C12: ZA | D12: NO | E12: Ground Handling / Trip Support
A13: VCC-0012 | B13: VND-012 | C13: ZA | D13: NO | E13: Ground Handling / Trip Support
... A296: VCC-0295 | B296: VND-115 | C296: AF | D296: NO | E296: Ground Handling / Trip Support

Sheet countries
A1: country_id | B1: country_name | C1: iso_alpha2 | D1: iso_alpha3 | E1: calling_code | F1: civil_aviation_authority | G1: overflight_permit_required | H1: landing_permit_required | I1: standard_lead_time_hours | J1: region | K1: notes | L1: ground_handling_mandatory | M1: self_handling_permitted | N1: notes_handling | O1: permit_flags_verified_on | P1: permit_flags_source | Q1: lead_time_source | R1: lead_time_verified_by | S1: lead_time_verified_on | T1: permit_flags_verified_by | U1: reference_status | V1: effective_lead_time_hours
B2: Afghanistan | C2: AF | D2: AFG | E2: +93 | G2: REQUIRED | H2: REQUIRED | J2: South Asia
B3: Angola | C3: AO | D3: AGO | E3: +244 | G3: REQUIRED | H3: REQUIRED | J3: Africa
B4: Albania | C4: AL | D4: ALB | G4: REQUIRED | H4: REQUIRED | J4: Europe
B5: United Arab Emirates | C5: AE | D5: ARE | E5: +971 | G5: REQUIRED | H5: REQUIRED | J5: Middle East
B6: Armenia | C6: AM | D6: ARM | G6: REQUIRED | H6: REQUIRED | J6: Asia
B7: Austria | C7: AT | D7: AUT | G7: REQUIRED | H7: REQUIRED | J7: Europe
B8: Azerbaijan | C8: AZ | D8: AZE | G8: REQUIRED | H8: REQUIRED | J8: Asia
B9: Burundi | C9: BI | D9: BDI | E9: +257 | G9: REQUIRED | H9: REQUIRED | J9: Africa
B10: Belgium | C10: BE | D10: BEL | G10: REQUIRED | H10: REQUIRED | J10: Europe
B11: Benin | C11: BJ | D11: BEN | E11: +229 | G11: REQUIRED | H11: REQUIRED | J11: Africa
B12: Burkina Faso | C12: BF | D12: BFA | E12: +226 | G12: REQUIRED | H12: REQUIRED | J12: Africa
B13: Bangladesh | C13: BD | D13: BGD | G13: REQUIRED | H13: REQUIRED | J13: Asia
B14: Bulgaria | C14: BG | D14: BGR | G14: REQUIRED | H14: REQUIRED | J14: Europe
B15: Bahrain | C15: BH | D15: BHR | E15: +973 | G15: REQUIRED | H15: REQUIRED | J15: Middle East
B16: Bosnia and Herzegovina | C16: BA | D16: BIH | G16: REQUIRED | H16: REQUIRED | J16: Europe
B17: Belarus | C17: BY | D17: BLR | G17: REQUIRED | H17: REQUIRED | J17: Europe
B18: Bhutan | C18: BT | D18: BTN | G18: REQUIRED | H18: REQUIRED | J18: Asia
B19: Botswana | C19: BW | D19: BWA | E19: +267 | G19: REQUIRED | H19: REQUIRED | J19: Africa
B20: Central African Republic | C20: CF | D20: CAF | E20: +236 | G20: REQUIRED | H20: REQUIRED | J20: Africa
B21: Switzerland | C21: CH | D21: CHE | G21: REQUIRED | H21: REQUIRED | J21: Europe
B22: China | C22: CN | D22: CHN | G22: REQUIRED | H22: REQUIRED | J22: Asia
B23: Côte d'Ivoire | C23: CI | D23: CIV | E23: +225 | G23: REQUIRED | H23: REQUIRED | J23: Africa
B24: Cameroon | C24: CM | D24: CMR | E24: +237 | G24: REQUIRED | H24: REQUIRED | J24: Africa
B25: Democratic Republic of the Congo | C25: CD | D25: COD | E25: +243 | G25: REQUIRED | H25: REQUIRED | J25: Africa
B26: Republic of the Congo | C26: CG | D26: COG | E26: +242 | G26: REQUIRED | H26: REQUIRED | J26: Africa
B27: Comoros | C27: KM | D27: COM | E27: +269 | G27: REQUIRED | H27: REQUIRED | J27: Africa
B28: Cape Verde | C28: CV | D28: CPV | E28: +238 | G28: REQUIRED | H28: REQUIRED | J28: Africa
B29: Northern Cyprus | D29: CYN | G29: REQUIRED | H29: REQUIRED | J29: Middle East
B30: Cyprus | C30: CY | D30: CYP | G30: REQUIRED | H30: REQUIRED | J30: Europe
B31: Czechia | C31: CZ | D31: CZE | G31: REQUIRED | H31: REQUIRED | J31: Europe
B32: Germany | C32: DE | D32: DEU | G32: REQUIRED | H32: REQUIRED | J32: Europe
B33: Djibouti | C33: DJ | D33: DJI | E33: +253 | G33: REQUIRED | H33: REQUIRED | J33: Africa
B34: Denmark | C34: DK | D34: DNK | G34: REQUIRED | H34: REQUIRED | J34: Europe
B35: Algeria | C35: DZ | D35: DZA | E35: +213 | G35: REQUIRED | H35: REQUIRED | J35: Africa
B36: Egypt | C36: EG | D36: EGY | E36: +20 | G36: REQUIRED | H36: REQUIRED | J36: Africa
B37: Eritrea | C37: ER | D37: ERI | E37: +291 | G37: REQUIRED | H37: REQUIRED | J37: Africa
B38: Western Sahara | C38: EH | D38: ESH | E38: +212 | G38: REQUIRED | H38: REQUIRED | J38: Africa
B39: Spain | C39: ES | D39: ESP | G39: REQUIRED | H39: REQUIRED | J39: Europe
B40: Estonia | C40: EE | D40: EST | G40: REQUIRED | H40: REQUIRED | J40: Europe
B41: Ethiopia | C41: ET | D41: ETH | E41: +251 | G41: REQUIRED | H41: REQUIRED | J41: Africa
B42: Finland | C42: FI | D42: FIN | G42: REQUIRED | H42: REQUIRED | J42: Europe
B43: France | D43: FRA | G43: REQUIRED | H43: REQUIRED | J43: Europe
B44: Gabon | C44: GA | D44: GAB | E44: +241 | G44: REQUIRED | H44: REQUIRED | J44: Africa
B45: United Kingdom | C45: GB | D45: GBR | G45: REQUIRED | H45: REQUIRED | J45: Europe
B46: Georgia | C46: GE | D46: GEO | G46: REQUIRED | H46: REQUIRED | J46: Asia
B47: Ghana | C47: GH | D47: GHA | E47: +233 | G47: REQUIRED | H47: REQUIRED | J47: Africa
B48: Guinea | C48: GN | D48: GIN | E48: +224 | G48: REQUIRED | H48: REQUIRED | J48: Africa
B49: Gambia | C49: GM | D49: GMB | E49: +220 | G49: REQUIRED | H49: REQUIRED | J49: Africa
B50: Guinea-Bissau | C50: GW | D50: GNB | E50: +245 | G50: REQUIRED | H50: REQUIRED | J50: Africa
B51: Equatorial Guinea | C51: GQ | D51: GNQ | E51: +240 | G51: REQUIRED | H51: REQUIRED | J51: Africa
B52: Greece | C52: GR | D52: GRC | G52: REQUIRED | H52: REQUIRED | J52: Europe
B53: Greenland | C53: GL | D53: GRL | G53: REQUIRED | H53: REQUIRED | J53: North America
B54: Croatia | C54: HR | D54: HRV | G54: REQUIRED | H54: REQUIRED | J54: Europe
B55: Hungary | C55: HU | D55: HUN | G55: REQUIRED | H55: REQUIRED | J55: Europe
B56: Indonesia | C56: ID | D56: IDN | G56: REQUIRED | H56: REQUIRED | J56: Asia
B57: India | C57: IN | D57: IND | G57: REQUIRED | H57: REQUIRED | J57: Asia
B58: Ireland | C58: IE | D58: IRL | G58: REQUIRED | H58: REQUIRED | J58: Europe
B59: Iran | C59: IR | D59: IRN | G59: REQUIRED | H59: REQUIRED | J59: Middle East
B60: Iraq | C60: IQ | D60: IRQ | E60: +964 | G60: REQUIRED | H60: REQUIRED | J60: Middle East
B61: Iceland | C61: IS | D61: ISL | G61: REQUIRED | H61: REQUIRED | J61: Europe
B62: Israel | C62: IL | D62: ISR | E62: +972 | G62: REQUIRED | H62: REQUIRED | J62: Middle East
B63: Italy | C63: IT | D63: ITA | G63: REQUIRED | H63: REQUIRED | J63: Europe
B64: Jordan | C64: JO | D64: JOR | E64: +962 | G64: REQUIRED | H64: REQUIRED | J64: Middle East
B65: Kazakhstan | C65: KZ | D65: KAZ | G65: REQUIRED | H65: REQUIRED | J65: Asia
B66: Kenya | C66: KE | D66: KEN | E66: +254 | G66: REQUIRED | H66: REQUIRED | J66: Africa
B67: Kyrgyzstan | C67: KG | D67: KGZ | G67: REQUIRED | H67: REQUIRED | J67: Asia
B68: Cambodia | C68: KH | D68: KHM | G68: REQUIRED | H68: REQUIRED | J68: Asia
B69: Kuwait | C69: KW | D69: KWT | E69: +965 | G69: REQUIRED | H69: REQUIRED | J69: Middle East
B70: Laos | C70: LA | D70: LAO | G70: REQUIRED | H70: REQUIRED | J70: Asia
B71: Lebanon | C71: LB | D71: LBN | E71: +961 | G71: REQUIRED | H71: REQUIRED | J71: Middle East
B72: Liberia | C72: LR | D72: LBR | E72: +231 | G72: REQUIRED | H72: REQUIRED | J72: Africa
B73: Libya | C73: LY | D73: LBY | E73: +218 | G73: REQUIRED | H73: REQUIRED | J73: Africa
B74: Sri Lanka | C74: LK | D74: LKA | G74: REQUIRED | H74: REQUIRED | J74: Asia
B75: Lesotho | C75: LS | D75: LSO | E75: +266 | G75: REQUIRED | H75: REQUIRED | J75: Africa
B76: Lithuania | C76: LT | D76: LTU | G76: REQUIRED | H76: REQUIRED | J76: Europe
B77: Luxembourg | C77: LU | D77: LUX | G77: REQUIRED | H77: REQUIRED | J77: Europe
B78: Latvia | C78: LV | D78: LVA | G78: REQUIRED | H78: REQUIRED | J78: Europe
B79: Morocco | C79: MA | D79: MAR | E79: +212 | G79: REQUIRED | H79: REQUIRED | J79: Africa
B80: Moldova | C80: MD | D80: MDA | G80: REQUIRED | H80: REQUIRED | J80: Europe
B81: Madagascar | C81: MG | D81: MDG | E81: +261 | G81: REQUIRED | H81: REQUIRED | J81: Africa
B82: Maldives | C82: MV | D82: MDV | G82: REQUIRED | H82: REQUIRED | J82: Asia
B83: North Macedonia | C83: MK | D83: MKD | G83: REQUIRED | H83: REQUIRED | J83: Europe
B84: Mali | C84: ML | D84: MLI | E84: +223 | G84: REQUIRED | H84: REQUIRED | J84: Africa
B85: Malta | C85: MT | D85: MLT | G85: REQUIRED | H85: REQUIRED | J85: Europe
B86: Myanmar | C86: MM | D86: MMR | G86: REQUIRED | H86: REQUIRED | J86: Asia
B87: Montenegro | C87: ME | D87: MNE | G87: REQUIRED | H87: REQUIRED | J87: Europe
